Workbook
Name INDUSTRY_MAP: Assumptions!$S$5:$AB$40

Sheet Cover
B2: CREDIT MONITORING ARRANGEMENT (CMA) REPORT
B3: Projected Financials for Bank Term-Loan & Working-Capital Appraisal
B5: Name of the Unit | C5: =Assumptions!C5
B6: Constitution | C6: =Assumptions!C6
B7: Line of Activity | C7: =Assumptions!C7
B8: Term Loan applied for (₹) | C8: =Assumptions!C8
B9: Promoters' Capital (₹) | C9: =Assumptions!C9
B10: Projection horizon | C10: 5 years (60 months), monthly
B12: CONTENTS
B13: Assumptions | C13: All input variables — the only sheet you type into (blue cells)
B14: Revenue Build-Up | C14: Revenue build-up — volume x price for every line, plus segments
B15: Expenses | C15: 60-month operating expenses, variable and period costs
B16: P & L | C16: 60-month P&L: revenue by line, EBITDA -> EBIT -> PBT -> PAT
B17: Annual_Summary | C17: Consolidated 5-year figures feeding every CMA form
B18: Form_II_Operating | C18: Form II — Operating statement for credit appraisal
B19: Form_III_BalanceSheet | C19: Form III — Projected balance sheet
B20: Form_IV_CA_CL | C20: Form IV — Current assets & current liabilities
B21: Form_V_MPBF | C21: Form V — Maximum permissible bank finance (Tandon)
B22: WC & CC-OD Limit | C22: Working capital assessment and the term-loan / WC borrowing split
B23: Form_VI_FundFlow | C23: Form VI — Fund-flow statement
B24: Repayment | C24: Term-loan repayment schedule, annual and month by month
... B29: Dashboard | C29: Charts: revenue, EBITDA, PAT, DSCR

Sheet Assumptions
A1: ASSUMPTIONS — KEY INPUTS
A2: Enter values only in the blue/shaded cells. Every other sheet updates automatically.
B3: TOTAL COST OF PROJECT | C3: =C8+C9 | D3: ₹ = promoters' capital + term loan applied for
B4: A. COMPANY & LOAN PARTICULARS | S4: Industry | T4: CapLabel | U4: ProdUnitLabel | V4: Cost1Long | W4: Cost1Short | X4: Cost2Long | Y4: Cost2Short | Z4: Cost3Short | AA4: ProdSheetTitle | AB4: SalesSheetTitle
B5: Name of the Unit | I5: INDUSTRY / BUSINESS TYPE → | S5: Agriculture & Farming | T5: Installed Capacity (land / livestock / output) | U5: Production (units) | V5: Seeds & fertiliser cost per unit (Year 1) | W5: Seeds & fertiliser | X5: Irrigation & power cost per unit (Year 1) | Y5: Irrigation & power | Z5: Farm overheads | AA5: Production Plan | AB5: Sales Plan
B6: Constitution (Proprietor / Partnership / Pvt Ltd) | S6: Technology & Software | T6: Service Delivery Capacity (billable hours/licenses p.a.) | U6: Service delivery (units) | V6: Cloud hosting cost per unit (Year 1) | W6: Cloud hosting | X6: API services & software licence cost per unit (Year 1) | Y6: API services & licences | Z6: Engineering overheads | AA6: Service Delivery Plan | AB6: Revenue Plan
B7: Line of Activity / Product | S7: Retail & E-Commerce | T7: Annual Purchase Capacity (units for resale) | U7: Purchase (units) | V7: Inventory purchase cost per unit (Year 1) | W7: Inventory purchase | X7: Packaging & freight cost per unit (Year 1) | Y7: Packaging & freight | Z7: Store overheads | AA7: Purchase / Inventory Plan | AB7: Sales Plan
B8: Term Loan applied for | D8: ₹ | S8: Manufacturing | T8: Installed Capacity (state your own unit -- tonnes/kg/pieces/sq.ft p.a. -- matching what you specified) | U8: Production (units) | V8: Raw material cost per unit (Year 1) | W8: Raw materials | X8: Power & fuel cost per unit (Year 1) | Y8: Power & fuel | Z8: Factory overheads | AA8: Production Plan | AB8: Sales Plan
B9: Promoters' Capital / Equity brought in | D9: ₹ | S9: Tourism & Hospitality | T9: Room / Cover Capacity (room-nights or covers p.a.) | U9: Rooms sold / covers served (units) | V9: F&B & housekeeping cost per room-night (Year 1) | W9: F&B & housekeeping | X9: Power & fuel cost per room-night (Year 1) | Y9: Power & fuel | Z9: Property overheads | AA9: Operations Plan | AB9: Revenue Plan
B10: Interest rate on Term Loan | D10: % p.a. | S10: Renewable Energy | T10: Installed Generation Capacity (units of energy p.a.) | U10: Energy generated (units) | V10: O&M cost per unit generated (Year 1) | W10: O&M cost | X10: Grid charges & evacuation cost per unit (Year 1) | Y10: Grid charges | Z10: Plant overheads | AA10: Generation Plan | AB10: Revenue Plan
B11: Term Loan tenure (in MONTHS, e.g. 60 for 5 years) | D11: years | S11: Healthcare & Pharma | T11: Service / Production Capacity (patients or units p.a.) | U11: Patients served / units produced | V11: Medicines & medical consumables per unit (Year 1) | W11: Medicines & consumables | X11: Diagnostic equipment & power cost per unit (Year 1) | Y11: Diagnostic equipment | Z11: Facility overheads | AA11: Service Delivery Plan | AB11: Revenue Plan
B12: Moratorium / holiday period (in MONTHS) | D12: months | S12: Education & Training | T12: Service Capacity (student seats / batches p.a.) | U12: Students / batches served | V12: Faculty & courseware cost per student (Year 1) | W12: Faculty cost | X12: Campus infrastructure cost per student (Year 1) | Y12: Campus infrastructure | Z12: Institute overheads | AA12: Academic Operations Plan | AB12: Revenue Plan
B13: Interest rate on Working Capital | D13: % p.a. | S13: General Business | T13: Capacity (units / customers / hours p.a.) | U13: Output (units) | V13: Direct cost per unit (Year 1) | W13: Direct cost | X13: Other direct cost per unit (Year 1) | Y13: Other direct cost | Z13: Operating overheads | AA13: Operations Plan | AB13: Revenue Plan
B14: Income Tax rate | D14: % | S14: Construction & Real Estate | T14: Project Execution Capacity (sq.ft / units p.a.) | U14: Construction / units completed | V14: Construction material cost per unit (Year 1) | W14: Construction materials | X14: Site machinery & power cost per unit (Year 1) | Y14: Site machinery | Z14: Project overheads | AA14: Project Execution Plan | AB14: Revenue Plan
B15: B. SALES VOLUME | S15: Food & Beverage / Restaurant | T15: Seating / Covers Capacity (covers p.a.) | U15: Covers served (units) | V15: Food & beverage cost per cover (Year 1) | W15: Food cost | X15: Kitchen fuel & gas cost per cover (Year 1) | Y15: Kitchen fuel | Z15: Restaurant overheads | AA15: Operations Plan | AB15: Revenue Plan
B16: Trips / consignments (Year 1) | D16: units p.a. | S16: Transportation & Logistics | T16: Fleet / Route Capacity (trips or tonnage p.a.) | U16: Trips / tonnage handled (units) | V16: Fuel & running cost per trip (Year 1) | W16: Fuel | X16: Vehicle maintenance cost per trip (Year 1) | Y16: Vehicle maintenance | Z16: Fleet overheads | AA16: Fleet Operations Plan | AB16: Revenue Plan
B17: Sales Growth | C17: Yr 1 | D17: Yr 2 | E17: Yr 3 | F17: Yr 4 | G17: Yr 5 | S17: Textile & Garments | T17: Installed Capacity (garments/fabric units p.a.) | U17: Production (units) | V17: Yarn & fabric cost per unit (Year 1) | W17: Yarn & fabric | X17: Power & fuel cost per unit (Year 1) | Y17: Power & fuel | Z17: Factory overheads | AA17: Production Plan | AB17: Sales Plan
B18: → growth index Year 1…5 (Year 1 = 1.00) | D18: % | S18: Automobile / Auto Ancillary | T18: Installed Capacity (components/vehicles p.a.) | U18: Production (units) | V18: Component & raw material cost per unit (Year 1) | W18: Components & raw materials | X18: Power & fuel cost per unit (Year 1) | Y18: Power & fuel | Z18: Factory overheads | AA18: Production Plan | AB18: Sales Plan
B19: C. MONTHLY PHASING FACTOR (optional — blank = equal spread) | S19: Import / Export Trading | T19: Annual Trading Capacity (units for import/export) | U19: Trading volume (units) | V19: Purchase / import cost per unit (Year 1) | W19: Purchase & import cost | X19: Freight, customs & logistics cost per unit (Year 1) | Y19: Freight & customs | Z19: Trading overheads | AA19: Trading Plan | AB19: Revenue Plan
B20: Relative weight per month (M1…M12) | C20: M1 | D20: M2 | E20: M3 | F20: M4 | G20: M5 | H20: M6 | I20: M7 | J20: M8 | K20: M9 | L20: M10 | M20: M11 | N20: M12 | S20: Media & Entertainment | T20: Content / Production Capacity (units/hours p.a.) | U20: Content produced (units) | V20: Content production cost per unit (Year 1) | W20: Content production | X20: Equipment & studio hire cost per unit (Year 1) | Y20: Equipment & studio hire | Z20: Studio overheads | AA20: Operations Plan | AB20: Revenue Plan
B21: → weights (e.g. 1.0 each, or seasonal) | S21: Mining & Minerals | T21: Installed Extraction Capacity (tonnes p.a.) | U21: Extraction (units) | V21: Extraction & blasting cost per tonne (Year 1) | W21: Extraction & blasting | X21: Power & fuel cost per tonne (Year 1) | Y21: Power & fuel | Z21: Mine overheads | AA21: Extraction Plan | AB21: Sales Plan
B22: D. PRICE & MARGIN (Year-1 base, escalated yearly)
B23: Revenue per trip (Year 1) | D23: ₹/unit
B24: annual price / value growth | D24: %
B25: Gross margin on sales (%) → Operating cost of services = Sales × (1 − margin) | D25: ₹/unit
B26: (cost of sales is margin-based, not per-unit) | D26: %
B27: (not used in this industry) | D27: ₹/unit
B28: annual power cost escalation | D28: %
B29: Other cost per unit of activity (packaging / fulfilment) | D29: ₹/unit
B30: annual other-variable escalation | D30: %
B31: E. FIXED / PERIOD COSTS (per month, Year-1 base, escalated below)
B32: Direct wages & salaries / month (Year 1) | D32: ₹/month
B33: annual wages escalation | D33: %
B34: Operating / facility overheads / month (Year 1) | D34: ₹/month
B35: annual factory-OH escalation | D35: %
B36: Repairs & maintenance / month (Year 1) | D36: ₹/month
B37: annual R&M escalation | D37: %
B38: Administrative expenses / month (Year 1) | D38: ₹/month
B39: annual admin escalation | D39: %
B40: Selling & distribution | D40: % of sales
B41: F. FIXED ASSETS & DEPRECIATION (straight-line on cost)
B42: Land (no depreciation) | D42: ₹
B43: Building — cost | D43: ₹
B44: Building — depreciation rate | D44: %
B45: Plant & Machinery — cost | D45: ₹
B46: Plant & Machinery — depreciation rate | D46: %
B47: Furniture / other — cost | D47: ₹
B48: Furniture / other — depreciation rate | D48: %
B49: G. WORKING CAPITAL CYCLE
B50: Raw material holding | D50: days
B51: Finished goods holding | D51: days
B52: Receivables / debtors | D52: days
B53: Creditors / payables | D53: days
B54: Minimum cash & bank balance | D54: ₹
B55: Bank's WC margin (borrower's stake) | D55: % | P55: Tandon Method-II uses 25%
B57: H. TARGET MARKET SEGMENTS (who the revenue actually comes from) | C57: Segment name | D57: Share of revenue
B58: Segment 1
B59: Segment 2
B60: Segment 3
B61: Segment 4
B62: Segment 5
B63: → shares must total 100% | D63: =SUM(D58:D62)
B65: I. ADDITIONAL REVENUE STREAMS (Year 1 — volume × price, escalated) | C65: Volume / units (Yr 1) | D65: Price (₹ / unit)
B66: Warehousing / Storage | C66: 0 | D66: 0
B67: Value-added logistics | C67: 0 | D67: 0
B68: Express / Priority | C68: 0 | D68: 0
B69: Other revenue | C69: 0 | D69: 0
B71: J. EXISTING LOAN (leave blank if the borrower has none)
B72: Treatment: 1 = Take-over by new loan, 2 = Additional (keeps running) | C72: 0 | D72: 1 or 2
B73: Existing loan — outstanding today | C73: 0 | D73: ₹
B74: Existing loan — interest rate | C74: 0 | D74: % p.a.
B75: Existing loan — remaining tenure | C75: 0 | D75: months

Sheet Revenue Build-Up
A1: REVENUE BUILD-UP — Trips / consignments revenue plus every ancillary revenue stream
A2: Volume × price for every revenue line, the total that feeds the P&L and every downstream form, and the split across target-market segments.
B3: YEAR 1 | O3: YEAR 2 | AB3: YEAR 3 | AO3: YEAR 4 | BB3: YEAR 5
A4: Particulars | B4: M1 | C4: M2 | D4: M3 | E4: M4 | F4: M5 | G4: M6 | H4: M7 | I4: M8 | J4: M9 | K4: M10 | L4: M11 | M4: M12 | N4: Yr 1 Total | O4: M1 | P4: M2 | Q4: M3 | R4: M4 | S4: M5 | T4: M6 | U4: M7 | V4: M8 | W4: M9 | X4: M10 | Y4: M11 | Z4: M12 | AA4: Yr 2 Total | AB4: M1 | AC4: M2 | AD4: M3 | AE4: M4 | AF4: M5 | AG4: M6 | AH4: M7 | AI4: M8 | AJ4: M9 | AK4: M10 | AL4: M11 | AM4: M12 | AN4: Yr 3 Total | AO4: M1 | AP4: M2 | AQ4: M3 | AR4: M4 | AS4: M5 | AT4: M6 | AU4: M7 | AV4: M8 | AW4: M9 | AX4: M10 | AY4: M11 | AZ4: M12 | BA4: Yr 4 Total | BB4: M1 | BC4: M2 | BD4: M3 | BE4: M4 | BF4: M5 | BG4: M6 | BH4: M7 | BI4: M8 | BJ4: M9 | BK4: M10 | BL4: M11 | BM4: M12 | BN4: Yr 5 Total
A5: Growth index (Yr 1 = 100%) | B5: =Assumptions!$C$18 | C5: =Assumptions!$C$18 | D5: =Assumptions!$C$18 | E5: =Assumptions!$C$18 | F5: =Assumptions!$C$18 | G5: =Assumptions!$C$18 | H5: =Assumptions!$C$18 | I5: =Assumptions!$C$18 | ... M5: =Assumptions!$C$18 | N5: =B5 | O5: =Assumptions!$D$18 | P5: =Assumptions!$D$18 | Q5: =Assumptions!$D$18 | R5: =Assumptions!$D$18 | S5: =Assumptions!$D$18 | T5: =Assumptions!$D$18 | U5: =Assumptions!$D$18 | V5: =Assumptions!$D$18 | ... Z5: =Assumptions!$D$18 | AA5: =O5 | AB5: =Assumptions!$E$18 | AC5: =Assumptions!$E$18 | AD5: =Assumptions!$E$18 | AE5: =Assumptions!$E$18 | AF5: =Assumptions!$E$18 | AG5: =Assumptions!$E$18 | AH5: =Assumptions!$E$18 | AI5: =Assumptions!$E$18 | ... AM5: =Assumptions!$E$18 | AN5: =AB5 | AO5: =Assumptions!$F$18 | AP5: =Assumptions!$F$18 | AQ5: =Assumptions!$F$18 | AR5: =Assumptions!$F$18 | AS5: =Assumptions!$F$18 | AT5: =Assumptions!$F$18 | AU5: =Assumptions!$F$18 | AV5: =Assumptions!$F$18 | ... AZ5: =Assumptions!$F$18 | BA5: =AO5 | BB5: =Assumptions!$G$18 | BC5: =Assumptions!$G$18 | BD5: =Assumptions!$G$18 | BE5: =Assumptions!$G$18 | BF5: =Assumptions!$G$18 | BG5: =Assumptions!$G$18 | BH5: =Assumptions!$G$18 | BI5: =Assumptions!$G$18 | ... BM5: =Assumptions!$G$18 | BN5: =BB5
A6: Trips / consignments (units) | B6: =(Assumptions!$C$16*Assumptions!$C$18/12)*IF(SUM(Assumptions!$C$21:$N$21)=0,1,12*Assumptions!C$21/SUM(Assumptions!$C$21:$N$21)) | C6: =(Assumptions!$C$16*Assumptions!$C$18/12)*IF(SUM(Assumptions!$C$21:$N$21)=0,1,12*Assumptions!D$21/SUM(Assumptions!$C$21:$N$21)) | D6: =(Assumptions!$C$16*Assumptions!$C$18/12)*IF(SUM(Assumptions!$C$21:$N$21)=0,1,12*Assumptions!E$21/SUM(Assumptions!$C$21:$N$21)) | E6: =(Assumptions!$C$16*Assumptions!$C$18/12)*IF(SUM(Assumptions!$C$21:$N$21)=0,1,12*Assumptions!F$21/SUM(Assumptions!$C$21:$N$21)) | F6: =(Assumptions!$C$16*Assumptions!$C$18/12)*IF(SUM(Assumptions!$C$21:$N$21)=0,1,12*Assumptions!G$21/SUM(Assumptions!$C$21:$N$21)) | G6: =(Assumptions!$C$16*Assumptions!$C$18/12)*IF(SUM(Assumptions!$C$21:$N$21)=0,1,12*Assumptions!H$21/SUM(Assumptions!$C$21:$N$21)) | H6: =(Assumptions!$C$16*Assumptions!$C$18/12)*IF(SUM(Assumptions!$C$21:$N$21)=0,1,12*Assumptions!I$21/SUM(Assumptions!$C$21:$N$21)) | I6: =(Assumptions!$C$16*Assumptions!$C$18/12)*IF(SUM(Assumptions!$C$21:$N$21)=0,1,12*Assumptions!J$21/SUM(Assumptions!$C$21:$N$21)) | ... M6: =(Assumptions!$C$16*Assumptions!$C$18/12)*IF(SUM(Assumptions!$C$21:$N$21)=0,1,12*Assumptions!N$21/SUM(Assumptions!$C$21:$N$21)) | N6: =SUM(B6:M6) | O6: =(Assumptions!$C$16*Assumptions!$D$18/12)*IF(SUM(Assumptions!$C$21:$N$21)=0,1,12*Assumptions!C$21/SUM(Assumptions!$C$21:$N$21)) | P6: =(Assumptions!$C$16*Assumptions!$D$18/12)*IF(SUM(Assumptions!$C$21:$N$21)=0,1,12*Assumptions!D$21/SUM(Assumptions!$C$21:$N$21)) | Q6: =(Assumptions!$C$16*Assumptions!$D$18/12)*IF(SUM(Assumptions!$C$21:$N$21)=0,1,12*Assumptions!E$21/SUM(Assumptions!$C$21:$N$21)) | R6: =(Assumptions!$C$16*Assumptions!$D$18/12)*IF(SUM(Assumptions!$C$21:$N$21)=0,1,12*Assumptions!F$21/SUM(Assumptions!$C$21:$N$21)) | S6: =(Assumptions!$C$16*Assumptions!$D$18/12)*IF(SUM(Assumptions!$C$21:$N$21)=0,1,12*Assumptions!G$21/SUM(Assumptions!$C$21:$N$21)) | T6: =(Assumptions!$C$16*Assumptions!$D$18/12)*IF(SUM(Assumptions!$C$21:$N$21)=0,1,12*Assumptions!H$21/SUM(Assumptions!$C$21:$N$21)) | U6: =(Assumptions!$C$16*Assumptions!$D$18/12)*IF(SUM(Assumptions!$C$21:$N$21)=0,1,12*Assumptions!I$21/SUM(Assumptions!$C$21:$N$21)) | V6: =(Assumptions!$C$16*Assumptions!$D$18/12)*IF(SUM(Assumptions!$C$21:$N$21)=0,1,12*Assumptions!J$21/SUM(Assumptions!$C$21:$N$21)) | ... Z6: =(Assumptions!$C$16*Assumptions!$D$18/12)*IF(SUM(Assumptions!$C$21:$N$21)=0,1,12*Assumptions!N$21/SUM(Assumptions!$C$21:$N$21)) | AA6: =SUM(O6:Z6) | AB6: =(Assumptions!$C$16*Assumptions!$E$18/12)*IF(SUM(Assumptions!$C$21:$N$21)=0,1,12*Assumptions!C$21/SUM(Assumptions!$C$21:$N$21)) | AC6: =(Assumptions!$C$16*Assumptions!$E$18/12)*IF(SUM(Assumptions!$C$21:$N$21)=0,1,12*Assumptions!D$21/SUM(Assumptions!$C$21:$N$21)) | AD6: =(Assumptions!$C$16*Assumptions!$E$18/12)*IF(SUM(Assumptions!$C$21:$N$21)=0,1,12*Assumptions!E$21/SUM(Assumptions!$C$21:$N$21)) | AE6: =(Assumptions!$C$16*Assumptions!$E$18/12)*IF(SUM(Assumptions!$C$21:$N$21)=0,1,12*Assumptions!F$21/SUM(Assumptions!$C$21:$N$21)) | AF6: =(Assumptions!$C$16*Assumptions!$E$18/12)*IF(SUM(Assumptions!$C$21:$N$21)=0,1,12*Assumptions!G$21/SUM(Assumptions!$C$21:$N$21)) | AG6: =(Assumptions!$C$16*Assumptions!$E$18/12)*IF(SUM(Assumptions!$C$21:$N$21)=0,1,12*Assumptions!H$21/SUM(Assumptions!$C$21:$N$21)) | AH6: =(Assumptions!$C$16*Assumptions!$E$18/12)*IF(SUM(Assumptions!$C$21:$N$21)=0,1,12*Assumptions!I$21/SUM(Assumptions!$C$21:$N$21)) | AI6: =(Assumptions!$C$16*Assumptions!$E$18/12)*IF(SUM(Assumptions!$C$21:$N$21)=0,1,12*Assumptions!J$21/SUM(Assumptions!$C$21:$N$21)) | ... AM6: =(Assumptions!$C$16*Assumptions!$E$18/12)*IF(SUM(Assumptions!$C$21:$N$21)=0,1,12*Assumptions!N$21/SUM(Assumptions!$C$21:$N$21)) | AN6: =SUM(AB6:AM6) | AO6: =(Assumptions!$C$16*Assumptions!$F$18/12)*IF(SUM(Assumptions!$C$21:$N$21)=0,1,12*Assumptions!C$21/SUM(Assumptions!$C$21:$N$21)) | AP6: =(Assumptions!$C$16*Assumptions!$F$18/12)*IF(SUM(Assumptions!$C$21:$N$21)=0,1,12*Assumptions!D$21/SUM(Assumptions!$C$21:$N$21)) | AQ6: =(Assumptions!$C$16*Assumptions!$F$18/12)*IF(SUM(Assumptions!$C$21:$N$21)=0,1,12*Assumptions!E$21/SUM(Assumptions!$C$21:$N$21)) | AR6: =(Assumptions!$C$16*Assumptions!$F$18/12)*IF(SUM(Assumptions!$C$21:$N$21)=0,1,12*Assumptions!F$21/SUM(Assumptions!$C$21:$N$21)) | AS6: =(Assumptions!$C$16*Assumptions!$F$18/12)*IF(SUM(Assumptions!$C$21:$N$21)=0,1,12*Assumptions!G$21/SUM(Assumptions!$C$21:$N$21)) | AT6: =(Assumptions!$C$16*Assumptions!$F$18/12)*IF(SUM(Assumptions!$C$21:$N$21)=0,1,12*Assumptions!H$21/SUM(Assumptions!$C$21:$N$21)) | AU6: =(Assumptions!$C$16*Assumptions!$F$18/12)*IF(SUM(Assumptions!$C$21:$N$21)=0,1,12*Assumptions!I$21/SUM(Assumptions!$C$21:$N$21)) | AV6: =(Assumptions!$C$16*Assumptions!$F$18/12)*IF(SUM(Assumptions!$C$21:$N$21)=0,1,12*Assumptions!J$21/SUM(Assumptions!$C$21:$N$21)) | ... AZ6: =(Assumptions!$C$16*Assumptions!$F$18/12)*IF(SUM(Assumptions!$C$21:$N$21)=0,1,12*Assumptions!N$21/SUM(Assumptions!$C$21:$N$21)) | BA6: =SUM(AO6:AZ6) | BB6: =(Assumptions!$C$16*Assumptions!$G$18/12)*IF(SUM(Assumptions!$C$21:$N$21)=0,1,12*Assumptions!C$21/SUM(Assumptions!$C$21:$N$21)) | BC6: =(Assumptions!$C$16*Assumptions!$G$18/12)*IF(SUM(Assumptions!$C$21:$N$21)=0,1,12*Assumptions!D$21/SUM(Assumptions!$C$21:$N$21)) | BD6: =(Assumptions!$C$16*Assumptions!$G$18/12)*IF(SUM(Assumptions!$C$21:$N$21)=0,1,12*Assumptions!E$21/SUM(Assumptions!$C$21:$N$21)) | BE6: =(Assumptions!$C$16*Assumptions!$G$18/12)*IF(SUM(Assumptions!$C$21:$N$21)=0,1,12*Assumptions!F$21/SUM(Assumptions!$C$21:$N$21)) | BF6: =(Assumptions!$C$16*Assumptions!$G$18/12)*IF(SUM(Assumptions!$C$21:$N$21)=0,1,12*Assumptions!G$21/SUM(Assumptions!$C$21:$N$21)) | BG6: =(Assumptions!$C$16*Assumptions!$G$18/12)*IF(SUM(Assumptions!$C$21:$N$21)=0,1,12*Assumptions!H$21/SUM(Assumptions!$C$21:$N$21)) | BH6: =(Assumptions!$C$16*Assumptions!$G$18/12)*IF(SUM(Assumptions!$C$21:$N$21)=0,1,12*Assumptions!I$21/SUM(Assumptions!$C$21:$N$21)) | BI6: =(Assumptions!$C$16*Assumptions!$G$18/12)*IF(SUM(Assumptions!$C$21:$N$21)=0,1,12*Assumptions!J$21/SUM(Assumptions!$C$21:$N$21)) | ... BM6: =(Assumptions!$C$16*Assumptions!$G$18/12)*IF(SUM(Assumptions!$C$21:$N$21)=0,1,12*Assumptions!N$21/SUM(Assumptions!$C$21:$N$21)) | BN6: =SUM(BB6:BM6)
A7: Revenue per trip (₹ / unit) | B7: =Assumptions!$C$23*(1+Assumptions!$C$24)^0 | C7: =Assumptions!$C$23*(1+Assumptions!$C$24)^0 | D7: =Assumptions!$C$23*(1+Assumptions!$C$24)^0 | E7: =Assumptions!$C$23*(1+Assumptions!$C$24)^0 | F7: =Assumptions!$C$23*(1+Assumptions!$C$24)^0 | G7: =Assumptions!$C$23*(1+Assumptions!$C$24)^0 | H7: =Assumptions!$C$23*(1+Assumptions!$C$24)^0 | I7: =Assumptions!$C$23*(1+Assumptions!$C$24)^0 | ... M7: =Assumptions!$C$23*(1+Assumptions!$C$24)^0 | N7: =B7 | O7: =Assumptions!$C$23*(1+Assumptions!$C$24)^1 | P7: =Assumptions!$C$23*(1+Assumptions!$C$24)^1 | Q7: =Assumptions!$C$23*(1+Assumptions!$C$24)^1 | R7: =Assumptions!$C$23*(1+Assumptions!$C$24)^1 | S7: =Assumptions!$C$23*(1+Assumptions!$C$24)^1 | T7: =Assumptions!$C$23*(1+Assumptions!$C$24)^1 | U7: =Assumptions!$C$23*(1+Assumptions!$C$24)^1 | V7: =Assumptions!$C$23*(1+Assumptions!$C$24)^1 | ... Z7: =Assumptions!$C$23*(1+Assumptions!$C$24)^1 | AA7: =O7 | AB7: =Assumptions!$C$23*(1+Assumptions!$C$24)^2 | AC7: =Assumptions!$C$23*(1+Assumptions!$C$24)^2 | AD7: =Assumptions!$C$23*(1+Assumptions!$C$24)^2 | AE7: =Assumptions!$C$23*(1+Assumptions!$C$24)^2 | AF7: =Assumptions!$C$23*(1+Assumptions!$C$24)^2 | AG7: =Assumptions!$C$23*(1+Assumptions!$C$24)^2 | AH7: =Assumptions!$C$23*(1+Assumptions!$C$24)^2 | AI7: =Assumptions!$C$23*(1+Assumptions!$C$24)^2 | ... AM7: =Assumptions!$C$23*(1+Assumptions!$C$24)^2 | AN7: =AB7 | AO7: =Assumptions!$C$23*(1+Assumptions!$C$24)^3 | AP7: =Assumptions!$C$23*(1+Assumptions!$C$24)^3 | AQ7: =Assumptions!$C$23*(1+Assumptions!$C$24)^3 | AR7: =Assumptions!$C$23*(1+Assumptions!$C$24)^3 | AS7: =Assumptions!$C$23*(1+Assumptions!$C$24)^3 | AT7: =Assumptions!$C$23*(1+Assumptions!$C$24)^3 | AU7: =Assumptions!$C$23*(1+Assumptions!$C$24)^3 | AV7: =Assumptions!$C$23*(1+Assumptions!$C$24)^3 | ... AZ7: =Assumptions!$C$23*(1+Assumptions!$C$24)^3 | BA7: =AO7 | BB7: =Assumptions!$C$23*(1+Assumptions!$C$24)^4 | BC7: =Assumptions!$C$23*(1+Assumptions!$C$24)^4 | BD7: =Assumptions!$C$23*(1+Assumptions!$C$24)^4 | BE7: =Assumptions!$C$23*(1+Assumptions!$C$24)^4 | BF7: =Assumptions!$C$23*(1+Assumptions!$C$24)^4 | BG7: =Assumptions!$C$23*(1+Assumptions!$C$24)^4 | BH7: =Assumptions!$C$23*(1+Assumptions!$C$24)^4 | BI7: =Assumptions!$C$23*(1+Assumptions!$C$24)^4 | ... BM7: =Assumptions!$C$23*(1+Assumptions!$C$24)^4 | BN7: =BB7
A8: Trips / consignments revenue | B8: =B6*B7 | C8: =C6*C7 | D8: =D6*D7 | E8: =E6*E7 | F8: =F6*F7 | G8: =G6*G7 | H8: =H6*H7 | I8: =I6*I7 | ... M8: =M6*M7 | N8: =SUM(B8:M8) | O8: =O6*O7 | P8: =P6*P7 | Q8: =Q6*Q7 | R8: =R6*R7 | S8: =S6*S7 | T8: =T6*T7 | U8: =U6*U7 | V8: =V6*V7 | ... Z8: =Z6*Z7 | AA8: =SUM(O8:Z8) | AB8: =AB6*AB7 | AC8: =AC6*AC7 | AD8: =AD6*AD7 | AE8: =AE6*AE7 | AF8: =AF6*AF7 | AG8: =AG6*AG7 | AH8: =AH6*AH7 | AI8: =AI6*AI7 | ... AM8: =AM6*AM7 | AN8: =SUM(AB8:AM8) | AO8: =AO6*AO7 | AP8: =AP6*AP7 | AQ8: =AQ6*AQ7 | AR8: =AR6*AR7 | AS8: =AS6*AS7 | AT8: =AT6*AT7 | AU8: =AU6*AU7 | AV8: =AV6*AV7 | ... AZ8: =AZ6*AZ7 | BA8: =SUM(AO8:AZ8) | BB8: =BB6*BB7 | BC8: =BC6*BC7 | BD8: =BD6*BD7 | BE8: =BE6*BE7 | BF8: =BF6*BF7 | BG8: =BG6*BG7 | BH8: =BH6*BH7 | BI8: =BI6*BI7 | ... BM8: =BM6*BM7 | BN8: =SUM(BB8:BM8)
A10: Warehousing / Storage — units | B10: =Assumptions!$C$66*Assumptions!$C$18/12 | C10: =Assumptions!$C$66*Assumptions!$C$18/12 | D10: =Assumptions!$C$66*Assumptions!$C$18/12 | E10: =Assumptions!$C$66*Assumptions!$C$18/12 | F10: =Assumptions!$C$66*Assumptions!$C$18/12 | G10: =Assumptions!$C$66*Assumptions!$C$18/12 | H10: =Assumptions!$C$66*Assumptions!$C$18/12 | I10: =Assumptions!$C$66*Assumptions!$C$18/12 | ... M10: =Assumptions!$C$66*Assumptions!$C$18/12 | N10: =SUM(B10:M10) | O10: =Assumptions!$C$66*Assumptions!$D$18/12 | P10: =Assumptions!$C$66*Assumptions!$D$18/12 | Q10: =Assumptions!$C$66*Assumptions!$D$18/12 | R10: =Assumptions!$C$66*Assumptions!$D$18/12 | S10: =Assumptions!$C$66*Assumptions!$D$18/12 | T10: =Assumptions!$C$66*Assumptions!$D$18/12 | U10: =Assumptions!$C$66*Assumptions!$D$18/12 | V10: =Assumptions!$C$66*Assumptions!$D$18/12 | ... Z10: =Assumptions!$C$66*Assumptions!$D$18/12 | AA10: =SUM(O10:Z10) | AB10: =Assumptions!$C$66*Assumptions!$E$18/12 | AC10: =Assumptions!$C$66*Assumptions!$E$18/12 | AD10: =Assumptions!$C$66*Assumptions!$E$18/12 | AE10: =Assumptions!$C$66*Assumptions!$E$18/12 | AF10: =Assumptions!$C$66*Assumptions!$E$18/12 | AG10: =Assumptions!$C$66*Assumptions!$E$18/12 | AH10: =Assumptions!$C$66*Assumptions!$E$18/12 | AI10: =Assumptions!$C$66*Assumptions!$E$18/12 | ... AM10: =Assumptions!$C$66*Assumptions!$E$18/12 | AN10: =SUM(AB10:AM10) | AO10: =Assumptions!$C$66*Assumptions!$F$18/12 | AP10: =Assumptions!$C$66*Assumptions!$F$18/12 | AQ10: =Assumptions!$C$66*Assumptions!$F$18/12 | AR10: =Assumptions!$C$66*Assumptions!$F$18/12 | AS10: =Assumptions!$C$66*Assumptions!$F$18/12 | AT10: =Assumptions!$C$66*Assumptions!$F$18/12 | AU10: =Assumptions!$C$66*Assumptions!$F$18/12 | AV10: =Assumptions!$C$66*Assumptions!$F$18/12 | ... AZ10: =Assumptions!$C$66*Assumptions!$F$18/12 | BA10: =SUM(AO10:AZ10) | BB10: =Assumptions!$C$66*Assumptions!$G$18/12 | BC10: =Assumptions!$C$66*Assumptions!$G$18/12 | BD10: =Assumptions!$C$66*Assumptions!$G$18/12 | BE10: =Assumptions!$C$66*Assumptions!$G$18/12 | BF10: =Assumptions!$C$66*Assumptions!$G$18/12 | BG10: =Assumptions!$C$66*Assumptions!$G$18/12 | BH10: =Assumptions!$C$66*Assumptions!$G$18/12 | BI10: =Assumptions!$C$66*Assumptions!$G$18/12 | ... BM10: =Assumptions!$C$66*Assumptions!$G$18/12 | BN10: =SUM(BB10:BM10)
A11: Warehousing / Storage — ₹ / unit | B11: =Assumptions!$D$66*(1+Assumptions!$C$24)^0 | C11: =Assumptions!$D$66*(1+Assumptions!$C$24)^0 | D11: =Assumptions!$D$66*(1+Assumptions!$C$24)^0 | E11: =Assumptions!$D$66*(1+Assumptions!$C$24)^0 | F11: =Assumptions!$D$66*(1+Assumptions!$C$24)^0 | G11: =Assumptions!$D$66*(1+Assumptions!$C$24)^0 | H11: =Assumptions!$D$66*(1+Assumptions!$C$24)^0 | I11: =Assumptions!$D$66*(1+Assumptions!$C$24)^0 | ... M11: =Assumptions!$D$66*(1+Assumptions!$C$24)^0 | N11: =B11 | O11: =Assumptions!$D$66*(1+Assumptions!$C$24)^1 | P11: =Assumptions!$D$66*(1+Assumptions!$C$24)^1 | Q11: =Assumptions!$D$66*(1+Assumptions!$C$24)^1 | R11: =Assumptions!$D$66*(1+Assumptions!$C$24)^1 | S11: =Assumptions!$D$66*(1+Assumptions!$C$24)^1 | T11: =Assumptions!$D$66*(1+Assumptions!$C$24)^1 | U11: =Assumptions!$D$66*(1+Assumptions!$C$24)^1 | V11: =Assumptions!$D$66*(1+Assumptions!$C$24)^1 | ... Z11: =Assumptions!$D$66*(1+Assumptions!$C$24)^1 | AA11: =O11 | AB11: =Assumptions!$D$66*(1+Assumptions!$C$24)^2 | AC11: =Assumptions!$D$66*(1+Assumptions!$C$24)^2 | AD11: =Assumptions!$D$66*(1+Assumptions!$C$24)^2 | AE11: =Assumptions!$D$66*(1+Assumptions!$C$24)^2 | AF11: =Assumptions!$D$66*(1+Assumptions!$C$24)^2 | AG11: =Assumptions!$D$66*(1+Assumptions!$C$24)^2 | AH11: =Assumptions!$D$66*(1+Assumptions!$C$24)^2 | AI11: =Assumptions!$D$66*(1+Assumptions!$C$24)^2 | ... AM11: =Assumptions!$D$66*(1+Assumptions!$C$24)^2 | AN11: =AB11 | AO11: =Assumptions!$D$66*(1+Assumptions!$C$24)^3 | AP11: =Assumptions!$D$66*(1+Assumptions!$C$24)^3 | AQ11: =Assumptions!$D$66*(1+Assumptions!$C$24)^3 | AR11: =Assumptions!$D$66*(1+Assumptions!$C$24)^3 | AS11: =Assumptions!$D$66*(1+Assumptions!$C$24)^3 | AT11: =Assumptions!$D$66*(1+Assumptions!$C$24)^3 | AU11: =Assumptions!$D$66*(1+Assumptions!$C$24)^3 | AV11: =Assumptions!$D$66*(1+Assumptions!$C$24)^3 | ... AZ11: =Assumptions!$D$66*(1+Assumptions!$C$24)^3 | BA11: =AO11 | BB11: =Assumptions!$D$66*(1+Assumptions!$C$24)^4 | BC11: =Assumptions!$D$66*(1+Assumptions!$C$24)^4 | BD11: =Assumptions!$D$66*(1+Assumptions!$C$24)^4 | BE11: =Assumptions!$D$66*(1+Assumptions!$C$24)^4 | BF11: =Assumptions!$D$66*(1+Assumptions!$C$24)^4 | BG11: =Assumptions!$D$66*(1+Assumptions!$C$24)^4 | BH11: =Assumptions!$D$66*(1+Assumptions!$C$24)^4 | BI11: =Assumptions!$D$66*(1+Assumptions!$C$24)^4 | ... BM11: =Assumptions!$D$66*(1+Assumptions!$C$24)^4 | BN11: =BB11
A12: Warehousing / Storage | B12: =B10*B11 | C12: =C10*C11 | D12: =D10*D11 | E12: =E10*E11 | F12: =F10*F11 | G12: =G10*G11 | H12: =H10*H11 | I12: =I10*I11 | ... M12: =M10*M11 | N12: =SUM(B12:M12) | O12: =O10*O11 | P12: =P10*P11 | Q12: =Q10*Q11 | R12: =R10*R11 | S12: =S10*S11 | T12: =T10*T11 | U12: =U10*U11 | V12: =V10*V11 | ... Z12: =Z10*Z11 | AA12: =SUM(O12:Z12) | AB12: =AB10*AB11 | AC12: =AC10*AC11 | AD12: =AD10*AD11 | AE12: =AE10*AE11 | AF12: =AF10*AF11 | AG12: =AG10*AG11 | AH12: =AH10*AH11 | AI12: =AI10*AI11 | ... AM12: =AM10*AM11 | AN12: =SUM(AB12:AM12) | AO12: =AO10*AO11 | AP12: =AP10*AP11 | AQ12: =AQ10*AQ11 | AR12: =AR10*AR11 | AS12: =AS10*AS11 | AT12: =AT10*AT11 | AU12: =AU10*AU11 | AV12: =AV10*AV11 | ... AZ12: =AZ10*AZ11 | BA12: =SUM(AO12:AZ12) | BB12: =BB10*BB11 | BC12: =BC10*BC11 | BD12: =BD10*BD11 | BE12: =BE10*BE11 | BF12: =BF10*BF11 | BG12: =BG10*BG11 | BH12: =BH10*BH11 | BI12: =BI10*BI11 | ... BM12: =BM10*BM11 | BN12: =SUM(BB12:BM12)
A14: Value-added logistics — units | B14: =Assumptions!$C$67*Assumptions!$C$18/12 | C14: =Assumptions!$C$67*Assumptions!$C$18/12 | D14: =Assumptions!$C$67*Assumptions!$C$18/12 | E14: =Assumptions!$C$67*Assumptions!$C$18/12 | F14: =Assumptions!$C$67*Assumptions!$C$18/12 | G14: =Assumptions!$C$67*Assumptions!$C$18/12 | H14: =Assumptions!$C$67*Assumptions!$C$18/12 | I14: =Assumptions!$C$67*Assumptions!$C$18/12 | ... M14: =Assumptions!$C$67*Assumptions!$C$18/12 | N14: =SUM(B14:M14) | O14: =Assumptions!$C$67*Assumptions!$D$18/12 | P14: =Assumptions!$C$67*Assumptions!$D$18/12 | Q14: =Assumptions!$C$67*Assumptions!$D$18/12 | R14: =Assumptions!$C$67*Assumptions!$D$18/12 | S14: =Assumptions!$C$67*Assumptions!$D$18/12 | T14: =Assumptions!$C$67*Assumptions!$D$18/12 | U14: =Assumptions!$C$67*Assumptions!$D$18/12 | V14: =Assumptions!$C$67*Assumptions!$D$18/12 | ... Z14: =Assumptions!$C$67*Assumptions!$D$18/12 | AA14: =SUM(O14:Z14) | AB14: =Assumptions!$C$67*Assumptions!$E$18/12 | AC14: =Assumptions!$C$67*Assumptions!$E$18/12 | AD14: =Assumptions!$C$67*Assumptions!$E$18/12 | AE14: =Assumptions!$C$67*Assumptions!$E$18/12 | AF14: =Assumptions!$C$67*Assumptions!$E$18/12 | AG14: =Assumptions!$C$67*Assumptions!$E$18/12 | AH14: =Assumptions!$C$67*Assumptions!$E$18/12 | AI14: =Assumptions!$C$67*Assumptions!$E$18/12 | ... AM14: =Assumptions!$C$67*Assumptions!$E$18/12 | AN14: =SUM(AB14:AM14) | AO14: =Assumptions!$C$67*Assumptions!$F$18/12 | AP14: =Assumptions!$C$67*Assumptions!$F$18/12 | AQ14: =Assumptions!$C$67*Assumptions!$F$18/12 | AR14: =Assumptions!$C$67*Assumptions!$F$18/12 | AS14: =Assumptions!$C$67*Assumptions!$F$18/12 | AT14: =Assumptions!$C$67*Assumptions!$F$18/12 | AU14: =Assumptions!$C$67*Assumptions!$F$18/12 | AV14: =Assumptions!$C$67*Assumptions!$F$18/12 | ... AZ14: =Assumptions!$C$67*Assumptions!$F$18/12 | BA14: =SUM(AO14:AZ14) | BB14: =Assumptions!$C$67*Assumptions!$G$18/12 | BC14: =Assumptions!$C$67*Assumptions!$G$18/12 | BD14: =Assumptions!$C$67*Assumptions!$G$18/12 | BE14: =Assumptions!$C$67*Assumptions!$G$18/12 | BF14: =Assumptions!$C$67*Assumptions!$G$18/12 | BG14: =Assumptions!$C$67*Assumptions!$G$18/12 | BH14: =Assumptions!$C$67*Assumptions!$G$18/12 | BI14: =Assumptions!$C$67*Assumptions!$G$18/12 | ... BM14: =Assumptions!$C$67*Assumptions!$G$18/12 | BN14: =SUM(BB14:BM14)
A15: Value-added logistics — ₹ / unit | B15: =Assumptions!$D$67*(1+Assumptions!$C$24)^0 | C15: =Assumptions!$D$67*(1+Assumptions!$C$24)^0 | D15: =Assumptions!$D$67*(1+Assumptions!$C$24)^0 | E15: =Assumptions!$D$67*(1+Assumptions!$C$24)^0 | F15: =Assumptions!$D$67*(1+Assumptions!$C$24)^0 | G15: =Assumptions!$D$67*(1+Assumptions!$C$24)^0 | H15: =Assumptions!$D$67*(1+Assumptions!$C$24)^0 | I15: =Assumptions!$D$67*(1+Assumptions!$C$24)^0 | ... M15: =Assumptions!$D$67*(1+Assumptions!$C$24)^0 | N15: =B15 | O15: =Assumptions!$D$67*(1+Assumptions!$C$24)^1 | P15: =Assumptions!$D$67*(1+Assumptions!$C$24)^1 | Q15: =Assumptions!$D$67*(1+Assumptions!$C$24)^1 | R15: =Assumptions!$D$67*(1+Assumptions!$C$24)^1 | S15: =Assumptions!$D$67*(1+Assumptions!$C$24)^1 | T15: =Assumptions!$D$67*(1+Assumptions!$C$24)^1 | U15: =Assumptions!$D$67*(1+Assumptions!$C$24)^1 | V15: =Assumptions!$D$67*(1+Assumptions!$C$24)^1 | ... Z15: =Assumptions!$D$67*(1+Assumptions!$C$24)^1 | AA15: =O15 | AB15: =Assumptions!$D$67*(1+Assumptions!$C$24)^2 | AC15: =Assumptions!$D$67*(1+Assumptions!$C$24)^2 | AD15: =Assumptions!$D$67*(1+Assumptions!$C$24)^2 | AE15: =Assumptions!$D$67*(1+Assumptions!$C$24)^2 | AF15: =Assumptions!$D$67*(1+Assumptions!$C$24)^2 | AG15: =Assumptions!$D$67*(1+Assumptions!$C$24)^2 | AH15: =Assumptions!$D$67*(1+Assumptions!$C$24)^2 | AI15: =Assumptions!$D$67*(1+Assumptions!$C$24)^2 | ... AM15: =Assumptions!$D$67*(1+Assumptions!$C$24)^2 | AN15: =AB15 | AO15: =Assumptions!$D$67*(1+Assumptions!$C$24)^3 | AP15: =Assumptions!$D$67*(1+Assumptions!$C$24)^3 | AQ15: =Assumptions!$D$67*(1+Assumptions!$C$24)^3 | AR15: =Assumptions!$D$67*(1+Assumptions!$C$24)^3 | AS15: =Assumptions!$D$67*(1+Assumptions!$C$24)^3 | AT15: =Assumptions!$D$67*(1+Assumptions!$C$24)^3 | AU15: =Assumptions!$D$67*(1+Assumptions!$C$24)^3 | AV15: =Assumptions!$D$67*(1+Assumptions!$C$24)^3 | ... AZ15: =Assumptions!$D$67*(1+Assumptions!$C$24)^3 | BA15: =AO15 | BB15: =Assumptions!$D$67*(1+Assumptions!$C$24)^4 | BC15: =Assumptions!$D$67*(1+Assumptions!$C$24)^4 | BD15: =Assumptions!$D$67*(1+Assumptions!$C$24)^4 | BE15: =Assumptions!$D$67*(1+Assumptions!$C$24)^4 | BF15: =Assumptions!$D$67*(1+Assumptions!$C$24)^4 | BG15: =Assumptions!$D$67*(1+Assumptions!$C$24)^4 | BH15: =Assumptions!$D$67*(1+Assumptions!$C$24)^4 | BI15: =Assumptions!$D$67*(1+Assumptions!$C$24)^4 | ... BM15: =Assumptions!$D$67*(1+Assumptions!$C$24)^4 | BN15: =BB15
A16: Value-added logistics | B16: =B14*B15 | C16: =C14*C15 | D16: =D14*D15 | E16: =E14*E15 | F16: =F14*F15 | G16: =G14*G15 | H16: =H14*H15 | I16: =I14*I15 | ... M16: =M14*M15 | N16: =SUM(B16:M16) | O16: =O14*O15 | P16: =P14*P15 | Q16: =Q14*Q15 | R16: =R14*R15 | S16: =S14*S15 | T16: =T14*T15 | U16: =U14*U15 | V16: =V14*V15 | ... Z16: =Z14*Z15 | AA16: =SUM(O16:Z16) | AB16: =AB14*AB15 | AC16: =AC14*AC15 | AD16: =AD14*AD15 | AE16: =AE14*AE15 | AF16: =AF14*AF15 | AG16: =AG14*AG15 | AH16: =AH14*AH15 | AI16: =AI14*AI15 | ... AM16: =AM14*AM15 | AN16: =SUM(AB16:AM16) | AO16: =AO14*AO15 | AP16: =AP14*AP15 | AQ16: =AQ14*AQ15 | AR16: =AR14*AR15 | AS16: =AS14*AS15 | AT16: =AT14*AT15 | AU16: =AU14*AU15 | AV16: =AV14*AV15 | ... AZ16: =AZ14*AZ15 | BA16: =SUM(AO16:AZ16) | BB16: =BB14*BB15 | BC16: =BC14*BC15 | BD16: =BD14*BD15 | BE16: =BE14*BE15 | BF16: =BF14*BF15 | BG16: =BG14*BG15 | BH16: =BH14*BH15 | BI16: =BI14*BI15 | ... BM16: =BM14*BM15 | BN16: =SUM(BB16:BM16)
A18: Express / Priority — units | B18: =Assumptions!$C$68*Assumptions!$C$18/12 | C18: =Assumptions!$C$68*Assumptions!$C$18/12 | D18: =Assumptions!$C$68*Assumptions!$C$18/12 | E18: =Assumptions!$C$68*Assumptions!$C$18/12 | F18: =Assumptions!$C$68*Assumptions!$C$18/12 | G18: =Assumptions!$C$68*Assumptions!$C$18/12 | H18: =Assumptions!$C$68*Assumptions!$C$18/12 | I18: =Assumptions!$C$68*Assumptions!$C$18/12 | ... M18: =Assumptions!$C$68*Assumptions!$C$18/12 | N18: =SUM(B18:M18) | O18: =Assumptions!$C$68*Assumptions!$D$18/12 | P18: =Assumptions!$C$68*Assumptions!$D$18/12 | Q18: =Assumptions!$C$68*Assumptions!$D$18/12 | R18: =Assumptions!$C$68*Assumptions!$D$18/12 | S18: =Assumptions!$C$68*Assumptions!$D$18/12 | T18: =Assumptions!$C$68*Assumptions!$D$18/12 | U18: =Assumptions!$C$68*Assumptions!$D$18/12 | V18: =Assumptions!$C$68*Assumptions!$D$18/12 | ... Z18: =Assumptions!$C$68*Assumptions!$D$18/12 | AA18: =SUM(O18:Z18) | AB18: =Assumptions!$C$68*Assumptions!$E$18/12 | AC18: =Assumptions!$C$68*Assumptions!$E$18/12 | AD18: =Assumptions!$C$68*Assumptions!$E$18/12 | AE18: =Assumptions!$C$68*Assumptions!$E$18/12 | AF18: =Assumptions!$C$68*Assumptions!$E$18/12 | AG18: =Assumptions!$C$68*Assumptions!$E$18/12 | AH18: =Assumptions!$C$68*Assumptions!$E$18/12 | AI18: =Assumptions!$C$68*Assumptions!$E$18/12 | ... AM18: =Assumptions!$C$68*Assumptions!$E$18/12 | AN18: =SUM(AB18:AM18) | AO18: =Assumptions!$C$68*Assumptions!$F$18/12 | AP18: =Assumptions!$C$68*Assumptions!$F$18/12 | AQ18: =Assumptions!$C$68*Assumptions!$F$18/12 | AR18: =Assumptions!$C$68*Assumptions!$F$18/12 | AS18: =Assumptions!$C$68*Assumptions!$F$18/12 | AT18: =Assumptions!$C$68*Assumptions!$F$18/12 | AU18: =Assumptions!$C$68*Assumptions!$F$18/12 | AV18: =Assumptions!$C$68*Assumptions!$F$18/12 | ... AZ18: =Assumptions!$C$68*Assumptions!$F$18/12 | BA18: =SUM(AO18:AZ18) | BB18: =Assumptions!$C$68*Assumptions!$G$18/12 | BC18: =Assumptions!$C$68*Assumptions!$G$18/12 | BD18: =Assumptions!$C$68*Assumptions!$G$18/12 | BE18: =Assumptions!$C$68*Assumptions!$G$18/12 | BF18: =Assumptions!$C$68*Assumptions!$G$18/12 | BG18: =Assumptions!$C$68*Assumptions!$G$18/12 | BH18: =Assumptions!$C$68*Assumptions!$G$18/12 | BI18: =Assumptions!$C$68*Assumptions!$G$18/12 | ... BM18: =Assumptions!$C$68*Assumptions!$G$18/12 | BN18: =SUM(BB18:BM18)
A19: Express / Priority — ₹ / unit | B19: =Assumptions!$D$68*(1+Assumptions!$C$24)^0 | C19: =Assumptions!$D$68*(1+Assumptions!$C$24)^0 | D19: =Assumptions!$D$68*(1+Assumptions!$C$24)^0 | E19: =Assumptions!$D$68*(1+Assumptions!$C$24)^0 | F19: =Assumptions!$D$68*(1+Assumptions!$C$24)^0 | G19: =Assumptions!$D$68*(1+Assumptions!$C$24)^0 | H19: =Assumptions!$D$68*(1+Assumptions!$C$24)^0 | I19: =Assumptions!$D$68*(1+Assumptions!$C$24)^0 | ... M19: =Assumptions!$D$68*(1+Assumptions!$C$24)^0 | N19: =B19 | O19: =Assumptions!$D$68*(1+Assumptions!$C$24)^1 | P19: =Assumptions!$D$68*(1+Assumptions!$C$24)^1 | Q19: =Assumptions!$D$68*(1+Assumptions!$C$24)^1 | R19: =Assumptions!$D$68*(1+Assumptions!$C$24)^1 | S19: =Assumptions!$D$68*(1+Assumptions!$C$24)^1 | T19: =Assumptions!$D$68*(1+Assumptions!$C$24)^1 | U19: =Assumptions!$D$68*(1+Assumptions!$C$24)^1 | V19: =Assumptions!$D$68*(1+Assumptions!$C$24)^1 | ... Z19: =Assumptions!$D$68*(1+Assumptions!$C$24)^1 | AA19: =O19 | AB19: =Assumptions!$D$68*(1+Assumptions!$C$24)^2 | AC19: =Assumptions!$D$68*(1+Assumptions!$C$24)^2 | AD19: =Assumptions!$D$68*(1+Assumptions!$C$24)^2 | AE19: =Assumptions!$D$68*(1+Assumptions!$C$24)^2 | AF19: =Assumptions!$D$68*(1+Assumptions!$C$24)^2 | AG19: =Assumptions!$D$68*(1+Assumptions!$C$24)^2 | AH19: =Assumptions!$D$68*(1+Assumptions!$C$24)^2 | AI19: =Assumptions!$D$68*(1+Assumptions!$C$24)^2 | ... AM19: =Assumptions!$D$68*(1+Assumptions!$C$24)^2 | AN19: =AB19 | AO19: =Assumptions!$D$68*(1+Assumptions!$C$24)^3 | AP19: =Assumptions!$D$68*(1+Assumptions!$C$24)^3 | AQ19: =Assumptions!$D$68*(1+Assumptions!$C$24)^3 | AR19: =Assumptions!$D$68*(1+Assumptions!$C$24)^3 | AS19: =Assumptions!$D$68*(1+Assumptions!$C$24)^3 | AT19: =Assumptions!$D$68*(1+Assumptions!$C$24)^3 | AU19: =Assumptions!$D$68*(1+Assumptions!$C$24)^3 | AV19: =Assumptions!$D$68*(1+Assumptions!$C$24)^3 | ... AZ19: =Assumptions!$D$68*(1+Assumptions!$C$24)^3 | BA19: =AO19 | BB19: =Assumptions!$D$68*(1+Assumptions!$C$24)^4 | BC19: =Assumptions!$D$68*(1+Assumptions!$C$24)^4 | BD19: =Assumptions!$D$68*(1+Assumptions!$C$24)^4 | BE19: =Assumptions!$D$68*(1+Assumptions!$C$24)^4 | BF19: =Assumptions!$D$68*(1+Assumptions!$C$24)^4 | BG19: =Assumptions!$D$68*(1+Assumptions!$C$24)^4 | BH19: =Assumptions!$D$68*(1+Assumptions!$C$24)^4 | BI19: =Assumptions!$D$68*(1+Assumptions!$C$24)^4 | ... BM19: =Assumptions!$D$68*(1+Assumptions!$C$24)^4 | BN19: =BB19
A20: Express / Priority | B20: =B18*B19 | C20: =C18*C19 | D20: =D18*D19 | E20: =E18*E19 | F20: =F18*F19 | G20: =G18*G19 | H20: =H18*H19 | I20: =I18*I19 | ... M20: =M18*M19 | N20: =SUM(B20:M20) | O20: =O18*O19 | P20: =P18*P19 | Q20: =Q18*Q19 | R20: =R18*R19 | S20: =S18*S19 | T20: =T18*T19 | U20: =U18*U19 | V20: =V18*V19 | ... Z20: =Z18*Z19 | AA20: =SUM(O20:Z20) | AB20: =AB18*AB19 | AC20: =AC18*AC19 | AD20: =AD18*AD19 | AE20: =AE18*AE19 | AF20: =AF18*AF19 | AG20: =AG18*AG19 | AH20: =AH18*AH19 | AI20: =AI18*AI19 | ... AM20: =AM18*AM19 | AN20: =SUM(AB20:AM20) | AO20: =AO18*AO19 | AP20: =AP18*AP19 | AQ20: =AQ18*AQ19 | AR20: =AR18*AR19 | AS20: =AS18*AS19 | AT20: =AT18*AT19 | AU20: =AU18*AU19 | AV20: =AV18*AV19 | ... AZ20: =AZ18*AZ19 | BA20: =SUM(AO20:AZ20) | BB20: =BB18*BB19 | BC20: =BC18*BC19 | BD20: =BD18*BD19 | BE20: =BE18*BE19 | BF20: =BF18*BF19 | BG20: =BG18*BG19 | BH20: =BH18*BH19 | BI20: =BI18*BI19 | ... BM20: =BM18*BM19 | BN20: =SUM(BB20:BM20)
A22: Other revenue — units | B22: =Assumptions!$C$69*Assumptions!$C$18/12 | C22: =Assumptions!$C$69*Assumptions!$C$18/12 | D22: =Assumptions!$C$69*Assumptions!$C$18/12 | E22: =Assumptions!$C$69*Assumptions!$C$18/12 | F22: =Assumptions!$C$69*Assumptions!$C$18/12 | G22: =Assumptions!$C$69*Assumptions!$C$18/12 | H22: =Assumptions!$C$69*Assumptions!$C$18/12 | I22: =Assumptions!$C$69*Assumptions!$C$18/12 | ... M22: =Assumptions!$C$69*Assumptions!$C$18/12 | N22: =SUM(B22:M22) | O22: =Assumptions!$C$69*Assumptions!$D$18/12 | P22: =Assumptions!$C$69*Assumptions!$D$18/12 | Q22: =Assumptions!$C$69*Assumptions!$D$18/12 | R22: =Assumptions!$C$69*Assumptions!$D$18/12 | S22: =Assumptions!$C$69*Assumptions!$D$18/12 | T22: =Assumptions!$C$69*Assumptions!$D$18/12 | U22: =Assumptions!$C$69*Assumptions!$D$18/12 | V22: =Assumptions!$C$69*Assumptions!$D$18/12 | ... Z22: =Assumptions!$C$69*Assumptions!$D$18/12 | AA22: =SUM(O22:Z22) | AB22: =Assumptions!$C$69*Assumptions!$E$18/12 | AC22: =Assumptions!$C$69*Assumptions!$E$18/12 | AD22: =Assumptions!$C$69*Assumptions!$E$18/12 | AE22: =Assumptions!$C$69*Assumptions!$E$18/12 | AF22: =Assumptions!$C$69*Assumptions!$E$18/12 | AG22: =Assumptions!$C$69*Assumptions!$E$18/12 | AH22: =Assumptions!$C$69*Assumptions!$E$18/12 | AI22: =Assumptions!$C$69*Assumptions!$E$18/12 | ... AM22: =Assumptions!$C$69*Assumptions!$E$18/12 | AN22: =SUM(AB22:AM22) | AO22: =Assumptions!$C$69*Assumptions!$F$18/12 | AP22: =Assumptions!$C$69*Assumptions!$F$18/12 | AQ22: =Assumptions!$C$69*Assumptions!$F$18/12 | AR22: =Assumptions!$C$69*Assumptions!$F$18/12 | AS22: =Assumptions!$C$69*Assumptions!$F$18/12 | AT22: =Assumptions!$C$69*Assumptions!$F$18/12 | AU22: =Assumptions!$C$69*Assumptions!$F$18/12 | AV22: =Assumptions!$C$69*Assumptions!$F$18/12 | ... AZ22: =Assumptions!$C$69*Assumptions!$F$18/12 | BA22: =SUM(AO22:AZ22) | BB22: =Assumptions!$C$69*Assumptions!$G$18/12 | BC22: =Assumptions!$C$69*Assumptions!$G$18/12 | BD22: =Assumptions!$C$69*Assumptions!$G$18/12 | BE22: =Assumptions!$C$69*Assumptions!$G$18/12 | BF22: =Assumptions!$C$69*Assumptions!$G$18/12 | BG22: =Assumptions!$C$69*Assumptions!$G$18/12 | BH22: =Assumptions!$C$69*Assumptions!$G$18/12 | BI22: =Assumptions!$C$69*Assumptions!$G$18/12 | ... BM22: =Assumptions!$C$69*Assumptions!$G$18/12 | BN22: =SUM(BB22:BM22)
A23: Other revenue — ₹ / unit | B23: =Assumptions!$D$69*(1+Assumptions!$C$24)^0 | C23: =Assumptions!$D$69*(1+Assumptions!$C$24)^0 | D23: =Assumptions!$D$69*(1+Assumptions!$C$24)^0 | E23: =Assumptions!$D$69*(1+Assumptions!$C$24)^0 | F23: =Assumptions!$D$69*(1+Assumptions!$C$24)^0 | G23: =Assumptions!$D$69*(1+Assumptions!$C$24)^0 | H23: =Assumptions!$D$69*(1+Assumptions!$C$24)^0 | I23: =Assumptions!$D$69*(1+Assumptions!$C$24)^0 | ... M23: =Assumptions!$D$69*(1+Assumptions!$C$24)^0 | N23: =B23 | O23: =Assumptions!$D$69*(1+Assumptions!$C$24)^1 | P23: =Assumptions!$D$69*(1+Assumptions!$C$24)^1 | Q23: =Assumptions!$D$69*(1+Assumptions!$C$24)^1 | R23: =Assumptions!$D$69*(1+Assumptions!$C$24)^1 | S23: =Assumptions!$D$69*(1+Assumptions!$C$24)^1 | T23: =Assumptions!$D$69*(1+Assumptions!$C$24)^1 | U23: =Assumptions!$D$69*(1+Assumptions!$C$24)^1 | V23: =Assumptions!$D$69*(1+Assumptions!$C$24)^1 | ... Z23: =Assumptions!$D$69*(1+Assumptions!$C$24)^1 | AA23: =O23 | AB23: =Assumptions!$D$69*(1+Assumptions!$C$24)^2 | AC23: =Assumptions!$D$69*(1+Assumptions!$C$24)^2 | AD23: =Assumptions!$D$69*(1+Assumptions!$C$24)^2 | AE23: =Assumptions!$D$69*(1+Assumptions!$C$24)^2 | AF23: =Assumptions!$D$69*(1+Assumptions!$C$24)^2 | AG23: =Assumptions!$D$69*(1+Assumptions!$C$24)^2 | AH23: =Assumptions!$D$69*(1+Assumptions!$C$24)^2 | AI23: =Assumptions!$D$69*(1+Assumptions!$C$24)^2 | ... AM23: =Assumptions!$D$69*(1+Assumptions!$C$24)^2 | AN23: =AB23 | AO23: =Assumptions!$D$69*(1+Assumptions!$C$24)^3 | AP23: =Assumptions!$D$69*(1+Assumptions!$C$24)^3 | AQ23: =Assumptions!$D$69*(1+Assumptions!$C$24)^3 | AR23: =Assumptions!$D$69*(1+Assumptions!$C$24)^3 | AS23: =Assumptions!$D$69*(1+Assumptions!$C$24)^3 | AT23: =Assumptions!$D$69*(1+Assumptions!$C$24)^3 | AU23: =Assumptions!$D$69*(1+Assumptions!$C$24)^3 | AV23: =Assumptions!$D$69*(1+Assumptions!$C$24)^3 | ... AZ23: =Assumptions!$D$69*(1+Assumptions!$C$24)^3 | BA23: =AO23 | BB23: =Assumptions!$D$69*(1+Assumptions!$C$24)^4 | BC23: =Assumptions!$D$69*(1+Assumptions!$C$24)^4 | BD23: =Assumptions!$D$69*(1+Assumptions!$C$24)^4 | BE23: =Assumptions!$D$69*(1+Assumptions!$C$24)^4 | BF23: =Assumptions!$D$69*(1+Assumptions!$C$24)^4 | BG23: =Assumptions!$D$69*(1+Assumptions!$C$24)^4 | BH23: =Assumptions!$D$69*(1+Assumptions!$C$24)^4 | BI23: =Assumptions!$D$69*(1+Assumptions!$C$24)^4 | ... BM23: =Assumptions!$D$69*(1+Assumptions!$C$24)^4 | BN23: =BB23
A24: Other revenue | B24: =B22*B23 | C24: =C22*C23 | D24: =D22*D23 | E24: =E22*E23 | F24: =F22*F23 | G24: =G22*G23 | H24: =H22*H23 | I24: =I22*I23 | ... M24: =M22*M23 | N24: =SUM(B24:M24) | O24: =O22*O23 | P24: =P22*P23 | Q24: =Q22*Q23 | R24: =R22*R23 | S24: =S22*S23 | T24: =T22*T23 | U24: =U22*U23 | V24: =V22*V23 | ... Z24: =Z22*Z23 | AA24: =SUM(O24:Z24) | AB24: =AB22*AB23 | AC24: =AC22*AC23 | AD24: =AD22*AD23 | AE24: =AE22*AE23 | AF24: =AF22*AF23 | AG24: =AG22*AG23 | AH24: =AH22*AH23 | AI24: =AI22*AI23 | ... AM24: =AM22*AM23 | AN24: =SUM(AB24:AM24) | AO24: =AO22*AO23 | AP24: =AP22*AP23 | AQ24: =AQ22*AQ23 | AR24: =AR22*AR23 | AS24: =AS22*AS23 | AT24: =AT22*AT23 | AU24: =AU22*AU23 | AV24: =AV22*AV23 | ... AZ24: =AZ22*AZ23 | BA24: =SUM(AO24:AZ24) | BB24: =BB22*BB23 | BC24: =BC22*BC23 | BD24: =BD22*BD23 | BE24: =BE22*BE23 | BF24: =BF22*BF23 | BG24: =BG22*BG23 | BH24: =BH22*BH23 | BI24: =BI22*BI23 | ... BM24: =BM22*BM23 | BN24: =SUM(BB24:BM24)
A26: TOTAL REVENUE | B26: =B8+B12+B16+B20+B24 | C26: =C8+C12+C16+C20+C24 | D26: =D8+D12+D16+D20+D24 | E26: =E8+E12+E16+E20+E24 | F26: =F8+F12+F16+F20+F24 | G26: =G8+G12+G16+G20+G24 | H26: =H8+H12+H16+H20+H24 | I26: =I8+I12+I16+I20+I24 | ... M26: =M8+M12+M16+M20+M24 | N26: =SUM(B26:M26) | O26: =O8+O12+O16+O20+O24 | P26: =P8+P12+P16+P20+P24 | Q26: =Q8+Q12+Q16+Q20+Q24 | R26: =R8+R12+R16+R20+R24 | S26: =S8+S12+S16+S20+S24 | T26: =T8+T12+T16+T20+T24 | U26: =U8+U12+U16+U20+U24 | V26: =V8+V12+V16+V20+V24 | ... Z26: =Z8+Z12+Z16+Z20+Z24 | AA26: =SUM(O26:Z26) | AB26: =AB8+AB12+AB16+AB20+AB24 | AC26: =AC8+AC12+AC16+AC20+AC24 | AD26: =AD8+AD12+AD16+AD20+AD24 | AE26: =AE8+AE12+AE16+AE20+AE24 | AF26: =AF8+AF12+AF16+AF20+AF24 | AG26: =AG8+AG12+AG16+AG20+AG24 | AH26: =AH8+AH12+AH16+AH20+AH24 | AI26: =AI8+AI12+AI16+AI20+AI24 | ... AM26: =AM8+AM12+AM16+AM20+AM24 | AN26: =SUM(AB26:AM26) | AO26: =AO8+AO12+AO16+AO20+AO24 | AP26: =AP8+AP12+AP16+AP20+AP24 | AQ26: =AQ8+AQ12+AQ16+AQ20+AQ24 | AR26: =AR8+AR12+AR16+AR20+AR24 | AS26: =AS8+AS12+AS16+AS20+AS24 | AT26: =AT8+AT12+AT16+AT20+AT24 | AU26: =AU8+AU12+AU16+AU20+AU24 | AV26: =AV8+AV12+AV16+AV20+AV24 | ... AZ26: =AZ8+AZ12+AZ16+AZ20+AZ24 | BA26: =SUM(AO26:AZ26) | BB26: =BB8+BB12+BB16+BB20+BB24 | BC26: =BC8+BC12+BC16+BC20+BC24 | BD26: =BD8+BD12+BD16+BD20+BD24 | BE26: =BE8+BE12+BE16+BE20+BE24 | BF26: =BF8+BF12+BF16+BF20+BF24 | BG26: =BG8+BG12+BG16+BG20+BG24 | BH26: =BH8+BH12+BH16+BH20+BH24 | BI26: =BI8+BI12+BI16+BI20+BI24 | ... BM26: =BM8+BM12+BM16+BM20+BM24 | BN26: =SUM(BB26:BM26)
A28: REVENUE BY TARGET MARKET SEGMENT (₹)
A29: =IF(Assumptions!$C$58="","",Assumptions!$C$58) | B29: =IF(Assumptions!$C$58="","",IFERROR(B26*Assumptions!$D$58,0)) | C29: =IF(Assumptions!$C$58="","",IFERROR(C26*Assumptions!$D$58,0)) | D29: =IF(Assumptions!$C$58="","",IFERROR(D26*Assumptions!$D$58,0)) | E29: =IF(Assumptions!$C$58="","",IFERROR(E26*Assumptions!$D$58,0)) | F29: =IF(Assumptions!$C$58="","",IFERROR(F26*Assumptions!$D$58,0)) | G29: =IF(Assumptions!$C$58="","",IFERROR(G26*Assumptions!$D$58,0)) | H29: =IF(Assumptions!$C$58="","",IFERROR(H26*Assumptions!$D$58,0)) | I29: =IF(Assumptions!$C$58="","",IFERROR(I26*Assumptions!$D$58,0)) | ... M29: =IF(Assumptions!$C$58="","",IFERROR(M26*Assumptions!$D$58,0)) | N29: =SUM(B29:M29) | O29: =IF(Assumptions!$C$58="","",IFERROR(O26*Assumptions!$D$58,0)) | P29: =IF(Assumptions!$C$58="","",IFERROR(P26*Assumptions!$D$58,0)) | Q29: =IF(Assumptions!$C$58="","",IFERROR(Q26*Assumptions!$D$58,0)) | R29: =IF(Assumptions!$C$58="","",IFERROR(R26*Assumptions!$D$58,0)) | S29: =IF(Assumptions!$C$58="","",IFERROR(S26*Assumptions!$D$58,0)) | T29: =IF(Assumptions!$C$58="","",IFERROR(T26*Assumptions!$D$58,0)) | U29: =IF(Assumptions!$C$58="","",IFERROR(U26*Assumptions!$D$58,0)) | V29: =IF(Assumptions!$C$58="","",IFERROR(V26*Assumptions!$D$58,0)) | ... Z29: =IF(Assumptions!$C$58="","",IFERROR(Z26*Assumptions!$D$58,0)) | AA29: =SUM(O29:Z29) | AB29: =IF(Assumptions!$C$58="","",IFERROR(AB26*Assumptions!$D$58,0)) | AC29: =IF(Assumptions!$C$58="","",IFERROR(AC26*Assumptions!$D$58,0)) | AD29: =IF(Assumptions!$C$58="","",IFERROR(AD26*Assumptions!$D$58,0)) | AE29: =IF(Assumptions!$C$58="","",IFERROR(AE26*Assumptions!$D$58,0)) | AF29: =IF(Assumptions!$C$58="","",IFERROR(AF26*Assumptions!$D$58,0)) | AG29: =IF(Assumptions!$C$58="","",IFERROR(AG26*Assumptions!$D$58,0)) | AH29: =IF(Assumptions!$C$58="","",IFERROR(AH26*Assumptions!$D$58,0)) | AI29: =IF(Assumptions!$C$58="","",IFERROR(AI26*Assumptions!$D$58,0)) | ... AM29: =IF(Assumptions!$C$58="","",IFERROR(AM26*Assumptions!$D$58,0)) | AN29: =SUM(AB29:AM29) | AO29: =IF(Assumptions!$C$58="","",IFERROR(AO26*Assumptions!$D$58,0)) | AP29: =IF(Assumptions!$C$58="","",IFERROR(AP26*Assumptions!$D$58,0)) | AQ29: =IF(Assumptions!$C$58="","",IFERROR(AQ26*Assumptions!$D$58,0)) | AR29: =IF(Assumptions!$C$58="","",IFERROR(AR26*Assumptions!$D$58,0)) | AS29: =IF(Assumptions!$C$58="","",IFERROR(AS26*Assumptions!$D$58,0)) | AT29: =IF(Assumptions!$C$58="","",IFERROR(AT26*Assumptions!$D$58,0)) | AU29: =IF(Assumptions!$C$58="","",IFERROR(AU26*Assumptions!$D$58,0)) | AV29: =IF(Assumptions!$C$58="","",IFERROR(AV26*Assumptions!$D$58,0)) | ... AZ29: =IF(Assumptions!$C$58="","",IFERROR(AZ26*Assumptions!$D$58,0)) | BA29: =SUM(AO29:AZ29) | BB29: =IF(Assumptions!$C$58="","",IFERROR(BB26*Assumptions!$D$58,0)) | BC29: =IF(Assumptions!$C$58="","",IFERROR(BC26*Assumptions!$D$58,0)) | BD29: =IF(Assumptions!$C$58="","",IFERROR(BD26*Assumptions!$D$58,0)) | BE29: =IF(Assumptions!$C$58="","",IFERROR(BE26*Assumptions!$D$58,0)) | BF29: =IF(Assumptions!$C$58="","",IFERROR(BF26*Assumptions!$D$58,0)) | BG29: =IF(Assumptions!$C$58="","",IFERROR(BG26*Assumptions!$D$58,0)) | BH29: =IF(Assumptions!$C$58="","",IFERROR(BH26*Assumptions!$D$58,0)) | BI29: =IF(Assumptions!$C$58="","",IFERROR(BI26*Assumptions!$D$58,0)) | ... BM29: =IF(Assumptions!$C$58="","",IFERROR(BM26*Assumptions!$D$58,0)) | BN29: =SUM(BB29:BM29)
A30: =IF(Assumptions!$C$59="","",Assumptions!$C$59) | B30: =IF(Assumptions!$C$59="","",IFERROR(B26*Assumptions!$D$59,0)) | C30: =IF(Assumptions!$C$59="","",IFERROR(C26*Assumptions!$D$59,0)) | D30: =IF(Assumptions!$C$59="","",IFERROR(D26*Assumptions!$D$59,0)) | E30: =IF(Assumptions!$C$59="","",IFERROR(E26*Assumptions!$D$59,0)) | F30: =IF(Assumptions!$C$59="","",IFERROR(F26*Assumptions!$D$59,0)) | G30: =IF(Assumptions!$C$59="","",IFERROR(G26*Assumptions!$D$59,0)) | H30: =IF(Assumptions!$C$59="","",IFERROR(H26*Assumptions!$D$59,0)) | I30: =IF(Assumptions!$C$59="","",IFERROR(I26*Assumptions!$D$59,0)) | ... M30: =IF(Assumptions!$C$59="","",IFERROR(M26*Assumptions!$D$59,0)) | N30: =SUM(B30:M30) | O30: =IF(Assumptions!$C$59="","",IFERROR(O26*Assumptions!$D$59,0)) | P30: =IF(Assumptions!$C$59="","",IFERROR(P26*Assumptions!$D$59,0)) | Q30: =IF(Assumptions!$C$59="","",IFERROR(Q26*Assumptions!$D$59,0)) | R30: =IF(Assumptions!$C$59="","",IFERROR(R26*Assumptions!$D$59,0)) | S30: =IF(Assumptions!$C$59="","",IFERROR(S26*Assumptions!$D$59,0)) | T30: =IF(Assumptions!$C$59="","",IFERROR(T26*Assumptions!$D$59,0)) | U30: =IF(Assumptions!$C$59="","",IFERROR(U26*Assumptions!$D$59,0)) | V30: =IF(Assumptions!$C$59="","",IFERROR(V26*Assumptions!$D$59,0)) | ... Z30: =IF(Assumptions!$C$59="","",IFERROR(Z26*Assumptions!$D$59,0)) | AA30: =SUM(O30:Z30) | AB30: =IF(Assumptions!$C$59="","",IFERROR(AB26*Assumptions!$D$59,0)) | AC30: =IF(Assumptions!$C$59="","",IFERROR(AC26*Assumptions!$D$59,0)) | AD30: =IF(Assumptions!$C$59="","",IFERROR(AD26*Assumptions!$D$59,0)) | AE30: =IF(Assumptions!$C$59="","",IFERROR(AE26*Assumptions!$D$59,0)) | AF30: =IF(Assumptions!$C$59="","",IFERROR(AF26*Assumptions!$D$59,0)) | AG30: =IF(Assumptions!$C$59="","",IFERROR(AG26*Assumptions!$D$59,0)) | AH30: =IF(Assumptions!$C$59="","",IFERROR(AH26*Assumptions!$D$59,0)) | AI30: =IF(Assumptions!$C$59="","",IFERROR(AI26*Assumptions!$D$59,0)) | ... AM30: =IF(Assumptions!$C$59="","",IFERROR(AM26*Assumptions!$D$59,0)) | AN30: =SUM(AB30:AM30) | AO30: =IF(Assumptions!$C$59="","",IFERROR(AO26*Assumptions!$D$59,0)) | AP30: =IF(Assumptions!$C$59="","",IFERROR(AP26*Assumptions!$D$59,0)) | AQ30: =IF(Assumptions!$C$59="","",IFERROR(AQ26*Assumptions!$D$59,0)) | AR30: =IF(Assumptions!$C$59="","",IFERROR(AR26*Assumptions!$D$59,0)) | AS30: =IF(Assumptions!$C$59="","",IFERROR(AS26*Assumptions!$D$59,0)) | AT30: =IF(Assumptions!$C$59="","",IFERROR(AT26*Assumptions!$D$59,0)) | AU30: =IF(Assumptions!$C$59="","",IFERROR(AU26*Assumptions!$D$59,0)) | AV30: =IF(Assumptions!$C$59="","",IFERROR(AV26*Assumptions!$D$59,0)) | ... AZ30: =IF(Assumptions!$C$59="","",IFERROR(AZ26*Assumptions!$D$59,0)) | BA30: =SUM(AO30:AZ30) | BB30: =IF(Assumptions!$C$59="","",IFERROR(BB26*Assumptions!$D$59,0)) | BC30: =IF(Assumptions!$C$59="","",IFERROR(BC26*Assumptions!$D$59,0)) | BD30: =IF(Assumptions!$C$59="","",IFERROR(BD26*Assumptions!$D$59,0)) | BE30: =IF(Assumptions!$C$59="","",IFERROR(BE26*Assumptions!$D$59,0)) | BF30: =IF(Assumptions!$C$59="","",IFERROR(BF26*Assumptions!$D$59,0)) | BG30: =IF(Assumptions!$C$59="","",IFERROR(BG26*Assumptions!$D$59,0)) | BH30: =IF(Assumptions!$C$59="","",IFERROR(BH26*Assumptions!$D$59,0)) | BI30: =IF(Assumptions!$C$59="","",IFERROR(BI26*Assumptions!$D$59,0)) | ... BM30: =IF(Assumptions!$C$59="","",IFERROR(BM26*Assumptions!$D$59,0)) | BN30: =SUM(BB30:BM30)
A31: =IF(Assumptions!$C$60="","",Assumptions!$C$60) | B31: =IF(Assumptions!$C$60="","",IFERROR(B26*Assumptions!$D$60,0)) | C31: =IF(Assumptions!$C$60="","",IFERROR(C26*Assumptions!$D$60,0)) | D31: =IF(Assumptions!$C$60="","",IFERROR(D26*Assumptions!$D$60,0)) | E31: =IF(Assumptions!$C$60="","",IFERROR(E26*Assumptions!$D$60,0)) | F31: =IF(Assumptions!$C$60="","",IFERROR(F26*Assumptions!$D$60,0)) | G31: =IF(Assumptions!$C$60="","",IFERROR(G26*Assumptions!$D$60,0)) | H31: =IF(Assumptions!$C$60="","",IFERROR(H26*Assumptions!$D$60,0)) | I31: =IF(Assumptions!$C$60="","",IFERROR(I26*Assumptions!$D$60,0)) | ... M31: =IF(Assumptions!$C$60="","",IFERROR(M26*Assumptions!$D$60,0)) | N31: =SUM(B31:M31) | O31: =IF(Assumptions!$C$60="","",IFERROR(O26*Assumptions!$D$60,0)) | P31: =IF(Assumptions!$C$60="","",IFERROR(P26*Assumptions!$D$60,0)) | Q31: =IF(Assumptions!$C$60="","",IFERROR(Q26*Assumptions!$D$60,0)) | R31: =IF(Assumptions!$C$60="","",IFERROR(R26*Assumptions!$D$60,0)) | S31: =IF(Assumptions!$C$60="","",IFERROR(S26*Assumptions!$D$60,0)) | T31: =IF(Assumptions!$C$60="","",IFERROR(T26*Assumptions!$D$60,0)) | U31: =IF(Assumptions!$C$60="","",IFERROR(U26*Assumptions!$D$60,0)) | V31: =IF(Assumptions!$C$60="","",IFERROR(V26*Assumptions!$D$60,0)) | ... Z31: =IF(Assumptions!$C$60="","",IFERROR(Z26*Assumptions!$D$60,0)) | AA31: =SUM(O31:Z31) | AB31: =IF(Assumptions!$C$60="","",IFERROR(AB26*Assumptions!$D$60,0)) | AC31: =IF(Assumptions!$C$60="","",IFERROR(AC26*Assumptions!$D$60,0)) | AD31: =IF(Assumptions!$C$60="","",IFERROR(AD26*Assumptions!$D$60,0)) | AE31: =IF(Assumptions!$C$60="","",IFERROR(AE26*Assumptions!$D$60,0)) | AF31: =IF(Assumptions!$C$60="","",IFERROR(AF26*Assumptions!$D$60,0)) | AG31: =IF(Assumptions!$C$60="","",IFERROR(AG26*Assumptions!$D$60,0)) | AH31: =IF(Assumptions!$C$60="","",IFERROR(AH26*Assumptions!$D$60,0)) | AI31: =IF(Assumptions!$C$60="","",IFERROR(AI26*Assumptions!$D$60,0)) | ... AM31: =IF(Assumptions!$C$60="","",IFERROR(AM26*Assumptions!$D$60,0)) | AN31: =SUM(AB31:AM31) | AO31: =IF(Assumptions!$C$60="","",IFERROR(AO26*Assumptions!$D$60,0)) | AP31: =IF(Assumptions!$C$60="","",IFERROR(AP26*Assumptions!$D$60,0)) | AQ31: =IF(Assumptions!$C$60="","",IFERROR(AQ26*Assumptions!$D$60,0)) | AR31: =IF(Assumptions!$C$60="","",IFERROR(AR26*Assumptions!$D$60,0)) | AS31: =IF(Assumptions!$C$60="","",IFERROR(AS26*Assumptions!$D$60,0)) | AT31: =IF(Assumptions!$C$60="","",IFERROR(AT26*Assumptions!$D$60,0)) | AU31: =IF(Assumptions!$C$60="","",IFERROR(AU26*Assumptions!$D$60,0)) | AV31: =IF(Assumptions!$C$60="","",IFERROR(AV26*Assumptions!$D$60,0)) | ... AZ31: =IF(Assumptions!$C$60="","",IFERROR(AZ26*Assumptions!$D$60,0)) | BA31: =SUM(AO31:AZ31) | BB31: =IF(Assumptions!$C$60="","",IFERROR(BB26*Assumptions!$D$60,0)) | BC31: =IF(Assumptions!$C$60="","",IFERROR(BC26*Assumptions!$D$60,0)) | BD31: =IF(Assumptions!$C$60="","",IFERROR(BD26*Assumptions!$D$60,0)) | BE31: =IF(Assumptions!$C$60="","",IFERROR(BE26*Assumptions!$D$60,0)) | BF31: =IF(Assumptions!$C$60="","",IFERROR(BF26*Assumptions!$D$60,0)) | BG31: =IF(Assumptions!$C$60="","",IFERROR(BG26*Assumptions!$D$60,0)) | BH31: =IF(Assumptions!$C$60="","",IFERROR(BH26*Assumptions!$D$60,0)) | BI31: =IF(Assumptions!$C$60="","",IFERROR(BI26*Assumptions!$D$60,0)) | ... BM31: =IF(Assumptions!$C$60="","",IFERROR(BM26*Assumptions!$D$60,0)) | BN31: =SUM(BB31:BM31)
A32: =IF(Assumptions!$C$61="","",Assumptions!$C$61) | B32: =IF(Assumptions!$C$61="","",IFERROR(B26*Assumptions!$D$61,0)) | C32: =IF(Assumptions!$C$61="","",IFERROR(C26*Assumptions!$D$61,0)) | D32: =IF(Assumptions!$C$61="","",IFERROR(D26*Assumptions!$D$61,0)) | E32: =IF(Assumptions!$C$61="","",IFERROR(E26*Assumptions!$D$61,0)) | F32: =IF(Assumptions!$C$61="","",IFERROR(F26*Assumptions!$D$61,0)) | G32: =IF(Assumptions!$C$61="","",IFERROR(G26*Assumptions!$D$61,0)) | H32: =IF(Assumptions!$C$61="","",IFERROR(H26*Assumptions!$D$61,0)) | I32: =IF(Assumptions!$C$61="","",IFERROR(I26*Assumptions!$D$61,0)) | ... M32: =IF(Assumptions!$C$61="","",IFERROR(M26*Assumptions!$D$61,0)) | N32: =SUM(B32:M32) | O32: =IF(Assumptions!$C$61="","",IFERROR(O26*Assumptions!$D$61,0)) | P32: =IF(Assumptions!$C$61="","",IFERROR(P26*Assumptions!$D$61,0)) | Q32: =IF(Assumptions!$C$61="","",IFERROR(Q26*Assumptions!$D$61,0)) | R32: =IF(Assumptions!$C$61="","",IFERROR(R26*Assumptions!$D$61,0)) | S32: =IF(Assumptions!$C$61="","",IFERROR(S26*Assumptions!$D$61,0)) | T32: =IF(Assumptions!$C$61="","",IFERROR(T26*Assumptions!$D$61,0)) | U32: =IF(Assumptions!$C$61="","",IFERROR(U26*Assumptions!$D$61,0)) | V32: =IF(Assumptions!$C$61="","",IFERROR(V26*Assumptions!$D$61,0)) | ... Z32: =IF(Assumptions!$C$61="","",IFERROR(Z26*Assumptions!$D$61,0)) | AA32: =SUM(O32:Z32) | AB32: =IF(Assumptions!$C$61="","",IFERROR(AB26*Assumptions!$D$61,0)) | AC32: =IF(Assumptions!$C$61="","",IFERROR(AC26*Assumptions!$D$61,0)) | AD32: =IF(Assumptions!$C$61="","",IFERROR(AD26*Assumptions!$D$61,0)) | AE32: =IF(Assumptions!$C$61="","",IFERROR(AE26*Assumptions!$D$61,0)) | AF32: =IF(Assumptions!$C$61="","",IFERROR(AF26*Assumptions!$D$61,0)) | AG32: =IF(Assumptions!$C$61="","",IFERROR(AG26*Assumptions!$D$61,0)) | AH32: =IF(Assumptions!$C$61="","",IFERROR(AH26*Assumptions!$D$61,0)) | AI32: =IF(Assumptions!$C$61="","",IFERROR(AI26*Assumptions!$D$61,0)) | ... AM32: =IF(Assumptions!$C$61="","",IFERROR(AM26*Assumptions!$D$61,0)) | AN32: =SUM(AB32:AM32) | AO32: =IF(Assumptions!$C$61="","",IFERROR(AO26*Assumptions!$D$61,0)) | AP32: =IF(Assumptions!$C$61="","",IFERROR(AP26*Assumptions!$D$61,0)) | AQ32: =IF(Assumptions!$C$61="","",IFERROR(AQ26*Assumptions!$D$61,0)) | AR32: =IF(Assumptions!$C$61="","",IFERROR(AR26*Assumptions!$D$61,0)) | AS32: =IF(Assumptions!$C$61="","",IFERROR(AS26*Assumptions!$D$61,0)) | AT32: =IF(Assumptions!$C$61="","",IFERROR(AT26*Assumptions!$D$61,0)) | AU32: =IF(Assumptions!$C$61="","",IFERROR(AU26*Assumptions!$D$61,0)) | AV32: =IF(Assumptions!$C$61="","",IFERROR(AV26*Assumptions!$D$61,0)) | ... AZ32: =IF(Assumptions!$C$61="","",IFERROR(AZ26*Assumptions!$D$61,0)) | BA32: =SUM(AO32:AZ32) | BB32: =IF(Assumptions!$C$61="","",IFERROR(BB26*Assumptions!$D$61,0)) | BC32: =IF(Assumptions!$C$61="","",IFERROR(BC26*Assumptions!$D$61,0)) | BD32: =IF(Assumptions!$C$61="","",IFERROR(BD26*Assumptions!$D$61,0)) | BE32: =IF(Assumptions!$C$61="","",IFERROR(BE26*Assumptions!$D$61,0)) | BF32: =IF(Assumptions!$C$61="","",IFERROR(BF26*Assumptions!$D$61,0)) | BG32: =IF(Assumptions!$C$61="","",IFERROR(BG26*Assumptions!$D$61,0)) | BH32: =IF(Assumptions!$C$61="","",IFERROR(BH26*Assumptions!$D$61,0)) | BI32: =IF(Assumptions!$C$61="","",IFERROR(BI26*Assumptions!$D$61,0)) | ... BM32: =IF(Assumptions!$C$61="","",IFERROR(BM26*Assumptions!$D$61,0)) | BN32: =SUM(BB32:BM32)
A33: =IF(Assumptions!$C$62="","",Assumptions!$C$62) | B33: =IF(Assumptions!$C$62="","",IFERROR(B26*Assumptions!$D$62,0)) | C33: =IF(Assumptions!$C$62="","",IFERROR(C26*Assumptions!$D$62,0)) | D33: =IF(Assumptions!$C$62="","",IFERROR(D26*Assumptions!$D$62,0)) | E33: =IF(Assumptions!$C$62="","",IFERROR(E26*Assumptions!$D$62,0)) | F33: =IF(Assumptions!$C$62="","",IFERROR(F26*Assumptions!$D$62,0)) | G33: =IF(Assumptions!$C$62="","",IFERROR(G26*Assumptions!$D$62,0)) | H33: =IF(Assumptions!$C$62="","",IFERROR(H26*Assumptions!$D$62,0)) | I33: =IF(Assumptions!$C$62="","",IFERROR(I26*Assumptions!$D$62,0)) | ... M33: =IF(Assumptions!$C$62="","",IFERROR(M26*Assumptions!$D$62,0)) | N33: =SUM(B33:M33) | O33: =IF(Assumptions!$C$62="","",IFERROR(O26*Assumptions!$D$62,0)) | P33: =IF(Assumptions!$C$62="","",IFERROR(P26*Assumptions!$D$62,0)) | Q33: =IF(Assumptions!$C$62="","",IFERROR(Q26*Assumptions!$D$62,0)) | R33: =IF(Assumptions!$C$62="","",IFERROR(R26*Assumptions!$D$62,0)) | S33: =IF(Assumptions!$C$62="","",IFERROR(S26*Assumptions!$D$62,0)) | T33: =IF(Assumptions!$C$62="","",IFERROR(T26*Assumptions!$D$62,0)) | U33: =IF(Assumptions!$C$62="","",IFERROR(U26*Assumptions!$D$62,0)) | V33: =IF(Assumptions!$C$62="","",IFERROR(V26*Assumptions!$D$62,0)) | ... Z33: =IF(Assumptions!$C$62="","",IFERROR(Z26*Assumptions!$D$62,0)) | AA33: =SUM(O33:Z33) | AB33: =IF(Assumptions!$C$62="","",IFERROR(AB26*Assumptions!$D$62,0)) | AC33: =IF(Assumptions!$C$62="","",IFERROR(AC26*Assumptions!$D$62,0)) | AD33: =IF(Assumptions!$C$62="","",IFERROR(AD26*Assumptions!$D$62,0)) | AE33: =IF(Assumptions!$C$62="","",IFERROR(AE26*Assumptions!$D$62,0)) | AF33: =IF(Assumptions!$C$62="","",IFERROR(AF26*Assumptions!$D$62,0)) | AG33: =IF(Assumptions!$C$62="","",IFERROR(AG26*Assumptions!$D$62,0)) | AH33: =IF(Assumptions!$C$62="","",IFERROR(AH26*Assumptions!$D$62,0)) | AI33: =IF(Assumptions!$C$62="","",IFERROR(AI26*Assumptions!$D$62,0)) | ... AM33: =IF(Assumptions!$C$62="","",IFERROR(AM26*Assumptions!$D$62,0)) | AN33: =SUM(AB33:AM33) | AO33: =IF(Assumptions!$C$62="","",IFERROR(AO26*Assumptions!$D$62,0)) | AP33: =IF(Assumptions!$C$62="","",IFERROR(AP26*Assumptions!$D$62,0)) | AQ33: =IF(Assumptions!$C$62="","",IFERROR(AQ26*Assumptions!$D$62,0)) | AR33: =IF(Assumptions!$C$62="","",IFERROR(AR26*Assumptions!$D$62,0)) | AS33: =IF(Assumptions!$C$62="","",IFERROR(AS26*Assumptions!$D$62,0)) | AT33: =IF(Assumptions!$C$62="","",IFERROR(AT26*Assumptions!$D$62,0)) | AU33: =IF(Assumptions!$C$62="","",IFERROR(AU26*Assumptions!$D$62,0)) | AV33: =IF(Assumptions!$C$62="","",IFERROR(AV26*Assumptions!$D$62,0)) | ... AZ33: =IF(Assumptions!$C$62="","",IFERROR(AZ26*Assumptions!$D$62,0)) | BA33: =SUM(AO33:AZ33) | BB33: =IF(Assumptions!$C$62="","",IFERROR(BB26*Assumptions!$D$62,0)) | BC33: =IF(Assumptions!$C$62="","",IFERROR(BC26*Assumptions!$D$62,0)) | BD33: =IF(Assumptions!$C$62="","",IFERROR(BD26*Assumptions!$D$62,0)) | BE33: =IF(Assumptions!$C$62="","",IFERROR(BE26*Assumptions!$D$62,0)) | BF33: =IF(Assumptions!$C$62="","",IFERROR(BF26*Assumptions!$D$62,0)) | BG33: =IF(Assumptions!$C$62="","",IFERROR(BG26*Assumptions!$D$62,0)) | BH33: =IF(Assumptions!$C$62="","",IFERROR(BH26*Assumptions!$D$62,0)) | BI33: =IF(Assumptions!$C$62="","",IFERROR(BI26*Assumptions!$D$62,0)) | ... BM33: =IF(Assumptions!$C$62="","",IFERROR(BM26*Assumptions!$D$62,0)) | BN33: =SUM(BB33:BM33)
A34: Total (ties to TOTAL REVENUE) | B34: =SUM(B29:B33) | C34: =SUM(C29:C33) | D34: =SUM(D29:D33) | E34: =SUM(E29:E33) | F34: =SUM(F29:F33) | G34: =SUM(G29:G33) | H34: =SUM(H29:H33) | I34: =SUM(I29:I33) | ... M34: =SUM(M29:M33) | N34: =SUM(B34:M34) | O34: =SUM(O29:O33) | P34: =SUM(P29:P33) | Q34: =SUM(Q29:Q33) | R34: =SUM(R29:R33) | S34: =SUM(S29:S33) | T34: =SUM(T29:T33) | U34: =SUM(U29:U33) | V34: =SUM(V29:V33) | ... Z34: =SUM(Z29:Z33) | AA34: =SUM(O34:Z34) | AB34: =SUM(AB29:AB33) | AC34: =SUM(AC29:AC33) | AD34: =SUM(AD29:AD33) | AE34: =SUM(AE29:AE33) | AF34: =SUM(AF29:AF33) | AG34: =SUM(AG29:AG33) | AH34: =SUM(AH29:AH33) | AI34: =SUM(AI29:AI33) | ... AM34: =SUM(AM29:AM33) | AN34: =SUM(AB34:AM34) | AO34: =SUM(AO29:AO33) | AP34: =SUM(AP29:AP33) | AQ34: =SUM(AQ29:AQ33) | AR34: =SUM(AR29:AR33) | AS34: =SUM(AS29:AS33) | AT34: =SUM(AT29:AT33) | AU34: =SUM(AU29:AU33) | AV34: =SUM(AV29:AV33) | ... AZ34: =SUM(AZ29:AZ33) | BA34: =SUM(AO34:AZ34) | BB34: =SUM(BB29:BB33) | BC34: =SUM(BC29:BC33) | BD34: =SUM(BD29:BD33) | BE34: =SUM(BE29:BE33) | BF34: =SUM(BF29:BF33) | BG34: =SUM(BG29:BG33) | BH34: =SUM(BH29:BH33) | BI34: =SUM(BI29:BI33) | ... BM34: =SUM(BM29:BM33) | BN34: =SUM(BB34:BM34)

Sheet Expenses
A1: OPERATING EXPENSES — 60-MONTH PROJECTION
A2: Cost of sales is margin-based; operating costs are period costs.
B3: YEAR 1 | O3: YEAR 2 | AB3: YEAR 3 | AO3: YEAR 4 | BB3: YEAR 5
A4: Particulars | B4: M1 | C4: M2 | D4: M3 | E4: M4 | F4: M5 | G4: M6 | H4: M7 | I4: M8 | J4: M9 | K4: M10 | L4: M11 | M4: M12 | N4: Yr 1 Total | O4: M13 | P4: M14 | Q4: M15 | R4: M16 | S4: M17 | T4: M18 | U4: M19 | V4: M20 | W4: M21 | X4: M22 | Y4: M23 | Z4: M24 | AA4: Yr 2 Total | AB4: M25 | AC4: M26 | AD4: M27 | AE4: M28 | AF4: M29 | AG4: M30 | AH4: M31 | AI4: M32 | AJ4: M33 | AK4: M34 | AL4: M35 | AM4: M36 | AN4: Yr 3 Total | AO4: M37 | AP4: M38 | AQ4: M39 | AR4: M40 | AS4: M41 | AT4: M42 | AU4: M43 | AV4: M44 | AW4: M45 | AX4: M46 | AY4: M47 | AZ4: M48 | BA4: Yr 4 Total | BB4: M49 | BC4: M50 | BD4: M51 | BE4: M52 | BF4: M53 | BG4: M54 | BH4: M55 | BI4: M56 | BJ4: M57 | BK4: M58 | BL4: M59 | BM4: M60 | BN4: Yr 5 Total
A5: Operating cost of services | B5: ='Revenue Build-Up'!B26*(1-Assumptions!$C$25) | C5: ='Revenue Build-Up'!C26*(1-Assumptions!$C$25) | D5: ='Revenue Build-Up'!D26*(1-Assumptions!$C$25) | E5: ='Revenue Build-Up'!E26*(1-Assumptions!$C$25) | F5: ='Revenue Build-Up'!F26*(1-Assumptions!$C$25) | G5: ='Revenue Build-Up'!G26*(1-Assumptions!$C$25) | H5: ='Revenue Build-Up'!H26*(1-Assumptions!$C$25) | I5: ='Revenue Build-Up'!I26*(1-Assumptions!$C$25) | ... M5: ='Revenue Build-Up'!M26*(1-Assumptions!$C$25) | N5: =SUM(B5:M5) | O5: ='Revenue Build-Up'!O26*(1-Assumptions!$C$25) | P5: ='Revenue Build-Up'!P26*(1-Assumptions!$C$25) | Q5: ='Revenue Build-Up'!Q26*(1-Assumptions!$C$25) | R5: ='Revenue Build-Up'!R26*(1-Assumptions!$C$25) | S5: ='Revenue Build-Up'!S26*(1-Assumptions!$C$25) | T5: ='Revenue Build-Up'!T26*(1-Assumptions!$C$25) | U5: ='Revenue Build-Up'!U26*(1-Assumptions!$C$25) | V5: ='Revenue Build-Up'!V26*(1-Assumptions!$C$25) | ... Z5: ='Revenue Build-Up'!Z26*(1-Assumptions!$C$25) | AA5: =SUM(O5:Z5) | AB5: ='Revenue Build-Up'!AB26*(1-Assumptions!$C$25) | AC5: ='Revenue Build-Up'!AC26*(1-Assumptions!$C$25) | AD5: ='Revenue Build-Up'!AD26*(1-Assumptions!$C$25) | AE5: ='Revenue Build-Up'!AE26*(1-Assumptions!$C$25) | AF5: ='Revenue Build-Up'!AF26*(1-Assumptions!$C$25) | AG5: ='Revenue Build-Up'!AG26*(1-Assumptions!$C$25) | AH5: ='Revenue Build-Up'!AH26*(1-Assumptions!$C$25) | AI5: ='Revenue Build-Up'!AI26*(1-Assumptions!$C$25) | ... AM5: ='Revenue Build-Up'!AM26*(1-Assumptions!$C$25) | AN5: =SUM(AB5:AM5) | AO5: ='Revenue Build-Up'!AO26*(1-Assumptions!$C$25) | AP5: ='Revenue Build-Up'!AP26*(1-Assumptions!$C$25) | AQ5: ='Revenue Build-Up'!AQ26*(1-Assumptions!$C$25) | AR5: ='Revenue Build-Up'!AR26*(1-Assumptions!$C$25) | AS5: ='Revenue Build-Up'!AS26*(1-Assumptions!$C$25) | AT5: ='Revenue Build-Up'!AT26*(1-Assumptions!$C$25) | AU5: ='Revenue Build-Up'!AU26*(1-Assumptions!$C$25) | AV5: ='Revenue Build-Up'!AV26*(1-Assumptions!$C$25) | ... AZ5: ='Revenue Build-Up'!AZ26*(1-Assumptions!$C$25) | BA5: =SUM(AO5:AZ5) | BB5: ='Revenue Build-Up'!BB26*(1-Assumptions!$C$25) | BC5: ='Revenue Build-Up'!BC26*(1-Assumptions!$C$25) | BD5: ='Revenue Build-Up'!BD26*(1-Assumptions!$C$25) | BE5: ='Revenue Build-Up'!BE26*(1-Assumptions!$C$25) | BF5: ='Revenue Build-Up'!BF26*(1-Assumptions!$C$25) | BG5: ='Revenue Build-Up'!BG26*(1-Assumptions!$C$25) | BH5: ='Revenue Build-Up'!BH26*(1-Assumptions!$C$25) | BI5: ='Revenue Build-Up'!BI26*(1-Assumptions!$C$25) | ... BM5: ='Revenue Build-Up'!BM26*(1-Assumptions!$C$25) | BN5: =SUM(BB5:BM5)
A6: =IFERROR(VLOOKUP(Assumptions!$J$5,INDUSTRY_MAP,7,FALSE()),"Power & fuel") | B6: 0 | C6: 0 | D6: 0 | E6: 0 | F6: 0 | G6: 0 | H6: 0 | I6: 0 | J6: 0 | K6: 0 | L6: 0 | M6: 0 | N6: =SUM(B6:M6) | O6: 0 | P6: 0 | Q6: 0 | R6: 0 | S6: 0 | T6: 0 | U6: 0 | V6: 0 | W6: 0 | X6: 0 | Y6: 0 | Z6: 0 | AA6: =SUM(O6:Z6) | AB6: 0 | AC6: 0 | AD6: 0 | AE6: 0 | AF6: 0 | AG6: 0 | AH6: 0 | AI6: 0 | AJ6: 0 | AK6: 0 | AL6: 0 | AM6: 0 | AN6: =SUM(AB6:AM6) | AO6: 0 | AP6: 0 | AQ6: 0 | AR6: 0 | AS6: 0 | AT6: 0 | AU6: 0 | AV6: 0 | AW6: 0 | AX6: 0 | AY6: 0 | AZ6: 0 | BA6: =SUM(AO6:AZ6) | BB6: 0 | BC6: 0 | BD6: 0 | BE6: 0 | BF6: 0 | BG6: 0 | BH6: 0 | BI6: 0 | BJ6: 0 | BK6: 0 | BL6: 0 | BM6: 0 | BN6: =SUM(BB6:BM6)
A7: Direct wages & salaries | B7: =Assumptions!$C$32*(1+Assumptions!$C$33)^0 | C7: =Assumptions!$C$32*(1+Assumptions!$C$33)^0 | D7: =Assumptions!$C$32*(1+Assumptions!$C$33)^0 | E7: =Assumptions!$C$32*(1+Assumptions!$C$33)^0 | F7: =Assumptions!$C$32*(1+Assumptions!$C$33)^0 | G7: =Assumptions!$C$32*(1+Assumptions!$C$33)^0 | H7: =Assumptions!$C$32*(1+Assumptions!$C$33)^0 | I7: =Assumptions!$C$32*(1+Assumptions!$C$33)^0 | ... M7: =Assumptions!$C$32*(1+Assumptions!$C$33)^0 | N7: =SUM(B7:M7) | O7: =Assumptions!$C$32*(1+Assumptions!$C$33)^1 | P7: =Assumptions!$C$32*(1+Assumptions!$C$33)^1 | Q7: =Assumptions!$C$32*(1+Assumptions!$C$33)^1 | R7: =Assumptions!$C$32*(1+Assumptions!$C$33)^1 | S7: =Assumptions!$C$32*(1+Assumptions!$C$33)^1 | T7: =Assumptions!$C$32*(1+Assumptions!$C$33)^1 | U7: =Assumptions!$C$32*(1+Assumptions!$C$33)^1 | V7: =Assumptions!$C$32*(1+Assumptions!$C$33)^1 | ... Z7: =Assumptions!$C$32*(1+Assumptions!$C$33)^1 | AA7: =SUM(O7:Z7) | AB7: =Assumptions!$C$32*(1+Assumptions!$C$33)^2 | AC7: =Assumptions!$C$32*(1+Assumptions!$C$33)^2 | AD7: =Assumptions!$C$32*(1+Assumptions!$C$33)^2 | AE7: =Assumptions!$C$32*(1+Assumptions!$C$33)^2 | AF7: =Assumptions!$C$32*(1+Assumptions!$C$33)^2 | AG7: =Assumptions!$C$32*(1+Assumptions!$C$33)^2 | AH7: =Assumptions!$C$32*(1+Assumptions!$C$33)^2 | AI7: =Assumptions!$C$32*(1+Assumptions!$C$33)^2 | ... AM7: =Assumptions!$C$32*(1+Assumptions!$C$33)^2 | AN7: =SUM(AB7:AM7) | AO7: =Assumptions!$C$32*(1+Assumptions!$C$33)^3 | AP7: =Assumptions!$C$32*(1+Assumptions!$C$33)^3 | AQ7: =Assumptions!$C$32*(1+Assumptions!$C$33)^3 | AR7: =Assumptions!$C$32*(1+Assumptions!$C$33)^3 | AS7: =Assumptions!$C$32*(1+Assumptions!$C$33)^3 | AT7: =Assumptions!$C$32*(1+Assumptions!$C$33)^3 | AU7: =Assumptions!$C$32*(1+Assumptions!$C$33)^3 | AV7: =Assumptions!$C$32*(1+Assumptions!$C$33)^3 | ... AZ7: =Assumptions!$C$32*(1+Assumptions!$C$33)^3 | BA7: =SUM(AO7:AZ7) | BB7: =Assumptions!$C$32*(1+Assumptions!$C$33)^4 | BC7: =Assumptions!$C$32*(1+Assumptions!$C$33)^4 | BD7: =Assumptions!$C$32*(1+Assumptions!$C$33)^4 | BE7: =Assumptions!$C$32*(1+Assumptions!$C$33)^4 | BF7: =Assumptions!$C$32*(1+Assumptions!$C$33)^4 | BG7: =Assumptions!$C$32*(1+Assumptions!$C$33)^4 | BH7: =Assumptions!$C$32*(1+Assumptions!$C$33)^4 | BI7: =Assumptions!$C$32*(1+Assumptions!$C$33)^4 | ... BM7: =Assumptions!$C$32*(1+Assumptions!$C$33)^4 | BN7: =SUM(BB7:BM7)
A8: Other variable cost | B8: ='Revenue Build-Up'!B6*(Assumptions!$C$29*(1+Assumptions!$C$30)^0) | C8: ='Revenue Build-Up'!C6*(Assumptions!$C$29*(1+Assumptions!$C$30)^0) | D8: ='Revenue Build-Up'!D6*(Assumptions!$C$29*(1+Assumptions!$C$30)^0) | E8: ='Revenue Build-Up'!E6*(Assumptions!$C$29*(1+Assumptions!$C$30)^0) | F8: ='Revenue Build-Up'!F6*(Assumptions!$C$29*(1+Assumptions!$C$30)^0) | G8: ='Revenue Build-Up'!G6*(Assumptions!$C$29*(1+Assumptions!$C$30)^0) | H8: ='Revenue Build-Up'!H6*(Assumptions!$C$29*(1+Assumptions!$C$30)^0) | I8: ='Revenue Build-Up'!I6*(Assumptions!$C$29*(1+Assumptions!$C$30)^0) | ... M8: ='Revenue Build-Up'!M6*(Assumptions!$C$29*(1+Assumptions!$C$30)^0) | N8: =SUM(B8:M8) | O8: ='Revenue Build-Up'!O6*(Assumptions!$C$29*(1+Assumptions!$C$30)^1) | P8: ='Revenue Build-Up'!P6*(Assumptions!$C$29*(1+Assumptions!$C$30)^1) | Q8: ='Revenue Build-Up'!Q6*(Assumptions!$C$29*(1+Assumptions!$C$30)^1) | R8: ='Revenue Build-Up'!R6*(Assumptions!$C$29*(1+Assumptions!$C$30)^1) | S8: ='Revenue Build-Up'!S6*(Assumptions!$C$29*(1+Assumptions!$C$30)^1) | T8: ='Revenue Build-Up'!T6*(Assumptions!$C$29*(1+Assumptions!$C$30)^1) | U8: ='Revenue Build-Up'!U6*(Assumptions!$C$29*(1+Assumptions!$C$30)^1) | V8: ='Revenue Build-Up'!V6*(Assumptions!$C$29*(1+Assumptions!$C$30)^1) | ... Z8: ='Revenue Build-Up'!Z6*(Assumptions!$C$29*(1+Assumptions!$C$30)^1) | AA8: =SUM(O8:Z8) | AB8: ='Revenue Build-Up'!AB6*(Assumptions!$C$29*(1+Assumptions!$C$30)^2) | AC8: ='Revenue Build-Up'!AC6*(Assumptions!$C$29*(1+Assumptions!$C$30)^2) | AD8: ='Revenue Build-Up'!AD6*(Assumptions!$C$29*(1+Assumptions!$C$30)^2) | AE8: ='Revenue Build-Up'!AE6*(Assumptions!$C$29*(1+Assumptions!$C$30)^2) | AF8: ='Revenue Build-Up'!AF6*(Assumptions!$C$29*(1+Assumptions!$C$30)^2) | AG8: ='Revenue Build-Up'!AG6*(Assumptions!$C$29*(1+Assumptions!$C$30)^2) | AH8: ='Revenue Build-Up'!AH6*(Assumptions!$C$29*(1+Assumptions!$C$30)^2) | AI8: ='Revenue Build-Up'!AI6*(Assumptions!$C$29*(1+Assumptions!$C$30)^2) | ... AM8: ='Revenue Build-Up'!AM6*(Assumptions!$C$29*(1+Assumptions!$C$30)^2) | AN8: =SUM(AB8:AM8) | AO8: ='Revenue Build-Up'!AO6*(Assumptions!$C$29*(1+Assumptions!$C$30)^3) | AP8: ='Revenue Build-Up'!AP6*(Assumptions!$C$29*(1+Assumptions!$C$30)^3) | AQ8: ='Revenue Build-Up'!AQ6*(Assumptions!$C$29*(1+Assumptions!$C$30)^3) | AR8: ='Revenue Build-Up'!AR6*(Assumptions!$C$29*(1+Assumptions!$C$30)^3) | AS8: ='Revenue Build-Up'!AS6*(Assumptions!$C$29*(1+Assumptions!$C$30)^3) | AT8: ='Revenue Build-Up'!AT6*(Assumptions!$C$29*(1+Assumptions!$C$30)^3) | AU8: ='Revenue Build-Up'!AU6*(Assumptions!$C$29*(1+Assumptions!$C$30)^3) | AV8: ='Revenue Build-Up'!AV6*(Assumptions!$C$29*(1+Assumptions!$C$30)^3) | ... AZ8: ='Revenue Build-Up'!AZ6*(Assumptions!$C$29*(1+Assumptions!$C$30)^3) | BA8: =SUM(AO8:AZ8) | BB8: ='Revenue Build-Up'!BB6*(Assumptions!$C$29*(1+Assumptions!$C$30)^4) | BC8: ='Revenue Build-Up'!BC6*(Assumptions!$C$29*(1+Assumptions!$C$30)^4) | BD8: ='Revenue Build-Up'!BD6*(Assumptions!$C$29*(1+Assumptions!$C$30)^4) | BE8: ='Revenue Build-Up'!BE6*(Assumptions!$C$29*(1+Assumptions!$C$30)^4) | BF8: ='Revenue Build-Up'!BF6*(Assumptions!$C$29*(1+Assumptions!$C$30)^4) | BG8: ='Revenue Build-Up'!BG6*(Assumptions!$C$29*(1+Assumptions!$C$30)^4) | BH8: ='Revenue Build-Up'!BH6*(Assumptions!$C$29*(1+Assumptions!$C$30)^4) | BI8: ='Revenue Build-Up'!BI6*(Assumptions!$C$29*(1+Assumptions!$C$30)^4) | ... BM8: ='Revenue Build-Up'!BM6*(Assumptions!$C$29*(1+Assumptions!$C$30)^4) | BN8: =SUM(BB8:BM8)
A9: =IFERROR(VLOOKUP(Assumptions!$J$5,INDUSTRY_MAP,8,FALSE()),"Factory overheads") | B9: =Assumptions!$C$34*(1+Assumptions!$C$35)^0 | C9: =Assumptions!$C$34*(1+Assumptions!$C$35)^0 | D9: =Assumptions!$C$34*(1+Assumptions!$C$35)^0 | E9: =Assumptions!$C$34*(1+Assumptions!$C$35)^0 | F9: =Assumptions!$C$34*(1+Assumptions!$C$35)^0 | G9: =Assumptions!$C$34*(1+Assumptions!$C$35)^0 | H9: =Assumptions!$C$34*(1+Assumptions!$C$35)^0 | I9: =Assumptions!$C$34*(1+Assumptions!$C$35)^0 | ... M9: =Assumptions!$C$34*(1+Assumptions!$C$35)^0 | N9: =SUM(B9:M9) | O9: =Assumptions!$C$34*(1+Assumptions!$C$35)^1 | P9: =Assumptions!$C$34*(1+Assumptions!$C$35)^1 | Q9: =Assumptions!$C$34*(1+Assumptions!$C$35)^1 | R9: =Assumptions!$C$34*(1+Assumptions!$C$35)^1 | S9: =Assumptions!$C$34*(1+Assumptions!$C$35)^1 | T9: =Assumptions!$C$34*(1+Assumptions!$C$35)^1 | U9: =Assumptions!$C$34*(1+Assumptions!$C$35)^1 | V9: =Assumptions!$C$34*(1+Assumptions!$C$35)^1 | ... Z9: =Assumptions!$C$34*(1+Assumptions!$C$35)^1 | AA9: =SUM(O9:Z9) | AB9: =Assumptions!$C$34*(1+Assumptions!$C$35)^2 | AC9: =Assumptions!$C$34*(1+Assumptions!$C$35)^2 | AD9: =Assumptions!$C$34*(1+Assumptions!$C$35)^2 | AE9: =Assumptions!$C$34*(1+Assumptions!$C$35)^2 | AF9: =Assumptions!$C$34*(1+Assumptions!$C$35)^2 | AG9: =Assumptions!$C$34*(1+Assumptions!$C$35)^2 | AH9: =Assumptions!$C$34*(1+Assumptions!$C$35)^2 | AI9: =Assumptions!$C$34*(1+Assumptions!$C$35)^2 | ... AM9: =Assumptions!$C$34*(1+Assumptions!$C$35)^2 | AN9: =SUM(AB9:AM9) | AO9: =Assumptions!$C$34*(1+Assumptions!$C$35)^3 | AP9: =Assumptions!$C$34*(1+Assumptions!$C$35)^3 | AQ9: =Assumptions!$C$34*(1+Assumptions!$C$35)^3 | AR9: =Assumptions!$C$34*(1+Assumptions!$C$35)^3 | AS9: =Assumptions!$C$34*(1+Assumptions!$C$35)^3 | AT9: =Assumptions!$C$34*(1+Assumptions!$C$35)^3 | AU9: =Assumptions!$C$34*(1+Assumptions!$C$35)^3 | AV9: =Assumptions!$C$34*(1+Assumptions!$C$35)^3 | ... AZ9: =Assumptions!$C$34*(1+Assumptions!$C$35)^3 | BA9: =SUM(AO9:AZ9) | BB9: =Assumptions!$C$34*(1+Assumptions!$C$35)^4 | BC9: =Assumptions!$C$34*(1+Assumptions!$C$35)^4 | BD9: =Assumptions!$C$34*(1+Assumptions!$C$35)^4 | BE9: =Assumptions!$C$34*(1+Assumptions!$C$35)^4 | BF9: =Assumptions!$C$34*(1+Assumptions!$C$35)^4 | BG9: =Assumptions!$C$34*(1+Assumptions!$C$35)^4 | BH9: =Assumptions!$C$34*(1+Assumptions!$C$35)^4 | BI9: =Assumptions!$C$34*(1+Assumptions!$C$35)^4 | ... BM9: =Assumptions!$C$34*(1+Assumptions!$C$35)^4 | BN9: =SUM(BB9:BM9)
A10: Repairs & maintenance | B10: =Assumptions!$C$36*(1+Assumptions!$C$37)^0 | C10: =Assumptions!$C$36*(1+Assumptions!$C$37)^0 | D10: =Assumptions!$C$36*(1+Assumptions!$C$37)^0 | E10: =Assumptions!$C$36*(1+Assumptions!$C$37)^0 | F10: =Assumptions!$C$36*(1+Assumptions!$C$37)^0 | G10: =Assumptions!$C$36*(1+Assumptions!$C$37)^0 | H10: =Assumptions!$C$36*(1+Assumptions!$C$37)^0 | I10: =Assumptions!$C$36*(1+Assumptions!$C$37)^0 | ... M10: =Assumptions!$C$36*(1+Assumptions!$C$37)^0 | N10: =SUM(B10:M10) | O10: =Assumptions!$C$36*(1+Assumptions!$C$37)^1 | P10: =Assumptions!$C$36*(1+Assumptions!$C$37)^1 | Q10: =Assumptions!$C$36*(1+Assumptions!$C$37)^1 | R10: =Assumptions!$C$36*(1+Assumptions!$C$37)^1 | S10: =Assumptions!$C$36*(1+Assumptions!$C$37)^1 | T10: =Assumptions!$C$36*(1+Assumptions!$C$37)^1 | U10: =Assumptions!$C$36*(1+Assumptions!$C$37)^1 | V10: =Assumptions!$C$36*(1+Assumptions!$C$37)^1 | ... Z10: =Assumptions!$C$36*(1+Assumptions!$C$37)^1 | AA10: =SUM(O10:Z10) | AB10: =Assumptions!$C$36*(1+Assumptions!$C$37)^2 | AC10: =Assumptions!$C$36*(1+Assumptions!$C$37)^2 | AD10: =Assumptions!$C$36*(1+Assumptions!$C$37)^2 | AE10: =Assumptions!$C$36*(1+Assumptions!$C$37)^2 | AF10: =Assumptions!$C$36*(1+Assumptions!$C$37)^2 | AG10: =Assumptions!$C$36*(1+Assumptions!$C$37)^2 | AH10: =Assumptions!$C$36*(1+Assumptions!$C$37)^2 | AI10: =Assumptions!$C$36*(1+Assumptions!$C$37)^2 | ... AM10: =Assumptions!$C$36*(1+Assumptions!$C$37)^2 | AN10: =SUM(AB10:AM10) | AO10: =Assumptions!$C$36*(1+Assumptions!$C$37)^3 | AP10: =Assumptions!$C$36*(1+Assumptions!$C$37)^3 | AQ10: =Assumptions!$C$36*(1+Assumptions!$C$37)^3 | AR10: =Assumptions!$C$36*(1+Assumptions!$C$37)^3 | AS10: =Assumptions!$C$36*(1+Assumptions!$C$37)^3 | AT10: =Assumptions!$C$36*(1+Assumptions!$C$37)^3 | AU10: =Assumptions!$C$36*(1+Assumptions!$C$37)^3 | AV10: =Assumptions!$C$36*(1+Assumptions!$C$37)^3 | ... AZ10: =Assumptions!$C$36*(1+Assumptions!$C$37)^3 | BA10: =SUM(AO10:AZ10) | BB10: =Assumptions!$C$36*(1+Assumptions!$C$37)^4 | BC10: =Assumptions!$C$36*(1+Assumptions!$C$37)^4 | BD10: =Assumptions!$C$36*(1+Assumptions!$C$37)^4 | BE10: =Assumptions!$C$36*(1+Assumptions!$C$37)^4 | BF10: =Assumptions!$C$36*(1+Assumptions!$C$37)^4 | BG10: =Assumptions!$C$36*(1+Assumptions!$C$37)^4 | BH10: =Assumptions!$C$36*(1+Assumptions!$C$37)^4 | BI10: =Assumptions!$C$36*(1+Assumptions!$C$37)^4 | ... BM10: =Assumptions!$C$36*(1+Assumptions!$C$37)^4 | BN10: =SUM(BB10:BM10)
A11: Administrative expenses | B11: =Assumptions!$C$38*(1+Assumptions!$C$39)^0 | C11: =Assumptions!$C$38*(1+Assumptions!$C$39)^0 | D11: =Assumptions!$C$38*(1+Assumptions!$C$39)^0 | E11: =Assumptions!$C$38*(1+Assumptions!$C$39)^0 | F11: =Assumptions!$C$38*(1+Assumptions!$C$39)^0 | G11: =Assumptions!$C$38*(1+Assumptions!$C$39)^0 | H11: =Assumptions!$C$38*(1+Assumptions!$C$39)^0 | I11: =Assumptions!$C$38*(1+Assumptions!$C$39)^0 | ... M11: =Assumptions!$C$38*(1+Assumptions!$C$39)^0 | N11: =SUM(B11:M11) | O11: =Assumptions!$C$38*(1+Assumptions!$C$39)^1 | P11: =Assumptions!$C$38*(1+Assumptions!$C$39)^1 | Q11: =Assumptions!$C$38*(1+Assumptions!$C$39)^1 | R11: =Assumptions!$C$38*(1+Assumptions!$C$39)^1 | S11: =Assumptions!$C$38*(1+Assumptions!$C$39)^1 | T11: =Assumptions!$C$38*(1+Assumptions!$C$39)^1 | U11: =Assumptions!$C$38*(1+Assumptions!$C$39)^1 | V11: =Assumptions!$C$38*(1+Assumptions!$C$39)^1 | ... Z11: =Assumptions!$C$38*(1+Assumptions!$C$39)^1 | AA11: =SUM(O11:Z11) | AB11: =Assumptions!$C$38*(1+Assumptions!$C$39)^2 | AC11: =Assumptions!$C$38*(1+Assumptions!$C$39)^2 | AD11: =Assumptions!$C$38*(1+Assumptions!$C$39)^2 | AE11: =Assumptions!$C$38*(1+Assumptions!$C$39)^2 | AF11: =Assumptions!$C$38*(1+Assumptions!$C$39)^2 | AG11: =Assumptions!$C$38*(1+Assumptions!$C$39)^2 | AH11: =Assumptions!$C$38*(1+Assumptions!$C$39)^2 | AI11: =Assumptions!$C$38*(1+Assumptions!$C$39)^2 | ... AM11: =Assumptions!$C$38*(1+Assumptions!$C$39)^2 | AN11: =SUM(AB11:AM11) | AO11: =Assumptions!$C$38*(1+Assumptions!$C$39)^3 | AP11: =Assumptions!$C$38*(1+Assumptions!$C$39)^3 | AQ11: =Assumptions!$C$38*(1+Assumptions!$C$39)^3 | AR11: =Assumptions!$C$38*(1+Assumptions!$C$39)^3 | AS11: =Assumptions!$C$38*(1+Assumptions!$C$39)^3 | AT11: =Assumptions!$C$38*(1+Assumptions!$C$39)^3 | AU11: =Assumptions!$C$38*(1+Assumptions!$C$39)^3 | AV11: =Assumptions!$C$38*(1+Assumptions!$C$39)^3 | ... AZ11: =Assumptions!$C$38*(1+Assumptions!$C$39)^3 | BA11: =SUM(AO11:AZ11) | BB11: =Assumptions!$C$38*(1+Assumptions!$C$39)^4 | BC11: =Assumptions!$C$38*(1+Assumptions!$C$39)^4 | BD11: =Assumptions!$C$38*(1+Assumptions!$C$39)^4 | BE11: =Assumptions!$C$38*(1+Assumptions!$C$39)^4 | BF11: =Assumptions!$C$38*(1+Assumptions!$C$39)^4 | BG11: =Assumptions!$C$38*(1+Assumptions!$C$39)^4 | BH11: =Assumptions!$C$38*(1+Assumptions!$C$39)^4 | BI11: =Assumptions!$C$38*(1+Assumptions!$C$39)^4 | ... BM11: =Assumptions!$C$38*(1+Assumptions!$C$39)^4 | BN11: =SUM(BB11:BM11)
A12: Selling & distribution | B12: ='Revenue Build-Up'!B26*Assumptions!$C$40 | C12: ='Revenue Build-Up'!C26*Assumptions!$C$40 | D12: ='Revenue Build-Up'!D26*Assumptions!$C$40 | E12: ='Revenue Build-Up'!E26*Assumptions!$C$40 | F12: ='Revenue Build-Up'!F26*Assumptions!$C$40 | G12: ='Revenue Build-Up'!G26*Assumptions!$C$40 | H12: ='Revenue Build-Up'!H26*Assumptions!$C$40 | I12: ='Revenue Build-Up'!I26*Assumptions!$C$40 | ... M12: ='Revenue Build-Up'!M26*Assumptions!$C$40 | N12: =SUM(B12:M12) | O12: ='Revenue Build-Up'!O26*Assumptions!$C$40 | P12: ='Revenue Build-Up'!P26*Assumptions!$C$40 | Q12: ='Revenue Build-Up'!Q26*Assumptions!$C$40 | R12: ='Revenue Build-Up'!R26*Assumptions!$C$40 | S12: ='Revenue Build-Up'!S26*Assumptions!$C$40 | T12: ='Revenue Build-Up'!T26*Assumptions!$C$40 | U12: ='Revenue Build-Up'!U26*Assumptions!$C$40 | V12: ='Revenue Build-Up'!V26*Assumptions!$C$40 | ... Z12: ='Revenue Build-Up'!Z26*Assumptions!$C$40 | AA12: =SUM(O12:Z12) | AB12: ='Revenue Build-Up'!AB26*Assumptions!$C$40 | AC12: ='Revenue Build-Up'!AC26*Assumptions!$C$40 | AD12: ='Revenue Build-Up'!AD26*Assumptions!$C$40 | AE12: ='Revenue Build-Up'!AE26*Assumptions!$C$40 | AF12: ='Revenue Build-Up'!AF26*Assumptions!$C$40 | AG12: ='Revenue Build-Up'!AG26*Assumptions!$C$40 | AH12: ='Revenue Build-Up'!AH26*Assumptions!$C$40 | AI12: ='Revenue Build-Up'!AI26*Assumptions!$C$40 | ... AM12: ='Revenue Build-Up'!AM26*Assumptions!$C$40 | AN12: =SUM(AB12:AM12) | AO12: ='Revenue Build-Up'!AO26*Assumptions!$C$40 | AP12: ='Revenue Build-Up'!AP26*Assumptions!$C$40 | AQ12: ='Revenue Build-Up'!AQ26*Assumptions!$C$40 | AR12: ='Revenue Build-Up'!AR26*Assumptions!$C$40 | AS12: ='Revenue Build-Up'!AS26*Assumptions!$C$40 | AT12: ='Revenue Build-Up'!AT26*Assumptions!$C$40 | AU12: ='Revenue Build-Up'!AU26*Assumptions!$C$40 | AV12: ='Revenue Build-Up'!AV26*Assumptions!$C$40 | ... AZ12: ='Revenue Build-Up'!AZ26*Assumptions!$C$40 | BA12: =SUM(AO12:AZ12) | BB12: ='Revenue Build-Up'!BB26*Assumptions!$C$40 | BC12: ='Revenue Build-Up'!BC26*Assumptions!$C$40 | BD12: ='Revenue Build-Up'!BD26*Assumptions!$C$40 | BE12: ='Revenue Build-Up'!BE26*Assumptions!$C$40 | BF12: ='Revenue Build-Up'!BF26*Assumptions!$C$40 | BG12: ='Revenue Build-Up'!BG26*Assumptions!$C$40 | BH12: ='Revenue Build-Up'!BH26*Assumptions!$C$40 | BI12: ='Revenue Build-Up'!BI26*Assumptions!$C$40 | ... BM12: ='Revenue Build-Up'!BM26*Assumptions!$C$40 | BN12: =SUM(BB12:BM12)
A13: Depreciation | B13: =(Assumptions!$C$43*Assumptions!$C$44+Assumptions!$C$45*Assumptions!$C$46+Assumptions!$C$47*Assumptions!$C$48)/12 | C13: =(Assumptions!$C$43*Assumptions!$C$44+Assumptions!$C$45*Assumptions!$C$46+Assumptions!$C$47*Assumptions!$C$48)/12 | D13: =(Assumptions!$C$43*Assumptions!$C$44+Assumptions!$C$45*Assumptions!$C$46+Assumptions!$C$47*Assumptions!$C$48)/12 | E13: =(Assumptions!$C$43*Assumptions!$C$44+Assumptions!$C$45*Assumptions!$C$46+Assumptions!$C$47*Assumptions!$C$48)/12 | F13: =(Assumptions!$C$43*Assumptions!$C$44+Assumptions!$C$45*Assumptions!$C$46+Assumptions!$C$47*Assumptions!$C$48)/12 | G13: =(Assumptions!$C$43*Assumptions!$C$44+Assumptions!$C$45*Assumptions!$C$46+Assumptions!$C$47*Assumptions!$C$48)/12 | H13: =(Assumptions!$C$43*Assumptions!$C$44+Assumptions!$C$45*Assumptions!$C$46+Assumptions!$C$47*Assumptions!$C$48)/12 | I13: =(Assumptions!$C$43*Assumptions!$C$44+Assumptions!$C$45*Assumptions!$C$46+Assumptions!$C$47*Assumptions!$C$48)/12 | ... M13: =(Assumptions!$C$43*Assumptions!$C$44+Assumptions!$C$45*Assumptions!$C$46+Assumptions!$C$47*Assumptions!$C$48)/12 | N13: =SUM(B13:M13) | O13: =(Assumptions!$C$43*Assumptions!$C$44+Assumptions!$C$45*Assumptions!$C$46+Assumptions!$C$47*Assumptions!$C$48)/12 | P13: =(Assumptions!$C$43*Assumptions!$C$44+Assumptions!$C$45*Assumptions!$C$46+Assumptions!$C$47*Assumptions!$C$48)/12 | Q13: =(Assumptions!$C$43*Assumptions!$C$44+Assumptions!$C$45*Assumptions!$C$46+Assumptions!$C$47*Assumptions!$C$48)/12 | R13: =(Assumptions!$C$43*Assumptions!$C$44+Assumptions!$C$45*Assumptions!$C$46+Assumptions!$C$47*Assumptions!$C$48)/12 | S13: =(Assumptions!$C$43*Assumptions!$C$44+Assumptions!$C$45*Assumptions!$C$46+Assumptions!$C$47*Assumptions!$C$48)/12 | T13: =(Assumptions!$C$43*Assumptions!$C$44+Assumptions!$C$45*Assumptions!$C$46+Assumptions!$C$47*Assumptions!$C$48)/12 | U13: =(Assumptions!$C$43*Assumptions!$C$44+Assumptions!$C$45*Assumptions!$C$46+Assumptions!$C$47*Assumptions!$C$48)/12 | V13: =(Assumptions!$C$43*Assumptions!$C$44+Assumptions!$C$45*Assumptions!$C$46+Assumptions!$C$47*Assumptions!$C$48)/12 | ... Z13: =(Assumptions!$C$43*Assumptions!$C$44+Assumptions!$C$45*Assumptions!$C$46+Assumptions!$C$47*Assumptions!$C$48)/12 | AA13: =SUM(O13:Z13) | AB13: =(Assumptions!$C$43*Assumptions!$C$44+Assumptions!$C$45*Assumptions!$C$46+Assumptions!$C$47*Assumptions!$C$48)/12 | AC13: =(Assumptions!$C$43*Assumptions!$C$44+Assumptions!$C$45*Assumptions!$C$46+Assumptions!$C$47*Assumptions!$C$48)/12 | AD13: =(Assumptions!$C$43*Assumptions!$C$44+Assumptions!$C$45*Assumptions!$C$46+Assumptions!$C$47*Assumptions!$C$48)/12 | AE13: =(Assumptions!$C$43*Assumptions!$C$44+Assumptions!$C$45*Assumptions!$C$46+Assumptions!$C$47*Assumptions!$C$48)/12 | AF13: =(Assumptions!$C$43*Assumptions!$C$44+Assumptions!$C$45*Assumptions!$C$46+Assumptions!$C$47*Assumptions!$C$48)/12 | AG13: =(Assumptions!$C$43*Assumptions!$C$44+Assumptions!$C$45*Assumptions!$C$46+Assumptions!$C$47*Assumptions!$C$48)/12 | AH13: =(Assumptions!$C$43*Assumptions!$C$44+Assumptions!$C$45*Assumptions!$C$46+Assumptions!$C$47*Assumptions!$C$48)/12 | AI13: =(Assumptions!$C$43*Assumptions!$C$44+Assumptions!$C$45*Assumptions!$C$46+Assumptions!$C$47*Assumptions!$C$48)/12 | ... AM13: =(Assumptions!$C$43*Assumptions!$C$44+Assumptions!$C$45*Assumptions!$C$46+Assumptions!$C$47*Assumptions!$C$48)/12 | AN13: =SUM(AB13:AM13) | AO13: =(Assumptions!$C$43*Assumptions!$C$44+Assumptions!$C$45*Assumptions!$C$46+Assumptions!$C$47*Assumptions!$C$48)/12 | AP13: =(Assumptions!$C$43*Assumptions!$C$44+Assumptions!$C$45*Assumptions!$C$46+Assumptions!$C$47*Assumptions!$C$48)/12 | AQ13: =(Assumptions!$C$43*Assumptions!$C$44+Assumptions!$C$45*Assumptions!$C$46+Assumptions!$C$47*Assumptions!$C$48)/12 | AR13: =(Assumptions!$C$43*Assumptions!$C$44+Assumptions!$C$45*Assumptions!$C$46+Assumptions!$C$47*Assumptions!$C$48)/12 | AS13: =(Assumptions!$C$43*Assumptions!$C$44+Assumptions!$C$45*Assumptions!$C$46+Assumptions!$C$47*Assumptions!$C$48)/12 | AT13: =(Assumptions!$C$43*Assumptions!$C$44+Assumptions!$C$45*Assumptions!$C$46+Assumptions!$C$47*Assumptions!$C$48)/12 | AU13: =(Assumptions!$C$43*Assumptions!$C$44+Assumptions!$C$45*Assumptions!$C$46+Assumptions!$C$47*Assumptions!$C$48)/12 | AV13: =(Assumptions!$C$43*Assumptions!$C$44+Assumptions!$C$45*Assumptions!$C$46+Assumptions!$C$47*Assumptions!$C$48)/12 | ... AZ13: =(Assumptions!$C$43*Assumptions!$C$44+Assumptions!$C$45*Assumptions!$C$46+Assumptions!$C$47*Assumptions!$C$48)/12 | BA13: =SUM(AO13:AZ13) | BB13: =(Assumptions!$C$43*Assumptions!$C$44+Assumptions!$C$45*Assumptions!$C$46+Assumptions!$C$47*Assumptions!$C$48)/12 | BC13: =(Assumptions!$C$43*Assumptions!$C$44+Assumptions!$C$45*Assumptions!$C$46+Assumptions!$C$47*Assumptions!$C$48)/12 | BD13: =(Assumptions!$C$43*Assumptions!$C$44+Assumptions!$C$45*Assumptions!$C$46+Assumptions!$C$47*Assumptions!$C$48)/12 | BE13: =(Assumptions!$C$43*Assumptions!$C$44+Assumptions!$C$45*Assumptions!$C$46+Assumptions!$C$47*Assumptions!$C$48)/12 | BF13: =(Assumptions!$C$43*Assumptions!$C$44+Assumptions!$C$45*Assumptions!$C$46+Assumptions!$C$47*Assumptions!$C$48)/12 | BG13: =(Assumptions!$C$43*Assumptions!$C$44+Assumptions!$C$45*Assumptions!$C$46+Assumptions!$C$47*Assumptions!$C$48)/12 | BH13: =(Assumptions!$C$43*Assumptions!$C$44+Assumptions!$C$45*Assumptions!$C$46+Assumptions!$C$47*Assumptions!$C$48)/12 | BI13: =(Assumptions!$C$43*Assumptions!$C$44+Assumptions!$C$45*Assumptions!$C$46+Assumptions!$C$47*Assumptions!$C$48)/12 | ... BM13: =(Assumptions!$C$43*Assumptions!$C$44+Assumptions!$C$45*Assumptions!$C$46+Assumptions!$C$47*Assumptions!$C$48)/12 | BN13: =SUM(BB13:BM13)
A14: Interest — Term Loan | B14: =Repayment!C6/12+'Existing Loan'!C14/12 | C14: =Repayment!C6/12+'Existing Loan'!C14/12 | D14: =Repayment!C6/12+'Existing Loan'!C14/12 | E14: =Repayment!C6/12+'Existing Loan'!C14/12 | F14: =Repayment!C6/12+'Existing Loan'!C14/12 | G14: =Repayment!C6/12+'Existing Loan'!C14/12 | H14: =Repayment!C6/12+'Existing Loan'!C14/12 | I14: =Repayment!C6/12+'Existing Loan'!C14/12 | J14: =Repayment!C6/12+'Existing Loan'!C14/12 | K14: =Repayment!C6/12+'Existing Loan'!C14/12 | L14: =Repayment!C6/12+'Existing Loan'!C14/12 | M14: =Repayment!C6/12+'Existing Loan'!C14/12 | N14: =SUM(B14:M14) | O14: =Repayment!D6/12+'Existing Loan'!D14/12 | P14: =Repayment!D6/12+'Existing Loan'!D14/12 | Q14: =Repayment!D6/12+'Existing Loan'!D14/12 | R14: =Repayment!D6/12+'Existing Loan'!D14/12 | S14: =Repayment!D6/12+'Existing Loan'!D14/12 | T14: =Repayment!D6/12+'Existing Loan'!D14/12 | U14: =Repayment!D6/12+'Existing Loan'!D14/12 | V14: =Repayment!D6/12+'Existing Loan'!D14/12 | W14: =Repayment!D6/12+'Existing Loan'!D14/12 | X14: =Repayment!D6/12+'Existing Loan'!D14/12 | Y14: =Repayment!D6/12+'Existing Loan'!D14/12 | Z14: =Repayment!D6/12+'Existing Loan'!D14/12 | AA14: =SUM(O14:Z14) | AB14: =Repayment!E6/12+'Existing Loan'!E14/12 | AC14: =Repayment!E6/12+'Existing Loan'!E14/12 | AD14: =Repayment!E6/12+'Existing Loan'!E14/12 | AE14: =Repayment!E6/12+'Existing Loan'!E14/12 | AF14: =Repayment!E6/12+'Existing Loan'!E14/12 | AG14: =Repayment!E6/12+'Existing Loan'!E14/12 | AH14: =Repayment!E6/12+'Existing Loan'!E14/12 | AI14: =Repayment!E6/12+'Existing Loan'!E14/12 | AJ14: =Repayment!E6/12+'Existing Loan'!E14/12 | AK14: =Repayment!E6/12+'Existing Loan'!E14/12 | AL14: =Repayment!E6/12+'Existing Loan'!E14/12 | AM14: =Repayment!E6/12+'Existing Loan'!E14/12 | AN14: =SUM(AB14:AM14) | AO14: =Repayment!F6/12+'Existing Loan'!F14/12 | AP14: =Repayment!F6/12+'Existing Loan'!F14/12 | AQ14: =Repayment!F6/12+'Existing Loan'!F14/12 | AR14: =Repayment!F6/12+'Existing Loan'!F14/12 | AS14: =Repayment!F6/12+'Existing Loan'!F14/12 | AT14: =Repayment!F6/12+'Existing Loan'!F14/12 | AU14: =Repayment!F6/12+'Existing Loan'!F14/12 | AV14: =Repayment!F6/12+'Existing Loan'!F14/12 | AW14: =Repayment!F6/12+'Existing Loan'!F14/12 | AX14: =Repayment!F6/12+'Existing Loan'!F14/12 | AY14: =Repayment!F6/12+'Existing Loan'!F14/12 | AZ14: =Repayment!F6/12+'Existing Loan'!F14/12 | BA14: =SUM(AO14:AZ14) | BB14: =Repayment!G6/12+'Existing Loan'!G14/12 | BC14: =Repayment!G6/12+'Existing Loan'!G14/12 | BD14: =Repayment!G6/12+'Existing Loan'!G14/12 | BE14: =Repayment!G6/12+'Existing Loan'!G14/12 | BF14: =Repayment!G6/12+'Existing Loan'!G14/12 | BG14: =Repayment!G6/12+'Existing Loan'!G14/12 | BH14: =Repayment!G6/12+'Existing Loan'!G14/12 | BI14: =Repayment!G6/12+'Existing Loan'!G14/12 | BJ14: =Repayment!G6/12+'Existing Loan'!G14/12 | BK14: =Repayment!G6/12+'Existing Loan'!G14/12 | BL14: =Repayment!G6/12+'Existing Loan'!G14/12 | BM14: =Repayment!G6/12+'Existing Loan'!G14/12 | BN14: =SUM(BB14:BM14)
A15: Interest — Working Capital | B15: =Form_V_MPBF!C11*Assumptions!$C$13/12 | C15: =Form_V_MPBF!C11*Assumptions!$C$13/12 | D15: =Form_V_MPBF!C11*Assumptions!$C$13/12 | E15: =Form_V_MPBF!C11*Assumptions!$C$13/12 | F15: =Form_V_MPBF!C11*Assumptions!$C$13/12 | G15: =Form_V_MPBF!C11*Assumptions!$C$13/12 | H15: =Form_V_MPBF!C11*Assumptions!$C$13/12 | I15: =Form_V_MPBF!C11*Assumptions!$C$13/12 | J15: =Form_V_MPBF!C11*Assumptions!$C$13/12 | K15: =Form_V_MPBF!C11*Assumptions!$C$13/12 | L15: =Form_V_MPBF!C11*Assumptions!$C$13/12 | M15: =Form_V_MPBF!C11*Assumptions!$C$13/12 | N15: =SUM(B15:M15) | O15: =Form_V_MPBF!D11*Assumptions!$C$13/12 | P15: =Form_V_MPBF!D11*Assumptions!$C$13/12 | Q15: =Form_V_MPBF!D11*Assumptions!$C$13/12 | R15: =Form_V_MPBF!D11*Assumptions!$C$13/12 | S15: =Form_V_MPBF!D11*Assumptions!$C$13/12 | T15: =Form_V_MPBF!D11*Assumptions!$C$13/12 | U15: =Form_V_MPBF!D11*Assumptions!$C$13/12 | V15: =Form_V_MPBF!D11*Assumptions!$C$13/12 | W15: =Form_V_MPBF!D11*Assumptions!$C$13/12 | X15: =Form_V_MPBF!D11*Assumptions!$C$13/12 | Y15: =Form_V_MPBF!D11*Assumptions!$C$13/12 | Z15: =Form_V_MPBF!D11*Assumptions!$C$13/12 | AA15: =SUM(O15:Z15) | AB15: =Form_V_MPBF!E11*Assumptions!$C$13/12 | AC15: =Form_V_MPBF!E11*Assumptions!$C$13/12 | AD15: =Form_V_MPBF!E11*Assumptions!$C$13/12 | AE15: =Form_V_MPBF!E11*Assumptions!$C$13/12 | AF15: =Form_V_MPBF!E11*Assumptions!$C$13/12 | AG15: =Form_V_MPBF!E11*Assumptions!$C$13/12 | AH15: =Form_V_MPBF!E11*Assumptions!$C$13/12 | AI15: =Form_V_MPBF!E11*Assumptions!$C$13/12 | AJ15: =Form_V_MPBF!E11*Assumptions!$C$13/12 | AK15: =Form_V_MPBF!E11*Assumptions!$C$13/12 | AL15: =Form_V_MPBF!E11*Assumptions!$C$13/12 | AM15: =Form_V_MPBF!E11*Assumptions!$C$13/12 | AN15: =SUM(AB15:AM15) | AO15: =Form_V_MPBF!F11*Assumptions!$C$13/12 | AP15: =Form_V_MPBF!F11*Assumptions!$C$13/12 | AQ15: =Form_V_MPBF!F11*Assumptions!$C$13/12 | AR15: =Form_V_MPBF!F11*Assumptions!$C$13/12 | AS15: =Form_V_MPBF!F11*Assumptions!$C$13/12 | AT15: =Form_V_MPBF!F11*Assumptions!$C$13/12 | AU15: =Form_V_MPBF!F11*Assumptions!$C$13/12 | AV15: =Form_V_MPBF!F11*Assumptions!$C$13/12 | AW15: =Form_V_MPBF!F11*Assumptions!$C$13/12 | AX15: =Form_V_MPBF!F11*Assumptions!$C$13/12 | AY15: =Form_V_MPBF!F11*Assumptions!$C$13/12 | AZ15: =Form_V_MPBF!F11*Assumptions!$C$13/12 | BA15: =SUM(AO15:AZ15) | BB15: =Form_V_MPBF!G11*Assumptions!$C$13/12 | BC15: =Form_V_MPBF!G11*Assumptions!$C$13/12 | BD15: =Form_V_MPBF!G11*Assumptions!$C$13/12 | BE15: =Form_V_MPBF!G11*Assumptions!$C$13/12 | BF15: =Form_V_MPBF!G11*Assumptions!$C$13/12 | BG15: =Form_V_MPBF!G11*Assumptions!$C$13/12 | BH15: =Form_V_MPBF!G11*Assumptions!$C$13/12 | BI15: =Form_V_MPBF!G11*Assumptions!$C$13/12 | BJ15: =Form_V_MPBF!G11*Assumptions!$C$13/12 | BK15: =Form_V_MPBF!G11*Assumptions!$C$13/12 | BL15: =Form_V_MPBF!G11*Assumptions!$C$13/12 | BM15: =Form_V_MPBF!G11*Assumptions!$C$13/12 | BN15: =SUM(BB15:BM15)
A16: Total Operating Expenses | B16: =SUM(B5:B15) | C16: =SUM(C5:C15) | D16: =SUM(D5:D15) | E16: =SUM(E5:E15) | F16: =SUM(F5:F15) | G16: =SUM(G5:G15) | H16: =SUM(H5:H15) | I16: =SUM(I5:I15) | ... M16: =SUM(M5:M15) | N16: =SUM(B16:M16) | O16: =SUM(O5:O15) | P16: =SUM(P5:P15) | Q16: =SUM(Q5:Q15) | R16: =SUM(R5:R15) | S16: =SUM(S5:S15) | T16: =SUM(T5:T15) | U16: =SUM(U5:U15) | V16: =SUM(V5:V15) | ... Z16: =SUM(Z5:Z15) | AA16: =SUM(O16:Z16) | AB16: =SUM(AB5:AB15) | AC16: =SUM(AC5:AC15) | AD16: =SUM(AD5:AD15) | AE16: =SUM(AE5:AE15) | AF16: =SUM(AF5:AF15) | AG16: =SUM(AG5:AG15) | AH16: =SUM(AH5:AH15) | AI16: =SUM(AI5:AI15) | ... AM16: =SUM(AM5:AM15) | AN16: =SUM(AB16:AM16) | AO16: =SUM(AO5:AO15) | AP16: =SUM(AP5:AP15) | AQ16: =SUM(AQ5:AQ15) | AR16: =SUM(AR5:AR15) | AS16: =SUM(AS5:AS15) | AT16: =SUM(AT5:AT15) | AU16: =SUM(AU5:AU15) | AV16: =SUM(AV5:AV15) | ... AZ16: =SUM(AZ5:AZ15) | BA16: =SUM(AO16:AZ16) | BB16: =SUM(BB5:BB15) | BC16: =SUM(BC5:BC15) | BD16: =SUM(BD5:BD15) | BE16: =SUM(BE5:BE15) | BF16: =SUM(BF5:BF15) | BG16: =SUM(BG5:BG15) | BH16: =SUM(BH5:BH15) | BI16: =SUM(BI5:BI15) | ... BM16: =SUM(BM5:BM15) | BN16: =SUM(BB16:BM16)

Sheet P & L
A1: PROFITABILITY (P&L) — 60-MONTH PROJECTION
A2: EBITDA → EBIT → PBT → PAT, fully linked to Sales and Expenses.
B3: YEAR 1 | O3: YEAR 2 | AB3: YEAR 3 | AO3: YEAR 4 | BB3: YEAR 5
A4: Particulars | B4: M1 | C4: M2 | D4: M3 | E4: M4 | F4: M5 | G4: M6 | H4: M7 | I4: M8 | J4: M9 | K4: M10 | L4: M11 | M4: M12 | N4: Yr 1 Total | O4: M13 | P4: M14 | Q4: M15 | R4: M16 | S4: M17 | T4: M18 | U4: M19 | V4: M20 | W4: M21 | X4: M22 | Y4: M23 | Z4: M24 | AA4: Yr 2 Total | AB4: M25 | AC4: M26 | AD4: M27 | AE4: M28 | AF4: M29 | AG4: M30 | AH4: M31 | AI4: M32 | AJ4: M33 | AK4: M34 | AL4: M35 | AM4: M36 | AN4: Yr 3 Total | AO4: M37 | AP4: M38 | AQ4: M39 | AR4: M40 | AS4: M41 | AT4: M42 | AU4: M43 | AV4: M44 | AW4: M45 | AX4: M46 | AY4: M47 | AZ4: M48 | BA4: Yr 4 Total | BB4: M49 | BC4: M50 | BD4: M51 | BE4: M52 | BF4: M53 | BG4: M54 | BH4: M55 | BI4: M56 | BJ4: M57 | BK4: M58 | BL4: M59 | BM4: M60 | BN4: Yr 5 Total
A5: Trips / consignments revenue | B5: ='Revenue Build-Up'!B8 | C5: ='Revenue Build-Up'!C8 | D5: ='Revenue Build-Up'!D8 | E5: ='Revenue Build-Up'!E8 | F5: ='Revenue Build-Up'!F8 | G5: ='Revenue Build-Up'!G8 | H5: ='Revenue Build-Up'!H8 | I5: ='Revenue Build-Up'!I8 | ... M5: ='Revenue Build-Up'!M8 | N5: =SUM(B5:M5) | O5: ='Revenue Build-Up'!O8 | P5: ='Revenue Build-Up'!P8 | Q5: ='Revenue Build-Up'!Q8 | R5: ='Revenue Build-Up'!R8 | S5: ='Revenue Build-Up'!S8 | T5: ='Revenue Build-Up'!T8 | U5: ='Revenue Build-Up'!U8 | V5: ='Revenue Build-Up'!V8 | ... Z5: ='Revenue Build-Up'!Z8 | AA5: =SUM(O5:Z5) | AB5: ='Revenue Build-Up'!AB8 | AC5: ='Revenue Build-Up'!AC8 | AD5: ='Revenue Build-Up'!AD8 | AE5: ='Revenue Build-Up'!AE8 | AF5: ='Revenue Build-Up'!AF8 | AG5: ='Revenue Build-Up'!AG8 | AH5: ='Revenue Build-Up'!AH8 | AI5: ='Revenue Build-Up'!AI8 | ... AM5: ='Revenue Build-Up'!AM8 | AN5: =SUM(AB5:AM5) | AO5: ='Revenue Build-Up'!AO8 | AP5: ='Revenue Build-Up'!AP8 | AQ5: ='Revenue Build-Up'!AQ8 | AR5: ='Revenue Build-Up'!AR8 | AS5: ='Revenue Build-Up'!AS8 | AT5: ='Revenue Build-Up'!AT8 | AU5: ='Revenue Build-Up'!AU8 | AV5: ='Revenue Build-Up'!AV8 | ... AZ5: ='Revenue Build-Up'!AZ8 | BA5: =SUM(AO5:AZ5) | BB5: ='Revenue Build-Up'!BB8 | BC5: ='Revenue Build-Up'!BC8 | BD5: ='Revenue Build-Up'!BD8 | BE5: ='Revenue Build-Up'!BE8 | BF5: ='Revenue Build-Up'!BF8 | BG5: ='Revenue Build-Up'!BG8 | BH5: ='Revenue Build-Up'!BH8 | BI5: ='Revenue Build-Up'!BI8 | ... BM5: ='Revenue Build-Up'!BM8 | BN5: =SUM(BB5:BM5)
A6: Warehousing / Storage | B6: ='Revenue Build-Up'!B12 | C6: ='Revenue Build-Up'!C12 | D6: ='Revenue Build-Up'!D12 | E6: ='Revenue Build-Up'!E12 | F6: ='Revenue Build-Up'!F12 | G6: ='Revenue Build-Up'!G12 | H6: ='Revenue Build-Up'!H12 | I6: ='Revenue Build-Up'!I12 | ... M6: ='Revenue Build-Up'!M12 | N6: =SUM(B6:M6) | O6: ='Revenue Build-Up'!O12 | P6: ='Revenue Build-Up'!P12 | Q6: ='Revenue Build-Up'!Q12 | R6: ='Revenue Build-Up'!R12 | S6: ='Revenue Build-Up'!S12 | T6: ='Revenue Build-Up'!T12 | U6: ='Revenue Build-Up'!U12 | V6: ='Revenue Build-Up'!V12 | ... Z6: ='Revenue Build-Up'!Z12 | AA6: =SUM(O6:Z6) | AB6: ='Revenue Build-Up'!AB12 | AC6: ='Revenue Build-Up'!AC12 | AD6: ='Revenue Build-Up'!AD12 | AE6: ='Revenue Build-Up'!AE12 | AF6: ='Revenue Build-Up'!AF12 | AG6: ='Revenue Build-Up'!AG12 | AH6: ='Revenue Build-Up'!AH12 | AI6: ='Revenue Build-Up'!AI12 | ... AM6: ='Revenue Build-Up'!AM12 | AN6: =SUM(AB6:AM6) | AO6: ='Revenue Build-Up'!AO12 | AP6: ='Revenue Build-Up'!AP12 | AQ6: ='Revenue Build-Up'!AQ12 | AR6: ='Revenue Build-Up'!AR12 | AS6: ='Revenue Build-Up'!AS12 | AT6: ='Revenue Build-Up'!AT12 | AU6: ='Revenue Build-Up'!AU12 | AV6: ='Revenue Build-Up'!AV12 | ... AZ6: ='Revenue Build-Up'!AZ12 | BA6: =SUM(AO6:AZ6) | BB6: ='Revenue Build-Up'!BB12 | BC6: ='Revenue Build-Up'!BC12 | BD6: ='Revenue Build-Up'!BD12 | BE6: ='Revenue Build-Up'!BE12 | BF6: ='Revenue Build-Up'!BF12 | BG6: ='Revenue Build-Up'!BG12 | BH6: ='Revenue Build-Up'!BH12 | BI6: ='Revenue Build-Up'!BI12 | ... BM6: ='Revenue Build-Up'!BM12 | BN6: =SUM(BB6:BM6)
A7: Value-added logistics | B7: ='Revenue Build-Up'!B16 | C7: ='Revenue Build-Up'!C16 | D7: ='Revenue Build-Up'!D16 | E7: ='Revenue Build-Up'!E16 | F7: ='Revenue Build-Up'!F16 | G7: ='Revenue Build-Up'!G16 | H7: ='Revenue Build-Up'!H16 | I7: ='Revenue Build-Up'!I16 | ... M7: ='Revenue Build-Up'!M16 | N7: =SUM(B7:M7) | O7: ='Revenue Build-Up'!O16 | P7: ='Revenue Build-Up'!P16 | Q7: ='Revenue Build-Up'!Q16 | R7: ='Revenue Build-Up'!R16 | S7: ='Revenue Build-Up'!S16 | T7: ='Revenue Build-Up'!T16 | U7: ='Revenue Build-Up'!U16 | V7: ='Revenue Build-Up'!V16 | ... Z7: ='Revenue Build-Up'!Z16 | AA7: =SUM(O7:Z7) | AB7: ='Revenue Build-Up'!AB16 | AC7: ='Revenue Build-Up'!AC16 | AD7: ='Revenue Build-Up'!AD16 | AE7: ='Revenue Build-Up'!AE16 | AF7: ='Revenue Build-Up'!AF16 | AG7: ='Revenue Build-Up'!AG16 | AH7: ='Revenue Build-Up'!AH16 | AI7: ='Revenue Build-Up'!AI16 | ... AM7: ='Revenue Build-Up'!AM16 | AN7: =SUM(AB7:AM7) | AO7: ='Revenue Build-Up'!AO16 | AP7: ='Revenue Build-Up'!AP16 | AQ7: ='Revenue Build-Up'!AQ16 | AR7: ='Revenue Build-Up'!AR16 | AS7: ='Revenue Build-Up'!AS16 | AT7: ='Revenue Build-Up'!AT16 | AU7: ='Revenue Build-Up'!AU16 | AV7: ='Revenue Build-Up'!AV16 | ... AZ7: ='Revenue Build-Up'!AZ16 | BA7: =SUM(AO7:AZ7) | BB7: ='Revenue Build-Up'!BB16 | BC7: ='Revenue Build-Up'!BC16 | BD7: ='Revenue Build-Up'!BD16 | BE7: ='Revenue Build-Up'!BE16 | BF7: ='Revenue Build-Up'!BF16 | BG7: ='Revenue Build-Up'!BG16 | BH7: ='Revenue Build-Up'!BH16 | BI7: ='Revenue Build-Up'!BI16 | ... BM7: ='Revenue Build-Up'!BM16 | BN7: =SUM(BB7:BM7)
A8: Express / Priority | B8: ='Revenue Build-Up'!B20 | C8: ='Revenue Build-Up'!C20 | D8: ='Revenue Build-Up'!D20 | E8: ='Revenue Build-Up'!E20 | F8: ='Revenue Build-Up'!F20 | G8: ='Revenue Build-Up'!G20 | H8: ='Revenue Build-Up'!H20 | I8: ='Revenue Build-Up'!I20 | ... M8: ='Revenue Build-Up'!M20 | N8: =SUM(B8:M8) | O8: ='Revenue Build-Up'!O20 | P8: ='Revenue Build-Up'!P20 | Q8: ='Revenue Build-Up'!Q20 | R8: ='Revenue Build-Up'!R20 | S8: ='Revenue Build-Up'!S20 | T8: ='Revenue Build-Up'!T20 | U8: ='Revenue Build-Up'!U20 | V8: ='Revenue Build-Up'!V20 | ... Z8: ='Revenue Build-Up'!Z20 | AA8: =SUM(O8:Z8) | AB8: ='Revenue Build-Up'!AB20 | AC8: ='Revenue Build-Up'!AC20 | AD8: ='Revenue Build-Up'!AD20 | AE8: ='Revenue Build-Up'!AE20 | AF8: ='Revenue Build-Up'!AF20 | AG8: ='Revenue Build-Up'!AG20 | AH8: ='Revenue Build-Up'!AH20 | AI8: ='Revenue Build-Up'!AI20 | ... AM8: ='Revenue Build-Up'!AM20 | AN8: =SUM(AB8:AM8) | AO8: ='Revenue Build-Up'!AO20 | AP8: ='Revenue Build-Up'!AP20 | AQ8: ='Revenue Build-Up'!AQ20 | AR8: ='Revenue Build-Up'!AR20 | AS8: ='Revenue Build-Up'!AS20 | AT8: ='Revenue Build-Up'!AT20 | AU8: ='Revenue Build-Up'!AU20 | AV8: ='Revenue Build-Up'!AV20 | ... AZ8: ='Revenue Build-Up'!AZ20 | BA8: =SUM(AO8:AZ8) | BB8: ='Revenue Build-Up'!BB20 | BC8: ='Revenue Build-Up'!BC20 | BD8: ='Revenue Build-Up'!BD20 | BE8: ='Revenue Build-Up'!BE20 | BF8: ='Revenue Build-Up'!BF20 | BG8: ='Revenue Build-Up'!BG20 | BH8: ='Revenue Build-Up'!BH20 | BI8: ='Revenue Build-Up'!BI20 | ... BM8: ='Revenue Build-Up'!BM20 | BN8: =SUM(BB8:BM8)
A9: Other revenue | B9: ='Revenue Build-Up'!B24 | C9: ='Revenue Build-Up'!C24 | D9: ='Revenue Build-Up'!D24 | E9: ='Revenue Build-Up'!E24 | F9: ='Revenue Build-Up'!F24 | G9: ='Revenue Build-Up'!G24 | H9: ='Revenue Build-Up'!H24 | I9: ='Revenue Build-Up'!I24 | ... M9: ='Revenue Build-Up'!M24 | N9: =SUM(B9:M9) | O9: ='Revenue Build-Up'!O24 | P9: ='Revenue Build-Up'!P24 | Q9: ='Revenue Build-Up'!Q24 | R9: ='Revenue Build-Up'!R24 | S9: ='Revenue Build-Up'!S24 | T9: ='Revenue Build-Up'!T24 | U9: ='Revenue Build-Up'!U24 | V9: ='Revenue Build-Up'!V24 | ... Z9: ='Revenue Build-Up'!Z24 | AA9: =SUM(O9:Z9) | AB9: ='Revenue Build-Up'!AB24 | AC9: ='Revenue Build-Up'!AC24 | AD9: ='Revenue Build-Up'!AD24 | AE9: ='Revenue Build-Up'!AE24 | AF9: ='Revenue Build-Up'!AF24 | AG9: ='Revenue Build-Up'!AG24 | AH9: ='Revenue Build-Up'!AH24 | AI9: ='Revenue Build-Up'!AI24 | ... AM9: ='Revenue Build-Up'!AM24 | AN9: =SUM(AB9:AM9) | AO9: ='Revenue Build-Up'!AO24 | AP9: ='Revenue Build-Up'!AP24 | AQ9: ='Revenue Build-Up'!AQ24 | AR9: ='Revenue Build-Up'!AR24 | AS9: ='Revenue Build-Up'!AS24 | AT9: ='Revenue Build-Up'!AT24 | AU9: ='Revenue Build-Up'!AU24 | AV9: ='Revenue Build-Up'!AV24 | ... AZ9: ='Revenue Build-Up'!AZ24 | BA9: =SUM(AO9:AZ9) | BB9: ='Revenue Build-Up'!BB24 | BC9: ='Revenue Build-Up'!BC24 | BD9: ='Revenue Build-Up'!BD24 | BE9: ='Revenue Build-Up'!BE24 | BF9: ='Revenue Build-Up'!BF24 | BG9: ='Revenue Build-Up'!BG24 | BH9: ='Revenue Build-Up'!BH24 | BI9: ='Revenue Build-Up'!BI24 | ... BM9: ='Revenue Build-Up'!BM24 | BN9: =SUM(BB9:BM9)
A10: Total Revenue | B10: =B5+B6+B7+B8+B9 | C10: =C5+C6+C7+C8+C9 | D10: =D5+D6+D7+D8+D9 | E10: =E5+E6+E7+E8+E9 | F10: =F5+F6+F7+F8+F9 | G10: =G5+G6+G7+G8+G9 | H10: =H5+H6+H7+H8+H9 | I10: =I5+I6+I7+I8+I9 | ... M10: =M5+M6+M7+M8+M9 | N10: =SUM(B10:M10) | O10: =O5+O6+O7+O8+O9 | P10: =P5+P6+P7+P8+P9 | Q10: =Q5+Q6+Q7+Q8+Q9 | R10: =R5+R6+R7+R8+R9 | S10: =S5+S6+S7+S8+S9 | T10: =T5+T6+T7+T8+T9 | U10: =U5+U6+U7+U8+U9 | V10: =V5+V6+V7+V8+V9 | ... Z10: =Z5+Z6+Z7+Z8+Z9 | AA10: =SUM(O10:Z10) | AB10: =AB5+AB6+AB7+AB8+AB9 | AC10: =AC5+AC6+AC7+AC8+AC9 | AD10: =AD5+AD6+AD7+AD8+AD9 | AE10: =AE5+AE6+AE7+AE8+AE9 | AF10: =AF5+AF6+AF7+AF8+AF9 | AG10: =AG5+AG6+AG7+AG8+AG9 | AH10: =AH5+AH6+AH7+AH8+AH9 | AI10: =AI5+AI6+AI7+AI8+AI9 | ... AM10: =AM5+AM6+AM7+AM8+AM9 | AN10: =SUM(AB10:AM10) | AO10: =AO5+AO6+AO7+AO8+AO9 | AP10: =AP5+AP6+AP7+AP8+AP9 | AQ10: =AQ5+AQ6+AQ7+AQ8+AQ9 | AR10: =AR5+AR6+AR7+AR8+AR9 | AS10: =AS5+AS6+AS7+AS8+AS9 | AT10: =AT5+AT6+AT7+AT8+AT9 | AU10: =AU5+AU6+AU7+AU8+AU9 | AV10: =AV5+AV6+AV7+AV8+AV9 | ... AZ10: =AZ5+AZ6+AZ7+AZ8+AZ9 | BA10: =SUM(AO10:AZ10) | BB10: =BB5+BB6+BB7+BB8+BB9 | BC10: =BC5+BC6+BC7+BC8+BC9 | BD10: =BD5+BD6+BD7+BD8+BD9 | BE10: =BE5+BE6+BE7+BE8+BE9 | BF10: =BF5+BF6+BF7+BF8+BF9 | BG10: =BG5+BG6+BG7+BG8+BG9 | BH10: =BH5+BH6+BH7+BH8+BH9 | BI10: =BI5+BI6+BI7+BI8+BI9 | ... BM10: =BM5+BM6+BM7+BM8+BM9 | BN10: =SUM(BB10:BM10)
A11: =IFERROR("(-) "&VLOOKUP(Assumptions!$J$5,INDUSTRY_MAP,5,FALSE()),"(-) Raw materials") | B11: =Expenses!B5 | C11: =Expenses!C5 | D11: =Expenses!D5 | E11: =Expenses!E5 | F11: =Expenses!F5 | G11: =Expenses!G5 | H11: =Expenses!H5 | I11: =Expenses!I5 | ... M11: =Expenses!M5 | N11: =SUM(B11:M11) | O11: =Expenses!O5 | P11: =Expenses!P5 | Q11: =Expenses!Q5 | R11: =Expenses!R5 | S11: =Expenses!S5 | T11: =Expenses!T5 | U11: =Expenses!U5 | V11: =Expenses!V5 | ... Z11: =Expenses!Z5 | AA11: =SUM(O11:Z11) | AB11: =Expenses!AB5 | AC11: =Expenses!AC5 | AD11: =Expenses!AD5 | AE11: =Expenses!AE5 | AF11: =Expenses!AF5 | AG11: =Expenses!AG5 | AH11: =Expenses!AH5 | AI11: =Expenses!AI5 | ... AM11: =Expenses!AM5 | AN11: =SUM(AB11:AM11) | AO11: =Expenses!AO5 | AP11: =Expenses!AP5 | AQ11: =Expenses!AQ5 | AR11: =Expenses!AR5 | AS11: =Expenses!AS5 | AT11: =Expenses!AT5 | AU11: =Expenses!AU5 | AV11: =Expenses!AV5 | ... AZ11: =Expenses!AZ5 | BA11: =SUM(AO11:AZ11) | BB11: =Expenses!BB5 | BC11: =Expenses!BC5 | BD11: =Expenses!BD5 | BE11: =Expenses!BE5 | BF11: =Expenses!BF5 | BG11: =Expenses!BG5 | BH11: =Expenses!BH5 | BI11: =Expenses!BI5 | ... BM11: =Expenses!BM5 | BN11: =SUM(BB11:BM11)
A12: =IFERROR("(-) "&VLOOKUP(Assumptions!$J$5,INDUSTRY_MAP,7,FALSE()),"(-) Power & fuel") | B12: =Expenses!B6 | C12: =Expenses!C6 | D12: =Expenses!D6 | E12: =Expenses!E6 | F12: =Expenses!F6 | G12: =Expenses!G6 | H12: =Expenses!H6 | I12: =Expenses!I6 | ... M12: =Expenses!M6 | N12: =SUM(B12:M12) | O12: =Expenses!O6 | P12: =Expenses!P6 | Q12: =Expenses!Q6 | R12: =Expenses!R6 | S12: =Expenses!S6 | T12: =Expenses!T6 | U12: =Expenses!U6 | V12: =Expenses!V6 | ... Z12: =Expenses!Z6 | AA12: =SUM(O12:Z12) | AB12: =Expenses!AB6 | AC12: =Expenses!AC6 | AD12: =Expenses!AD6 | AE12: =Expenses!AE6 | AF12: =Expenses!AF6 | AG12: =Expenses!AG6 | AH12: =Expenses!AH6 | AI12: =Expenses!AI6 | ... AM12: =Expenses!AM6 | AN12: =SUM(AB12:AM12) | AO12: =Expenses!AO6 | AP12: =Expenses!AP6 | AQ12: =Expenses!AQ6 | AR12: =Expenses!AR6 | AS12: =Expenses!AS6 | AT12: =Expenses!AT6 | AU12: =Expenses!AU6 | AV12: =Expenses!AV6 | ... AZ12: =Expenses!AZ6 | BA12: =SUM(AO12:AZ12) | BB12: =Expenses!BB6 | BC12: =Expenses!BC6 | BD12: =Expenses!BD6 | BE12: =Expenses!BE6 | BF12: =Expenses!BF6 | BG12: =Expenses!BG6 | BH12: =Expenses!BH6 | BI12: =Expenses!BI6 | ... BM12: =Expenses!BM6 | BN12: =SUM(BB12:BM12)
A13: (-) Direct wages & salaries | B13: =Expenses!B7 | C13: =Expenses!C7 | D13: =Expenses!D7 | E13: =Expenses!E7 | F13: =Expenses!F7 | G13: =Expenses!G7 | H13: =Expenses!H7 | I13: =Expenses!I7 | ... M13: =Expenses!M7 | N13: =SUM(B13:M13) | O13: =Expenses!O7 | P13: =Expenses!P7 | Q13: =Expenses!Q7 | R13: =Expenses!R7 | S13: =Expenses!S7 | T13: =Expenses!T7 | U13: =Expenses!U7 | V13: =Expenses!V7 | ... Z13: =Expenses!Z7 | AA13: =SUM(O13:Z13) | AB13: =Expenses!AB7 | AC13: =Expenses!AC7 | AD13: =Expenses!AD7 | AE13: =Expenses!AE7 | AF13: =Expenses!AF7 | AG13: =Expenses!AG7 | AH13: =Expenses!AH7 | AI13: =Expenses!AI7 | ... AM13: =Expenses!AM7 | AN13: =SUM(AB13:AM13) | AO13: =Expenses!AO7 | AP13: =Expenses!AP7 | AQ13: =Expenses!AQ7 | AR13: =Expenses!AR7 | AS13: =Expenses!AS7 | AT13: =Expenses!AT7 | AU13: =Expenses!AU7 | AV13: =Expenses!AV7 | ... AZ13: =Expenses!AZ7 | BA13: =SUM(AO13:AZ13) | BB13: =Expenses!BB7 | BC13: =Expenses!BC7 | BD13: =Expenses!BD7 | BE13: =Expenses!BE7 | BF13: =Expenses!BF7 | BG13: =Expenses!BG7 | BH13: =Expenses!BH7 | BI13: =Expenses!BI7 | ... BM13: =Expenses!BM7 | BN13: =SUM(BB13:BM13)
A14: (-) Other variable cost | B14: =Expenses!B8 | C14: =Expenses!C8 | D14: =Expenses!D8 | E14: =Expenses!E8 | F14: =Expenses!F8 | G14: =Expenses!G8 | H14: =Expenses!H8 | I14: =Expenses!I8 | ... M14: =Expenses!M8 | N14: =SUM(B14:M14) | O14: =Expenses!O8 | P14: =Expenses!P8 | Q14: =Expenses!Q8 | R14: =Expenses!R8 | S14: =Expenses!S8 | T14: =Expenses!T8 | U14: =Expenses!U8 | V14: =Expenses!V8 | ... Z14: =Expenses!Z8 | AA14: =SUM(O14:Z14) | AB14: =Expenses!AB8 | AC14: =Expenses!AC8 | AD14: =Expenses!AD8 | AE14: =Expenses!AE8 | AF14: =Expenses!AF8 | AG14: =Expenses!AG8 | AH14: =Expenses!AH8 | AI14: =Expenses!AI8 | ... AM14: =Expenses!AM8 | AN14: =SUM(AB14:AM14) | AO14: =Expenses!AO8 | AP14: =Expenses!AP8 | AQ14: =Expenses!AQ8 | AR14: =Expenses!AR8 | AS14: =Expenses!AS8 | AT14: =Expenses!AT8 | AU14: =Expenses!AU8 | AV14: =Expenses!AV8 | ... AZ14: =Expenses!AZ8 | BA14: =SUM(AO14:AZ14) | BB14: =Expenses!BB8 | BC14: =Expenses!BC8 | BD14: =Expenses!BD8 | BE14: =Expenses!BE8 | BF14: =Expenses!BF8 | BG14: =Expenses!BG8 | BH14: =Expenses!BH8 | BI14: =Expenses!BI8 | ... BM14: =Expenses!BM8 | BN14: =SUM(BB14:BM14)
A15: =IFERROR("(-) "&VLOOKUP(Assumptions!$J$5,INDUSTRY_MAP,8,FALSE()),"(-) Factory overheads") | B15: =Expenses!B9 | C15: =Expenses!C9 | D15: =Expenses!D9 | E15: =Expenses!E9 | F15: =Expenses!F9 | G15: =Expenses!G9 | H15: =Expenses!H9 | I15: =Expenses!I9 | ... M15: =Expenses!M9 | N15: =SUM(B15:M15) | O15: =Expenses!O9 | P15: =Expenses!P9 | Q15: =Expenses!Q9 | R15: =Expenses!R9 | S15: =Expenses!S9 | T15: =Expenses!T9 | U15: =Expenses!U9 | V15: =Expenses!V9 | ... Z15: =Expenses!Z9 | AA15: =SUM(O15:Z15) | AB15: =Expenses!AB9 | AC15: =Expenses!AC9 | AD15: =Expenses!AD9 | AE15: =Expenses!AE9 | AF15: =Expenses!AF9 | AG15: =Expenses!AG9 | AH15: =Expenses!AH9 | AI15: =Expenses!AI9 | ... AM15: =Expenses!AM9 | AN15: =SUM(AB15:AM15) | AO15: =Expenses!AO9 | AP15: =Expenses!AP9 | AQ15: =Expenses!AQ9 | AR15: =Expenses!AR9 | AS15: =Expenses!AS9 | AT15: =Expenses!AT9 | AU15: =Expenses!AU9 | AV15: =Expenses!AV9 | ... AZ15: =Expenses!AZ9 | BA15: =SUM(AO15:AZ15) | BB15: =Expenses!BB9 | BC15: =Expenses!BC9 | BD15: =Expenses!BD9 | BE15: =Expenses!BE9 | BF15: =Expenses!BF9 | BG15: =Expenses!BG9 | BH15: =Expenses!BH9 | BI15: =Expenses!BI9 | ... BM15: =Expenses!BM9 | BN15: =SUM(BB15:BM15)
A16: (-) Repairs & maintenance | B16: =Expenses!B10 | C16: =Expenses!C10 | D16: =Expenses!D10 | E16: =Expenses!E10 | F16: =Expenses!F10 | G16: =Expenses!G10 | H16: =Expenses!H10 | I16: =Expenses!I10 | ... M16: =Expenses!M10 | N16: =SUM(B16:M16) | O16: =Expenses!O10 | P16: =Expenses!P10 | Q16: =Expenses!Q10 | R16: =Expenses!R10 | S16: =Expenses!S10 | T16: =Expenses!T10 | U16: =Expenses!U10 | V16: =Expenses!V10 | ... Z16: =Expenses!Z10 | AA16: =SUM(O16:Z16) | AB16: =Expenses!AB10 | AC16: =Expenses!AC10 | AD16: =Expenses!AD10 | AE16: =Expenses!AE10 | AF16: =Expenses!AF10 | AG16: =Expenses!AG10 | AH16: =Expenses!AH10 | AI16: =Expenses!AI10 | ... AM16: =Expenses!AM10 | AN16: =SUM(AB16:AM16) | AO16: =Expenses!AO10 | AP16: =Expenses!AP10 | AQ16: =Expenses!AQ10 | AR16: =Expenses!AR10 | AS16: =Expenses!AS10 | AT16: =Expenses!AT10 | AU16: =Expenses!AU10 | AV16: =Expenses!AV10 | ... AZ16: =Expenses!AZ10 | BA16: =SUM(AO16:AZ16) | BB16: =Expenses!BB10 | BC16: =Expenses!BC10 | BD16: =Expenses!BD10 | BE16: =Expenses!BE10 | BF16: =Expenses!BF10 | BG16: =Expenses!BG10 | BH16: =Expenses!BH10 | BI16: =Expenses!BI10 | ... BM16: =Expenses!BM10 | BN16: =SUM(BB16:BM16)
A17: (-) Administrative expenses | B17: =Expenses!B11 | C17: =Expenses!C11 | D17: =Expenses!D11 | E17: =Expenses!E11 | F17: =Expenses!F11 | G17: =Expenses!G11 | H17: =Expenses!H11 | I17: =Expenses!I11 | ... M17: =Expenses!M11 | N17: =SUM(B17:M17) | O17: =Expenses!O11 | P17: =Expenses!P11 | Q17: =Expenses!Q11 | R17: =Expenses!R11 | S17: =Expenses!S11 | T17: =Expenses!T11 | U17: =Expenses!U11 | V17: =Expenses!V11 | ... Z17: =Expenses!Z11 | AA17: =SUM(O17:Z17) | AB17: =Expenses!AB11 | AC17: =Expenses!AC11 | AD17: =Expenses!AD11 | AE17: =Expenses!AE11 | AF17: =Expenses!AF11 | AG17: =Expenses!AG11 | AH17: =Expenses!AH11 | AI17: =Expenses!AI11 | ... AM17: =Expenses!AM11 | AN17: =SUM(AB17:AM17) | AO17: =Expenses!AO11 | AP17: =Expenses!AP11 | AQ17: =Expenses!AQ11 | AR17: =Expenses!AR11 | AS17: =Expenses!AS11 | AT17: =Expenses!AT11 | AU17: =Expenses!AU11 | AV17: =Expenses!AV11 | ... AZ17: =Expenses!AZ11 | BA17: =SUM(AO17:AZ17) | BB17: =Expenses!BB11 | BC17: =Expenses!BC11 | BD17: =Expenses!BD11 | BE17: =Expenses!BE11 | BF17: =Expenses!BF11 | BG17: =Expenses!BG11 | BH17: =Expenses!BH11 | BI17: =Expenses!BI11 | ... BM17: =Expenses!BM11 | BN17: =SUM(BB17:BM17)
A18: (-) Selling & distribution | B18: =Expenses!B12 | C18: =Expenses!C12 | D18: =Expenses!D12 | E18: =Expenses!E12 | F18: =Expenses!F12 | G18: =Expenses!G12 | H18: =Expenses!H12 | I18: =Expenses!I12 | ... M18: =Expenses!M12 | N18: =SUM(B18:M18) | O18: =Expenses!O12 | P18: =Expenses!P12 | Q18: =Expenses!Q12 | R18: =Expenses!R12 | S18: =Expenses!S12 | T18: =Expenses!T12 | U18: =Expenses!U12 | V18: =Expenses!V12 | ... Z18: =Expenses!Z12 | AA18: =SUM(O18:Z18) | AB18: =Expenses!AB12 | AC18: =Expenses!AC12 | AD18: =Expenses!AD12 | AE18: =Expenses!AE12 | AF18: =Expenses!AF12 | AG18: =Expenses!AG12 | AH18: =Expenses!AH12 | AI18: =Expenses!AI12 | ... AM18: =Expenses!AM12 | AN18: =SUM(AB18:AM18) | AO18: =Expenses!AO12 | AP18: =Expenses!AP12 | AQ18: =Expenses!AQ12 | AR18: =Expenses!AR12 | AS18: =Expenses!AS12 | AT18: =Expenses!AT12 | AU18: =Expenses!AU12 | AV18: =Expenses!AV12 | ... AZ18: =Expenses!AZ12 | BA18: =SUM(AO18:AZ18) | BB18: =Expenses!BB12 | BC18: =Expenses!BC12 | BD18: =Expenses!BD12 | BE18: =Expenses!BE12 | BF18: =Expenses!BF12 | BG18: =Expenses!BG12 | BH18: =Expenses!BH12 | BI18: =Expenses!BI12 | ... BM18: =Expenses!BM12 | BN18: =SUM(BB18:BM18)
A19: EBITDA | B19: =B10-SUM(B11:B18) | C19: =C10-SUM(C11:C18) | D19: =D10-SUM(D11:D18) | E19: =E10-SUM(E11:E18) | F19: =F10-SUM(F11:F18) | G19: =G10-SUM(G11:G18) | H19: =H10-SUM(H11:H18) | I19: =I10-SUM(I11:I18) | ... M19: =M10-SUM(M11:M18) | N19: =SUM(B19:M19) | O19: =O10-SUM(O11:O18) | P19: =P10-SUM(P11:P18) | Q19: =Q10-SUM(Q11:Q18) | R19: =R10-SUM(R11:R18) | S19: =S10-SUM(S11:S18) | T19: =T10-SUM(T11:T18) | U19: =U10-SUM(U11:U18) | V19: =V10-SUM(V11:V18) | ... Z19: =Z10-SUM(Z11:Z18) | AA19: =SUM(O19:Z19) | AB19: =AB10-SUM(AB11:AB18) | AC19: =AC10-SUM(AC11:AC18) | AD19: =AD10-SUM(AD11:AD18) | AE19: =AE10-SUM(AE11:AE18) | AF19: =AF10-SUM(AF11:AF18) | AG19: =AG10-SUM(AG11:AG18) | AH19: =AH10-SUM(AH11:AH18) | AI19: =AI10-SUM(AI11:AI18) | ... AM19: =AM10-SUM(AM11:AM18) | AN19: =SUM(AB19:AM19) | AO19: =AO10-SUM(AO11:AO18) | AP19: =AP10-SUM(AP11:AP18) | AQ19: =AQ10-SUM(AQ11:AQ18) | AR19: =AR10-SUM(AR11:AR18) | AS19: =AS10-SUM(AS11:AS18) | AT19: =AT10-SUM(AT11:AT18) | AU19: =AU10-SUM(AU11:AU18) | AV19: =AV10-SUM(AV11:AV18) | ... AZ19: =AZ10-SUM(AZ11:AZ18) | BA19: =SUM(AO19:AZ19) | BB19: =BB10-SUM(BB11:BB18) | BC19: =BC10-SUM(BC11:BC18) | BD19: =BD10-SUM(BD11:BD18) | BE19: =BE10-SUM(BE11:BE18) | BF19: =BF10-SUM(BF11:BF18) | BG19: =BG10-SUM(BG11:BG18) | BH19: =BH10-SUM(BH11:BH18) | BI19: =BI10-SUM(BI11:BI18) | ... BM19: =BM10-SUM(BM11:BM18) | BN19: =SUM(BB19:BM19)
A20: (-) Depreciation | B20: =Expenses!B13 | C20: =Expenses!C13 | D20: =Expenses!D13 | E20: =Expenses!E13 | F20: =Expenses!F13 | G20: =Expenses!G13 | H20: =Expenses!H13 | I20: =Expenses!I13 | ... M20: =Expenses!M13 | N20: =SUM(B20:M20) | O20: =Expenses!O13 | P20: =Expenses!P13 | Q20: =Expenses!Q13 | R20: =Expenses!R13 | S20: =Expenses!S13 | T20: =Expenses!T13 | U20: =Expenses!U13 | V20: =Expenses!V13 | ... Z20: =Expenses!Z13 | AA20: =SUM(O20:Z20) | AB20: =Expenses!AB13 | AC20: =Expenses!AC13 | AD20: =Expenses!AD13 | AE20: =Expenses!AE13 | AF20: =Expenses!AF13 | AG20: =Expenses!AG13 | AH20: =Expenses!AH13 | AI20: =Expenses!AI13 | ... AM20: =Expenses!AM13 | AN20: =SUM(AB20:AM20) | AO20: =Expenses!AO13 | AP20: =Expenses!AP13 | AQ20: =Expenses!AQ13 | AR20: =Expenses!AR13 | AS20: =Expenses!AS13 | AT20: =Expenses!AT13 | AU20: =Expenses!AU13 | AV20: =Expenses!AV13 | ... AZ20: =Expenses!AZ13 | BA20: =SUM(AO20:AZ20) | BB20: =Expenses!BB13 | BC20: =Expenses!BC13 | BD20: =Expenses!BD13 | BE20: =Expenses!BE13 | BF20: =Expenses!BF13 | BG20: =Expenses!BG13 | BH20: =Expenses!BH13 | BI20: =Expenses!BI13 | ... BM20: =Expenses!BM13 | BN20: =SUM(BB20:BM20)
A21: EBIT (Operating Profit) | B21: =B19-B20 | C21: =C19-C20 | D21: =D19-D20 | E21: =E19-E20 | F21: =F19-F20 | G21: =G19-G20 | H21: =H19-H20 | I21: =I19-I20 | ... M21: =M19-M20 | N21: =SUM(B21:M21) | O21: =O19-O20 | P21: =P19-P20 | Q21: =Q19-Q20 | R21: =R19-R20 | S21: =S19-S20 | T21: =T19-T20 | U21: =U19-U20 | V21: =V19-V20 | ... Z21: =Z19-Z20 | AA21: =SUM(O21:Z21) | AB21: =AB19-AB20 | AC21: =AC19-AC20 | AD21: =AD19-AD20 | AE21: =AE19-AE20 | AF21: =AF19-AF20 | AG21: =AG19-AG20 | AH21: =AH19-AH20 | AI21: =AI19-AI20 | ... AM21: =AM19-AM20 | AN21: =SUM(AB21:AM21) | AO21: =AO19-AO20 | AP21: =AP19-AP20 | AQ21: =AQ19-AQ20 | AR21: =AR19-AR20 | AS21: =AS19-AS20 | AT21: =AT19-AT20 | AU21: =AU19-AU20 | AV21: =AV19-AV20 | ... AZ21: =AZ19-AZ20 | BA21: =SUM(AO21:AZ21) | BB21: =BB19-BB20 | BC21: =BC19-BC20 | BD21: =BD19-BD20 | BE21: =BE19-BE20 | BF21: =BF19-BF20 | BG21: =BG19-BG20 | BH21: =BH19-BH20 | BI21: =BI19-BI20 | ... BM21: =BM19-BM20 | BN21: =SUM(BB21:BM21)
A22: (-) Interest — Term Loan | B22: =Expenses!B14 | C22: =Expenses!C14 | D22: =Expenses!D14 | E22: =Expenses!E14 | F22: =Expenses!F14 | G22: =Expenses!G14 | H22: =Expenses!H14 | I22: =Expenses!I14 | ... M22: =Expenses!M14 | N22: =SUM(B22:M22) | O22: =Expenses!O14 | P22: =Expenses!P14 | Q22: =Expenses!Q14 | R22: =Expenses!R14 | S22: =Expenses!S14 | T22: =Expenses!T14 | U22: =Expenses!U14 | V22: =Expenses!V14 | ... Z22: =Expenses!Z14 | AA22: =SUM(O22:Z22) | AB22: =Expenses!AB14 | AC22: =Expenses!AC14 | AD22: =Expenses!AD14 | AE22: =Expenses!AE14 | AF22: =Expenses!AF14 | AG22: =Expenses!AG14 | AH22: =Expenses!AH14 | AI22: =Expenses!AI14 | ... AM22: =Expenses!AM14 | AN22: =SUM(AB22:AM22) | AO22: =Expenses!AO14 | AP22: =Expenses!AP14 | AQ22: =Expenses!AQ14 | AR22: =Expenses!AR14 | AS22: =Expenses!AS14 | AT22: =Expenses!AT14 | AU22: =Expenses!AU14 | AV22: =Expenses!AV14 | ... AZ22: =Expenses!AZ14 | BA22: =SUM(AO22:AZ22) | BB22: =Expenses!BB14 | BC22: =Expenses!BC14 | BD22: =Expenses!BD14 | BE22: =Expenses!BE14 | BF22: =Expenses!BF14 | BG22: =Expenses!BG14 | BH22: =Expenses!BH14 | BI22: =Expenses!BI14 | ... BM22: =Expenses!BM14 | BN22: =SUM(BB22:BM22)
A23: (-) Interest — Working Capital | B23: =Expenses!B15 | C23: =Expenses!C15 | D23: =Expenses!D15 | E23: =Expenses!E15 | F23: =Expenses!F15 | G23: =Expenses!G15 | H23: =Expenses!H15 | I23: =Expenses!I15 | ... M23: =Expenses!M15 | N23: =SUM(B23:M23) | O23: =Expenses!O15 | P23: =Expenses!P15 | Q23: =Expenses!Q15 | R23: =Expenses!R15 | S23: =Expenses!S15 | T23: =Expenses!T15 | U23: =Expenses!U15 | V23: =Expenses!V15 | ... Z23: =Expenses!Z15 | AA23: =SUM(O23:Z23) | AB23: =Expenses!AB15 | AC23: =Expenses!AC15 | AD23: =Expenses!AD15 | AE23: =Expenses!AE15 | AF23: =Expenses!AF15 | AG23: =Expenses!AG15 | AH23: =Expenses!AH15 | AI23: =Expenses!AI15 | ... AM23: =Expenses!AM15 | AN23: =SUM(AB23:AM23) | AO23: =Expenses!AO15 | AP23: =Expenses!AP15 | AQ23: =Expenses!AQ15 | AR23: =Expenses!AR15 | AS23: =Expenses!AS15 | AT23: =Expenses!AT15 | AU23: =Expenses!AU15 | AV23: =Expenses!AV15 | ... AZ23: =Expenses!AZ15 | BA23: =SUM(AO23:AZ23) | BB23: =Expenses!BB15 | BC23: =Expenses!BC15 | BD23: =Expenses!BD15 | BE23: =Expenses!BE15 | BF23: =Expenses!BF15 | BG23: =Expenses!BG15 | BH23: =Expenses!BH15 | BI23: =Expenses!BI15 | ... BM23: =Expenses!BM15 | BN23: =SUM(BB23:BM23)
A24: Profit Before Tax (PBT) | B24: =B21-B22-B23 | C24: =C21-C22-C23 | D24: =D21-D22-D23 | E24: =E21-E22-E23 | F24: =F21-F22-F23 | G24: =G21-G22-G23 | H24: =H21-H22-H23 | I24: =I21-I22-I23 | ... M24: =M21-M22-M23 | N24: =SUM(B24:M24) | O24: =O21-O22-O23 | P24: =P21-P22-P23 | Q24: =Q21-Q22-Q23 | R24: =R21-R22-R23 | S24: =S21-S22-S23 | T24: =T21-T22-T23 | U24: =U21-U22-U23 | V24: =V21-V22-V23 | ... Z24: =Z21-Z22-Z23 | AA24: =SUM(O24:Z24) | AB24: =AB21-AB22-AB23 | AC24: =AC21-AC22-AC23 | AD24: =AD21-AD22-AD23 | AE24: =AE21-AE22-AE23 | AF24: =AF21-AF22-AF23 | AG24: =AG21-AG22-AG23 | AH24: =AH21-AH22-AH23 | AI24: =AI21-AI22-AI23 | ... AM24: =AM21-AM22-AM23 | AN24: =SUM(AB24:AM24) | AO24: =AO21-AO22-AO23 | AP24: =AP21-AP22-AP23 | AQ24: =AQ21-AQ22-AQ23 | AR24: =AR21-AR22-AR23 | AS24: =AS21-AS22-AS23 | AT24: =AT21-AT22-AT23 | AU24: =AU21-AU22-AU23 | AV24: =AV21-AV22-AV23 | ... AZ24: =AZ21-AZ22-AZ23 | BA24: =SUM(AO24:AZ24) | BB24: =BB21-BB22-BB23 | BC24: =BC21-BC22-BC23 | BD24: =BD21-BD22-BD23 | BE24: =BE21-BE22-BE23 | BF24: =BF21-BF22-BF23 | BG24: =BG21-BG22-BG23 | BH24: =BH21-BH22-BH23 | BI24: =BI21-BI22-BI23 | ... BM24: =BM21-BM22-BM23 | BN24: =SUM(BB24:BM24)
A25: (-) Income Tax | B25: =IF(B24>0,B24*Assumptions!$C$14,0) | C25: =IF(C24>0,C24*Assumptions!$C$14,0) | D25: =IF(D24>0,D24*Assumptions!$C$14,0) | E25: =IF(E24>0,E24*Assumptions!$C$14,0) | F25: =IF(F24>0,F24*Assumptions!$C$14,0) | G25: =IF(G24>0,G24*Assumptions!$C$14,0) | H25: =IF(H24>0,H24*Assumptions!$C$14,0) | I25: =IF(I24>0,I24*Assumptions!$C$14,0) | ... BN25: =IF(BN24>0,BN24*Assumptions!$C$14,0)
A26: Profit After Tax (PAT) | B26: =B24-B25 | C26: =C24-C25 | D26: =D24-D25 | E26: =E24-E25 | F26: =F24-F25 | G26: =G24-G25 | H26: =H24-H25 | I26: =I24-I25 | ... BN26: =BN24-BN25
A27: Cash Accrual (PAT + Depreciation) | B27: =B26+B20 | C27: =C26+C20 | D27: =D26+D20 | E27: =E26+E20 | F27: =F26+F20 | G27: =G26+G20 | H27: =H26+H20 | I27: =I26+I20 | ... BN27: =BN26+BN20

Sheet Annual_Summary
A1: ANNUAL SUMMARY — CONSOLIDATED 5-YEAR VIEW
A2: Roll-up of the 60-month projections. Feeds every CMA form below.
B4: Particulars | C4: Year 1 | D4: Year 2 | E4: Year 3 | F4: Year 4 | G4: Year 5
B5: PRODUCTION & SALES
B6: =IFERROR(VLOOKUP(Assumptions!$J$5,INDUSTRY_MAP,3,FALSE()),"Production (units)") | C6: ='Revenue Build-Up'!N6 | D6: ='Revenue Build-Up'!AA6 | E6: ='Revenue Build-Up'!AN6 | F6: ='Revenue Build-Up'!BA6 | G6: ='Revenue Build-Up'!BN6
B7: Growth index (Year 1 = 100%) | C7: =Assumptions!$C$18 | D7: =Assumptions!$D$18 | E7: =Assumptions!$E$18 | F7: =Assumptions!$F$18 | G7: =Assumptions!$G$18
B8: Net Sales / Revenue (₹) | C8: ='Revenue Build-Up'!N26 | D8: ='Revenue Build-Up'!AA26 | E8: ='Revenue Build-Up'!AN26 | F8: ='Revenue Build-Up'!BA26 | G8: ='Revenue Build-Up'!BN26
B9: COST STRUCTURE (₹)
B10: =IFERROR(VLOOKUP(Assumptions!$J$5,INDUSTRY_MAP,5,FALSE()),"Raw materials") | C10: =Expenses!N5 | D10: =Expenses!AA5 | E10: =Expenses!AN5 | F10: =Expenses!BA5 | G10: =Expenses!BN5
B11: =IFERROR(VLOOKUP(Assumptions!$J$5,INDUSTRY_MAP,7,FALSE()),"Power & fuel") | C11: =Expenses!N6 | D11: =Expenses!AA6 | E11: =Expenses!AN6 | F11: =Expenses!BA6 | G11: =Expenses!BN6
B12: Direct wages & salaries | C12: =Expenses!N7 | D12: =Expenses!AA7 | E12: =Expenses!AN7 | F12: =Expenses!BA7 | G12: =Expenses!BN7
B13: Other variable cost | C13: =Expenses!N8 | D13: =Expenses!AA8 | E13: =Expenses!AN8 | F13: =Expenses!BA8 | G13: =Expenses!BN8
B14: =IFERROR(VLOOKUP(Assumptions!$J$5,INDUSTRY_MAP,8,FALSE()),"Factory overheads") | C14: =Expenses!N9 | D14: =Expenses!AA9 | E14: =Expenses!AN9 | F14: =Expenses!BA9 | G14: =Expenses!BN9
B15: Repairs & maintenance | C15: =Expenses!N10 | D15: =Expenses!AA10 | E15: =Expenses!AN10 | F15: =Expenses!BA10 | G15: =Expenses!BN10
B16: Administrative expenses | C16: =Expenses!N11 | D16: =Expenses!AA11 | E16: =Expenses!AN11 | F16: =Expenses!BA11 | G16: =Expenses!BN11
B17: Selling & distribution | C17: =Expenses!N12 | D17: =Expenses!AA12 | E17: =Expenses!AN12 | F17: =Expenses!BA12 | G17: =Expenses!BN12
B18: Depreciation | C18: =Expenses!N13 | D18: =Expenses!AA13 | E18: =Expenses!AN13 | F18: =Expenses!BA13 | G18: =Expenses!BN13
B19: Interest — Term Loan | C19: =Expenses!N14 | D19: =Expenses!AA14 | E19: =Expenses!AN14 | F19: =Expenses!BA14 | G19: =Expenses!BN14
B20: Interest — Working Capital | C20: =Expenses!N15 | D20: =Expenses!AA15 | E20: =Expenses!AN15 | F20: =Expenses!BA15 | G20: =Expenses!BN15
B21: PROFITABILITY (₹)
B22: EBITDA | C22: ='P & L'!N19 | D22: ='P & L'!AA19 | E22: ='P & L'!AN19 | F22: ='P & L'!BA19 | G22: ='P & L'!BN19
B23: EBIT (Operating Profit) | C23: ='P & L'!N21 | D23: ='P & L'!AA21 | E23: ='P & L'!AN21 | F23: ='P & L'!BA21 | G23: ='P & L'!BN21
B24: Profit Before Tax | C24: ='P & L'!N24 | D24: ='P & L'!AA24 | E24: ='P & L'!AN24 | F24: ='P & L'!BA24 | G24: ='P & L'!BN24
B25: Income Tax | C25: ='P & L'!N25 | D25: ='P & L'!AA25 | E25: ='P & L'!AN25 | F25: ='P & L'!BA25 | G25: ='P & L'!BN25
B26: Profit After Tax (PAT) | C26: ='P & L'!N26 | D26: ='P & L'!AA26 | E26: ='P & L'!AN26 | F26: ='P & L'!BA26 | G26: ='P & L'!BN26
B27: Cash Accrual (PAT + Depreciation) | C27: ='P & L'!N27 | D27: ='P & L'!AA27 | E27: ='P & L'!AN27 | F27: ='P & L'!BA27 | G27: ='P & L'!BN27

Sheet Form_II_Operating
A1: FORM II — OPERATING STATEMENT
A2: Projected profitability in the format required for credit appraisal (₹).
B4: Particulars | C4: Year 1 | D4: Year 2 | E4: Year 3 | F4: Year 4 | G4: Year 5
B5: Net Sales | C5: =Annual_Summary!C8 | D5: =Annual_Summary!D8 | E5: =Annual_Summary!E8 | F5: =Annual_Summary!F8 | G5: =Annual_Summary!G8
B6: Cost of Production
B7: =IFERROR(VLOOKUP(Assumptions!$J$5,INDUSTRY_MAP,5,FALSE()),"Raw materials") | C7: =Annual_Summary!C10 | D7: =Annual_Summary!D10 | E7: =Annual_Summary!E10 | F7: =Annual_Summary!F10 | G7: =Annual_Summary!G10
B8: =IFERROR(VLOOKUP(Assumptions!$J$5,INDUSTRY_MAP,7,FALSE()),"Power & fuel") | C8: =Annual_Summary!C11 | D8: =Annual_Summary!D11 | E8: =Annual_Summary!E11 | F8: =Annual_Summary!F11 | G8: =Annual_Summary!G11
B9: Direct wages & salaries | C9: =Annual_Summary!C12 | D9: =Annual_Summary!D12 | E9: =Annual_Summary!E12 | F9: =Annual_Summary!F12 | G9: =Annual_Summary!G12
B10: Other variable cost | C10: =Annual_Summary!C13 | D10: =Annual_Summary!D13 | E10: =Annual_Summary!E13 | F10: =Annual_Summary!F13 | G10: =Annual_Summary!G13
B11: =IFERROR(VLOOKUP(Assumptions!$J$5,INDUSTRY_MAP,8,FALSE()),"Factory overheads") | C11: =Annual_Summary!C14 | D11: =Annual_Summary!D14 | E11: =Annual_Summary!E14 | F11: =Annual_Summary!F14 | G11: =Annual_Summary!G14
B12: Repairs & maintenance | C12: =Annual_Summary!C15 | D12: =Annual_Summary!D15 | E12: =Annual_Summary!E15 | F12: =Annual_Summary!F15 | G12: =Annual_Summary!G15
B13: Depreciation | C13: =Annual_Summary!C18 | D13: =Annual_Summary!D18 | E13: =Annual_Summary!E18 | F13: =Annual_Summary!F18 | G13: =Annual_Summary!G18
B14: Cost of Production | C14: =Annual_Summary!C10+Annual_Summary!C11+Annual_Summary!C12+Annual_Summary!C13+Annual_Summary!C14+Annual_Summary!C15+Annual_Summary!C18 | D14: =Annual_Summary!D10+Annual_Summary!D11+Annual_Summary!D12+Annual_Summary!D13+Annual_Summary!D14+Annual_Summary!D15+Annual_Summary!D18 | E14: =Annual_Summary!E10+Annual_Summary!E11+Annual_Summary!E12+Annual_Summary!E13+Annual_Summary!E14+Annual_Summary!E15+Annual_Summary!E18 | F14: =Annual_Summary!F10+Annual_Summary!F11+Annual_Summary!F12+Annual_Summary!F13+Annual_Summary!F14+Annual_Summary!F15+Annual_Summary!F18 | G14: =Annual_Summary!G10+Annual_Summary!G11+Annual_Summary!G12+Annual_Summary!G13+Annual_Summary!G14+Annual_Summary!G15+Annual_Summary!G18
B15: Gross Profit | C15: =Annual_Summary!C8-C14 | D15: =Annual_Summary!D8-D14 | E15: =Annual_Summary!E8-E14 | F15: =Annual_Summary!F8-F14 | G15: =Annual_Summary!G8-G14
B16: (-) Administrative expenses | C16: =Annual_Summary!C16 | D16: =Annual_Summary!D16 | E16: =Annual_Summary!E16 | F16: =Annual_Summary!F16 | G16: =Annual_Summary!G16
B17: (-) Selling & distribution | C17: =Annual_Summary!C17 | D17: =Annual_Summary!D17 | E17: =Annual_Summary!E17 | F17: =Annual_Summary!F17 | G17: =Annual_Summary!G17
B18: Operating Profit (EBIT) | C18: =C15-Annual_Summary!C16-Annual_Summary!C17 | D18: =D15-Annual_Summary!D16-Annual_Summary!D17 | E18: =E15-Annual_Summary!E16-Annual_Summary!E17 | F18: =F15-Annual_Summary!F16-Annual_Summary!F17 | G18: =G15-Annual_Summary!G16-Annual_Summary!G17
B19: (-) Interest — Term Loan | C19: =Annual_Summary!C19 | D19: =Annual_Summary!D19 | E19: =Annual_Summary!E19 | F19: =Annual_Summary!F19 | G19: =Annual_Summary!G19
B20: (-) Interest — Working Capital | C20: =Annual_Summary!C20 | D20: =Annual_Summary!D20 | E20: =Annual_Summary!E20 | F20: =Annual_Summary!F20 | G20: =Annual_Summary!G20
B21: Profit Before Tax | C21: =C18-Annual_Summary!C19-Annual_Summary!C20 | D21: =D18-Annual_Summary!D19-Annual_Summary!D20 | E21: =E18-Annual_Summary!E19-Annual_Summary!E20 | F21: =F18-Annual_Summary!F19-Annual_Summary!F20 | G21: =G18-Annual_Summary!G19-Annual_Summary!G20
B22: (-) Provision for Tax | C22: =Annual_Summary!C25 | D22: =Annual_Summary!D25 | E22: =Annual_Summary!E25 | F22: =Annual_Summary!F25 | G22: =Annual_Summary!G25
B23: Profit After Tax | C23: =C21-Annual_Summary!C25 | D23: =D21-Annual_Summary!D25 | E23: =E21-Annual_Summary!E25 | F23: =F21-Annual_Summary!F25 | G23: =G21-Annual_Summary!G25

Sheet Form_III_BalanceSheet
A1: FORM III — PROJECTED BALANCE SHEET
A2: Sources & application of funds; cash is the balancing figure (₹).
B4: Particulars | C4: Year 1 | D4: Year 2 | E4: Year 3 | F4: Year 4 | G4: Year 5
B5: LIABILITIES (₹)
B6: Capital / Promoters' equity | C6: =Assumptions!$C$9 | D6: =Assumptions!$C$9 | E6: =Assumptions!$C$9 | F6: =Assumptions!$C$9 | G6: =Assumptions!$C$9
B7: Reserves & surplus (accumulated PAT) | C7: =Annual_Summary!C26 | D7: =C7+Annual_Summary!D26 | E7: =D7+Annual_Summary!E26 | F7: =E7+Annual_Summary!F26 | G7: =F7+Annual_Summary!G26
B8: Net Worth | C8: =C6+C7 | D8: =D6+D7 | E8: =E6+E7 | F8: =F6+F7 | G8: =G6+G7
B9: Term loan (closing balance) | C9: =Repayment!C8+'Existing Loan'!C16 | D9: =Repayment!D8+'Existing Loan'!D16 | E9: =Repayment!E8+'Existing Loan'!E16 | F9: =Repayment!F8+'Existing Loan'!F16 | G9: =Repayment!G8+'Existing Loan'!G16
B10: Bank borrowing — working capital | C10: =Form_V_MPBF!C11 | D10: =Form_V_MPBF!D11 | E10: =Form_V_MPBF!E11 | F10: =Form_V_MPBF!F11 | G10: =Form_V_MPBF!G11
B11: Sundry creditors | C11: =Form_IV_CA_CL!C16 | D11: =Form_IV_CA_CL!D16 | E11: =Form_IV_CA_CL!E16 | F11: =Form_IV_CA_CL!F16 | G11: =Form_IV_CA_CL!G16
B12: Other current liabilities / provisions | C12: =Form_IV_CA_CL!C17 | D12: =Form_IV_CA_CL!D17 | E12: =Form_IV_CA_CL!E17 | F12: =Form_IV_CA_CL!F17 | G12: =Form_IV_CA_CL!G17
B13: TOTAL LIABILITIES | C13: =SUM(C8:C12) | D13: =SUM(D8:D12) | E13: =SUM(E8:E12) | F13: =SUM(F8:F12) | G13: =SUM(G8:G12)
B14: ASSETS (₹)
B15: Gross fixed assets | C15: =Assumptions!$C$42+Assumptions!$C$43+Assumptions!$C$45+Assumptions!$C$47 | D15: =Assumptions!$C$42+Assumptions!$C$43+Assumptions!$C$45+Assumptions!$C$47 | E15: =Assumptions!$C$42+Assumptions!$C$43+Assumptions!$C$45+Assumptions!$C$47 | F15: =Assumptions!$C$42+Assumptions!$C$43+Assumptions!$C$45+Assumptions!$C$47 | G15: =Assumptions!$C$42+Assumptions!$C$43+Assumptions!$C$45+Assumptions!$C$47
B16: (-) Accumulated depreciation | C16: =Annual_Summary!C18 | D16: =C16+Annual_Summary!D18 | E16: =D16+Annual_Summary!E18 | F16: =E16+Annual_Summary!F18 | G16: =F16+Annual_Summary!G18
B17: Net fixed assets | C17: =C15-C16 | D17: =D15-D16 | E17: =E15-E16 | F17: =F15-F16 | G17: =G15-G16
B18: Inventory | C18: =Form_IV_CA_CL!C10+Form_IV_CA_CL!C11 | D18: =Form_IV_CA_CL!D10+Form_IV_CA_CL!D11 | E18: =Form_IV_CA_CL!E10+Form_IV_CA_CL!E11 | F18: =Form_IV_CA_CL!F10+Form_IV_CA_CL!F11 | G18: =Form_IV_CA_CL!G10+Form_IV_CA_CL!G11
B19: Sundry debtors / receivables | C19: =Form_IV_CA_CL!C12 | D19: =Form_IV_CA_CL!D12 | E19: =Form_IV_CA_CL!E12 | F19: =Form_IV_CA_CL!F12 | G19: =Form_IV_CA_CL!G12
B20: Cash & bank (balancing figure) | C20: =C13-(C17+C18+C19) | D20: =D13-(D17+D18+D19) | E20: =E13-(E17+E18+E19) | F20: =F13-(F17+F18+F19) | G20: =G13-(G17+G18+G19)
B21: TOTAL ASSETS | C21: =C17+C18+C19+C20 | D21: =D17+D18+D19+D20 | E21: =E17+E18+E19+E20 | F21: =F17+F18+F19+F20 | G21: =G17+G18+G19+G20
B22: Check (Liabilities − Assets = 0) | C22: =C13-C21 | D22: =D13-D21 | E22: =E13-E21 | F22: =F13-F21 | G22: =G13-G21

Sheet Form_IV_CA_CL
A1: FORM IV — CURRENT ASSETS & CURRENT LIABILITIES
A2: Build-up of working-capital requirement from holding-period assumptions (₹).
B4: Particulars | C4: Year 1 | D4: Year 2 | E4: Year 3 | F4: Year 4 | G4: Year 5
B5: OPERATING BASIS
B6: Cost of Production | C6: =Annual_Summary!C10+Annual_Summary!C11+Annual_Summary!C12+Annual_Summary!C13+Annual_Summary!C14+Annual_Summary!C15+Annual_Summary!C18 | D6: =Annual_Summary!D10+Annual_Summary!D11+Annual_Summary!D12+Annual_Summary!D13+Annual_Summary!D14+Annual_Summary!D15+Annual_Summary!D18 | E6: =Annual_Summary!E10+Annual_Summary!E11+Annual_Summary!E12+Annual_Summary!E13+Annual_Summary!E14+Annual_Summary!E15+Annual_Summary!E18 | F6: =Annual_Summary!F10+Annual_Summary!F11+Annual_Summary!F12+Annual_Summary!F13+Annual_Summary!F14+Annual_Summary!F15+Annual_Summary!F18 | G6: =Annual_Summary!G10+Annual_Summary!G11+Annual_Summary!G12+Annual_Summary!G13+Annual_Summary!G14+Annual_Summary!G15+Annual_Summary!G18
B7: Purchases (raw material) | C7: =Annual_Summary!C10 | D7: =Annual_Summary!D10 | E7: =Annual_Summary!E10 | F7: =Annual_Summary!F10 | G7: =Annual_Summary!G10
B8: Net Sales | C8: =Annual_Summary!C8 | D8: =Annual_Summary!D8 | E8: =Annual_Summary!E8 | F8: =Annual_Summary!F8 | G8: =Annual_Summary!G8
B9: CURRENT ASSETS (₹)
B10: Inventory — Raw material | C10: =C7*Assumptions!$C$50/365 | D10: =D7*Assumptions!$C$50/365 | E10: =E7*Assumptions!$C$50/365 | F10: =F7*Assumptions!$C$50/365 | G10: =G7*Assumptions!$C$50/365
B11: Inventory — Finished goods | C11: =C6*Assumptions!$C$51/365 | D11: =D6*Assumptions!$C$51/365 | E11: =E6*Assumptions!$C$51/365 | F11: =F6*Assumptions!$C$51/365 | G11: =G6*Assumptions!$C$51/365
B12: Sundry debtors / receivables | C12: =C8*Assumptions!$C$52/365 | D12: =D8*Assumptions!$C$52/365 | E12: =E8*Assumptions!$C$52/365 | F12: =F8*Assumptions!$C$52/365 | G12: =G8*Assumptions!$C$52/365
B13: Cash & bank (minimum) | C13: =Assumptions!$C$54 | D13: =Assumptions!$C$54 | E13: =Assumptions!$C$54 | F13: =Assumptions!$C$54 | G13: =Assumptions!$C$54
B14: Total Current Assets | C14: =SUM(C10:C13) | D14: =SUM(D10:D13) | E14: =SUM(E10:E13) | F14: =SUM(F10:F13) | G14: =SUM(G10:G13)
B15: CURRENT LIABILITIES (other than bank finance) (₹)
B16: Sundry creditors / payables | C16: =C7*Assumptions!$C$53/365 | D16: =D7*Assumptions!$C$53/365 | E16: =E7*Assumptions!$C$53/365 | F16: =F7*Assumptions!$C$53/365 | G16: =G7*Assumptions!$C$53/365
B17: Other current liabilities / provisions | C17: =0 | D17: =0 | E17: =0 | F17: =0 | G17: =0
B18: Total Current Liabilities (excl. bank) | C18: =C16+C17 | D18: =D16+D17 | E18: =E16+E17 | F18: =F16+F17 | G18: =G16+G17
B19: Working Capital Gap (TCA − TCL) | C19: =C14-C18 | D19: =D14-D18 | E19: =E14-E18 | F19: =F14-F18 | G19: =G14-G18

Sheet Form_V_MPBF
A1: FORM V — MAXIMUM PERMISSIBLE BANK FINANCE
A2: MPBF computed on the Tandon methodology; Method II drives the working-capital limit (₹).
B4: Particulars | C4: Year 1 | D4: Year 2 | E4: Year 3 | F4: Year 4 | G4: Year 5
B5: Total Current Assets | C5: =Form_IV_CA_CL!C14 | D5: =Form_IV_CA_CL!D14 | E5: =Form_IV_CA_CL!E14 | F5: =Form_IV_CA_CL!F14 | G5: =Form_IV_CA_CL!G14
B6: Current Liabilities (other than bank) | C6: =Form_IV_CA_CL!C18 | D6: =Form_IV_CA_CL!D18 | E6: =Form_IV_CA_CL!E18 | F6: =Form_IV_CA_CL!F18 | G6: =Form_IV_CA_CL!G18
B7: Working Capital Gap (WCG) | C7: =Form_IV_CA_CL!C19 | D7: =Form_IV_CA_CL!D19 | E7: =Form_IV_CA_CL!E19 | F7: =Form_IV_CA_CL!F19 | G7: =Form_IV_CA_CL!G19
B8: Min. stipulated NWC (margin × CA) | C8: =Assumptions!$C$55*Form_IV_CA_CL!C14 | D8: =Assumptions!$C$55*Form_IV_CA_CL!D14 | E8: =Assumptions!$C$55*Form_IV_CA_CL!E14 | F8: =Assumptions!$C$55*Form_IV_CA_CL!F14 | G8: =Assumptions!$C$55*Form_IV_CA_CL!G14
B9: MPBF — Method I (WCG − margin) | C9: =MAX(0,Form_IV_CA_CL!C19*(1-Assumptions!$C$55)) | D9: =MAX(0,Form_IV_CA_CL!D19*(1-Assumptions!$C$55)) | E9: =MAX(0,Form_IV_CA_CL!E19*(1-Assumptions!$C$55)) | F9: =MAX(0,Form_IV_CA_CL!F19*(1-Assumptions!$C$55)) | G9: =MAX(0,Form_IV_CA_CL!G19*(1-Assumptions!$C$55))
B10: MPBF — Method II (0.75·CA − CL) | C10: =MAX(0,Form_IV_CA_CL!C14*0.75-Form_IV_CA_CL!C18) | D10: =MAX(0,Form_IV_CA_CL!D14*0.75-Form_IV_CA_CL!D18) | E10: =MAX(0,Form_IV_CA_CL!E14*0.75-Form_IV_CA_CL!E18) | F10: =MAX(0,Form_IV_CA_CL!F14*0.75-Form_IV_CA_CL!F18) | G10: =MAX(0,Form_IV_CA_CL!G14*0.75-Form_IV_CA_CL!G18)
B11: Recommended MPBF (Method II, net of surplus cash) | C11: =MAX(0,C10-C13) | D11: =MAX(0,D10-D13) | E11: =MAX(0,E10-E13) | F11: =MAX(0,F10-F13) | G11: =MAX(0,G10-G13)
B12: Cumulative free cash generated (before WC draw) | C12: =Annual_Summary!C27-(Assumptions!$C$42+Assumptions!$C$43+Assumptions!$C$45+Assumptions!$C$47)-(Repayment!C7+'Existing Loan'!C15) | D12: =C12+Annual_Summary!D27-(Repayment!D7+'Existing Loan'!D15) | E12: =D12+Annual_Summary!E27-(Repayment!E7+'Existing Loan'!E15) | F12: =E12+Annual_Summary!F27-(Repayment!F7+'Existing Loan'!F15) | G12: =F12+Annual_Summary!G27-(Repayment!G7+'Existing Loan'!G15)
B13: Available surplus carried in from prior years (over min. cash buffer) | C13: 0 | D13: =MAX(0,C12-Assumptions!$C$54) | E13: =MAX(0,D12-Assumptions!$C$54) | F13: =MAX(0,E12-Assumptions!$C$54) | G13: =MAX(0,F12-Assumptions!$C$54)

Sheet WC & CC-OD Limit
A1: WORKING CAPITAL & LOAN STRUCTURE — MPBF (Tandon) and the borrowing split
A2: Assessed from this model's own current assets and liabilities. Section B splits the borrowing into term loan and working capital, year by year.
B4: Particulars | C4: Year 1 | D4: Year 2 | E4: Year 3 | F4: Year 4 | G4: Year 5
B5: A. WORKING CAPITAL ASSESSMENT (Tandon methodology)
B6: Total Current Assets (TCA) | C6: =Form_IV_CA_CL!C14 | D6: =Form_IV_CA_CL!D14 | E6: =Form_IV_CA_CL!E14 | F6: =Form_IV_CA_CL!F14 | G6: =Form_IV_CA_CL!G14
B7: Current Liabilities other than bank (TCL) | C7: =Form_IV_CA_CL!C18 | D7: =Form_IV_CA_CL!D18 | E7: =Form_IV_CA_CL!E18 | F7: =Form_IV_CA_CL!F18 | G7: =Form_IV_CA_CL!G18
B8: Working Capital Gap (TCA − TCL) | C8: =Form_IV_CA_CL!C19 | D8: =Form_IV_CA_CL!D19 | E8: =Form_IV_CA_CL!E19 | F8: =Form_IV_CA_CL!F19 | G8: =Form_IV_CA_CL!G19
B9: Margin — borrower's stake (%) | C9: =Assumptions!$C$55 | D9: =Assumptions!$C$55 | E9: =Assumptions!$C$55 | F9: =Assumptions!$C$55 | G9: =Assumptions!$C$55
B10: Min. stipulated NWC (margin × TCA) | C10: =C9*C6 | D10: =D9*D6 | E10: =E9*E6 | F10: =F9*F6 | G10: =G9*G6
B11: MPBF — Method I (WCG × (1 − margin)) | C11: =MAX(0,C8*(1-C9)) | D11: =MAX(0,D8*(1-D9)) | E11: =MAX(0,E8*(1-E9)) | F11: =MAX(0,F8*(1-F9)) | G11: =MAX(0,G8*(1-G9))
B12: MPBF — Method II (0.75·TCA − TCL) | C12: =MAX(0,C6*(1-C9)-C7) | D12: =MAX(0,D6*(1-D9)-D7) | E12: =MAX(0,E6*(1-E9)-E7) | F12: =MAX(0,F6*(1-F9)-F7) | G12: =MAX(0,G6*(1-G9)-G7)
B13: RECOMMENDED CC / OD LIMIT (Method II) | C13: =C12 | D13: =D12 | E13: =E12 | F13: =F12 | G13: =G12
B15: B. LOAN STRUCTURE — TERM LOAN vs WORKING CAPITAL
B16: Particulars | C16: Year 1 | D16: Year 2 | E16: Year 3 | F16: Year 4 | G16: Year 5
B17: Term Loan — sanctioned | C17: =Assumptions!$C$8 | D17: =Assumptions!$C$8 | E17: =Assumptions!$C$8 | F17: =Assumptions!$C$8 | G17: =Assumptions!$C$8
B18: Term Loan — opening balance | C18: =Repayment!C5 | D18: =Repayment!D5 | E18: =Repayment!E5 | F18: =Repayment!F5 | G18: =Repayment!G5
B19: Term Loan — principal repaid in the year | C19: =Repayment!C7 | D19: =Repayment!D7 | E19: =Repayment!E7 | F19: =Repayment!F7 | G19: =Repayment!G7
B20: Term Loan — closing balance | C20: =Repayment!C8 | D20: =Repayment!D8 | E20: =Repayment!E8 | F20: =Repayment!F8 | G20: =Repayment!G8
B22: Working Capital (CC/OD) limit assessed | C22: =C13 | D22: =D13 | E22: =E13 | F22: =F13 | G22: =G13
B23: Working Capital — utilised / drawn | C23: =Form_V_MPBF!C11 | D23: =Form_V_MPBF!D11 | E23: =Form_V_MPBF!E11 | F23: =Form_V_MPBF!F11 | G23: =Form_V_MPBF!G11
B25: TOTAL BANK BORROWING (term + working capital) | C25: =C20+C23 | D25: =D20+D23 | E25: =E20+E23 | F25: =F20+F23 | G25: =G20+G23
B26: Promoters' capital / equity | C26: =Assumptions!$C$9 | D26: =Assumptions!$C$9 | E26: =Assumptions!$C$9 | F26: =Assumptions!$C$9 | G26: =Assumptions!$C$9
B27: TOTAL FUNDING (bank + promoters) | C27: =C25+C26 | D27: =D25+D26 | E27: =E25+E26 | F27: =F25+F26 | G27: =G25+G26
B28: Term loan as % of total bank borrowing | C28: =IFERROR(C20/C25,0) | D28: =IFERROR(D20/D25,0) | E28: =IFERROR(E20/E25,0) | F28: =IFERROR(F20/F25,0) | G28: =IFERROR(G20/G25,0)
B29: Working capital as % of total bank borrowing | C29: =IFERROR(C23/C25,0) | D29: =IFERROR(D23/D25,0) | E29: =IFERROR(E23/E25,0) | F29: =IFERROR(F23/F25,0) | G29: =IFERROR(G23/G25,0)
B31: C. FINANCE COST — split by facility
B32: Particulars | C32: Year 1 | D32: Year 2 | E32: Year 3 | F32: Year 4 | G32: Year 5
B33: Interest — Term Loan | C33: =Repayment!C6 | D33: =Repayment!D6 | E33: =Repayment!E6 | F33: =Repayment!F6 | G33: =Repayment!G6
B34: Interest — Working Capital | C34: =C23*Assumptions!$C$13 | D34: =D23*Assumptions!$C$13 | E34: =E23*Assumptions!$C$13 | F34: =F23*Assumptions!$C$13 | G34: =G23*Assumptions!$C$13
B35: TOTAL INTEREST / FINANCE COST | C35: =C33+C34 | D35: =D33+D34 | E35: =E33+E34 | F35: =F33+F34 | G35: =G33+G34
B36: Debt service (interest + term-loan principal) | C36: =C35+C19 | D36: =D35+D19 | E36: =E35+E19 | F36: =F35+F19 | G36: =G35+G19

Sheet Form_VI_FundFlow
A1: FORM VI — FUND FLOW STATEMENT
A2: Year-on-year sources and applications of funds (₹).
B4: Particulars | C4: Year 1 | D4: Year 2 | E4: Year 3 | F4: Year 4 | G4: Year 5
B5: SOURCES OF FUNDS (₹)
B6: Cash accrual (PAT + Depreciation) | C6: =Annual_Summary!C27 | D6: =Annual_Summary!D27 | E6: =Annual_Summary!E27 | F6: =Annual_Summary!F27 | G6: =Annual_Summary!G27
B7: Capital introduced | C7: =Assumptions!$C$9 | D7: =0 | E7: =0 | F7: =0 | G7: =0
B8: Term loan raised / existing loan brought forward | C8: =Assumptions!$C$8+IF(Assumptions!$C$72=2,Assumptions!$C$73,0) | D8: =0 | E8: =0 | F8: =0 | G8: =0
B9: Increase / (decrease) in bank WC finance | C9: =Form_V_MPBF!C11 | D9: =(Form_V_MPBF!D11-Form_V_MPBF!C11) | E9: =(Form_V_MPBF!E11-Form_V_MPBF!D11) | F9: =(Form_V_MPBF!F11-Form_V_MPBF!E11) | G9: =(Form_V_MPBF!G11-Form_V_MPBF!F11)
B10: Increase / (decrease) in creditors | C10: =Form_IV_CA_CL!C16 | D10: =(Form_IV_CA_CL!D16-Form_IV_CA_CL!C16) | E10: =(Form_IV_CA_CL!E16-Form_IV_CA_CL!D16) | F10: =(Form_IV_CA_CL!F16-Form_IV_CA_CL!E16) | G10: =(Form_IV_CA_CL!G16-Form_IV_CA_CL!F16)
B11: TOTAL SOURCES (A) | C11: =SUM(C6:C10) | D11: =SUM(D6:D10) | E11: =SUM(E6:E10) | F11: =SUM(F6:F10) | G11: =SUM(G6:G10)
B12: APPLICATION OF FUNDS (₹)
B13: Capital expenditure (fixed assets) | C13: =Form_III_BalanceSheet!C15 | D13: =(Form_III_BalanceSheet!D15-Form_III_BalanceSheet!C15) | E13: =(Form_III_BalanceSheet!E15-Form_III_BalanceSheet!D15) | F13: =(Form_III_BalanceSheet!F15-Form_III_BalanceSheet!E15) | G13: =(Form_III_BalanceSheet!G15-Form_III_BalanceSheet!F15)
B14: Repayment of term loan | C14: =Repayment!C7+'Existing Loan'!C15 | D14: =Repayment!D7+'Existing Loan'!D15 | E14: =Repayment!E7+'Existing Loan'!E15 | F14: =Repayment!F7+'Existing Loan'!F15 | G14: =Repayment!G7+'Existing Loan'!G15
B15: Increase / (decrease) in current assets | C15: =(Form_III_BalanceSheet!C18+Form_III_BalanceSheet!C19+Form_III_BalanceSheet!C20) | D15: =((Form_III_BalanceSheet!D18+Form_III_BalanceSheet!D19+Form_III_BalanceSheet!D20)-(Form_III_BalanceSheet!C18+Form_III_BalanceSheet!C19+Form_III_BalanceSheet!C20)) | E15: =((Form_III_BalanceSheet!E18+Form_III_BalanceSheet!E19+Form_III_BalanceSheet!E20)-(Form_III_BalanceSheet!D18+Form_III_BalanceSheet!D19+Form_III_BalanceSheet!D20)) | F15: =((Form_III_BalanceSheet!F18+Form_III_BalanceSheet!F19+Form_III_BalanceSheet!F20)-(Form_III_BalanceSheet!E18+Form_III_BalanceSheet!E19+Form_III_BalanceSheet!E20)) | G15: =((Form_III_BalanceSheet!G18+Form_III_BalanceSheet!G19+Form_III_BalanceSheet!G20)-(Form_III_BalanceSheet!F18+Form_III_BalanceSheet!F19+Form_III_BalanceSheet!F20))
B16: TOTAL APPLICATIONS (B) | C16: =SUM(C13:C15) | D16: =SUM(D13:D15) | E16: =SUM(E13:E15) | F16: =SUM(F13:F15) | G16: =SUM(G13:G15)
B17: Net Surplus / (Deficit) (A − B) | C17: =C11-C16 | D17: =D11-D16 | E17: =E11-E16 | F17: =F11-F16 | G17: =G11-G16

Sheet Repayment
A1: TERM LOAN — REPAYMENT SCHEDULE
A2: ="Interest @ "&TEXT(Assumptions!$C$10,"0.00%")&" p.a. on the reducing balance · Tenure "&TEXT(Assumptions!$C$11,"0")&" months · Moratorium "&TEXT(Assumptions!$C$12,"0")&" months · Sanctioned "&TEXT(Assumptions!$C$8,"#,##0")
B4: Particulars | C4: Year 1 | D4: Year 2 | E4: Year 3 | F4: Year 4 | G4: Year 5
B5: Opening balance | C5: =Assumptions!$C$8 | D5: =C8 | E5: =D8 | F5: =E8 | G5: =F8
B6: Interest for the year | C6: =SUM(C25:N25) | D6: =SUM(C32:N32) | E6: =SUM(C39:N39) | F6: =SUM(C46:N46) | G6: =SUM(C53:N53)
B7: Principal repayment | C7: =SUM(C26:N26) | D7: =SUM(C33:N33) | E7: =SUM(C40:N40) | F7: =SUM(C47:N47) | G7: =SUM(C54:N54)
B8: Closing balance | C8: =C5-C7 | D8: =D5-D7 | E8: =E5-E7 | F8: =F5-F7 | G8: =G5-G7
B10: Note: schedule shows the first 5 years of the projection horizon; any balance beyond Year 5 continues per the sanctioned tenure.
A12: MONTH-BY-MONTH REPAYMENT SCHEDULE
A13: Interest accrues monthly on the reducing balance; principal is nil during the moratorium and starts thereafter. Each year's totals are the sum of its months.
B15: Sanctioned term loan | C15: =Assumptions!$C$8
B16: Interest rate on term loan (per annum) | C16: =Assumptions!$C$10
B17: Tenure (months) | C17: =Assumptions!$C$11
B18: Moratorium / holiday period (months) | C18: =Assumptions!$C$12
B19: Monthly principal instalment | C19: =IFERROR(Assumptions!$C$8/(Assumptions!$C$11/12-Assumptions!$C$12/12)/12,0)
A22: YEAR 1
B23: Particulars | C23: M1 | D23: M2 | E23: M3 | F23: M4 | G23: M5 | H23: M6 | I23: M7 | J23: M8 | K23: M9 | L23: M10 | M23: M11 | N23: M12 | O23: Year 1 Total
B24: Opening balance | C24: =$C$5 | D24: =C27 | E24: =D27 | F24: =E27 | G24: =F27 | H24: =G27 | I24: =H27 | J24: =I27 | K24: =J27 | ... N24: =M27 | O24: =$C$5
B25: Interest for the month | C25: =C24*Assumptions!$C$10/12 | D25: =D24*Assumptions!$C$10/12 | E25: =E24*Assumptions!$C$10/12 | F25: =F24*Assumptions!$C$10/12 | G25: =G24*Assumptions!$C$10/12 | H25: =H24*Assumptions!$C$10/12 | I25: =I24*Assumptions!$C$10/12 | J25: =J24*Assumptions!$C$10/12 | ... N25: =N24*Assumptions!$C$10/12 | O25: =SUM(C25:N25)
B26: Principal repayment | C26: =IF(1<=Assumptions!$C$12,0,MIN(C24,$C$19)) | D26: =IF(2<=Assumptions!$C$12,0,MIN(D24,$C$19)) | E26: =IF(3<=Assumptions!$C$12,0,MIN(E24,$C$19)) | F26: =IF(4<=Assumptions!$C$12,0,MIN(F24,$C$19)) | G26: =IF(5<=Assumptions!$C$12,0,MIN(G24,$C$19)) | H26: =IF(6<=Assumptions!$C$12,0,MIN(H24,$C$19)) | I26: =IF(7<=Assumptions!$C$12,0,MIN(I24,$C$19)) | J26: =IF(8<=Assumptions!$C$12,0,MIN(J24,$C$19)) | K26: =IF(9<=Assumptions!$C$12,0,MIN(K24,$C$19)) | L26: =IF(10<=Assumptions!$C$12,0,MIN(L24,$C$19)) | M26: =IF(11<=Assumptions!$C$12,0,MIN(M24,$C$19)) | N26: =IF(12<=Assumptions!$C$12,0,MIN(N24,$C$19)) | O26: =SUM(C26:N26)
B27: Closing balance | C27: =C24-C26 | D27: =D24-D26 | E27: =E24-E26 | F27: =F24-F26 | G27: =G24-G26 | H27: =H24-H26 | I27: =I24-I26 | J27: =J24-J26 | ... N27: =N24-N26 | O27: =$C$8
A29: YEAR 2
B30: Particulars | C30: M1 | D30: M2 | E30: M3 | F30: M4 | G30: M5 | H30: M6 | I30: M7 | J30: M8 | K30: M9 | L30: M10 | M30: M11 | N30: M12 | O30: Year 2 Total
B31: Opening balance | C31: =$D$5 | D31: =C34 | E31: =D34 | F31: =E34 | G31: =F34 | H31: =G34 | I31: =H34 | J31: =I34 | K31: =J34 | ... N31: =M34 | O31: =$D$5
B32: Interest for the month | C32: =C31*Assumptions!$C$10/12 | D32: =D31*Assumptions!$C$10/12 | E32: =E31*Assumptions!$C$10/12 | F32: =F31*Assumptions!$C$10/12 | G32: =G31*Assumptions!$C$10/12 | H32: =H31*Assumptions!$C$10/12 | I32: =I31*Assumptions!$C$10/12 | J32: =J31*Assumptions!$C$10/12 | ... N32: =N31*Assumptions!$C$10/12 | O32: =SUM(C32:N32)
B33: Principal repayment | C33: =IF(13<=Assumptions!$C$12,0,MIN(C31,$C$19)) | D33: =IF(14<=Assumptions!$C$12,0,MIN(D31,$C$19)) | E33: =IF(15<=Assumptions!$C$12,0,MIN(E31,$C$19)) | F33: =IF(16<=Assumptions!$C$12,0,MIN(F31,$C$19)) | G33: =IF(17<=Assumptions!$C$12,0,MIN(G31,$C$19)) | H33: =IF(18<=Assumptions!$C$12,0,MIN(H31,$C$19)) | I33: =IF(19<=Assumptions!$C$12,0,MIN(I31,$C$19)) | J33: =IF(20<=Assumptions!$C$12,0,MIN(J31,$C$19)) | K33: =IF(21<=Assumptions!$C$12,0,MIN(K31,$C$19)) | L33: =IF(22<=Assumptions!$C$12,0,MIN(L31,$C$19)) | M33: =IF(23<=Assumptions!$C$12,0,MIN(M31,$C$19)) | N33: =IF(24<=Assumptions!$C$12,0,MIN(N31,$C$19)) | O33: =SUM(C33:N33)
B34: Closing balance | C34: =C31-C33 | D34: =D31-D33 | E34: =E31-E33 | F34: =F31-F33 | G34: =G31-G33 | H34: =H31-H33 | I34: =I31-I33 | J34: =J31-J33 | ... N34: =N31-N33 | O34: =$D$8
A36: YEAR 3
B37: Particulars | C37: M1 | D37: M2 | E37: M3 | F37: M4 | G37: M5 | H37: M6 | I37: M7 | J37: M8 | K37: M9 | L37: M10 | M37: M11 | N37: M12 | O37: Year 3 Total
B38: Opening balance | C38: =$E$5 | D38: =C41 | E38: =D41 | F38: =E41 | G38: =F41 | H38: =G41 | I38: =H41 | J38: =I41 | K38: =J41 | ... N38: =M41 | O38: =$E$5
B39: Interest for the month | C39: =C38*Assumptions!$C$10/12 | D39: =D38*Assumptions!$C$10/12 | E39: =E38*Assumptions!$C$10/12 | F39: =F38*Assumptions!$C$10/12 | G39: =G38*Assumptions!$C$10/12 | H39: =H38*Assumptions!$C$10/12 | I39: =I38*Assumptions!$C$10/12 | J39: =J38*Assumptions!$C$10/12 | ... N39: =N38*Assumptions!$C$10/12 | O39: =SUM(C39:N39)
B40: Principal repayment | C40: =IF(25<=Assumptions!$C$12,0,MIN(C38,$C$19)) | D40: =IF(26<=Assumptions!$C$12,0,MIN(D38,$C$19)) | E40: =IF(27<=Assumptions!$C$12,0,MIN(E38,$C$19)) | F40: =IF(28<=Assumptions!$C$12,0,MIN(F38,$C$19)) | G40: =IF(29<=Assumptions!$C$12,0,MIN(G38,$C$19)) | H40: =IF(30<=Assumptions!$C$12,0,MIN(H38,$C$19)) | I40: =IF(31<=Assumptions!$C$12,0,MIN(I38,$C$19)) | J40: =IF(32<=Assumptions!$C$12,0,MIN(J38,$C$19)) | K40: =IF(33<=Assumptions!$C$12,0,MIN(K38,$C$19)) | L40: =IF(34<=Assumptions!$C$12,0,MIN(L38,$C$19)) | M40: =IF(35<=Assumptions!$C$12,0,MIN(M38,$C$19)) | N40: =IF(36<=Assumptions!$C$12,0,MIN(N38,$C$19)) | O40: =SUM(C40:N40)
B41: Closing balance | C41: =C38-C40 | D41: =D38-D40 | E41: =E38-E40 | F41: =F38-F40 | G41: =G38-G40 | H41: =H38-H40 | I41: =I38-I40 | J41: =J38-J40 | ... N41: =N38-N40 | O41: =$E$8
A43: YEAR 4
B44: Particulars | C44: M1 | D44: M2 | E44: M3 | F44: M4 | G44: M5 | H44: M6 | I44: M7 | J44: M8 | K44: M9 | L44: M10 | M44: M11 | N44: M12 | O44: Year 4 Total
B45: Opening balance | C45: =$F$5 | D45: =C48 | E45: =D48 | F45: =E48 | G45: =F48 | H45: =G48 | I45: =H48 | J45: =I48 | K45: =J48 | ... N45: =M48 | O45: =$F$5
B46: Interest for the month | C46: =C45*Assumptions!$C$10/12 | D46: =D45*Assumptions!$C$10/12 | E46: =E45*Assumptions!$C$10/12 | F46: =F45*Assumptions!$C$10/12 | G46: =G45*Assumptions!$C$10/12 | H46: =H45*Assumptions!$C$10/12 | I46: =I45*Assumptions!$C$10/12 | J46: =J45*Assumptions!$C$10/12 | ... N46: =N45*Assumptions!$C$10/12 | O46: =SUM(C46:N46)
B47: Principal repayment | C47: =IF(37<=Assumptions!$C$12,0,MIN(C45,$C$19)) | D47: =IF(38<=Assumptions!$C$12,0,MIN(D45,$C$19)) | E47: =IF(39<=Assumptions!$C$12,0,MIN(E45,$C$19)) | F47: =IF(40<=Assumptions!$C$12,0,MIN(F45,$C$19)) | G47: =IF(41<=Assumptions!$C$12,0,MIN(G45,$C$19)) | H47: =IF(42<=Assumptions!$C$12,0,MIN(H45,$C$19)) | I47: =IF(43<=Assumptions!$C$12,0,MIN(I45,$C$19)) | J47: =IF(44<=Assumptions!$C$12,0,MIN(J45,$C$19)) | K47: =IF(45<=Assumptions!$C$12,0,MIN(K45,$C$19)) | L47: =IF(46<=Assumptions!$C$12,0,MIN(L45,$C$19)) | M47: =IF(47<=Assumptions!$C$12,0,MIN(M45,$C$19)) | N47: =IF(48<=Assumptions!$C$12,0,MIN(N45,$C$19)) | O47: =SUM(C47:N47)
B48: Closing balance | C48: =C45-C47 | D48: =D45-D47 | E48: =E45-E47 | F48: =F45-F47 | G48: =G45-G47 | H48: =H45-H47 | I48: =I45-I47 | J48: =J45-J47 | ... N48: =N45-N47 | O48: =$F$8
A50: YEAR 5
B51: Particulars | C51: M1 | D51: M2 | E51: M3 | F51: M4 | G51: M5 | H51: M6 | I51: M7 | J51: M8 | K51: M9 | L51: M10 | M51: M11 | N51: M12 | O51: Year 5 Total
B52: Opening balance | C52: =$G$5 | D52: =C55 | E52: =D55 | F52: =E55 | G52: =F55 | H52: =G55 | I52: =H55 | J52: =I55 | K52: =J55 | ... N52: =M55 | O52: =$G$5
B53: Interest for the month | C53: =C52*Assumptions!$C$10/12 | D53: =D52*Assumptions!$C$10/12 | E53: =E52*Assumptions!$C$10/12 | F53: =F52*Assumptions!$C$10/12 | G53: =G52*Assumptions!$C$10/12 | H53: =H52*Assumptions!$C$10/12 | I53: =I52*Assumptions!$C$10/12 | J53: =J52*Assumptions!$C$10/12 | ... N53: =N52*Assumptions!$C$10/12 | O53: =SUM(C53:N53)
B54: Principal repayment | C54: =IF(49<=Assumptions!$C$12,0,MIN(C52,$C$19)) | D54: =IF(50<=Assumptions!$C$12,0,MIN(D52,$C$19)) | E54: =IF(51<=Assumptions!$C$12,0,MIN(E52,$C$19)) | F54: =IF(52<=Assumptions!$C$12,0,MIN(F52,$C$19)) | G54: =IF(53<=Assumptions!$C$12,0,MIN(G52,$C$19)) | H54: =IF(54<=Assumptions!$C$12,0,MIN(H52,$C$19)) | I54: =IF(55<=Assumptions!$C$12,0,MIN(I52,$C$19)) | J54: =IF(56<=Assumptions!$C$12,0,MIN(J52,$C$19)) | K54: =IF(57<=Assumptions!$C$12,0,MIN(K52,$C$19)) | L54: =IF(58<=Assumptions!$C$12,0,MIN(L52,$C$19)) | M54: =IF(59<=Assumptions!$C$12,0,MIN(M52,$C$19)) | N54: =IF(60<=Assumptions!$C$12,0,MIN(N52,$C$19)) | O54: =SUM(C54:N54)
B55: Closing balance | C55: =C52-C54 | D55: =D52-D54 | E55: =E52-E54 | F55: =F52-F54 | G55: =G52-G54 | H55: =H52-H54 | I55: =I52-I54 | J55: =J52-J54 | ... N55: =N52-N54 | O55: =$G$8

Sheet Existing Loan
A1: EXISTING LOAN — take-over or additional facility
A2: Set the treatment on Assumptions row 72. On take-over the new term loan clears this debt, so it stops costing interest and leaves the balance sheet; on 'additional' it runs alongside and is part of debt service.
B3: Particulars | C3: Year 1 | D3: Year 2 | E3: Year 3 | F3: Year 4 | G3: Year 5
B4: Outstanding today | C4: =Assumptions!$C$73
B5: Interest rate (% p.a.) | C5: =Assumptions!$C$74
B6: Remaining tenure (months) / annual principal | C6: =Assumptions!$C$75 | D6: =IFERROR(Assumptions!$C$73/(Assumptions!$C$75/12),0)
B7: A. AMORTISATION OF THE EXISTING FACILITY (as if it continues)
B8: Opening balance | C8: =Assumptions!$C$73 | D8: =C11 | E8: =D11 | F8: =E11 | G8: =F11
B9: Interest for the year | C9: =C8*Assumptions!$C$74 | D9: =D8*Assumptions!$C$74 | E9: =E8*Assumptions!$C$74 | F9: =F8*Assumptions!$C$74 | G9: =G8*Assumptions!$C$74
B10: Principal repayment | C10: =MIN(C8,$D$6) | D10: =MIN(D8,$D$6) | E10: =MIN(E8,$D$6) | F10: =MIN(F8,$D$6) | G10: =MIN(G8,$D$6)
B11: Closing balance | C11: =C8-C10 | D11: =D8-D10 | E11: =E8-E10 | F11: =F8-F10 | G11: =G8-G10
B13: B. WHAT THE MODEL ACTUALLY CHARGES (after the treatment switch)
B14: Interest charged to the P&L | C14: =IF(Assumptions!$C$72=2,C9,0) | D14: =IF(Assumptions!$C$72=2,D9,0) | E14: =IF(Assumptions!$C$72=2,E9,0) | F14: =IF(Assumptions!$C$72=2,F9,0) | G14: =IF(Assumptions!$C$72=2,G9,0)
B15: Principal repaid in the year | C15: =IF(Assumptions!$C$72=2,C10,0) | D15: =IF(Assumptions!$C$72=2,D10,0) | E15: =IF(Assumptions!$C$72=2,E10,0) | F15: =IF(Assumptions!$C$72=2,F10,0) | G15: =IF(Assumptions!$C$72=2,G10,0)
B16: Closing balance carried to the balance sheet | C16: =IF(Assumptions!$C$72=2,C11,0) | D16: =IF(Assumptions!$C$72=2,D11,0) | E16: =IF(Assumptions!$C$72=2,E11,0) | F16: =IF(Assumptions!$C$72=2,F11,0) | G16: =IF(Assumptions!$C$72=2,G11,0)
B17: Taken over by the new term loan (Year 1) | C17: =IF(Assumptions!$C$72=1,Assumptions!$C$73,0) | D17: =0 | E17: =0 | F17: =0 | G17: =0

Sheet DSCR
A1: DEBT SERVICE COVERAGE (DSCR)
A2: Repayment capacity: cash available for debt service ÷ debt obligation.
B4: Particulars | C4: Year 1 | D4: Year 2 | E4: Year 3 | F4: Year 4 | G4: Year 5 | H4: Average
B5: Cash available for debt service (₹)
B6: Profit After Tax | C6: =Annual_Summary!C26 | D6: =Annual_Summary!D26 | E6: =Annual_Summary!E26 | F6: =Annual_Summary!F26 | G6: =Annual_Summary!G26
B7: (+) Depreciation | C7: =Annual_Summary!C18 | D7: =Annual_Summary!D18 | E7: =Annual_Summary!E18 | F7: =Annual_Summary!F18 | G7: =Annual_Summary!G18
B8: (+) Interest on Term Loan | C8: =Repayment!C6+'Existing Loan'!C14 | D8: =Repayment!D6+'Existing Loan'!D14 | E8: =Repayment!E6+'Existing Loan'!E14 | F8: =Repayment!F6+'Existing Loan'!F14 | G8: =Repayment!G6+'Existing Loan'!G14
B9: Cash Available for Debt Service (A) | C9: =C6+C7+C8 | D9: =D6+D7+D8 | E9: =E6+E7+E8 | F9: =F6+F7+F8 | G9: =G6+G7+G8
B10: Debt obligation (₹)
B11: Principal repayment | C11: =Repayment!C7+'Existing Loan'!C15 | D11: =Repayment!D7+'Existing Loan'!D15 | E11: =Repayment!E7+'Existing Loan'!E15 | F11: =Repayment!F7+'Existing Loan'!F15 | G11: =Repayment!G7+'Existing Loan'!G15
B12: Interest on Term Loan | C12: =Repayment!C6+'Existing Loan'!C14 | D12: =Repayment!D6+'Existing Loan'!D14 | E12: =Repayment!E6+'Existing Loan'!E14 | F12: =Repayment!F6+'Existing Loan'!F14 | G12: =Repayment!G6+'Existing Loan'!G14
B13: Total Debt Obligation (B) | C13: =C11+C12 | D13: =D11+D12 | E13: =E11+E12 | F13: =F11+F12 | G13: =G11+G12
B14: DSCR (A ÷ B) | C14: =IFERROR(C9/C13,0) | D14: =IFERROR(D9/D13,0) | E14: =IFERROR(E9/E13,0) | F14: =IFERROR(F9/F13,0) | G14: =IFERROR(G9/G13,0) | H14: =IFERROR(AVERAGE(C14:G14),0)

Sheet Ratios
A1: FINANCIAL VIABILITY — KEY RATIOS
A2: Liquidity, leverage, profitability and coverage indicators for appraisal.
B4: Particulars | C4: Year 1 | D4: Year 2 | E4: Year 3 | F4: Year 4 | G4: Year 5
B5: LIQUIDITY & LEVERAGE
B6: Current Ratio | C6: =IFERROR((Form_III_BalanceSheet!C18+Form_III_BalanceSheet!C19+Form_III_BalanceSheet!C20)/(Form_III_BalanceSheet!C11+Form_III_BalanceSheet!C12+Form_III_BalanceSheet!C10),0) | D6: =IFERROR((Form_III_BalanceSheet!D18+Form_III_BalanceSheet!D19+Form_III_BalanceSheet!D20)/(Form_III_BalanceSheet!D11+Form_III_BalanceSheet!D12+Form_III_BalanceSheet!D10),0) | E6: =IFERROR((Form_III_BalanceSheet!E18+Form_III_BalanceSheet!E19+Form_III_BalanceSheet!E20)/(Form_III_BalanceSheet!E11+Form_III_BalanceSheet!E12+Form_III_BalanceSheet!E10),0) | F6: =IFERROR((Form_III_BalanceSheet!F18+Form_III_BalanceSheet!F19+Form_III_BalanceSheet!F20)/(Form_III_BalanceSheet!F11+Form_III_BalanceSheet!F12+Form_III_BalanceSheet!F10),0) | G6: =IFERROR((Form_III_BalanceSheet!G18+Form_III_BalanceSheet!G19+Form_III_BalanceSheet!G20)/(Form_III_BalanceSheet!G11+Form_III_BalanceSheet!G12+Form_III_BalanceSheet!G10),0)
B7: Debt–Equity Ratio | C7: =IFERROR((Form_III_BalanceSheet!C9+Form_III_BalanceSheet!C10)/Form_III_BalanceSheet!C8,0) | D7: =IFERROR((Form_III_BalanceSheet!D9+Form_III_BalanceSheet!D10)/Form_III_BalanceSheet!D8,0) | E7: =IFERROR((Form_III_BalanceSheet!E9+Form_III_BalanceSheet!E10)/Form_III_BalanceSheet!E8,0) | F7: =IFERROR((Form_III_BalanceSheet!F9+Form_III_BalanceSheet!F10)/Form_III_BalanceSheet!F8,0) | G7: =IFERROR((Form_III_BalanceSheet!G9+Form_III_BalanceSheet!G10)/Form_III_BalanceSheet!G8,0)
B8: TOL / TNW | C8: =IFERROR((Form_III_BalanceSheet!C9+Form_III_BalanceSheet!C10+Form_III_BalanceSheet!C11+Form_III_BalanceSheet!C12)/Form_III_BalanceSheet!C8,0) | D8: =IFERROR((Form_III_BalanceSheet!D9+Form_III_BalanceSheet!D10+Form_III_BalanceSheet!D11+Form_III_BalanceSheet!D12)/Form_III_BalanceSheet!D8,0) | E8: =IFERROR((Form_III_BalanceSheet!E9+Form_III_BalanceSheet!E10+Form_III_BalanceSheet!E11+Form_III_BalanceSheet!E12)/Form_III_BalanceSheet!E8,0) | F8: =IFERROR((Form_III_BalanceSheet!F9+Form_III_BalanceSheet!F10+Form_III_BalanceSheet!F11+Form_III_BalanceSheet!F12)/Form_III_BalanceSheet!F8,0) | G8: =IFERROR((Form_III_BalanceSheet!G9+Form_III_BalanceSheet!G10+Form_III_BalanceSheet!G11+Form_III_BalanceSheet!G12)/Form_III_BalanceSheet!G8,0)
B9: PROFITABILITY
B10: EBITDA Margin | C10: =IFERROR(Annual_Summary!C22/Annual_Summary!C8,0) | D10: =IFERROR(Annual_Summary!D22/Annual_Summary!D8,0) | E10: =IFERROR(Annual_Summary!E22/Annual_Summary!E8,0) | F10: =IFERROR(Annual_Summary!F22/Annual_Summary!F8,0) | G10: =IFERROR(Annual_Summary!G22/Annual_Summary!G8,0)
B11: Net Profit Margin | C11: =IFERROR(Annual_Summary!C26/Annual_Summary!C8,0) | D11: =IFERROR(Annual_Summary!D26/Annual_Summary!D8,0) | E11: =IFERROR(Annual_Summary!E26/Annual_Summary!E8,0) | F11: =IFERROR(Annual_Summary!F26/Annual_Summary!F8,0) | G11: =IFERROR(Annual_Summary!G26/Annual_Summary!G8,0)
B12: Return on Capital Employed | C12: =IFERROR(Annual_Summary!C23/(Form_III_BalanceSheet!C8+Form_III_BalanceSheet!C9),0) | D12: =IFERROR(Annual_Summary!D23/(Form_III_BalanceSheet!D8+Form_III_BalanceSheet!D9),0) | E12: =IFERROR(Annual_Summary!E23/(Form_III_BalanceSheet!E8+Form_III_BalanceSheet!E9),0) | F12: =IFERROR(Annual_Summary!F23/(Form_III_BalanceSheet!F8+Form_III_BalanceSheet!F9),0) | G12: =IFERROR(Annual_Summary!G23/(Form_III_BalanceSheet!G8+Form_III_BalanceSheet!G9),0)
B13: COVERAGE & RISK
B14: Interest Coverage | C14: =IFERROR(Annual_Summary!C23/(Annual_Summary!C19+Annual_Summary!C20),0) | D14: =IFERROR(Annual_Summary!D23/(Annual_Summary!D19+Annual_Summary!D20),0) | E14: =IFERROR(Annual_Summary!E23/(Annual_Summary!E19+Annual_Summary!E20),0) | F14: =IFERROR(Annual_Summary!F23/(Annual_Summary!F19+Annual_Summary!F20),0) | G14: =IFERROR(Annual_Summary!G23/(Annual_Summary!G19+Annual_Summary!G20),0)
B15: DSCR | C15: =DSCR!C14 | D15: =DSCR!D14 | E15: =DSCR!E14 | F15: =DSCR!F14 | G15: =DSCR!G14
B16: Break-even (% of sales) | C16: =IFERROR((Annual_Summary!C12+Annual_Summary!C14+Annual_Summary!C15+Annual_Summary!C16+Annual_Summary!C18+Annual_Summary!C19+Annual_Summary!C20)/(Annual_Summary!C8-(Annual_Summary!C10+Annual_Summary!C11+Annual_Summary!C13+Annual_Summary!C17)),0) | D16: =IFERROR((Annual_Summary!D12+Annual_Summary!D14+Annual_Summary!D15+Annual_Summary!D16+Annual_Summary!D18+Annual_Summary!D19+Annual_Summary!D20)/(Annual_Summary!D8-(Annual_Summary!D10+Annual_Summary!D11+Annual_Summary!D13+Annual_Summary!D17)),0) | E16: =IFERROR((Annual_Summary!E12+Annual_Summary!E14+Annual_Summary!E15+Annual_Summary!E16+Annual_Summary!E18+Annual_Summary!E19+Annual_Summary!E20)/(Annual_Summary!E8-(Annual_Summary!E10+Annual_Summary!E11+Annual_Summary!E13+Annual_Summary!E17)),0) | F16: =IFERROR((Annual_Summary!F12+Annual_Summary!F14+Annual_Summary!F15+Annual_Summary!F16+Annual_Summary!F18+Annual_Summary!F19+Annual_Summary!F20)/(Annual_Summary!F8-(Annual_Summary!F10+Annual_Summary!F11+Annual_Summary!F13+Annual_Summary!F17)),0) | G16: =IFERROR((Annual_Summary!G12+Annual_Summary!G14+Annual_Summary!G15+Annual_Summary!G16+Annual_Summary!G18+Annual_Summary!G19+Annual_Summary!G20)/(Annual_Summary!G8-(Annual_Summary!G10+Annual_Summary!G11+Annual_Summary!G13+Annual_Summary!G17)),0)

Sheet Conclusion
B2: CONCLUSION & SUMMARY ANALYSIS
B3: Executive verdict on financial viability and bankability of the project
B5: PROJECT SNAPSHOT
B6: Name of the Unit | C6: =Assumptions!C5
B7: Constitution | C7: =Assumptions!C6
B8: Line of Activity | C8: =Assumptions!C7
B9: Industry | C9: =Assumptions!J5
B10: Term Loan applied for (₹) | C10: =Assumptions!C8
B11: Promoters' Capital (₹) | C11: =Assumptions!C9
B13: KEY FINANCIAL INDICATORS (₹, all five years)
B14: Particulars | C14: Year 1 | D14: Year 2 | E14: Year 3 | F14: Year 4 | G14: Year 5
B15: Net Sales / Revenue | C15: =Annual_Summary!C8 | D15: =Annual_Summary!D8 | E15: =Annual_Summary!E8 | F15: =Annual_Summary!F8 | G15: =Annual_Summary!G8
B16: EBITDA | C16: =Annual_Summary!C22 | D16: =Annual_Summary!D22 | E16: =Annual_Summary!E22 | F16: =Annual_Summary!F22 | G16: =Annual_Summary!G22
B17: Profit After Tax (PAT) | C17: =Annual_Summary!C26 | D17: =Annual_Summary!D26 | E17: =Annual_Summary!E26 | F17: =Annual_Summary!F26 | G17: =Annual_Summary!G26
B18: Cash Accrual (PAT + Dep.) | C18: =Annual_Summary!C27 | D18: =Annual_Summary!D27 | E18: =Annual_Summary!E27 | F18: =Annual_Summary!F27 | G18: =Annual_Summary!G27
B19: Current Ratio | C19: =Ratios!C6 | D19: =Ratios!D6 | E19: =Ratios!E6 | F19: =Ratios!F6 | G19: =Ratios!G6
B20: Debt–Equity Ratio | C20: =Ratios!C7 | D20: =Ratios!D7 | E20: =Ratios!E7 | F20: =Ratios!F7 | G20: =Ratios!G7
B21: Net Profit Margin | C21: =Ratios!C11 | D21: =Ratios!D11 | E21: =Ratios!E11 | F21: =Ratios!F11 | G21: =Ratios!G11
B22: DSCR | C22: =DSCR!C14 | D22: =DSCR!D14 | E22: =DSCR!E14 | F22: =DSCR!F14 | G22: =DSCR!G14
B24: BANKABILITY VERDICT
B25: Average DSCR (5-yr) | C25: =AVERAGE(DSCR!C14:G14) | D25: =IFERROR(IF(OR(MAX(Annual_Summary!C22/Annual_Summary!C8,Annual_Summary!D22/Annual_Summary!D8,Annual_Summary!E22/Annual_Summary!E8,Annual_Summary!F22/Annual_Summary!F8,Annual_Summary!G22/Annual_Summary!G8)>0.4,Annual_Summary!C8/(C10+C11)<0.3,Annual_Summary!C8/(C10+C11)>8,AVERAGE(DSCR!C14:G14)>10),"REVIEW REQUIRED — figures need verification (EBITDA margin, revenue/cost scale, or DSCR outside normal range)",IF(AND(AVERAGE(DSCR!C14:G14)>=1.5,MIN(DSCR!C14:G14)>=1.25),"STRONG — comfortably serviceable (avg DSCR >= 1.50, minimum-year DSCR >= 1.25)",IF(AND(AVERAGE(DSCR!C14:G14)>=1.2,MIN(DSCR!C14:G14)>=1.0),"BANKABLE — meets the 1.20 minimum average DSCR with no year below 1.00","BELOW NORM — average or minimum-year DSCR under the bank floor"))),"REVIEW REQUIRED — could not verify DSCR / scale ratios (check inputs)")
B26: Minimum DSCR (5-yr) | C26: =MIN(DSCR!C14:G14)
B27: CONCLUSION

Sheet Dashboard
B1: INVESTMENT DASHBOARD
B3: Bank & investor summary — every figure is a live formula and recalculates from the Assumptions sheet.
B4: SNAPSHOT YEAR → | C4: 1 | D4: ← pick 1-5; the four cards below follow it
B6: REVENUE | F6: EBITDA | J6: NET PROFIT (PAT) | N6: CASH & BANK
B7: =INDEX(Annual_Summary!$C$8:$G$8,1,$C$4) | F7: =INDEX(Annual_Summary!$C$22:$G$22,1,$C$4) | J7: =INDEX(Annual_Summary!$C$26:$G$26,1,$C$4) | N7: =INDEX(Form_III_BalanceSheet!$C$20:$G$20,1,$C$4)
B8: Net sales, selected year · from Annual_Summary | F8: Operating profit before D&I · from Annual_Summary | J8: Profit after tax · from Annual_Summary | N8: Closing cash & bank balance · from Form III Balance Sheet
B10: PROJECT COST | F10: TERM LOAN | J10: PROMOTERS' EQUITY | N10: AVERAGE DSCR
B11: =Form_III_BalanceSheet!$C$15 | F11: =Assumptions!$C$8 | J11: =Assumptions!$C$9 | N11: =DSCR!$H$14
B12: Gross fixed assets (land + building + equipment) · from Form III Balance Sheet | F12: Term loan applied for · from Assumptions | J12: Promoters' capital brought in · from Assumptions | N12: 5-year average DSCR — bank floor 1.20x · from DSCR sheet
B14: FINANCIAL PERFORMANCE
B70: KEY RATIOS & PROJECT SUMMARY
B72: Liquidity & Leverage | C72: Year 1 | D72: Year 5 | F72: Project Summary
B73: Current Ratio | C73: =Ratios!C6 | D73: =Ratios!G6 | F73: Name of the Unit | G73: =Assumptions!C5
B74: Debt-Equity Ratio | C74: =Ratios!C7 | D74: =Ratios!G7 | F74: Constitution | G74: =Assumptions!C6
F75: Line of Activity | G75: =Assumptions!C7
B76: Profitability Margin | C76: Year 1 | D76: Year 5 | F76: Industry | G76: =Assumptions!J5
B77: EBITDA Margin | C77: =Ratios!C10 | D77: =Ratios!G10 | F77: Installed Capacity (p.a.) | G77: =Assumptions!C16
B78: Net Profit Margin | C78: =Ratios!C11 | D78: =Ratios!G11 | F78: Term Loan Tenure (months) | G78: =Assumptions!C11
F79: Interest Rate — Term Loan | G79: =Assumptions!C10
B80: WC Component | C80: Days | F80: Moratorium (months) | G80: =Assumptions!C12
B81: Raw Material Holding | C81: =Assumptions!C50 | F81: Income Tax Rate | G81: =Assumptions!C14
B82: Finished Goods Holding | C82: =Assumptions!C51 | F82: Break-even (% of sales, Yr 1) | G82: =Ratios!C16
B83: Receivables | C83: =Assumptions!C52
B84: Payables | C84: =Assumptions!C53
