Workbook

Sheet Cover
B4: CREDIT MONITORING ARRANGEMENT (CMA) & FINANCIAL FEASIBILITY REPORT
B9: ="Proposed "&Assumptions!$B$3&" Project" -> Proposed General Business Project
B11: ="Installed Capacity: __________ "&IFERROR(INDEX('Industry Labels'!$C$6:$Z$6,MATCH(Assumptions!$B$3,'Industry Labels'!$C$4:$Z$4,0)),"units/month")&" | Target Market: __________" -> Installed Capacity: __________ units/month | Target Market: __________
B13: PROJECT SNAPSHOT
B14: Project | D14: Project description (to be entered)
B15: Installed Capacity
B16: Location | D16: Location (to be entered)
B17: Constitution | D17: Constitution (e.g. Private Limited Company / LLP / Proprietorship)
B18: Total Project Cost
B19: Means of Finance
B20: Projection Horizon | D20: 5 Years × 12 Months = 60 Months (Monthly & Annual)
B21: Projected Start | D21: ="April "&IF(ISNUMBER(Assumptions!$B$6),Assumptions!$B$6,2026)&" (FY "&IF(ISNUMBER(Assumptions!$B$6),Assumptions!$B$6,2026)&"-"&RIGHT((IF(ISNUMBER(Assumptions!$B$6),Assumptions!$B$6,2026)+1),2)&" to FY "&(IF(ISNUMBER(Assumptions!$B$6),Assumptions!$B$6,2026)+4)&"-"&RIGHT((IF(ISNUMBER(Assumptions!$B$6),Assumptions!$B$6,2026)+5),2)&")" -> April 2026 (FY 2026-27 to FY 2030-31)
B22: Report Basis | D22: All figures in ₹ Lakh unless stated. BLANK TEMPLATE — enter inputs on the 'Assumptions' & 'Project Cost' sheets; all statements populate automatically.
B23: Prepared on
B25: DISCLAIMER: This projection is prepared for feasibility / bank appraisal (CMA) purposes. It is based on market data referenced in the 'Assumptions' sheet (live source links provided) and on stated assumptions which the promoter/appraiser must validate. Actual results will vary with market, utilisation and execution. Figures are indicative and do not constitute investment or lending advice.

Sheet Overview
A1: OVERVIEW — CMA FEASIBILITY MODEL (ALL INDUSTRIES)
A2: Industry-neutral greenfield project appraised in the Indian CMA / bank-appraisal format. Documentation only — links live to the model and changes nothing downstream.
A4: EXECUTIVE SUMMARY
A5: The project is a proposed new business unit, underwritten over a five-year horizon (60 months, all figures in ₹ Lakh). Value is created by commissioning the facility, equipment and support assets, then ramping capacity utilisation from a conservative Year-1 launch ramp to a sustainable ceiling by Year 5: installed capacity (Assumptions!B5) × the monthly utilisation ramp drives volume, which at an escalating realisation net of GST (Assumptions!B10) builds net sales, while direct cost (Assumptions!B11), utilities, consumables, labour and fixed overheads — each escalated year-on-year — convert that revenue into EBITDA, PAT and cash accruals. The capital stack funds the total project cost ('Project Cost'!C14) with promoter equity (Assumptions!B52) plus a bank term loan (Assumptions!B51), backed by a working-capital cash-credit line sized on the MPBF / Tandon 2nd-method assessment. The industry (Assumptions!B3) only changes labels and units, never the arithmetic.
A10: =IFERROR("Base-case headline returns — Average DSCR (Yrs 1-5): "&TEXT('Ratios & DSCR'!C26,"0.00")&"x • Year-5 EBITDA margin: "&TEXT('Ratios & DSCR'!G6,"0.0%")&" • Year-5 return on net worth: "&TEXT('Ratios & DSCR'!G10,"0.0%")&" (populate once inputs are entered).","Base-case headline returns — enter inputs on the 'Assumptions' sheet to populate DSCR, EBITDA margin and RoNW.") -> Base-case headline returns — Average DSCR (Yrs 1-5): 0.00x • Year-5 EBITDA margin: • Year-5 return on net worth: (populate once inputs are entered).
A12: AT A GLANCE
A13: Total project cost (₹ L) | B13: =IFERROR('Project Cost'!$C$14,"") -> 0 | D13: Debt : Equity (TL / Equity) | E13: =IFERROR(Assumptions!$B$51/Assumptions!$B$52,"")
A15: Net sales — Year 5 (₹ L) | B15: =IFERROR('Profitability (Annual)'!$G$9,"") -> 0 | D15: Average DSCR (Years 1-5) | E15: =IFERROR('Ratios & DSCR'!$C$26,"") -> 0
A17: All four figures are live links to the model, not typed numbers — they recalculate the moment inputs change. ₹ L = ₹ Lakh; a metric shows blank until its driver cells are filled in.
A19: HOW THE MODEL WORKS
A20: 1. Inputs live on 'Assumptions' (the single control panel).
A21: Every blue-font / yellow-fill cell in column B is a lever — capacity (B5), Year-1 price & material per unit (B10, B11), the 12-month utilisation ramp (B16:B27) and annual plateaus (B28:B31), escalations (B33:B37), cost drivers (B39:B49), financing (B51:B56), WC norms (B58:B62) and depreciation/tax (B64:B71). Nothing else should be typed.
A22: 2. 'Project Cost' fixes the capital stack.
A23: Cost of project (land, building, P&M, electricals, utilities, misc, contingency, pre-op, WC margin) totals in C14; means of finance pulls equity (=Assumptions!$B$52) and term loan (=Assumptions!$B$51) into C18:C19, and derives debt:equity (C22) and promoter contribution % (C23).
A24: 3. Linking mechanism — direct cross-sheet references.
A25: The model uses no named ranges; every sheet points straight at source cells with quoted sheet names — for example 'Profitability (Annual)'!$C$9 or Assumptions!$B$51. Each output is wrapped in IFERROR so a blank template shows clean empty cells rather than divide-by-zero errors while the inputs are still empty.
A26: 4. 'Depreciation' schedule (SLM, Companies Act Sch II).
A27: Takes the gross block from 'Project Cost' and the SLM rates from 'Assumptions' (B64:B69), producing the annual charge and closing net-fixed-asset book value (O13) and unamortised pre-op (O14) that feed the Balance Sheet.
A28: 5. 'Term Loan' repayment engine (60 months).
A29: Disburses the sanctioned loan, applies the principal moratorium (Assumptions!B54) then equal monthly principal over the repayment period (B55), and computes monthly interest at the term-loan rate (B53). Its opening/closing balances and interest feed the P&L, DSCR and Balance Sheet.
... A38: TIP — to re-underwrite: edit ONLY the blue / yellow input cells in column B of 'Assumptions' (and the cost lines in column C of 'Project Cost'). Every statement, ratio and the metrics above recalculate automatically; never overwrite a black formula cell.

Sheet Index
A1: INDEX / TABLE OF CONTENTS
A2: Click any row to jump to the sheet. The model is fully linked — change any blue input on 'Assumptions' and every sheet recalculates.
B4: # | C4: Sheet | D4: Description | E4: Go
C5: Cover | D5: Title page & project snapshot | E5: Open ↗
C6: Assumptions | D6: All inputs, blended price/cost engine & live data-source links | E6: Open ↗
C7: Project Cost | D7: Cost of project & means of finance (D:E) | E7: Open ↗
C8: Depreciation | D8: WDV depreciation & amortisation schedule | E8: Open ↗
C9: Term Loan | D9: Monthly term-loan repayment schedule (principal + interest) | E9: Open ↗
C10: Production & Sales | D10: 60-month volume plan: units × realisation → net sales | E10: Open ↗
C11: Profitability (Monthly) | D11: 60-month P&L — revenue to PAT, fully linked | E11: Open ↗
C12: Profitability (Annual) | D12: CMA Operating Statement (Form II) — 5-year roll-up | E12: Open ↗
C13: Working Capital | D13: Working-capital assessment & MPBF (Tandon II) | E13: Open ↗
C14: Balance Sheet | D14: Projected balance sheet (Form III) | E14: Open ↗
C15: Cash Flow | D15: Projected cash-flow statement (Form VI) + reconciliation | E15: Open ↗
C16: Ratios & DSCR | D16: Bankability ratios & debt-service coverage | E16: Open ↗
C17: Break-even & Sensitivity | D17: Break-even, margin of safety & sensitivity tables | E17: Open ↗
B19: KEY OUTPUTS AT A GLANCE
C20: Total project cost | E20: =IFERROR('Project Cost'!$C$14,"") -> 0
C21: Debt : Equity | E21: =IFERROR(Assumptions!$B$51/Assumptions!$B$52,"")
C22: Net sales – Year 1 | E22: =IFERROR('Profitability (Annual)'!$C$9,"") -> 0
C23: Net sales – Year 5 | E23: =IFERROR('Profitability (Annual)'!$G$9,"") -> 0
C24: EBITDA – Year 5 | E24: =IFERROR('Profitability (Annual)'!$G$27,"") -> 0
C25: PAT – Year 5 | E25: =IFERROR('Profitability (Annual)'!$G$36,"") -> 0
C26: Net worth – Year 5 | E26: =IFERROR('Balance Sheet'!$H$8,"") -> 0
C27: Average DSCR (Years 1-5) | E27: =IFERROR('Ratios & DSCR'!C26,"") -> 0

Sheet Assumptions
A1: ASSUMPTIONS & BASIS OF PROJECTIONS — full calculation engine (all downstream sheets link here)
A2: Blue = input you can change • Black = calculated • Yellow = key driver • Source column links are live (as at Jul-2026)
A3: Industry / business type | B3: General Business | C3: select | D3: Pick the business type — labels, units and notes across the whole model adapt. Calculations are identical for every industry.
A4: 1. GENERAL & TIMELINE
A5: =IFERROR(INDEX('Industry Labels'!$C$5:$Z$5,MATCH(Assumptions!$B$3,'Industry Labels'!$C$4:$Z$4,0)),"Installed / service capacity") -> Installed / service capacity | C5: =IFERROR(INDEX('Industry Labels'!$C$6:$Z$6,MATCH(Assumptions!$B$3,'Industry Labels'!$C$4:$Z$4,0)),"units/month") -> units/month | D5: Rated output at 100% utilisation; effective output is governed by the utilisation ramp (Section 3). Define one 'unit' clearly for your business.
A6: Commercial operations start (FY) | B6: 2026 | C6: year Yr1 starts | D6: Calendar year in which Year 1 starts (April). 2026 = FY2026-27. Every year / month heading in the model follows this.
A7: Working days / month (for WC norms) | C7: days | D7: Standard month convention for holding-period working-capital sizing.
A8: 2. UNIT ECONOMICS (PRICE & DIRECT MATERIAL, Year-1 base)
A9: Per-unit economics. Enter the selling price and direct cost from the promoter's own quotations / market survey — every downstream sheet recalculates automatically.
A10: =IFERROR(INDEX('Industry Labels'!$C$9:$Z$9,MATCH(Assumptions!$B$3,'Industry Labels'!$C$4:$Z$4,0)),"Average selling price / unit (Yr1)") -> Average selling price / unit (Yr1) | C10: ="₹/"&IFERROR(INDEX('Industry Labels'!$C$8:$Z$8,MATCH(Assumptions!$B$3,'Industry Labels'!$C$4:$Z$4,0)),"unit") -> ₹/unit | D10: Net-of-GST realisation per unit; escalated year-on-year by the price escalation (Section 4).
A11: =IFERROR(INDEX('Industry Labels'!$C$10:$Z$10,MATCH(Assumptions!$B$3,'Industry Labels'!$C$4:$Z$4,0)),"Direct cost of goods / services per unit (Yr1)") -> Direct cost of goods / services per unit (Yr1) | C11: ="₹/"&IFERROR(INDEX('Industry Labels'!$C$8:$Z$8,MATCH(Assumptions!$B$3,'Industry Labels'!$C$4:$Z$4,0)),"unit") -> ₹/unit | D11: Bought-in goods / direct cost of delivering one unit, inclusive of normal wastage.
A12: 3. CAPACITY UTILISATION (RAMP-UP)
A13: Year-1 monthly ramp (new facility / market development), then annual plateau. Conservative feasibility ramp.
A14: Year-1 utilisation, Months 1-12
A15: (month → util %)
A16: Year 1 – Month 1 | C16: % | D16: Commissioning / launch ramp-up
A17: Year 1 – Month 2 | C17: % | D17: Commissioning / launch ramp-up
A18: Year 1 – Month 3 | C18: % | D18: Commissioning / launch ramp-up
A19: Year 1 – Month 4 | C19: % | D19: Commissioning / launch ramp-up
A20: Year 1 – Month 5 | C20: % | D20: Commissioning / launch ramp-up
A21: Year 1 – Month 6 | C21: % | D21: Commissioning / launch ramp-up
A22: Year 1 – Month 7 | C22: % | D22: Stabilised ramp
A23: Year 1 – Month 8 | C23: % | D23: Stabilised ramp
A24: Year 1 – Month 9 | C24: % | D24: Stabilised ramp
A25: Year 1 – Month 10 | C25: % | D25: Stabilised ramp
A26: Year 1 – Month 11 | C26: % | D26: Stabilised ramp
A27: Year 1 – Month 12 | C27: % | D27: Stabilised ramp
... A31: Year 5 utilisation | C31: % | D31: Sustainable ceiling (allows maintenance downtime).
A32: 4. ANNUAL ESCALATION (applied Year-on-Year)
A33: Selling-price escalation | C33: % p.a. | D33: Realisation growth broadly tracking input inflation.
A34: Direct-material escalation | C34: % p.a. | D34: Expected annual input-material price trend.
A35: Utility / power tariff escalation | C35: % p.a. | D35: Annual drift in utility tariffs.
A36: Wage / salary escalation | C36: % p.a. | D36: Annual increments + statutory revisions.
A37: Other overhead escalation | C37: % p.a. | D37: General inflation on fixed overheads.
A38: 5. OTHER VARIABLE COST DRIVERS (Year-1 base)
A39: =IFERROR(INDEX('Industry Labels'!$C$11:$Z$11,MATCH(Assumptions!$B$3,'Industry Labels'!$C$4:$Z$4,0)),"Utilities & energy / unit") -> Utilities & energy / unit | C39: ="₹/"&IFERROR(INDEX('Industry Labels'!$C$8:$Z$8,MATCH(Assumptions!$B$3,'Industry Labels'!$C$4:$Z$4,0)),"unit") -> ₹/unit | D39: Energy / utilities cost per unit; escalates with the utility-cost escalation (Section 4).
A40: =IFERROR(INDEX('Industry Labels'!$C$12:$Z$12,MATCH(Assumptions!$B$3,'Industry Labels'!$C$4:$Z$4,0)),"Consumables & supplies / unit") -> Consumables & supplies / unit | C40: ="₹/"&IFERROR(INDEX('Industry Labels'!$C$8:$Z$8,MATCH(Assumptions!$B$3,'Industry Labels'!$C$4:$Z$4,0)),"unit") -> ₹/unit | D40: Consumable supplies consumed per unit.
A41: =IFERROR(INDEX('Industry Labels'!$C$13:$Z$13,MATCH(Assumptions!$B$3,'Industry Labels'!$C$4:$Z$4,0)),"Packing & delivery / unit") -> Packing & delivery / unit | C41: ="₹/"&IFERROR(INDEX('Industry Labels'!$C$8:$Z$8,MATCH(Assumptions!$B$3,'Industry Labels'!$C$4:$Z$4,0)),"unit") -> ₹/unit | D41: Packing / delivery / distribution cost per unit.
A42: =IFERROR(INDEX('Industry Labels'!$C$14:$Z$14,MATCH(Assumptions!$B$3,'Industry Labels'!$C$4:$Z$4,0)),"Direct labour (Year-1)") -> Direct labour (Year-1) | C42: ₹L/mo | D42: Operating staff across shifts; semi-fixed, escalates with wages.
A43: 6. FIXED / OVERHEAD COSTS (Year-1 base, monthly)
A44: Admin & management salaries | C44: ₹L/mo | D44: Management, sales, accounts, admin, security.
A45: =IFERROR(INDEX('Industry Labels'!$C$24:$Z$24,MATCH(Assumptions!$B$3,'Industry Labels'!$C$4:$Z$4,0)),"Fixed utility / facility charges") -> Fixed utility / facility charges | C45: ₹L/mo | D45: Fixed utility / contract-demand charges independent of volume.
A46: Repairs & maintenance | C46: % of P&M/yr | D46: Typically 1–2% of equipment cost per annum (spares, servicing).
A47: Insurance | C47: % of FA/yr | D47: Typically ~0.4% of gross fixed assets p.a. (fire, burglary, breakdown).
A48: Other admin overheads | C48: ₹L/mo | D48: Office, travel, communication, audit, statutory, misc.
A49: Selling & distribution | C49: % of sales | D49: Freight, commission, marketing & distribution (variable with sales).
A50: 7. PROJECT FINANCING
A51: Term loan sanctioned | C51: ₹L | D51: Funds ~57% of fixed assets. See 'Project Cost' sheet.
A52: Promoter equity / capital | C52: ₹L | D52: Balancing contribution incl. WC margin money; D:E ≈ 1.04.
A53: Term-loan interest rate | C53: % p.a. | D53: MSME term loan ≈ Repo (5.25%) + ~2.65% + spread. SBI/BoB EBLR basis, 2026. | E53: Bank of Baroda BRLLR / SBI EBLR 2026
A54: Term-loan moratorium (principal) | C54: months | D54: Principal holiday during ramp-up; interest serviced monthly.
A55: Term-loan repayment period | C55: months | D55: Equal monthly principal after moratorium (8-yr door-to-door).
A56: Working-capital (CC) interest rate | C56: % p.a. | D56: Cash-credit on assessed bank finance. MSME WC 2026. | E56: SBI SME / MSME WC rate 2026
A57: 8. WORKING-CAPITAL HOLDING NORMS (for MPBF)
A58: =IFERROR(INDEX('Industry Labels'!$C$27:$Z$27,MATCH(Assumptions!$B$3,'Industry Labels'!$C$4:$Z$4,0)),"Raw-material / stock inventory (days of consumption held)") -> Raw-material / stock inventory (days of consumption held) | C58: days | D58: Days of direct-cost consumption held in stock.
A59: =IFERROR(INDEX('Industry Labels'!$C$28:$Z$28,MATCH(Assumptions!$B$3,'Industry Labels'!$C$4:$Z$4,0)),"Finished goods / stock-in-trade (days of cost held)") -> Finished goods / stock-in-trade (days of cost held) | C59: days | D59: Days of cost of operations held as finished stock.
A60: Receivables (debtors) | C60: days | D60: Credit allowed to customers.
A61: Payables (creditors) | C61: days | D61: Credit received from suppliers.
A62: Margin on working capital (NWC) | C62: % | D62: Tandon 2nd method: 25% of current assets from long-term funds.
A63: 9. DEPRECIATION (SLM, Companies Act Sch II) & TAX
A64: =IFERROR(INDEX('Industry Labels'!$C$29:$Z$29,MATCH(Assumptions!$B$3,'Industry Labels'!$C$4:$Z$4,0)),"Premises, building & civil / fit-out depreciation (SLM)") -> Premises, building & civil / fit-out depreciation (SLM) | C64: % SLM | D64: Building / civil — Companies Act Sch II (typical life ~30 yrs; confirm per asset).
A65: =IFERROR(INDEX('Industry Labels'!$C$30:$Z$30,MATCH(Assumptions!$B$3,'Industry Labels'!$C$4:$Z$4,0)),"Equipment, machinery & systems depreciation (SLM)") -> Equipment, machinery & systems depreciation (SLM) | C65: % SLM | D65: Equipment / machinery — Companies Act Sch II (typical life ~15 yrs; set per asset type).
A66: Electrical installation depreciation (SLM) | C66: % SLM | D66: Electrical installation — Companies Act Sch II (~10 yrs).
A67: Utilities depreciation (SLM) | C67: % SLM | D67: Utilities & services — Companies Act Sch II (~15 yrs).
A68: Misc / office assets depreciation (SLM) | C68: % SLM | D68: Office / furniture / IT — Companies Act Sch II (furniture 10 yrs, computers 3 yrs).
A69: Pre-operative amortisation | C69: % / yr | D69: Written off over 5 years (straight line).
A70: Corporate tax rate (effective) | C70: % | D70: Sec 115BAA new domestic company: 22% + surcharge + cess ≈ 25.17%. | E70: Income Tax Act s.115BAA
A71: GST (pass-through) | C71: % | D71: Illustrative 18% output & input GST; revenue modelled net of GST. Set to the product’s actual GST rate. | E71: CBIC GST rate finder
A72: 10. KEY DATA SOURCES (live links, accessed Jul-2026)
A73: Note: the financing, tax & GST anchors below are public sources. Selling price, direct cost and capacity are placeholders — substantiate them with the promoter's quotations / market survey.
A74: [1] MSME term-loan / MCLR-EBLR rates (Bank of Baroda) | C74: Open link ↗
A75: [2] SBI SME segment interest rates | C75: Open link ↗
A76: [3] MSME working-capital loan rates 2026 (BankBazaar) | C76: Open link ↗
A77: [4] Income Tax India (s.115BAA corporate tax) | C77: Open link ↗
A78: [5] CBIC-GST (GST rate finder / HSN) | C78: Open link ↗

Sheet Project Cost
A1: PROJECT COST & MEANS OF FINANCE (₹ Lakh)
A3: A. COST OF PROJECT
A4: # | B4: Particulars | C4: Amount | D4: Dep. block | E4: Basis / remarks
B5: Land & site development | D5: Land (nil dep.) | E5: Land / site / premises development (enter nil if premises are leased).
B6: =IFERROR(INDEX('Industry Labels'!$C$15:$Z$15,MATCH(Assumptions!$B$3,'Industry Labels'!$C$4:$Z$4,0)),"Premises, building & civil / fit-out") -> Premises, building & civil / fit-out | D6: Building | E6: Construction / civil works / interiors & fit-out of premises.
B7: =IFERROR(INDEX('Industry Labels'!$C$16:$Z$16,MATCH(Assumptions!$B$3,'Industry Labels'!$C$4:$Z$4,0)),"Equipment, machinery & systems") -> Equipment, machinery & systems | D7: Equipment | E7: Core equipment, machinery, vehicles or systems & installation.
B8: Electrical installation & power back-up | D8: Electrical | E8: Panels, wiring, transformer, DG / UPS back-up.
B9: Utilities & services (water, HVAC, fire-fighting etc.) | D9: Utilities | E9: Water, cooling / air-conditioning, fire-fighting, other services.
B10: Miscellaneous fixed assets (office, IT, furniture, tools) | D10: Misc | E10: Furniture, computers, software / ERP, tools, testing equipment.
B11: Contingency | D11: Equipment | E11: ~3% on equipment / civil for cost overrun.
B12: Pre-operative & preliminary expenses | D12: Pre-op (amort.) | E12: Trial runs, interest during construction, fees, start-up and licensing costs.
B13: Margin money for working capital | D13: Current assets | E13: Promoter margin toward the first working-capital cycle.
B14: TOTAL PROJECT COST | C14: =IFERROR(SUM(C5:C13),"") -> 0
A16: B. MEANS OF FINANCE
A17: # | B17: Source | C17: Amount | D17: % of cost | E17: Remarks
B18: Promoter's equity / capital | C18: =IFERROR(Assumptions!$B$52,"") -> 0 | D18: =IFERROR(C18/$C$14,"") | E18: Incl. WC margin money.
B19: Term loan from bank | C19: =IFERROR(Assumptions!$B$51,"") -> 0 | D19: =IFERROR(C19/$C$14,"") | E19: Secured against fixed assets.
B20: TOTAL MEANS OF FINANCE | C20: =IFERROR(SUM(C18:C19),"") -> 0 | D20: =IFERROR(C20/$C$14,"")
B21: Check (Cost = Finance) | C21: =IFERROR(C14-C20,"") -> 0
B22: Debt : Equity (Term loan / Equity) | C22: =IFERROR(Assumptions!$B$51/Assumptions!$B$52,"")
B23: Promoter contribution % | C23: =IFERROR(Assumptions!$B$52/C14,"")

Sheet Depreciation
A1: DEPRECIATION SCHEDULE — Straight-Line Method, Companies Act Schedule II (₹ Lakh)
A2: Gross block from 'Project Cost'; SLM rates (per asset useful life) from 'Assumptions'. Gross block × SLM rate = annual charge, floored at residual book value.
D3: Year 1 | G3: Year 2 | J3: Year 3 | M3: Year 4 | P3: Year 5
A4: Asset block | B4: Gross | C4: Rate | D4: Open | E4: Dep. | F4: Close | G4: Open | H4: Dep. | I4: Close | J4: Open | K4: Dep. | L4: Close | M4: Open | N4: Dep. | O4: Close | P4: Open | Q4: Dep. | R4: Close
A5: =IFERROR(INDEX('Industry Labels'!$C$15:$Z$15,MATCH(Assumptions!$B$3,'Industry Labels'!$C$4:$Z$4,0)),"Premises, building & civil / fit-out") -> Premises, building & civil / fit-out | B5: =IFERROR('Project Cost'!$C$6,"") -> 0 | C5: =IFERROR(Assumptions!$B$64,"") -> 0 | D5: =IFERROR(B5,"") -> 0 | E5: =IFERROR(MIN(D5,$B5*$C5),"") -> 0 | F5: =IFERROR(D5-E5,"") -> 0 | G5: =IFERROR(F5,"") -> 0 | H5: =IFERROR(MIN(G5,$B5*$C5),"") -> 0 | I5: =IFERROR(G5-H5,"") -> 0 | J5: =IFERROR(I5,"") -> 0 | K5: =IFERROR(MIN(J5,$B5*$C5),"") -> 0 | L5: =IFERROR(J5-K5,"") -> 0 | M5: =IFERROR(L5,"") -> 0 | N5: =IFERROR(MIN(M5,$B5*$C5),"") -> 0 | O5: =IFERROR(M5-N5,"") -> 0 | P5: =IFERROR(O5,"") -> 0 | Q5: =IFERROR(MIN(P5,$B5*$C5),"") -> 0 | R5: =IFERROR(P5-Q5,"") -> 0
A6: =IFERROR(INDEX('Industry Labels'!$C$16:$Z$16,MATCH(Assumptions!$B$3,'Industry Labels'!$C$4:$Z$4,0)),"Equipment, machinery & systems")&" (+contingency)" -> Equipment, machinery & systems (+contingency) | B6: =IFERROR(('Project Cost'!$C$7+'Project Cost'!$C$11),"") -> 0 | C6: =IFERROR(Assumptions!$B$65,"") -> 0 | D6: =IFERROR(B6,"") -> 0 | E6: =IFERROR(MIN(D6,$B6*$C6),"") -> 0 | F6: =IFERROR(D6-E6,"") -> 0 | G6: =IFERROR(F6,"") -> 0 | H6: =IFERROR(MIN(G6,$B6*$C6),"") -> 0 | I6: =IFERROR(G6-H6,"") -> 0 | J6: =IFERROR(I6,"") -> 0 | K6: =IFERROR(MIN(J6,$B6*$C6),"") -> 0 | L6: =IFERROR(J6-K6,"") -> 0 | M6: =IFERROR(L6,"") -> 0 | N6: =IFERROR(MIN(M6,$B6*$C6),"") -> 0 | O6: =IFERROR(M6-N6,"") -> 0 | P6: =IFERROR(O6,"") -> 0 | Q6: =IFERROR(MIN(P6,$B6*$C6),"") -> 0 | R6: =IFERROR(P6-Q6,"") -> 0
A7: Electrical installation | B7: =IFERROR('Project Cost'!$C$8,"") -> 0 | C7: =IFERROR(Assumptions!$B$66,"") -> 0 | D7: =IFERROR(B7,"") -> 0 | E7: =IFERROR(MIN(D7,$B7*$C7),"") -> 0 | F7: =IFERROR(D7-E7,"") -> 0 | G7: =IFERROR(F7,"") -> 0 | H7: =IFERROR(MIN(G7,$B7*$C7),"") -> 0 | I7: =IFERROR(G7-H7,"") -> 0 | J7: =IFERROR(I7,"") -> 0 | K7: =IFERROR(MIN(J7,$B7*$C7),"") -> 0 | L7: =IFERROR(J7-K7,"") -> 0 | M7: =IFERROR(L7,"") -> 0 | N7: =IFERROR(MIN(M7,$B7*$C7),"") -> 0 | O7: =IFERROR(M7-N7,"") -> 0 | P7: =IFERROR(O7,"") -> 0 | Q7: =IFERROR(MIN(P7,$B7*$C7),"") -> 0 | R7: =IFERROR(P7-Q7,"") -> 0
A8: Utilities | B8: =IFERROR('Project Cost'!$C$9,"") -> 0 | C8: =IFERROR(Assumptions!$B$67,"") -> 0 | D8: =IFERROR(B8,"") -> 0 | E8: =IFERROR(MIN(D8,$B8*$C8),"") -> 0 | F8: =IFERROR(D8-E8,"") -> 0 | G8: =IFERROR(F8,"") -> 0 | H8: =IFERROR(MIN(G8,$B8*$C8),"") -> 0 | I8: =IFERROR(G8-H8,"") -> 0 | J8: =IFERROR(I8,"") -> 0 | K8: =IFERROR(MIN(J8,$B8*$C8),"") -> 0 | L8: =IFERROR(J8-K8,"") -> 0 | M8: =IFERROR(L8,"") -> 0 | N8: =IFERROR(MIN(M8,$B8*$C8),"") -> 0 | O8: =IFERROR(M8-N8,"") -> 0 | P8: =IFERROR(O8,"") -> 0 | Q8: =IFERROR(MIN(P8,$B8*$C8),"") -> 0 | R8: =IFERROR(P8-Q8,"") -> 0
A9: Miscellaneous / office assets | B9: =IFERROR('Project Cost'!$C$10,"") -> 0 | C9: =IFERROR(Assumptions!$B$68,"") -> 0 | D9: =IFERROR(B9,"") -> 0 | E9: =IFERROR(MIN(D9,$B9*$C9),"") -> 0 | F9: =IFERROR(D9-E9,"") -> 0 | G9: =IFERROR(F9,"") -> 0 | H9: =IFERROR(MIN(G9,$B9*$C9),"") -> 0 | I9: =IFERROR(G9-H9,"") -> 0 | J9: =IFERROR(I9,"") -> 0 | K9: =IFERROR(MIN(J9,$B9*$C9),"") -> 0 | L9: =IFERROR(J9-K9,"") -> 0 | M9: =IFERROR(L9,"") -> 0 | N9: =IFERROR(MIN(M9,$B9*$C9),"") -> 0 | O9: =IFERROR(M9-N9,"") -> 0 | P9: =IFERROR(O9,"") -> 0 | Q9: =IFERROR(MIN(P9,$B9*$C9),"") -> 0 | R9: =IFERROR(P9-Q9,"") -> 0
A10: Pre-operative (amortised 5 yr SL) | B10: =IFERROR('Project Cost'!$C$12,"") -> 0 | C10: =IFERROR(Assumptions!$B$69,"") -> 0 | D10: =IFERROR(B10,"") -> 0 | E10: =IFERROR(MIN(D10,$B10*$C10),"") -> 0 | F10: =IFERROR(D10-E10,"") -> 0 | G10: =IFERROR(F10,"") -> 0 | H10: =IFERROR(MIN(G10,$B10*$C10),"") -> 0 | I10: =IFERROR(G10-H10,"") -> 0 | J10: =IFERROR(I10,"") -> 0 | K10: =IFERROR(MIN(J10,$B10*$C10),"") -> 0 | L10: =IFERROR(J10-K10,"") -> 0 | M10: =IFERROR(L10,"") -> 0 | N10: =IFERROR(MIN(M10,$B10*$C10),"") -> 0 | O10: =IFERROR(M10-N10,"") -> 0 | P10: =IFERROR(O10,"") -> 0 | Q10: =IFERROR(MIN(P10,$B10*$C10),"") -> 0 | R10: =IFERROR(P10-Q10,"") -> 0
A11: TOTAL DEPRECIATION & AMORTISATION | E11: =IFERROR(SUM(E5:E10),"") -> 0 | H11: =IFERROR(SUM(H5:H10),"") -> 0 | K11: =IFERROR(SUM(K5:K10),"") -> 0 | N11: =IFERROR(SUM(N5:N10),"") -> 0 | Q11: =IFERROR(SUM(Q5:Q10),"") -> 0
A13: Net fixed assets (closing book value incl. land, excl. pre-op) | F13: =IFERROR(SUM(F5:F9)+'Project Cost'!$C$5,"") -> 0 | I13: =IFERROR(SUM(I5:I9)+'Project Cost'!$C$5,"") -> 0 | L13: =IFERROR(SUM(L5:L9)+'Project Cost'!$C$5,"") -> 0 | O13: =IFERROR(SUM(O5:O9)+'Project Cost'!$C$5,"") -> 0 | R13: =IFERROR(SUM(R5:R9)+'Project Cost'!$C$5,"") -> 0
A14: Pre-operative (unamortised, closing) | F14: =IFERROR(F10,"") -> 0 | I14: =IFERROR(I10,"") -> 0 | L14: =IFERROR(L10,"") -> 0 | O14: =IFERROR(O10,"") -> 0 | R14: =IFERROR(R10,"") -> 0

Sheet Term Loan
A1: TERM LOAN REPAYMENT SCHEDULE (₹ Lakh)
A2: Disbursed at start. Moratorium on principal per Assumptions; interest serviced monthly. Repaid in equal monthly principal thereafter.
C3: ="YEAR 1 • FY"&(IF(ISNUMBER(Assumptions!$B$6),Assumptions!$B$6,2026)+0)&"-"&RIGHT((IF(ISNUMBER(Assumptions!$B$6),Assumptions!$B$6,2026)+0+1),2) -> YEAR 1 • FY2026-27 | O3: ="YEAR 2 • FY"&(IF(ISNUMBER(Assumptions!$B$6),Assumptions!$B$6,2026)+1)&"-"&RIGHT((IF(ISNUMBER(Assumptions!$B$6),Assumptions!$B$6,2026)+1+1),2) -> YEAR 2 • FY2027-28 | AA3: ="YEAR 3 • FY"&(IF(ISNUMBER(Assumptions!$B$6),Assumptions!$B$6,2026)+2)&"-"&RIGHT((IF(ISNUMBER(Assumptions!$B$6),Assumptions!$B$6,2026)+2+1),2) -> YEAR 3 • FY2028-29 | AM3: ="YEAR 4 • FY"&(IF(ISNUMBER(Assumptions!$B$6),Assumptions!$B$6,2026)+3)&"-"&RIGHT((IF(ISNUMBER(Assumptions!$B$6),Assumptions!$B$6,2026)+3+1),2) -> YEAR 4 • FY2029-30 | AY3: ="YEAR 5 • FY"&(IF(ISNUMBER(Assumptions!$B$6),Assumptions!$B$6,2026)+4)&"-"&RIGHT((IF(ISNUMBER(Assumptions!$B$6),Assumptions!$B$6,2026)+4+1),2) -> YEAR 5 • FY2030-31
A4: Month | B4: Unit | C4: =DATE(IF(ISNUMBER(Assumptions!$B$6),Assumptions!$B$6,2026),4+0,1) -> 46113 | D4: =DATE(IF(ISNUMBER(Assumptions!$B$6),Assumptions!$B$6,2026),4+1,1) -> 46143 | E4: =DATE(IF(ISNUMBER(Assumptions!$B$6),Assumptions!$B$6,2026),4+2,1) -> 46174 | F4: =DATE(IF(ISNUMBER(Assumptions!$B$6),Assumptions!$B$6,2026),4+3,1) -> 46204 | G4: =DATE(IF(ISNUMBER(Assumptions!$B$6),Assumptions!$B$6,2026),4+4,1) -> 46235 | H4: =DATE(IF(ISNUMBER(Assumptions!$B$6),Assumptions!$B$6,2026),4+5,1) -> 46266 | I4: =DATE(IF(ISNUMBER(Assumptions!$B$6),Assumptions!$B$6,2026),4+6,1) -> 46296 | J4: =DATE(IF(ISNUMBER(Assumptions!$B$6),Assumptions!$B$6,2026),4+7,1) -> 46327 | K4: =DATE(IF(ISNUMBER(Assumptions!$B$6),Assumptions!$B$6,2026),4+8,1) -> 46357 | L4: =DATE(IF(ISNUMBER(Assumptions!$B$6),Assumptions!$B$6,2026),4+9,1) -> 46388 | M4: =DATE(IF(ISNUMBER(Assumptions!$B$6),Assumptions!$B$6,2026),4+10,1) -> 46419 | N4: =DATE(IF(ISNUMBER(Assumptions!$B$6),Assumptions!$B$6,2026),4+11,1) -> 46447 | O4: =DATE(IF(ISNUMBER(Assumptions!$B$6),Assumptions!$B$6,2026),4+12,1) -> 46478 | P4: =DATE(IF(ISNUMBER(Assumptions!$B$6),Assumptions!$B$6,2026),4+13,1) -> 46508 | Q4: =DATE(IF(ISNUMBER(Assumptions!$B$6),Assumptions!$B$6,2026),4+14,1) -> 46539 | R4: =DATE(IF(ISNUMBER(Assumptions!$B$6),Assumptions!$B$6,2026),4+15,1) -> 46569 | S4: =DATE(IF(ISNUMBER(Assumptions!$B$6),Assumptions!$B$6,2026),4+16,1) -> 46600 | T4: =DATE(IF(ISNUMBER(Assumptions!$B$6),Assumptions!$B$6,2026),4+17,1) -> 46631 | U4: =DATE(IF(ISNUMBER(Assumptions!$B$6),Assumptions!$B$6,2026),4+18,1) -> 46661 | V4: =DATE(IF(ISNUMBER(Assumptions!$B$6),Assumptions!$B$6,2026),4+19,1) -> 46692 | W4: =DATE(IF(ISNUMBER(Assumptions!$B$6),Assumptions!$B$6,2026),4+20,1) -> 46722 | X4: =DATE(IF(ISNUMBER(Assumptions!$B$6),Assumptions!$B$6,2026),4+21,1) -> 46753 | Y4: =DATE(IF(ISNUMBER(Assumptions!$B$6),Assumptions!$B$6,2026),4+22,1) -> 46784 | Z4: =DATE(IF(ISNUMBER(Assumptions!$B$6),Assumptions!$B$6,2026),4+23,1) -> 46813 | AA4: =DATE(IF(ISNUMBER(Assumptions!$B$6),Assumptions!$B$6,2026),4+24,1) -> 46844 | AB4: =DATE(IF(ISNUMBER(Assumptions!$B$6),Assumptions!$B$6,2026),4+25,1) -> 46874 | AC4: =DATE(IF(ISNUMBER(Assumptions!$B$6),Assumptions!$B$6,2026),4+26,1) -> 46905 | AD4: =DATE(IF(ISNUMBER(Assumptions!$B$6),Assumptions!$B$6,2026),4+27,1) -> 46935 | AE4: =DATE(IF(ISNUMBER(Assumptions!$B$6),Assumptions!$B$6,2026),4+28,1) -> 46966 | AF4: =DATE(IF(ISNUMBER(Assumptions!$B$6),Assumptions!$B$6,2026),4+29,1) -> 46997 | AG4: =DATE(IF(ISNUMBER(Assumptions!$B$6),Assumptions!$B$6,2026),4+30,1) -> 47027 | AH4: =DATE(IF(ISNUMBER(Assumptions!$B$6),Assumptions!$B$6,2026),4+31,1) -> 47058 | AI4: =DATE(IF(ISNUMBER(Assumptions!$B$6),Assumptions!$B$6,2026),4+32,1) -> 47088 | AJ4: =DATE(IF(ISNUMBER(Assumptions!$B$6),Assumptions!$B$6,2026),4+33,1) -> 47119 | AK4: =DATE(IF(ISNUMBER(Assumptions!$B$6),Assumptions!$B$6,2026),4+34,1) -> 47150 | AL4: =DATE(IF(ISNUMBER(Assumptions!$B$6),Assumptions!$B$6,2026),4+35,1) -> 47178 | AM4: =DATE(IF(ISNUMBER(Assumptions!$B$6),Assumptions!$B$6,2026),4+36,1) -> 47209 | AN4: =DATE(IF(ISNUMBER(Assumptions!$B$6),Assumptions!$B$6,2026),4+37,1) -> 47239 | AO4: =DATE(IF(ISNUMBER(Assumptions!$B$6),Assumptions!$B$6,2026),4+38,1) -> 47270 | AP4: =DATE(IF(ISNUMBER(Assumptions!$B$6),Assumptions!$B$6,2026),4+39,1) -> 47300 | AQ4: =DATE(IF(ISNUMBER(Assumptions!$B$6),Assumptions!$B$6,2026),4+40,1) -> 47331 | AR4: =DATE(IF(ISNUMBER(Assumptions!$B$6),Assumptions!$B$6,2026),4+41,1) -> 47362 | AS4: =DATE(IF(ISNUMBER(Assumptions!$B$6),Assumptions!$B$6,2026),4+42,1) -> 47392 | AT4: =DATE(IF(ISNUMBER(Assumptions!$B$6),Assumptions!$B$6,2026),4+43,1) -> 47423 | AU4: =DATE(IF(ISNUMBER(Assumptions!$B$6),Assumptions!$B$6,2026),4+44,1) -> 47453 | AV4: =DATE(IF(ISNUMBER(Assumptions!$B$6),Assumptions!$B$6,2026),4+45,1) -> 47484 | AW4: =DATE(IF(ISNUMBER(Assumptions!$B$6),Assumptions!$B$6,2026),4+46,1) -> 47515 | AX4: =DATE(IF(ISNUMBER(Assumptions!$B$6),Assumptions!$B$6,2026),4+47,1) -> 47543 | AY4: =DATE(IF(ISNUMBER(Assumptions!$B$6),Assumptions!$B$6,2026),4+48,1) -> 47574 | AZ4: =DATE(IF(ISNUMBER(Assumptions!$B$6),Assumptions!$B$6,2026),4+49,1) -> 47604 | BA4: =DATE(IF(ISNUMBER(Assumptions!$B$6),Assumptions!$B$6,2026),4+50,1) -> 47635 | BB4: =DATE(IF(ISNUMBER(Assumptions!$B$6),Assumptions!$B$6,2026),4+51,1) -> 47665 | BC4: =DATE(IF(ISNUMBER(Assumptions!$B$6),Assumptions!$B$6,2026),4+52,1) -> 47696 | BD4: =DATE(IF(ISNUMBER(Assumptions!$B$6),Assumptions!$B$6,2026),4+53,1) -> 47727 | BE4: =DATE(IF(ISNUMBER(Assumptions!$B$6),Assumptions!$B$6,2026),4+54,1) -> 47757 | BF4: =DATE(IF(ISNUMBER(Assumptions!$B$6),Assumptions!$B$6,2026),4+55,1) -> 47788 | BG4: =DATE(IF(ISNUMBER(Assumptions!$B$6),Assumptions!$B$6,2026),4+56,1) -> 47818 | BH4: =DATE(IF(ISNUMBER(Assumptions!$B$6),Assumptions!$B$6,2026),4+57,1) -> 47849 | BI4: =DATE(IF(ISNUMBER(Assumptions!$B$6),Assumptions!$B$6,2026),4+58,1) -> 47880 | BJ4: =DATE(IF(ISNUMBER(Assumptions!$B$6),Assumptions!$B$6,2026),4+59,1) -> 47908
A5: Month # | C5: 1 | D5: 2 | E5: 3 | F5: 4 | G5: 5 | H5: 6 | I5: 7 | J5: 8 | K5: 9 | L5: 10 | M5: 11 | N5: 12 | O5: 13 | P5: 14 | Q5: 15 | R5: 16 | S5: 17 | T5: 18 | U5: 19 | V5: 20 | W5: 21 | X5: 22 | Y5: 23 | Z5: 24 | AA5: 25 | AB5: 26 | AC5: 27 | AD5: 28 | AE5: 29 | AF5: 30 | AG5: 31 | AH5: 32 | AI5: 33 | AJ5: 34 | AK5: 35 | AL5: 36 | AM5: 37 | AN5: 38 | AO5: 39 | AP5: 40 | AQ5: 41 | AR5: 42 | AS5: 43 | AT5: 44 | AU5: 45 | AV5: 46 | AW5: 47 | AX5: 48 | AY5: 49 | AZ5: 50 | BA5: 51 | BB5: 52 | BC5: 53 | BD5: 54 | BE5: 55 | BF5: 56 | BG5: 57 | BH5: 58 | BI5: 59 | BJ5: 60
A6: Year # | C6: 1 | D6: 1 | E6: 1 | F6: 1 | G6: 1 | H6: 1 | I6: 1 | J6: 1 | K6: 1 | L6: 1 | M6: 1 | N6: 1 | O6: 2 | P6: 2 | Q6: 2 | R6: 2 | S6: 2 | T6: 2 | U6: 2 | V6: 2 | W6: 2 | X6: 2 | Y6: 2 | Z6: 2 | AA6: 3 | AB6: 3 | AC6: 3 | AD6: 3 | AE6: 3 | AF6: 3 | AG6: 3 | AH6: 3 | AI6: 3 | AJ6: 3 | AK6: 3 | AL6: 3 | AM6: 4 | AN6: 4 | AO6: 4 | AP6: 4 | AQ6: 4 | AR6: 4 | AS6: 4 | AT6: 4 | AU6: 4 | AV6: 4 | AW6: 4 | AX6: 4 | AY6: 5 | AZ6: 5 | BA6: 5 | BB6: 5 | BC6: 5 | BD6: 5 | BE6: 5 | BF6: 5 | BG6: 5 | BH6: 5 | BI6: 5 | BJ6: 5
A7: Opening loan balance | B7: ₹ L | C7: =IFERROR(Assumptions!$B$51,"") -> 0 | D7: =IFERROR(C11,"") -> 0 | E7: =IFERROR(D11,"") -> 0 | F7: =IFERROR(E11,"") -> 0 | G7: =IFERROR(F11,"") -> 0 | H7: =IFERROR(G11,"") -> 0 | I7: =IFERROR(H11,"") -> 0 | J7: =IFERROR(I11,"") -> 0 | K7: =IFERROR(J11,"") -> 0 | ... BJ7: =IFERROR(BI11,"") -> 0
A8: Add: disbursement | B8: ₹ L
A9: Less: principal repayment | B9: ₹ L | C9: =IFERROR(IF(AND(C5>Assumptions!$B$54,C5<=Assumptions!$B$54+Assumptions!$B$55),Assumptions!$B$51/Assumptions!$B$55,0),"") -> 0 | D9: =IFERROR(IF(AND(D5>Assumptions!$B$54,D5<=Assumptions!$B$54+Assumptions!$B$55),Assumptions!$B$51/Assumptions!$B$55,0),"") -> 0 | E9: =IFERROR(IF(AND(E5>Assumptions!$B$54,E5<=Assumptions!$B$54+Assumptions!$B$55),Assumptions!$B$51/Assumptions!$B$55,0),"") -> 0 | F9: =IFERROR(IF(AND(F5>Assumptions!$B$54,F5<=Assumptions!$B$54+Assumptions!$B$55),Assumptions!$B$51/Assumptions!$B$55,0),"") -> 0 | G9: =IFERROR(IF(AND(G5>Assumptions!$B$54,G5<=Assumptions!$B$54+Assumptions!$B$55),Assumptions!$B$51/Assumptions!$B$55,0),"") -> 0 | H9: =IFERROR(IF(AND(H5>Assumptions!$B$54,H5<=Assumptions!$B$54+Assumptions!$B$55),Assumptions!$B$51/Assumptions!$B$55,0),"") -> 0 | I9: =IFERROR(IF(AND(I5>Assumptions!$B$54,I5<=Assumptions!$B$54+Assumptions!$B$55),Assumptions!$B$51/Assumptions!$B$55,0),"") -> 0 | J9: =IFERROR(IF(AND(J5>Assumptions!$B$54,J5<=Assumptions!$B$54+Assumptions!$B$55),Assumptions!$B$51/Assumptions!$B$55,0),"") -> 0 | ... BJ9: =IFERROR(IF(AND(BJ5>Assumptions!$B$54,BJ5<=Assumptions!$B$54+Assumptions!$B$55),Assumptions!$B$51/Assumptions!$B$55,0),"") -> 0
A10: Interest for the month | B10: ₹ L | C10: =IFERROR(C7*Assumptions!$B$53/12,"") -> 0 | D10: =IFERROR(D7*Assumptions!$B$53/12,"") -> 0 | E10: =IFERROR(E7*Assumptions!$B$53/12,"") -> 0 | F10: =IFERROR(F7*Assumptions!$B$53/12,"") -> 0 | G10: =IFERROR(G7*Assumptions!$B$53/12,"") -> 0 | H10: =IFERROR(H7*Assumptions!$B$53/12,"") -> 0 | I10: =IFERROR(I7*Assumptions!$B$53/12,"") -> 0 | J10: =IFERROR(J7*Assumptions!$B$53/12,"") -> 0 | ... BJ10: =IFERROR(BJ7*Assumptions!$B$53/12,"") -> 0
A11: Closing loan balance | B11: ₹ L | C11: =IFERROR(C7+C8-C9,"") -> 0 | D11: =IFERROR(D7+D8-D9,"") -> 0 | E11: =IFERROR(E7+E8-E9,"") -> 0 | F11: =IFERROR(F7+F8-F9,"") -> 0 | G11: =IFERROR(G7+G8-G9,"") -> 0 | H11: =IFERROR(H7+H8-H9,"") -> 0 | I11: =IFERROR(I7+I8-I9,"") -> 0 | J11: =IFERROR(J7+J8-J9,"") -> 0 | ... BJ11: =IFERROR(BJ7+BJ8-BJ9,"") -> 0
A12: Total outflow (principal + interest) | B12: ₹ L | C12: =IFERROR(C9+C10,"") -> 0 | D12: =IFERROR(D9+D10,"") -> 0 | E12: =IFERROR(E9+E10,"") -> 0 | F12: =IFERROR(F9+F10,"") -> 0 | G12: =IFERROR(G9+G10,"") -> 0 | H12: =IFERROR(H9+H10,"") -> 0 | I12: =IFERROR(I9+I10,"") -> 0 | J12: =IFERROR(J9+J10,"") -> 0 | ... BJ12: =IFERROR(BJ9+BJ10,"") -> 0

Sheet Production & Sales
A1: OUTPUT / VOLUME & SALES PLAN (monthly, 5 years)
A2: Capacity × utilisation = units delivered; units × escalated realisation = net sales (₹ Lakh).
C3: ="YEAR 1 • FY"&(IF(ISNUMBER(Assumptions!$B$6),Assumptions!$B$6,2026)+0)&"-"&RIGHT((IF(ISNUMBER(Assumptions!$B$6),Assumptions!$B$6,2026)+0+1),2) -> YEAR 1 • FY2026-27 | O3: ="YEAR 2 • FY"&(IF(ISNUMBER(Assumptions!$B$6),Assumptions!$B$6,2026)+1)&"-"&RIGHT((IF(ISNUMBER(Assumptions!$B$6),Assumptions!$B$6,2026)+1+1),2) -> YEAR 2 • FY2027-28 | AA3: ="YEAR 3 • FY"&(IF(ISNUMBER(Assumptions!$B$6),Assumptions!$B$6,2026)+2)&"-"&RIGHT((IF(ISNUMBER(Assumptions!$B$6),Assumptions!$B$6,2026)+2+1),2) -> YEAR 3 • FY2028-29 | AM3: ="YEAR 4 • FY"&(IF(ISNUMBER(Assumptions!$B$6),Assumptions!$B$6,2026)+3)&"-"&RIGHT((IF(ISNUMBER(Assumptions!$B$6),Assumptions!$B$6,2026)+3+1),2) -> YEAR 4 • FY2029-30 | AY3: ="YEAR 5 • FY"&(IF(ISNUMBER(Assumptions!$B$6),Assumptions!$B$6,2026)+4)&"-"&RIGHT((IF(ISNUMBER(Assumptions!$B$6),Assumptions!$B$6,2026)+4+1),2) -> YEAR 5 • FY2030-31
A4: Month | B4: Unit | C4: =DATE(IF(ISNUMBER(Assumptions!$B$6),Assumptions!$B$6,2026),4+0,1) -> 46113 | D4: =DATE(IF(ISNUMBER(Assumptions!$B$6),Assumptions!$B$6,2026),4+1,1) -> 46143 | E4: =DATE(IF(ISNUMBER(Assumptions!$B$6),Assumptions!$B$6,2026),4+2,1) -> 46174 | F4: =DATE(IF(ISNUMBER(Assumptions!$B$6),Assumptions!$B$6,2026),4+3,1) -> 46204 | G4: =DATE(IF(ISNUMBER(Assumptions!$B$6),Assumptions!$B$6,2026),4+4,1) -> 46235 | H4: =DATE(IF(ISNUMBER(Assumptions!$B$6),Assumptions!$B$6,2026),4+5,1) -> 46266 | I4: =DATE(IF(ISNUMBER(Assumptions!$B$6),Assumptions!$B$6,2026),4+6,1) -> 46296 | J4: =DATE(IF(ISNUMBER(Assumptions!$B$6),Assumptions!$B$6,2026),4+7,1) -> 46327 | K4: =DATE(IF(ISNUMBER(Assumptions!$B$6),Assumptions!$B$6,2026),4+8,1) -> 46357 | L4: =DATE(IF(ISNUMBER(Assumptions!$B$6),Assumptions!$B$6,2026),4+9,1) -> 46388 | M4: =DATE(IF(ISNUMBER(Assumptions!$B$6),Assumptions!$B$6,2026),4+10,1) -> 46419 | N4: =DATE(IF(ISNUMBER(Assumptions!$B$6),Assumptions!$B$6,2026),4+11,1) -> 46447 | O4: =DATE(IF(ISNUMBER(Assumptions!$B$6),Assumptions!$B$6,2026),4+12,1) -> 46478 | P4: =DATE(IF(ISNUMBER(Assumptions!$B$6),Assumptions!$B$6,2026),4+13,1) -> 46508 | Q4: =DATE(IF(ISNUMBER(Assumptions!$B$6),Assumptions!$B$6,2026),4+14,1) -> 46539 | R4: =DATE(IF(ISNUMBER(Assumptions!$B$6),Assumptions!$B$6,2026),4+15,1) -> 46569 | S4: =DATE(IF(ISNUMBER(Assumptions!$B$6),Assumptions!$B$6,2026),4+16,1) -> 46600 | T4: =DATE(IF(ISNUMBER(Assumptions!$B$6),Assumptions!$B$6,2026),4+17,1) -> 46631 | U4: =DATE(IF(ISNUMBER(Assumptions!$B$6),Assumptions!$B$6,2026),4+18,1) -> 46661 | V4: =DATE(IF(ISNUMBER(Assumptions!$B$6),Assumptions!$B$6,2026),4+19,1) -> 46692 | W4: =DATE(IF(ISNUMBER(Assumptions!$B$6),Assumptions!$B$6,2026),4+20,1) -> 46722 | X4: =DATE(IF(ISNUMBER(Assumptions!$B$6),Assumptions!$B$6,2026),4+21,1) -> 46753 | Y4: =DATE(IF(ISNUMBER(Assumptions!$B$6),Assumptions!$B$6,2026),4+22,1) -> 46784 | Z4: =DATE(IF(ISNUMBER(Assumptions!$B$6),Assumptions!$B$6,2026),4+23,1) -> 46813 | AA4: =DATE(IF(ISNUMBER(Assumptions!$B$6),Assumptions!$B$6,2026),4+24,1) -> 46844 | AB4: =DATE(IF(ISNUMBER(Assumptions!$B$6),Assumptions!$B$6,2026),4+25,1) -> 46874 | AC4: =DATE(IF(ISNUMBER(Assumptions!$B$6),Assumptions!$B$6,2026),4+26,1) -> 46905 | AD4: =DATE(IF(ISNUMBER(Assumptions!$B$6),Assumptions!$B$6,2026),4+27,1) -> 46935 | AE4: =DATE(IF(ISNUMBER(Assumptions!$B$6),Assumptions!$B$6,2026),4+28,1) -> 46966 | AF4: =DATE(IF(ISNUMBER(Assumptions!$B$6),Assumptions!$B$6,2026),4+29,1) -> 46997 | AG4: =DATE(IF(ISNUMBER(Assumptions!$B$6),Assumptions!$B$6,2026),4+30,1) -> 47027 | AH4: =DATE(IF(ISNUMBER(Assumptions!$B$6),Assumptions!$B$6,2026),4+31,1) -> 47058 | AI4: =DATE(IF(ISNUMBER(Assumptions!$B$6),Assumptions!$B$6,2026),4+32,1) -> 47088 | AJ4: =DATE(IF(ISNUMBER(Assumptions!$B$6),Assumptions!$B$6,2026),4+33,1) -> 47119 | AK4: =DATE(IF(ISNUMBER(Assumptions!$B$6),Assumptions!$B$6,2026),4+34,1) -> 47150 | AL4: =DATE(IF(ISNUMBER(Assumptions!$B$6),Assumptions!$B$6,2026),4+35,1) -> 47178 | AM4: =DATE(IF(ISNUMBER(Assumptions!$B$6),Assumptions!$B$6,2026),4+36,1) -> 47209 | AN4: =DATE(IF(ISNUMBER(Assumptions!$B$6),Assumptions!$B$6,2026),4+37,1) -> 47239 | AO4: =DATE(IF(ISNUMBER(Assumptions!$B$6),Assumptions!$B$6,2026),4+38,1) -> 47270 | AP4: =DATE(IF(ISNUMBER(Assumptions!$B$6),Assumptions!$B$6,2026),4+39,1) -> 47300 | AQ4: =DATE(IF(ISNUMBER(Assumptions!$B$6),Assumptions!$B$6,2026),4+40,1) -> 47331 | AR4: =DATE(IF(ISNUMBER(Assumptions!$B$6),Assumptions!$B$6,2026),4+41,1) -> 47362 | AS4: =DATE(IF(ISNUMBER(Assumptions!$B$6),Assumptions!$B$6,2026),4+42,1) -> 47392 | AT4: =DATE(IF(ISNUMBER(Assumptions!$B$6),Assumptions!$B$6,2026),4+43,1) -> 47423 | AU4: =DATE(IF(ISNUMBER(Assumptions!$B$6),Assumptions!$B$6,2026),4+44,1) -> 47453 | AV4: =DATE(IF(ISNUMBER(Assumptions!$B$6),Assumptions!$B$6,2026),4+45,1) -> 47484 | AW4: =DATE(IF(ISNUMBER(Assumptions!$B$6),Assumptions!$B$6,2026),4+46,1) -> 47515 | AX4: =DATE(IF(ISNUMBER(Assumptions!$B$6),Assumptions!$B$6,2026),4+47,1) -> 47543 | AY4: =DATE(IF(ISNUMBER(Assumptions!$B$6),Assumptions!$B$6,2026),4+48,1) -> 47574 | AZ4: =DATE(IF(ISNUMBER(Assumptions!$B$6),Assumptions!$B$6,2026),4+49,1) -> 47604 | BA4: =DATE(IF(ISNUMBER(Assumptions!$B$6),Assumptions!$B$6,2026),4+50,1) -> 47635 | BB4: =DATE(IF(ISNUMBER(Assumptions!$B$6),Assumptions!$B$6,2026),4+51,1) -> 47665 | BC4: =DATE(IF(ISNUMBER(Assumptions!$B$6),Assumptions!$B$6,2026),4+52,1) -> 47696 | BD4: =DATE(IF(ISNUMBER(Assumptions!$B$6),Assumptions!$B$6,2026),4+53,1) -> 47727 | BE4: =DATE(IF(ISNUMBER(Assumptions!$B$6),Assumptions!$B$6,2026),4+54,1) -> 47757 | BF4: =DATE(IF(ISNUMBER(Assumptions!$B$6),Assumptions!$B$6,2026),4+55,1) -> 47788 | BG4: =DATE(IF(ISNUMBER(Assumptions!$B$6),Assumptions!$B$6,2026),4+56,1) -> 47818 | BH4: =DATE(IF(ISNUMBER(Assumptions!$B$6),Assumptions!$B$6,2026),4+57,1) -> 47849 | BI4: =DATE(IF(ISNUMBER(Assumptions!$B$6),Assumptions!$B$6,2026),4+58,1) -> 47880 | BJ4: =DATE(IF(ISNUMBER(Assumptions!$B$6),Assumptions!$B$6,2026),4+59,1) -> 47908
A5: Month # | C5: 1 | D5: 2 | E5: 3 | F5: 4 | G5: 5 | H5: 6 | I5: 7 | J5: 8 | K5: 9 | L5: 10 | M5: 11 | N5: 12 | O5: 13 | P5: 14 | Q5: 15 | R5: 16 | S5: 17 | T5: 18 | U5: 19 | V5: 20 | W5: 21 | X5: 22 | Y5: 23 | Z5: 24 | AA5: 25 | AB5: 26 | AC5: 27 | AD5: 28 | AE5: 29 | AF5: 30 | AG5: 31 | AH5: 32 | AI5: 33 | AJ5: 34 | AK5: 35 | AL5: 36 | AM5: 37 | AN5: 38 | AO5: 39 | AP5: 40 | AQ5: 41 | AR5: 42 | AS5: 43 | AT5: 44 | AU5: 45 | AV5: 46 | AW5: 47 | AX5: 48 | AY5: 49 | AZ5: 50 | BA5: 51 | BB5: 52 | BC5: 53 | BD5: 54 | BE5: 55 | BF5: 56 | BG5: 57 | BH5: 58 | BI5: 59 | BJ5: 60
A6: Year # | C6: 1 | D6: 1 | E6: 1 | F6: 1 | G6: 1 | H6: 1 | I6: 1 | J6: 1 | K6: 1 | L6: 1 | M6: 1 | N6: 1 | O6: 2 | P6: 2 | Q6: 2 | R6: 2 | S6: 2 | T6: 2 | U6: 2 | V6: 2 | W6: 2 | X6: 2 | Y6: 2 | Z6: 2 | AA6: 3 | AB6: 3 | AC6: 3 | AD6: 3 | AE6: 3 | AF6: 3 | AG6: 3 | AH6: 3 | AI6: 3 | AJ6: 3 | AK6: 3 | AL6: 3 | AM6: 4 | AN6: 4 | AO6: 4 | AP6: 4 | AQ6: 4 | AR6: 4 | AS6: 4 | AT6: 4 | AU6: 4 | AV6: 4 | AW6: 4 | AX6: 4 | AY6: 5 | AZ6: 5 | BA6: 5 | BB6: 5 | BC6: 5 | BD6: 5 | BE6: 5 | BF6: 5 | BG6: 5 | BH6: 5 | BI6: 5 | BJ6: 5
A7: Capacity utilisation | B7: % | C7: =IFERROR(Assumptions!$B$16,"") -> 0 | D7: =IFERROR(Assumptions!$B$17,"") -> 0 | E7: =IFERROR(Assumptions!$B$18,"") -> 0 | F7: =IFERROR(Assumptions!$B$19,"") -> 0 | G7: =IFERROR(Assumptions!$B$20,"") -> 0 | H7: =IFERROR(Assumptions!$B$21,"") -> 0 | I7: =IFERROR(Assumptions!$B$22,"") -> 0 | J7: =IFERROR(Assumptions!$B$23,"") -> 0 | K7: =IFERROR(Assumptions!$B$24,"") -> 0 | L7: =IFERROR(Assumptions!$B$25,"") -> 0 | M7: =IFERROR(Assumptions!$B$26,"") -> 0 | N7: =IFERROR(Assumptions!$B$27,"") -> 0 | O7: =IFERROR(Assumptions!$B$28,"") -> 0 | P7: =IFERROR(Assumptions!$B$28,"") -> 0 | Q7: =IFERROR(Assumptions!$B$28,"") -> 0 | R7: =IFERROR(Assumptions!$B$28,"") -> 0 | S7: =IFERROR(Assumptions!$B$28,"") -> 0 | T7: =IFERROR(Assumptions!$B$28,"") -> 0 | U7: =IFERROR(Assumptions!$B$28,"") -> 0 | V7: =IFERROR(Assumptions!$B$28,"") -> 0 | ... Z7: =IFERROR(Assumptions!$B$28,"") -> 0 | AA7: =IFERROR(Assumptions!$B$29,"") -> 0 | AB7: =IFERROR(Assumptions!$B$29,"") -> 0 | AC7: =IFERROR(Assumptions!$B$29,"") -> 0 | AD7: =IFERROR(Assumptions!$B$29,"") -> 0 | AE7: =IFERROR(Assumptions!$B$29,"") -> 0 | AF7: =IFERROR(Assumptions!$B$29,"") -> 0 | AG7: =IFERROR(Assumptions!$B$29,"") -> 0 | AH7: =IFERROR(Assumptions!$B$29,"") -> 0 | ... AL7: =IFERROR(Assumptions!$B$29,"") -> 0 | AM7: =IFERROR(Assumptions!$B$30,"") -> 0 | AN7: =IFERROR(Assumptions!$B$30,"") -> 0 | AO7: =IFERROR(Assumptions!$B$30,"") -> 0 | AP7: =IFERROR(Assumptions!$B$30,"") -> 0 | AQ7: =IFERROR(Assumptions!$B$30,"") -> 0 | AR7: =IFERROR(Assumptions!$B$30,"") -> 0 | AS7: =IFERROR(Assumptions!$B$30,"") -> 0 | AT7: =IFERROR(Assumptions!$B$30,"") -> 0 | ... AX7: =IFERROR(Assumptions!$B$30,"") -> 0 | AY7: =IFERROR(Assumptions!$B$31,"") -> 0 | AZ7: =IFERROR(Assumptions!$B$31,"") -> 0 | BA7: =IFERROR(Assumptions!$B$31,"") -> 0 | BB7: =IFERROR(Assumptions!$B$31,"") -> 0 | BC7: =IFERROR(Assumptions!$B$31,"") -> 0 | BD7: =IFERROR(Assumptions!$B$31,"") -> 0 | BE7: =IFERROR(Assumptions!$B$31,"") -> 0 | BF7: =IFERROR(Assumptions!$B$31,"") -> 0 | ... BJ7: =IFERROR(Assumptions!$B$31,"") -> 0
A8: =IFERROR(INDEX('Industry Labels'!$C$5:$Z$5,MATCH(Assumptions!$B$3,'Industry Labels'!$C$4:$Z$4,0)),"Installed / service capacity") -> Installed / service capacity | B8: =IFERROR(INDEX('Industry Labels'!$C$6:$Z$6,MATCH(Assumptions!$B$3,'Industry Labels'!$C$4:$Z$4,0)),"units/month") -> units/month | C8: =IFERROR(Assumptions!$B$5,"") -> 0 | D8: =IFERROR(Assumptions!$B$5,"") -> 0 | E8: =IFERROR(Assumptions!$B$5,"") -> 0 | F8: =IFERROR(Assumptions!$B$5,"") -> 0 | G8: =IFERROR(Assumptions!$B$5,"") -> 0 | H8: =IFERROR(Assumptions!$B$5,"") -> 0 | I8: =IFERROR(Assumptions!$B$5,"") -> 0 | J8: =IFERROR(Assumptions!$B$5,"") -> 0 | ... BJ8: =IFERROR(Assumptions!$B$5,"") -> 0
A9: Output delivered (volume) | B9: =IFERROR(INDEX('Industry Labels'!$C$7:$Z$7,MATCH(Assumptions!$B$3,'Industry Labels'!$C$4:$Z$4,0)),"units") -> units | C9: =IFERROR(C8*C7,"") -> 0 | D9: =IFERROR(D8*D7,"") -> 0 | E9: =IFERROR(E8*E7,"") -> 0 | F9: =IFERROR(F8*F7,"") -> 0 | G9: =IFERROR(G8*G7,"") -> 0 | H9: =IFERROR(H8*H7,"") -> 0 | I9: =IFERROR(I8*I7,"") -> 0 | J9: =IFERROR(J8*J7,"") -> 0 | ... BJ9: =IFERROR(BJ8*BJ7,"") -> 0
A10: Sales volume | B10: =IFERROR(INDEX('Industry Labels'!$C$7:$Z$7,MATCH(Assumptions!$B$3,'Industry Labels'!$C$4:$Z$4,0)),"units") -> units | C10: =IFERROR(C9,"") -> 0 | D10: =IFERROR(D9,"") -> 0 | E10: =IFERROR(E9,"") -> 0 | F10: =IFERROR(F9,"") -> 0 | G10: =IFERROR(G9,"") -> 0 | H10: =IFERROR(H9,"") -> 0 | I10: =IFERROR(I9,"") -> 0 | J10: =IFERROR(J9,"") -> 0 | ... BJ10: =IFERROR(BJ9,"") -> 0
A11: Realisation | B11: ="₹/"&IFERROR(INDEX('Industry Labels'!$C$8:$Z$8,MATCH(Assumptions!$B$3,'Industry Labels'!$C$4:$Z$4,0)),"unit") -> ₹/unit | C11: =IFERROR(Assumptions!$B$10*(1+Assumptions!$B$33)^(C6-1),"") -> 0 | D11: =IFERROR(Assumptions!$B$10*(1+Assumptions!$B$33)^(D6-1),"") -> 0 | E11: =IFERROR(Assumptions!$B$10*(1+Assumptions!$B$33)^(E6-1),"") -> 0 | F11: =IFERROR(Assumptions!$B$10*(1+Assumptions!$B$33)^(F6-1),"") -> 0 | G11: =IFERROR(Assumptions!$B$10*(1+Assumptions!$B$33)^(G6-1),"") -> 0 | H11: =IFERROR(Assumptions!$B$10*(1+Assumptions!$B$33)^(H6-1),"") -> 0 | I11: =IFERROR(Assumptions!$B$10*(1+Assumptions!$B$33)^(I6-1),"") -> 0 | J11: =IFERROR(Assumptions!$B$10*(1+Assumptions!$B$33)^(J6-1),"") -> 0 | ... BJ11: =IFERROR(Assumptions!$B$10*(1+Assumptions!$B$33)^(BJ6-1),"") -> 0
A12: NET SALES | B12: ₹ L | C12: =IFERROR(C10*C11/100000,"") -> 0 | D12: =IFERROR(D10*D11/100000,"") -> 0 | E12: =IFERROR(E10*E11/100000,"") -> 0 | F12: =IFERROR(F10*F11/100000,"") -> 0 | G12: =IFERROR(G10*G11/100000,"") -> 0 | H12: =IFERROR(H10*H11/100000,"") -> 0 | I12: =IFERROR(I10*I11/100000,"") -> 0 | J12: =IFERROR(J10*J11/100000,"") -> 0 | ... BJ12: =IFERROR(BJ10*BJ11/100000,"") -> 0

Sheet Profitability (Monthly)
A1: PROFITABILITY STATEMENT (monthly, 5 years) — ₹ Lakh
A2: Every line links to Assumptions / Production & Sales / Term Loan / Working Capital. Escalation applied by year.
C3: ="YEAR 1 • FY"&(IF(ISNUMBER(Assumptions!$B$6),Assumptions!$B$6,2026)+0)&"-"&RIGHT((IF(ISNUMBER(Assumptions!$B$6),Assumptions!$B$6,2026)+0+1),2) -> YEAR 1 • FY2026-27 | O3: ="YEAR 2 • FY"&(IF(ISNUMBER(Assumptions!$B$6),Assumptions!$B$6,2026)+1)&"-"&RIGHT((IF(ISNUMBER(Assumptions!$B$6),Assumptions!$B$6,2026)+1+1),2) -> YEAR 2 • FY2027-28 | AA3: ="YEAR 3 • FY"&(IF(ISNUMBER(Assumptions!$B$6),Assumptions!$B$6,2026)+2)&"-"&RIGHT((IF(ISNUMBER(Assumptions!$B$6),Assumptions!$B$6,2026)+2+1),2) -> YEAR 3 • FY2028-29 | AM3: ="YEAR 4 • FY"&(IF(ISNUMBER(Assumptions!$B$6),Assumptions!$B$6,2026)+3)&"-"&RIGHT((IF(ISNUMBER(Assumptions!$B$6),Assumptions!$B$6,2026)+3+1),2) -> YEAR 4 • FY2029-30 | AY3: ="YEAR 5 • FY"&(IF(ISNUMBER(Assumptions!$B$6),Assumptions!$B$6,2026)+4)&"-"&RIGHT((IF(ISNUMBER(Assumptions!$B$6),Assumptions!$B$6,2026)+4+1),2) -> YEAR 5 • FY2030-31
A4: Month | B4: Unit | C4: =DATE(IF(ISNUMBER(Assumptions!$B$6),Assumptions!$B$6,2026),4+0,1) -> 46113 | D4: =DATE(IF(ISNUMBER(Assumptions!$B$6),Assumptions!$B$6,2026),4+1,1) -> 46143 | E4: =DATE(IF(ISNUMBER(Assumptions!$B$6),Assumptions!$B$6,2026),4+2,1) -> 46174 | F4: =DATE(IF(ISNUMBER(Assumptions!$B$6),Assumptions!$B$6,2026),4+3,1) -> 46204 | G4: =DATE(IF(ISNUMBER(Assumptions!$B$6),Assumptions!$B$6,2026),4+4,1) -> 46235 | H4: =DATE(IF(ISNUMBER(Assumptions!$B$6),Assumptions!$B$6,2026),4+5,1) -> 46266 | I4: =DATE(IF(ISNUMBER(Assumptions!$B$6),Assumptions!$B$6,2026),4+6,1) -> 46296 | J4: =DATE(IF(ISNUMBER(Assumptions!$B$6),Assumptions!$B$6,2026),4+7,1) -> 46327 | K4: =DATE(IF(ISNUMBER(Assumptions!$B$6),Assumptions!$B$6,2026),4+8,1) -> 46357 | L4: =DATE(IF(ISNUMBER(Assumptions!$B$6),Assumptions!$B$6,2026),4+9,1) -> 46388 | M4: =DATE(IF(ISNUMBER(Assumptions!$B$6),Assumptions!$B$6,2026),4+10,1) -> 46419 | N4: =DATE(IF(ISNUMBER(Assumptions!$B$6),Assumptions!$B$6,2026),4+11,1) -> 46447 | O4: =DATE(IF(ISNUMBER(Assumptions!$B$6),Assumptions!$B$6,2026),4+12,1) -> 46478 | P4: =DATE(IF(ISNUMBER(Assumptions!$B$6),Assumptions!$B$6,2026),4+13,1) -> 46508 | Q4: =DATE(IF(ISNUMBER(Assumptions!$B$6),Assumptions!$B$6,2026),4+14,1) -> 46539 | R4: =DATE(IF(ISNUMBER(Assumptions!$B$6),Assumptions!$B$6,2026),4+15,1) -> 46569 | S4: =DATE(IF(ISNUMBER(Assumptions!$B$6),Assumptions!$B$6,2026),4+16,1) -> 46600 | T4: =DATE(IF(ISNUMBER(Assumptions!$B$6),Assumptions!$B$6,2026),4+17,1) -> 46631 | U4: =DATE(IF(ISNUMBER(Assumptions!$B$6),Assumptions!$B$6,2026),4+18,1) -> 46661 | V4: =DATE(IF(ISNUMBER(Assumptions!$B$6),Assumptions!$B$6,2026),4+19,1) -> 46692 | W4: =DATE(IF(ISNUMBER(Assumptions!$B$6),Assumptions!$B$6,2026),4+20,1) -> 46722 | X4: =DATE(IF(ISNUMBER(Assumptions!$B$6),Assumptions!$B$6,2026),4+21,1) -> 46753 | Y4: =DATE(IF(ISNUMBER(Assumptions!$B$6),Assumptions!$B$6,2026),4+22,1) -> 46784 | Z4: =DATE(IF(ISNUMBER(Assumptions!$B$6),Assumptions!$B$6,2026),4+23,1) -> 46813 | AA4: =DATE(IF(ISNUMBER(Assumptions!$B$6),Assumptions!$B$6,2026),4+24,1) -> 46844 | AB4: =DATE(IF(ISNUMBER(Assumptions!$B$6),Assumptions!$B$6,2026),4+25,1) -> 46874 | AC4: =DATE(IF(ISNUMBER(Assumptions!$B$6),Assumptions!$B$6,2026),4+26,1) -> 46905 | AD4: =DATE(IF(ISNUMBER(Assumptions!$B$6),Assumptions!$B$6,2026),4+27,1) -> 46935 | AE4: =DATE(IF(ISNUMBER(Assumptions!$B$6),Assumptions!$B$6,2026),4+28,1) -> 46966 | AF4: =DATE(IF(ISNUMBER(Assumptions!$B$6),Assumptions!$B$6,2026),4+29,1) -> 46997 | AG4: =DATE(IF(ISNUMBER(Assumptions!$B$6),Assumptions!$B$6,2026),4+30,1) -> 47027 | AH4: =DATE(IF(ISNUMBER(Assumptions!$B$6),Assumptions!$B$6,2026),4+31,1) -> 47058 | AI4: =DATE(IF(ISNUMBER(Assumptions!$B$6),Assumptions!$B$6,2026),4+32,1) -> 47088 | AJ4: =DATE(IF(ISNUMBER(Assumptions!$B$6),Assumptions!$B$6,2026),4+33,1) -> 47119 | AK4: =DATE(IF(ISNUMBER(Assumptions!$B$6),Assumptions!$B$6,2026),4+34,1) -> 47150 | AL4: =DATE(IF(ISNUMBER(Assumptions!$B$6),Assumptions!$B$6,2026),4+35,1) -> 47178 | AM4: =DATE(IF(ISNUMBER(Assumptions!$B$6),Assumptions!$B$6,2026),4+36,1) -> 47209 | AN4: =DATE(IF(ISNUMBER(Assumptions!$B$6),Assumptions!$B$6,2026),4+37,1) -> 47239 | AO4: =DATE(IF(ISNUMBER(Assumptions!$B$6),Assumptions!$B$6,2026),4+38,1) -> 47270 | AP4: =DATE(IF(ISNUMBER(Assumptions!$B$6),Assumptions!$B$6,2026),4+39,1) -> 47300 | AQ4: =DATE(IF(ISNUMBER(Assumptions!$B$6),Assumptions!$B$6,2026),4+40,1) -> 47331 | AR4: =DATE(IF(ISNUMBER(Assumptions!$B$6),Assumptions!$B$6,2026),4+41,1) -> 47362 | AS4: =DATE(IF(ISNUMBER(Assumptions!$B$6),Assumptions!$B$6,2026),4+42,1) -> 47392 | AT4: =DATE(IF(ISNUMBER(Assumptions!$B$6),Assumptions!$B$6,2026),4+43,1) -> 47423 | AU4: =DATE(IF(ISNUMBER(Assumptions!$B$6),Assumptions!$B$6,2026),4+44,1) -> 47453 | AV4: =DATE(IF(ISNUMBER(Assumptions!$B$6),Assumptions!$B$6,2026),4+45,1) -> 47484 | AW4: =DATE(IF(ISNUMBER(Assumptions!$B$6),Assumptions!$B$6,2026),4+46,1) -> 47515 | AX4: =DATE(IF(ISNUMBER(Assumptions!$B$6),Assumptions!$B$6,2026),4+47,1) -> 47543 | AY4: =DATE(IF(ISNUMBER(Assumptions!$B$6),Assumptions!$B$6,2026),4+48,1) -> 47574 | AZ4: =DATE(IF(ISNUMBER(Assumptions!$B$6),Assumptions!$B$6,2026),4+49,1) -> 47604 | BA4: =DATE(IF(ISNUMBER(Assumptions!$B$6),Assumptions!$B$6,2026),4+50,1) -> 47635 | BB4: =DATE(IF(ISNUMBER(Assumptions!$B$6),Assumptions!$B$6,2026),4+51,1) -> 47665 | BC4: =DATE(IF(ISNUMBER(Assumptions!$B$6),Assumptions!$B$6,2026),4+52,1) -> 47696 | BD4: =DATE(IF(ISNUMBER(Assumptions!$B$6),Assumptions!$B$6,2026),4+53,1) -> 47727 | BE4: =DATE(IF(ISNUMBER(Assumptions!$B$6),Assumptions!$B$6,2026),4+54,1) -> 47757 | BF4: =DATE(IF(ISNUMBER(Assumptions!$B$6),Assumptions!$B$6,2026),4+55,1) -> 47788 | BG4: =DATE(IF(ISNUMBER(Assumptions!$B$6),Assumptions!$B$6,2026),4+56,1) -> 47818 | BH4: =DATE(IF(ISNUMBER(Assumptions!$B$6),Assumptions!$B$6,2026),4+57,1) -> 47849 | BI4: =DATE(IF(ISNUMBER(Assumptions!$B$6),Assumptions!$B$6,2026),4+58,1) -> 47880 | BJ4: =DATE(IF(ISNUMBER(Assumptions!$B$6),Assumptions!$B$6,2026),4+59,1) -> 47908
A5: Month # | C5: 1 | D5: 2 | E5: 3 | F5: 4 | G5: 5 | H5: 6 | I5: 7 | J5: 8 | K5: 9 | L5: 10 | M5: 11 | N5: 12 | O5: 13 | P5: 14 | Q5: 15 | R5: 16 | S5: 17 | T5: 18 | U5: 19 | V5: 20 | W5: 21 | X5: 22 | Y5: 23 | Z5: 24 | AA5: 25 | AB5: 26 | AC5: 27 | AD5: 28 | AE5: 29 | AF5: 30 | AG5: 31 | AH5: 32 | AI5: 33 | AJ5: 34 | AK5: 35 | AL5: 36 | AM5: 37 | AN5: 38 | AO5: 39 | AP5: 40 | AQ5: 41 | AR5: 42 | AS5: 43 | AT5: 44 | AU5: 45 | AV5: 46 | AW5: 47 | AX5: 48 | AY5: 49 | AZ5: 50 | BA5: 51 | BB5: 52 | BC5: 53 | BD5: 54 | BE5: 55 | BF5: 56 | BG5: 57 | BH5: 58 | BI5: 59 | BJ5: 60
A6: Year # | C6: 1 | D6: 1 | E6: 1 | F6: 1 | G6: 1 | H6: 1 | I6: 1 | J6: 1 | K6: 1 | L6: 1 | M6: 1 | N6: 1 | O6: 2 | P6: 2 | Q6: 2 | R6: 2 | S6: 2 | T6: 2 | U6: 2 | V6: 2 | W6: 2 | X6: 2 | Y6: 2 | Z6: 2 | AA6: 3 | AB6: 3 | AC6: 3 | AD6: 3 | AE6: 3 | AF6: 3 | AG6: 3 | AH6: 3 | AI6: 3 | AJ6: 3 | AK6: 3 | AL6: 3 | AM6: 4 | AN6: 4 | AO6: 4 | AP6: 4 | AQ6: 4 | AR6: 4 | AS6: 4 | AT6: 4 | AU6: 4 | AV6: 4 | AW6: 4 | AX6: 4 | AY6: 5 | AZ6: 5 | BA6: 5 | BB6: 5 | BC6: 5 | BD6: 5 | BE6: 5 | BF6: 5 | BG6: 5 | BH6: 5 | BI6: 5 | BJ6: 5
A7: A. REVENUE
A8: Net Sales (net of GST) | B8: ₹ L | C8: =IFERROR('Production & Sales'!C12,"") -> 0 | D8: =IFERROR('Production & Sales'!D12,"") -> 0 | E8: =IFERROR('Production & Sales'!E12,"") -> 0 | F8: =IFERROR('Production & Sales'!F12,"") -> 0 | G8: =IFERROR('Production & Sales'!G12,"") -> 0 | H8: =IFERROR('Production & Sales'!H12,"") -> 0 | I8: =IFERROR('Production & Sales'!I12,"") -> 0 | J8: =IFERROR('Production & Sales'!J12,"") -> 0 | ... BJ8: =IFERROR('Production & Sales'!BJ12,"") -> 0
A9: =IFERROR(INDEX('Industry Labels'!$C$20:$Z$20,MATCH(Assumptions!$B$3,'Industry Labels'!$C$4:$Z$4,0)),"B. VARIABLE / DIRECT COST") -> B. VARIABLE / DIRECT COST
A10: =IFERROR(INDEX('Industry Labels'!$C$21:$Z$21,MATCH(Assumptions!$B$3,'Industry Labels'!$C$4:$Z$4,0)),"Direct cost consumed") -> Direct cost consumed | B10: ₹ L | C10: =IFERROR('Production & Sales'!C9*Assumptions!$B$11*(1+Assumptions!$B$34)^(C6-1)/100000,"") -> 0 | D10: =IFERROR('Production & Sales'!D9*Assumptions!$B$11*(1+Assumptions!$B$34)^(D6-1)/100000,"") -> 0 | E10: =IFERROR('Production & Sales'!E9*Assumptions!$B$11*(1+Assumptions!$B$34)^(E6-1)/100000,"") -> 0 | F10: =IFERROR('Production & Sales'!F9*Assumptions!$B$11*(1+Assumptions!$B$34)^(F6-1)/100000,"") -> 0 | G10: =IFERROR('Production & Sales'!G9*Assumptions!$B$11*(1+Assumptions!$B$34)^(G6-1)/100000,"") -> 0 | H10: =IFERROR('Production & Sales'!H9*Assumptions!$B$11*(1+Assumptions!$B$34)^(H6-1)/100000,"") -> 0 | I10: =IFERROR('Production & Sales'!I9*Assumptions!$B$11*(1+Assumptions!$B$34)^(I6-1)/100000,"") -> 0 | J10: =IFERROR('Production & Sales'!J9*Assumptions!$B$11*(1+Assumptions!$B$34)^(J6-1)/100000,"") -> 0 | ... BJ10: =IFERROR('Production & Sales'!BJ9*Assumptions!$B$11*(1+Assumptions!$B$34)^(BJ6-1)/100000,"") -> 0
A11: =IFERROR(INDEX('Industry Labels'!$C$22:$Z$22,MATCH(Assumptions!$B$3,'Industry Labels'!$C$4:$Z$4,0)),"Utilities & energy")&" (variable)" -> Utilities & energy (variable) | B11: ₹ L | C11: =IFERROR('Production & Sales'!C9*Assumptions!$B$39*(1+Assumptions!$B$35)^(C6-1)/100000,"") -> 0 | D11: =IFERROR('Production & Sales'!D9*Assumptions!$B$39*(1+Assumptions!$B$35)^(D6-1)/100000,"") -> 0 | E11: =IFERROR('Production & Sales'!E9*Assumptions!$B$39*(1+Assumptions!$B$35)^(E6-1)/100000,"") -> 0 | F11: =IFERROR('Production & Sales'!F9*Assumptions!$B$39*(1+Assumptions!$B$35)^(F6-1)/100000,"") -> 0 | G11: =IFERROR('Production & Sales'!G9*Assumptions!$B$39*(1+Assumptions!$B$35)^(G6-1)/100000,"") -> 0 | H11: =IFERROR('Production & Sales'!H9*Assumptions!$B$39*(1+Assumptions!$B$35)^(H6-1)/100000,"") -> 0 | I11: =IFERROR('Production & Sales'!I9*Assumptions!$B$39*(1+Assumptions!$B$35)^(I6-1)/100000,"") -> 0 | J11: =IFERROR('Production & Sales'!J9*Assumptions!$B$39*(1+Assumptions!$B$35)^(J6-1)/100000,"") -> 0 | ... BJ11: =IFERROR('Production & Sales'!BJ9*Assumptions!$B$39*(1+Assumptions!$B$35)^(BJ6-1)/100000,"") -> 0
A12: =IFERROR(INDEX('Industry Labels'!$C$23:$Z$23,MATCH(Assumptions!$B$3,'Industry Labels'!$C$4:$Z$4,0)),"Consumables, supplies & packing") -> Consumables, supplies & packing | B12: ₹ L | C12: =IFERROR('Production & Sales'!C9*(Assumptions!$B$40+Assumptions!$B$41)*(1+Assumptions!$B$37)^(C6-1)/100000,"") -> 0 | D12: =IFERROR('Production & Sales'!D9*(Assumptions!$B$40+Assumptions!$B$41)*(1+Assumptions!$B$37)^(D6-1)/100000,"") -> 0 | E12: =IFERROR('Production & Sales'!E9*(Assumptions!$B$40+Assumptions!$B$41)*(1+Assumptions!$B$37)^(E6-1)/100000,"") -> 0 | F12: =IFERROR('Production & Sales'!F9*(Assumptions!$B$40+Assumptions!$B$41)*(1+Assumptions!$B$37)^(F6-1)/100000,"") -> 0 | G12: =IFERROR('Production & Sales'!G9*(Assumptions!$B$40+Assumptions!$B$41)*(1+Assumptions!$B$37)^(G6-1)/100000,"") -> 0 | H12: =IFERROR('Production & Sales'!H9*(Assumptions!$B$40+Assumptions!$B$41)*(1+Assumptions!$B$37)^(H6-1)/100000,"") -> 0 | I12: =IFERROR('Production & Sales'!I9*(Assumptions!$B$40+Assumptions!$B$41)*(1+Assumptions!$B$37)^(I6-1)/100000,"") -> 0 | J12: =IFERROR('Production & Sales'!J9*(Assumptions!$B$40+Assumptions!$B$41)*(1+Assumptions!$B$37)^(J6-1)/100000,"") -> 0 | ... BJ12: =IFERROR('Production & Sales'!BJ9*(Assumptions!$B$40+Assumptions!$B$41)*(1+Assumptions!$B$37)^(BJ6-1)/100000,"") -> 0
A13: Direct labour | B13: ₹ L | C13: =IFERROR(Assumptions!$B$42*(1+Assumptions!$B$36)^(C6-1),"") -> 0 | D13: =IFERROR(Assumptions!$B$42*(1+Assumptions!$B$36)^(D6-1),"") -> 0 | E13: =IFERROR(Assumptions!$B$42*(1+Assumptions!$B$36)^(E6-1),"") -> 0 | F13: =IFERROR(Assumptions!$B$42*(1+Assumptions!$B$36)^(F6-1),"") -> 0 | G13: =IFERROR(Assumptions!$B$42*(1+Assumptions!$B$36)^(G6-1),"") -> 0 | H13: =IFERROR(Assumptions!$B$42*(1+Assumptions!$B$36)^(H6-1),"") -> 0 | I13: =IFERROR(Assumptions!$B$42*(1+Assumptions!$B$36)^(I6-1),"") -> 0 | J13: =IFERROR(Assumptions!$B$42*(1+Assumptions!$B$36)^(J6-1),"") -> 0 | ... BJ13: =IFERROR(Assumptions!$B$42*(1+Assumptions!$B$36)^(BJ6-1),"") -> 0
A14: Total variable / direct cost | B14: ₹ L | C14: =IFERROR(SUM(C10:C13),"") -> 0 | D14: =IFERROR(SUM(D10:D13),"") -> 0 | E14: =IFERROR(SUM(E10:E13),"") -> 0 | F14: =IFERROR(SUM(F10:F13),"") -> 0 | G14: =IFERROR(SUM(G10:G13),"") -> 0 | H14: =IFERROR(SUM(H10:H13),"") -> 0 | I14: =IFERROR(SUM(I10:I13),"") -> 0 | J14: =IFERROR(SUM(J10:J13),"") -> 0 | ... BJ14: =IFERROR(SUM(BJ10:BJ13),"") -> 0
A15: CONTRIBUTION (Gross margin) | B15: ₹ L | C15: =IFERROR(C8-C14,"") -> 0 | D15: =IFERROR(D8-D14,"") -> 0 | E15: =IFERROR(E8-E14,"") -> 0 | F15: =IFERROR(F8-F14,"") -> 0 | G15: =IFERROR(G8-G14,"") -> 0 | H15: =IFERROR(H8-H14,"") -> 0 | I15: =IFERROR(I8-I14,"") -> 0 | J15: =IFERROR(J8-J14,"") -> 0 | ... BJ15: =IFERROR(BJ8-BJ14,"") -> 0
A16: Contribution margin | B16: % | C16: =IFERROR(IF(C8=0,0,C15/C8),"") -> 0 | D16: =IFERROR(IF(D8=0,0,D15/D8),"") -> 0 | E16: =IFERROR(IF(E8=0,0,E15/E8),"") -> 0 | F16: =IFERROR(IF(F8=0,0,F15/F8),"") -> 0 | G16: =IFERROR(IF(G8=0,0,G15/G8),"") -> 0 | H16: =IFERROR(IF(H8=0,0,H15/H8),"") -> 0 | I16: =IFERROR(IF(I8=0,0,I15/I8),"") -> 0 | J16: =IFERROR(IF(J8=0,0,J15/J8),"") -> 0 | ... BJ16: =IFERROR(IF(BJ8=0,0,BJ15/BJ8),"") -> 0
A17: C. FIXED & OVERHEAD COST
A18: Admin & management salaries | B18: ₹ L | C18: =IFERROR(Assumptions!$B$44*(1+Assumptions!$B$36)^(C6-1),"") -> 0 | D18: =IFERROR(Assumptions!$B$44*(1+Assumptions!$B$36)^(D6-1),"") -> 0 | E18: =IFERROR(Assumptions!$B$44*(1+Assumptions!$B$36)^(E6-1),"") -> 0 | F18: =IFERROR(Assumptions!$B$44*(1+Assumptions!$B$36)^(F6-1),"") -> 0 | G18: =IFERROR(Assumptions!$B$44*(1+Assumptions!$B$36)^(G6-1),"") -> 0 | H18: =IFERROR(Assumptions!$B$44*(1+Assumptions!$B$36)^(H6-1),"") -> 0 | I18: =IFERROR(Assumptions!$B$44*(1+Assumptions!$B$36)^(I6-1),"") -> 0 | J18: =IFERROR(Assumptions!$B$44*(1+Assumptions!$B$36)^(J6-1),"") -> 0 | ... BJ18: =IFERROR(Assumptions!$B$44*(1+Assumptions!$B$36)^(BJ6-1),"") -> 0
A19: =IFERROR(INDEX('Industry Labels'!$C$24:$Z$24,MATCH(Assumptions!$B$3,'Industry Labels'!$C$4:$Z$4,0)),"Fixed utility / facility charges") -> Fixed utility / facility charges | B19: ₹ L | C19: =IFERROR(Assumptions!$B$45*(1+Assumptions!$B$35)^(C6-1),"") -> 0 | D19: =IFERROR(Assumptions!$B$45*(1+Assumptions!$B$35)^(D6-1),"") -> 0 | E19: =IFERROR(Assumptions!$B$45*(1+Assumptions!$B$35)^(E6-1),"") -> 0 | F19: =IFERROR(Assumptions!$B$45*(1+Assumptions!$B$35)^(F6-1),"") -> 0 | G19: =IFERROR(Assumptions!$B$45*(1+Assumptions!$B$35)^(G6-1),"") -> 0 | H19: =IFERROR(Assumptions!$B$45*(1+Assumptions!$B$35)^(H6-1),"") -> 0 | I19: =IFERROR(Assumptions!$B$45*(1+Assumptions!$B$35)^(I6-1),"") -> 0 | J19: =IFERROR(Assumptions!$B$45*(1+Assumptions!$B$35)^(J6-1),"") -> 0 | ... BJ19: =IFERROR(Assumptions!$B$45*(1+Assumptions!$B$35)^(BJ6-1),"") -> 0
A20: Repairs & maintenance | B20: ₹ L | C20: =IFERROR(('Project Cost'!$C$7+'Project Cost'!$C$11)*Assumptions!$B$46/12*(1+Assumptions!$B$37)^(C6-1),"") -> 0 | D20: =IFERROR(('Project Cost'!$C$7+'Project Cost'!$C$11)*Assumptions!$B$46/12*(1+Assumptions!$B$37)^(D6-1),"") -> 0 | E20: =IFERROR(('Project Cost'!$C$7+'Project Cost'!$C$11)*Assumptions!$B$46/12*(1+Assumptions!$B$37)^(E6-1),"") -> 0 | F20: =IFERROR(('Project Cost'!$C$7+'Project Cost'!$C$11)*Assumptions!$B$46/12*(1+Assumptions!$B$37)^(F6-1),"") -> 0 | G20: =IFERROR(('Project Cost'!$C$7+'Project Cost'!$C$11)*Assumptions!$B$46/12*(1+Assumptions!$B$37)^(G6-1),"") -> 0 | H20: =IFERROR(('Project Cost'!$C$7+'Project Cost'!$C$11)*Assumptions!$B$46/12*(1+Assumptions!$B$37)^(H6-1),"") -> 0 | I20: =IFERROR(('Project Cost'!$C$7+'Project Cost'!$C$11)*Assumptions!$B$46/12*(1+Assumptions!$B$37)^(I6-1),"") -> 0 | J20: =IFERROR(('Project Cost'!$C$7+'Project Cost'!$C$11)*Assumptions!$B$46/12*(1+Assumptions!$B$37)^(J6-1),"") -> 0 | ... BJ20: =IFERROR(('Project Cost'!$C$7+'Project Cost'!$C$11)*Assumptions!$B$46/12*(1+Assumptions!$B$37)^(BJ6-1),"") -> 0
A21: Insurance | B21: ₹ L | C21: =IFERROR(('Project Cost'!$C$14-'Project Cost'!$C$5-'Project Cost'!$C$13)*Assumptions!$B$47/12*(1+Assumptions!$B$37)^(C6-1),"") -> 0 | D21: =IFERROR(('Project Cost'!$C$14-'Project Cost'!$C$5-'Project Cost'!$C$13)*Assumptions!$B$47/12*(1+Assumptions!$B$37)^(D6-1),"") -> 0 | E21: =IFERROR(('Project Cost'!$C$14-'Project Cost'!$C$5-'Project Cost'!$C$13)*Assumptions!$B$47/12*(1+Assumptions!$B$37)^(E6-1),"") -> 0 | F21: =IFERROR(('Project Cost'!$C$14-'Project Cost'!$C$5-'Project Cost'!$C$13)*Assumptions!$B$47/12*(1+Assumptions!$B$37)^(F6-1),"") -> 0 | G21: =IFERROR(('Project Cost'!$C$14-'Project Cost'!$C$5-'Project Cost'!$C$13)*Assumptions!$B$47/12*(1+Assumptions!$B$37)^(G6-1),"") -> 0 | H21: =IFERROR(('Project Cost'!$C$14-'Project Cost'!$C$5-'Project Cost'!$C$13)*Assumptions!$B$47/12*(1+Assumptions!$B$37)^(H6-1),"") -> 0 | I21: =IFERROR(('Project Cost'!$C$14-'Project Cost'!$C$5-'Project Cost'!$C$13)*Assumptions!$B$47/12*(1+Assumptions!$B$37)^(I6-1),"") -> 0 | J21: =IFERROR(('Project Cost'!$C$14-'Project Cost'!$C$5-'Project Cost'!$C$13)*Assumptions!$B$47/12*(1+Assumptions!$B$37)^(J6-1),"") -> 0 | ... BJ21: =IFERROR(('Project Cost'!$C$14-'Project Cost'!$C$5-'Project Cost'!$C$13)*Assumptions!$B$47/12*(1+Assumptions!$B$37)^(BJ6-1),"") -> 0
A22: Other admin overheads | B22: ₹ L | C22: =IFERROR(Assumptions!$B$48*(1+Assumptions!$B$37)^(C6-1),"") -> 0 | D22: =IFERROR(Assumptions!$B$48*(1+Assumptions!$B$37)^(D6-1),"") -> 0 | E22: =IFERROR(Assumptions!$B$48*(1+Assumptions!$B$37)^(E6-1),"") -> 0 | F22: =IFERROR(Assumptions!$B$48*(1+Assumptions!$B$37)^(F6-1),"") -> 0 | G22: =IFERROR(Assumptions!$B$48*(1+Assumptions!$B$37)^(G6-1),"") -> 0 | H22: =IFERROR(Assumptions!$B$48*(1+Assumptions!$B$37)^(H6-1),"") -> 0 | I22: =IFERROR(Assumptions!$B$48*(1+Assumptions!$B$37)^(I6-1),"") -> 0 | J22: =IFERROR(Assumptions!$B$48*(1+Assumptions!$B$37)^(J6-1),"") -> 0 | ... BJ22: =IFERROR(Assumptions!$B$48*(1+Assumptions!$B$37)^(BJ6-1),"") -> 0
A23: Selling & distribution | B23: ₹ L | C23: =IFERROR(C8*Assumptions!$B$49,"") -> 0 | D23: =IFERROR(D8*Assumptions!$B$49,"") -> 0 | E23: =IFERROR(E8*Assumptions!$B$49,"") -> 0 | F23: =IFERROR(F8*Assumptions!$B$49,"") -> 0 | G23: =IFERROR(G8*Assumptions!$B$49,"") -> 0 | H23: =IFERROR(H8*Assumptions!$B$49,"") -> 0 | I23: =IFERROR(I8*Assumptions!$B$49,"") -> 0 | J23: =IFERROR(J8*Assumptions!$B$49,"") -> 0 | ... BJ23: =IFERROR(BJ8*Assumptions!$B$49,"") -> 0
A24: Total fixed overheads | B24: ₹ L | C24: =IFERROR(SUM(C18:C23),"") -> 0 | D24: =IFERROR(SUM(D18:D23),"") -> 0 | E24: =IFERROR(SUM(E18:E23),"") -> 0 | F24: =IFERROR(SUM(F18:F23),"") -> 0 | G24: =IFERROR(SUM(G18:G23),"") -> 0 | H24: =IFERROR(SUM(H18:H23),"") -> 0 | I24: =IFERROR(SUM(I18:I23),"") -> 0 | J24: =IFERROR(SUM(J18:J23),"") -> 0 | ... BJ24: =IFERROR(SUM(BJ18:BJ23),"") -> 0
A25: D. PROFITABILITY
A26: EBITDA | B26: ₹ L | C26: =IFERROR(C15-C24,"") -> 0 | D26: =IFERROR(D15-D24,"") -> 0 | E26: =IFERROR(E15-E24,"") -> 0 | F26: =IFERROR(F15-F24,"") -> 0 | G26: =IFERROR(G15-G24,"") -> 0 | H26: =IFERROR(H15-H24,"") -> 0 | I26: =IFERROR(I15-I24,"") -> 0 | J26: =IFERROR(J15-J24,"") -> 0 | ... BJ26: =IFERROR(BJ15-BJ24,"") -> 0
A27: EBITDA margin | B27: % | C27: =IFERROR(IF(C8=0,0,C26/C8),"") -> 0 | D27: =IFERROR(IF(D8=0,0,D26/D8),"") -> 0 | E27: =IFERROR(IF(E8=0,0,E26/E8),"") -> 0 | F27: =IFERROR(IF(F8=0,0,F26/F8),"") -> 0 | G27: =IFERROR(IF(G8=0,0,G26/G8),"") -> 0 | H27: =IFERROR(IF(H8=0,0,H26/H8),"") -> 0 | I27: =IFERROR(IF(I8=0,0,I26/I8),"") -> 0 | J27: =IFERROR(IF(J8=0,0,J26/J8),"") -> 0 | ... BJ27: =IFERROR(IF(BJ8=0,0,BJ26/BJ8),"") -> 0
A28: Depreciation & amortisation | B28: ₹ L | C28: =IFERROR(Depreciation!$E$11/12,"") -> 0 | D28: =IFERROR(Depreciation!$E$11/12,"") -> 0 | E28: =IFERROR(Depreciation!$E$11/12,"") -> 0 | F28: =IFERROR(Depreciation!$E$11/12,"") -> 0 | G28: =IFERROR(Depreciation!$E$11/12,"") -> 0 | H28: =IFERROR(Depreciation!$E$11/12,"") -> 0 | I28: =IFERROR(Depreciation!$E$11/12,"") -> 0 | J28: =IFERROR(Depreciation!$E$11/12,"") -> 0 | ... N28: =IFERROR(Depreciation!$E$11/12,"") -> 0 | O28: =IFERROR(Depreciation!$H$11/12,"") -> 0 | P28: =IFERROR(Depreciation!$H$11/12,"") -> 0 | Q28: =IFERROR(Depreciation!$H$11/12,"") -> 0 | R28: =IFERROR(Depreciation!$H$11/12,"") -> 0 | S28: =IFERROR(Depreciation!$H$11/12,"") -> 0 | T28: =IFERROR(Depreciation!$H$11/12,"") -> 0 | U28: =IFERROR(Depreciation!$H$11/12,"") -> 0 | V28: =IFERROR(Depreciation!$H$11/12,"") -> 0 | ... Z28: =IFERROR(Depreciation!$H$11/12,"") -> 0 | AA28: =IFERROR(Depreciation!$K$11/12,"") -> 0 | AB28: =IFERROR(Depreciation!$K$11/12,"") -> 0 | AC28: =IFERROR(Depreciation!$K$11/12,"") -> 0 | AD28: =IFERROR(Depreciation!$K$11/12,"") -> 0 | AE28: =IFERROR(Depreciation!$K$11/12,"") -> 0 | AF28: =IFERROR(Depreciation!$K$11/12,"") -> 0 | AG28: =IFERROR(Depreciation!$K$11/12,"") -> 0 | AH28: =IFERROR(Depreciation!$K$11/12,"") -> 0 | ... AL28: =IFERROR(Depreciation!$K$11/12,"") -> 0 | AM28: =IFERROR(Depreciation!$N$11/12,"") -> 0 | AN28: =IFERROR(Depreciation!$N$11/12,"") -> 0 | AO28: =IFERROR(Depreciation!$N$11/12,"") -> 0 | AP28: =IFERROR(Depreciation!$N$11/12,"") -> 0 | AQ28: =IFERROR(Depreciation!$N$11/12,"") -> 0 | AR28: =IFERROR(Depreciation!$N$11/12,"") -> 0 | AS28: =IFERROR(Depreciation!$N$11/12,"") -> 0 | AT28: =IFERROR(Depreciation!$N$11/12,"") -> 0 | ... AX28: =IFERROR(Depreciation!$N$11/12,"") -> 0 | AY28: =IFERROR(Depreciation!$Q$11/12,"") -> 0 | AZ28: =IFERROR(Depreciation!$Q$11/12,"") -> 0 | BA28: =IFERROR(Depreciation!$Q$11/12,"") -> 0 | BB28: =IFERROR(Depreciation!$Q$11/12,"") -> 0 | BC28: =IFERROR(Depreciation!$Q$11/12,"") -> 0 | BD28: =IFERROR(Depreciation!$Q$11/12,"") -> 0 | BE28: =IFERROR(Depreciation!$Q$11/12,"") -> 0 | BF28: =IFERROR(Depreciation!$Q$11/12,"") -> 0 | ... BJ28: =IFERROR(Depreciation!$Q$11/12,"") -> 0
A29: EBIT | B29: ₹ L | C29: =IFERROR(C26-C28,"") -> 0 | D29: =IFERROR(D26-D28,"") -> 0 | E29: =IFERROR(E26-E28,"") -> 0 | F29: =IFERROR(F26-F28,"") -> 0 | G29: =IFERROR(G26-G28,"") -> 0 | H29: =IFERROR(H26-H28,"") -> 0 | I29: =IFERROR(I26-I28,"") -> 0 | J29: =IFERROR(J26-J28,"") -> 0 | ... BJ29: =IFERROR(BJ26-BJ28,"") -> 0
A30: Interest on term loan | B30: ₹ L | C30: =IFERROR('Term Loan'!C10,"") -> 0 | D30: =IFERROR('Term Loan'!D10,"") -> 0 | E30: =IFERROR('Term Loan'!E10,"") -> 0 | F30: =IFERROR('Term Loan'!F10,"") -> 0 | G30: =IFERROR('Term Loan'!G10,"") -> 0 | H30: =IFERROR('Term Loan'!H10,"") -> 0 | I30: =IFERROR('Term Loan'!I10,"") -> 0 | J30: =IFERROR('Term Loan'!J10,"") -> 0 | ... BJ30: =IFERROR('Term Loan'!BJ10,"") -> 0
A31: Interest on working capital | B31: ₹ L | C31: =IFERROR('Working Capital'!$C$27/12,"") -> 0 | D31: =IFERROR('Working Capital'!$C$27/12,"") -> 0 | E31: =IFERROR('Working Capital'!$C$27/12,"") -> 0 | F31: =IFERROR('Working Capital'!$C$27/12,"") -> 0 | G31: =IFERROR('Working Capital'!$C$27/12,"") -> 0 | H31: =IFERROR('Working Capital'!$C$27/12,"") -> 0 | I31: =IFERROR('Working Capital'!$C$27/12,"") -> 0 | J31: =IFERROR('Working Capital'!$C$27/12,"") -> 0 | ... N31: =IFERROR('Working Capital'!$C$27/12,"") -> 0 | O31: =IFERROR('Working Capital'!$D$27/12,"") -> 0 | P31: =IFERROR('Working Capital'!$D$27/12,"") -> 0 | Q31: =IFERROR('Working Capital'!$D$27/12,"") -> 0 | R31: =IFERROR('Working Capital'!$D$27/12,"") -> 0 | S31: =IFERROR('Working Capital'!$D$27/12,"") -> 0 | T31: =IFERROR('Working Capital'!$D$27/12,"") -> 0 | U31: =IFERROR('Working Capital'!$D$27/12,"") -> 0 | V31: =IFERROR('Working Capital'!$D$27/12,"") -> 0 | ... Z31: =IFERROR('Working Capital'!$D$27/12,"") -> 0 | AA31: =IFERROR('Working Capital'!$E$27/12,"") -> 0 | AB31: =IFERROR('Working Capital'!$E$27/12,"") -> 0 | AC31: =IFERROR('Working Capital'!$E$27/12,"") -> 0 | AD31: =IFERROR('Working Capital'!$E$27/12,"") -> 0 | AE31: =IFERROR('Working Capital'!$E$27/12,"") -> 0 | AF31: =IFERROR('Working Capital'!$E$27/12,"") -> 0 | AG31: =IFERROR('Working Capital'!$E$27/12,"") -> 0 | AH31: =IFERROR('Working Capital'!$E$27/12,"") -> 0 | ... AL31: =IFERROR('Working Capital'!$E$27/12,"") -> 0 | AM31: =IFERROR('Working Capital'!$F$27/12,"") -> 0 | AN31: =IFERROR('Working Capital'!$F$27/12,"") -> 0 | AO31: =IFERROR('Working Capital'!$F$27/12,"") -> 0 | AP31: =IFERROR('Working Capital'!$F$27/12,"") -> 0 | AQ31: =IFERROR('Working Capital'!$F$27/12,"") -> 0 | AR31: =IFERROR('Working Capital'!$F$27/12,"") -> 0 | AS31: =IFERROR('Working Capital'!$F$27/12,"") -> 0 | AT31: =IFERROR('Working Capital'!$F$27/12,"") -> 0 | ... AX31: =IFERROR('Working Capital'!$F$27/12,"") -> 0 | AY31: =IFERROR('Working Capital'!$G$27/12,"") -> 0 | AZ31: =IFERROR('Working Capital'!$G$27/12,"") -> 0 | BA31: =IFERROR('Working Capital'!$G$27/12,"") -> 0 | BB31: =IFERROR('Working Capital'!$G$27/12,"") -> 0 | BC31: =IFERROR('Working Capital'!$G$27/12,"") -> 0 | BD31: =IFERROR('Working Capital'!$G$27/12,"") -> 0 | BE31: =IFERROR('Working Capital'!$G$27/12,"") -> 0 | BF31: =IFERROR('Working Capital'!$G$27/12,"") -> 0 | ... BJ31: =IFERROR('Working Capital'!$G$27/12,"") -> 0
A32: Total interest | B32: ₹ L | C32: =IFERROR(C30+C31,"") -> 0 | D32: =IFERROR(D30+D31,"") -> 0 | E32: =IFERROR(E30+E31,"") -> 0 | F32: =IFERROR(F30+F31,"") -> 0 | G32: =IFERROR(G30+G31,"") -> 0 | H32: =IFERROR(H30+H31,"") -> 0 | I32: =IFERROR(I30+I31,"") -> 0 | J32: =IFERROR(J30+J31,"") -> 0 | ... BJ32: =IFERROR(BJ30+BJ31,"") -> 0
A33: Profit before tax (PBT) | B33: ₹ L | C33: =IFERROR(C29-C32,"") -> 0 | D33: =IFERROR(D29-D32,"") -> 0 | E33: =IFERROR(E29-E32,"") -> 0 | F33: =IFERROR(F29-F32,"") -> 0 | G33: =IFERROR(G29-G32,"") -> 0 | H33: =IFERROR(H29-H32,"") -> 0 | I33: =IFERROR(I29-I32,"") -> 0 | J33: =IFERROR(J29-J32,"") -> 0 | ... BJ33: =IFERROR(BJ29-BJ32,"") -> 0
A34: Provision for tax | B34: ₹ L | C34: =IFERROR(MAX(0,C33)*Assumptions!$B$70,"") -> 0 | D34: =IFERROR(MAX(0,D33)*Assumptions!$B$70,"") -> 0 | E34: =IFERROR(MAX(0,E33)*Assumptions!$B$70,"") -> 0 | F34: =IFERROR(MAX(0,F33)*Assumptions!$B$70,"") -> 0 | G34: =IFERROR(MAX(0,G33)*Assumptions!$B$70,"") -> 0 | H34: =IFERROR(MAX(0,H33)*Assumptions!$B$70,"") -> 0 | I34: =IFERROR(MAX(0,I33)*Assumptions!$B$70,"") -> 0 | J34: =IFERROR(MAX(0,J33)*Assumptions!$B$70,"") -> 0 | ... BJ34: =IFERROR(MAX(0,BJ33)*Assumptions!$B$70,"") -> 0
A35: PROFIT AFTER TAX (PAT) | B35: ₹ L | C35: =IFERROR(C33-C34,"") -> 0 | D35: =IFERROR(D33-D34,"") -> 0 | E35: =IFERROR(E33-E34,"") -> 0 | F35: =IFERROR(F33-F34,"") -> 0 | G35: =IFERROR(G33-G34,"") -> 0 | H35: =IFERROR(H33-H34,"") -> 0 | I35: =IFERROR(I33-I34,"") -> 0 | J35: =IFERROR(J33-J34,"") -> 0 | ... BJ35: =IFERROR(BJ33-BJ34,"") -> 0
A36: PAT margin | B36: % | C36: =IFERROR(IF(C8=0,0,C35/C8),"") -> 0 | D36: =IFERROR(IF(D8=0,0,D35/D8),"") -> 0 | E36: =IFERROR(IF(E8=0,0,E35/E8),"") -> 0 | F36: =IFERROR(IF(F8=0,0,F35/F8),"") -> 0 | G36: =IFERROR(IF(G8=0,0,G35/G8),"") -> 0 | H36: =IFERROR(IF(H8=0,0,H35/H8),"") -> 0 | I36: =IFERROR(IF(I8=0,0,I35/I8),"") -> 0 | J36: =IFERROR(IF(J8=0,0,J35/J8),"") -> 0 | ... BJ36: =IFERROR(IF(BJ8=0,0,BJ35/BJ8),"") -> 0
A37: Cumulative PAT | B37: ₹ L | C37: =IFERROR(C35,"") -> 0 | D37: =IFERROR(C37+D35,"") -> 0 | E37: =IFERROR(D37+E35,"") -> 0 | F37: =IFERROR(E37+F35,"") -> 0 | G37: =IFERROR(F37+G35,"") -> 0 | H37: =IFERROR(G37+H35,"") -> 0 | I37: =IFERROR(H37+I35,"") -> 0 | J37: =IFERROR(I37+J35,"") -> 0 | K37: =IFERROR(J37+K35,"") -> 0 | ... BJ37: =IFERROR(BI37+BJ35,"") -> 0

Sheet Profitability (Annual)
A1: OPERATING STATEMENT — PROJECTED PROFITABILITY (5 YEARS) — ₹ Lakh [CMA Form II]
A2: Annual totals rolled up from the monthly Profitability statement. Margins recomputed on annual aggregates.
A4: Particulars | B4: Unit | C4: ="Year 1"&CHAR(10)&"FY"&RIGHT((IF(ISNUMBER(Assumptions!$B$6),Assumptions!$B$6,2026)+0+1),2) -> Year 1 FY27 | D4: ="Year 2"&CHAR(10)&"FY"&RIGHT((IF(ISNUMBER(Assumptions!$B$6),Assumptions!$B$6,2026)+1+1),2) -> Year 2 FY28 | E4: ="Year 3"&CHAR(10)&"FY"&RIGHT((IF(ISNUMBER(Assumptions!$B$6),Assumptions!$B$6,2026)+2+1),2) -> Year 3 FY29 | F4: ="Year 4"&CHAR(10)&"FY"&RIGHT((IF(ISNUMBER(Assumptions!$B$6),Assumptions!$B$6,2026)+3+1),2) -> Year 4 FY30 | G4: ="Year 5"&CHAR(10)&"FY"&RIGHT((IF(ISNUMBER(Assumptions!$B$6),Assumptions!$B$6,2026)+4+1),2) -> Year 5 FY31
A5: A. CAPACITY & VOLUME
A6: Average capacity utilisation | B6: % | C6: =IFERROR(AVERAGE('Production & Sales'!C9:N9)/Assumptions!$B$5,"") | D6: =IFERROR(AVERAGE('Production & Sales'!O9:Z9)/Assumptions!$B$5,"") | E6: =IFERROR(AVERAGE('Production & Sales'!AA9:AL9)/Assumptions!$B$5,"") | F6: =IFERROR(AVERAGE('Production & Sales'!AM9:AX9)/Assumptions!$B$5,"") | G6: =IFERROR(AVERAGE('Production & Sales'!AY9:BJ9)/Assumptions!$B$5,"")
A7: Output / sales volume | B7: =IFERROR(INDEX('Industry Labels'!$C$7:$Z$7,MATCH(Assumptions!$B$3,'Industry Labels'!$C$4:$Z$4,0)),"units") -> units | C7: =IFERROR(SUM('Production & Sales'!C9:N9),"") -> 0 | D7: =IFERROR(SUM('Production & Sales'!O9:Z9),"") -> 0 | E7: =IFERROR(SUM('Production & Sales'!AA9:AL9),"") -> 0 | F7: =IFERROR(SUM('Production & Sales'!AM9:AX9),"") -> 0 | G7: =IFERROR(SUM('Production & Sales'!AY9:BJ9),"") -> 0
A8: B. REVENUE
A9: Net Sales (net of GST) | B9: ₹ L | C9: =IFERROR(SUM('Profitability (Monthly)'!C8:N8),"") -> 0 | D9: =IFERROR(SUM('Profitability (Monthly)'!O8:Z8),"") -> 0 | E9: =IFERROR(SUM('Profitability (Monthly)'!AA8:AL8),"") -> 0 | F9: =IFERROR(SUM('Profitability (Monthly)'!AM8:AX8),"") -> 0 | G9: =IFERROR(SUM('Profitability (Monthly)'!AY8:BJ8),"") -> 0
A10: C. COST OF SALES – VARIABLE
A11: =IFERROR(INDEX('Industry Labels'!$C$21:$Z$21,MATCH(Assumptions!$B$3,'Industry Labels'!$C$4:$Z$4,0)),"Direct cost consumed") -> Direct cost consumed | B11: ₹ L | C11: =IFERROR(SUM('Profitability (Monthly)'!C10:N10),"") -> 0 | D11: =IFERROR(SUM('Profitability (Monthly)'!O10:Z10),"") -> 0 | E11: =IFERROR(SUM('Profitability (Monthly)'!AA10:AL10),"") -> 0 | F11: =IFERROR(SUM('Profitability (Monthly)'!AM10:AX10),"") -> 0 | G11: =IFERROR(SUM('Profitability (Monthly)'!AY10:BJ10),"") -> 0
A12: =IFERROR(INDEX('Industry Labels'!$C$22:$Z$22,MATCH(Assumptions!$B$3,'Industry Labels'!$C$4:$Z$4,0)),"Utilities & energy")&" (variable)" -> Utilities & energy (variable) | B12: ₹ L | C12: =IFERROR(SUM('Profitability (Monthly)'!C11:N11),"") -> 0 | D12: =IFERROR(SUM('Profitability (Monthly)'!O11:Z11),"") -> 0 | E12: =IFERROR(SUM('Profitability (Monthly)'!AA11:AL11),"") -> 0 | F12: =IFERROR(SUM('Profitability (Monthly)'!AM11:AX11),"") -> 0 | G12: =IFERROR(SUM('Profitability (Monthly)'!AY11:BJ11),"") -> 0
A13: =IFERROR(INDEX('Industry Labels'!$C$23:$Z$23,MATCH(Assumptions!$B$3,'Industry Labels'!$C$4:$Z$4,0)),"Consumables, supplies & packing") -> Consumables, supplies & packing | B13: ₹ L | C13: =IFERROR(SUM('Profitability (Monthly)'!C12:N12),"") -> 0 | D13: =IFERROR(SUM('Profitability (Monthly)'!O12:Z12),"") -> 0 | E13: =IFERROR(SUM('Profitability (Monthly)'!AA12:AL12),"") -> 0 | F13: =IFERROR(SUM('Profitability (Monthly)'!AM12:AX12),"") -> 0 | G13: =IFERROR(SUM('Profitability (Monthly)'!AY12:BJ12),"") -> 0
A14: Direct labour | B14: ₹ L | C14: =IFERROR(SUM('Profitability (Monthly)'!C13:N13),"") -> 0 | D14: =IFERROR(SUM('Profitability (Monthly)'!O13:Z13),"") -> 0 | E14: =IFERROR(SUM('Profitability (Monthly)'!AA13:AL13),"") -> 0 | F14: =IFERROR(SUM('Profitability (Monthly)'!AM13:AX13),"") -> 0 | G14: =IFERROR(SUM('Profitability (Monthly)'!AY13:BJ13),"") -> 0
A15: Total variable cost | B15: ₹ L | C15: =IFERROR(SUM('Profitability (Monthly)'!C14:N14),"") -> 0 | D15: =IFERROR(SUM('Profitability (Monthly)'!O14:Z14),"") -> 0 | E15: =IFERROR(SUM('Profitability (Monthly)'!AA14:AL14),"") -> 0 | F15: =IFERROR(SUM('Profitability (Monthly)'!AM14:AX14),"") -> 0 | G15: =IFERROR(SUM('Profitability (Monthly)'!AY14:BJ14),"") -> 0
A16: Contribution | B16: ₹ L | C16: =IFERROR(SUM('Profitability (Monthly)'!C15:N15),"") -> 0 | D16: =IFERROR(SUM('Profitability (Monthly)'!O15:Z15),"") -> 0 | E16: =IFERROR(SUM('Profitability (Monthly)'!AA15:AL15),"") -> 0 | F16: =IFERROR(SUM('Profitability (Monthly)'!AM15:AX15),"") -> 0 | G16: =IFERROR(SUM('Profitability (Monthly)'!AY15:BJ15),"") -> 0
A17: Contribution margin | B17: % | C17: =IFERROR(IF(C9=0,0,C16/C9),"") -> 0 | D17: =IFERROR(IF(D9=0,0,D16/D9),"") -> 0 | E17: =IFERROR(IF(E9=0,0,E16/E9),"") -> 0 | F17: =IFERROR(IF(F9=0,0,F16/F9),"") -> 0 | G17: =IFERROR(IF(G9=0,0,G16/G9),"") -> 0
A18: D. FIXED & OVERHEAD COST
A19: Admin & management salaries | B19: ₹ L | C19: =IFERROR(SUM('Profitability (Monthly)'!C18:N18),"") -> 0 | D19: =IFERROR(SUM('Profitability (Monthly)'!O18:Z18),"") -> 0 | E19: =IFERROR(SUM('Profitability (Monthly)'!AA18:AL18),"") -> 0 | F19: =IFERROR(SUM('Profitability (Monthly)'!AM18:AX18),"") -> 0 | G19: =IFERROR(SUM('Profitability (Monthly)'!AY18:BJ18),"") -> 0
A20: =IFERROR(INDEX('Industry Labels'!$C$24:$Z$24,MATCH(Assumptions!$B$3,'Industry Labels'!$C$4:$Z$4,0)),"Fixed utility / facility charges") -> Fixed utility / facility charges | B20: ₹ L | C20: =IFERROR(SUM('Profitability (Monthly)'!C19:N19),"") -> 0 | D20: =IFERROR(SUM('Profitability (Monthly)'!O19:Z19),"") -> 0 | E20: =IFERROR(SUM('Profitability (Monthly)'!AA19:AL19),"") -> 0 | F20: =IFERROR(SUM('Profitability (Monthly)'!AM19:AX19),"") -> 0 | G20: =IFERROR(SUM('Profitability (Monthly)'!AY19:BJ19),"") -> 0
A21: Repairs & maintenance | B21: ₹ L | C21: =IFERROR(SUM('Profitability (Monthly)'!C20:N20),"") -> 0 | D21: =IFERROR(SUM('Profitability (Monthly)'!O20:Z20),"") -> 0 | E21: =IFERROR(SUM('Profitability (Monthly)'!AA20:AL20),"") -> 0 | F21: =IFERROR(SUM('Profitability (Monthly)'!AM20:AX20),"") -> 0 | G21: =IFERROR(SUM('Profitability (Monthly)'!AY20:BJ20),"") -> 0
A22: Insurance | B22: ₹ L | C22: =IFERROR(SUM('Profitability (Monthly)'!C21:N21),"") -> 0 | D22: =IFERROR(SUM('Profitability (Monthly)'!O21:Z21),"") -> 0 | E22: =IFERROR(SUM('Profitability (Monthly)'!AA21:AL21),"") -> 0 | F22: =IFERROR(SUM('Profitability (Monthly)'!AM21:AX21),"") -> 0 | G22: =IFERROR(SUM('Profitability (Monthly)'!AY21:BJ21),"") -> 0
A23: Other admin overheads | B23: ₹ L | C23: =IFERROR(SUM('Profitability (Monthly)'!C22:N22),"") -> 0 | D23: =IFERROR(SUM('Profitability (Monthly)'!O22:Z22),"") -> 0 | E23: =IFERROR(SUM('Profitability (Monthly)'!AA22:AL22),"") -> 0 | F23: =IFERROR(SUM('Profitability (Monthly)'!AM22:AX22),"") -> 0 | G23: =IFERROR(SUM('Profitability (Monthly)'!AY22:BJ22),"") -> 0
A24: Selling & distribution | B24: ₹ L | C24: =IFERROR(SUM('Profitability (Monthly)'!C23:N23),"") -> 0 | D24: =IFERROR(SUM('Profitability (Monthly)'!O23:Z23),"") -> 0 | E24: =IFERROR(SUM('Profitability (Monthly)'!AA23:AL23),"") -> 0 | F24: =IFERROR(SUM('Profitability (Monthly)'!AM23:AX23),"") -> 0 | G24: =IFERROR(SUM('Profitability (Monthly)'!AY23:BJ23),"") -> 0
A25: Total fixed overheads | B25: ₹ L | C25: =IFERROR(SUM('Profitability (Monthly)'!C24:N24),"") -> 0 | D25: =IFERROR(SUM('Profitability (Monthly)'!O24:Z24),"") -> 0 | E25: =IFERROR(SUM('Profitability (Monthly)'!AA24:AL24),"") -> 0 | F25: =IFERROR(SUM('Profitability (Monthly)'!AM24:AX24),"") -> 0 | G25: =IFERROR(SUM('Profitability (Monthly)'!AY24:BJ24),"") -> 0
A26: E. PROFITABILITY
A27: EBITDA (Operating profit) | B27: ₹ L | C27: =IFERROR(SUM('Profitability (Monthly)'!C26:N26),"") -> 0 | D27: =IFERROR(SUM('Profitability (Monthly)'!O26:Z26),"") -> 0 | E27: =IFERROR(SUM('Profitability (Monthly)'!AA26:AL26),"") -> 0 | F27: =IFERROR(SUM('Profitability (Monthly)'!AM26:AX26),"") -> 0 | G27: =IFERROR(SUM('Profitability (Monthly)'!AY26:BJ26),"") -> 0
A28: EBITDA margin | B28: % | C28: =IFERROR(IF(C9=0,0,C27/C9),"") -> 0 | D28: =IFERROR(IF(D9=0,0,D27/D9),"") -> 0 | E28: =IFERROR(IF(E9=0,0,E27/E9),"") -> 0 | F28: =IFERROR(IF(F9=0,0,F27/F9),"") -> 0 | G28: =IFERROR(IF(G9=0,0,G27/G9),"") -> 0
A29: Depreciation & amortisation | B29: ₹ L | C29: =IFERROR(SUM('Profitability (Monthly)'!C28:N28),"") -> 0 | D29: =IFERROR(SUM('Profitability (Monthly)'!O28:Z28),"") -> 0 | E29: =IFERROR(SUM('Profitability (Monthly)'!AA28:AL28),"") -> 0 | F29: =IFERROR(SUM('Profitability (Monthly)'!AM28:AX28),"") -> 0 | G29: =IFERROR(SUM('Profitability (Monthly)'!AY28:BJ28),"") -> 0
A30: EBIT | B30: ₹ L | C30: =IFERROR(SUM('Profitability (Monthly)'!C29:N29),"") -> 0 | D30: =IFERROR(SUM('Profitability (Monthly)'!O29:Z29),"") -> 0 | E30: =IFERROR(SUM('Profitability (Monthly)'!AA29:AL29),"") -> 0 | F30: =IFERROR(SUM('Profitability (Monthly)'!AM29:AX29),"") -> 0 | G30: =IFERROR(SUM('Profitability (Monthly)'!AY29:BJ29),"") -> 0
A31: Interest on term loan | B31: ₹ L | C31: =IFERROR(SUM('Profitability (Monthly)'!C30:N30),"") -> 0 | D31: =IFERROR(SUM('Profitability (Monthly)'!O30:Z30),"") -> 0 | E31: =IFERROR(SUM('Profitability (Monthly)'!AA30:AL30),"") -> 0 | F31: =IFERROR(SUM('Profitability (Monthly)'!AM30:AX30),"") -> 0 | G31: =IFERROR(SUM('Profitability (Monthly)'!AY30:BJ30),"") -> 0
A32: Interest on working capital | B32: ₹ L | C32: =IFERROR(SUM('Profitability (Monthly)'!C31:N31),"") -> 0 | D32: =IFERROR(SUM('Profitability (Monthly)'!O31:Z31),"") -> 0 | E32: =IFERROR(SUM('Profitability (Monthly)'!AA31:AL31),"") -> 0 | F32: =IFERROR(SUM('Profitability (Monthly)'!AM31:AX31),"") -> 0 | G32: =IFERROR(SUM('Profitability (Monthly)'!AY31:BJ31),"") -> 0
A33: Total interest & finance cost | B33: ₹ L | C33: =IFERROR(C31+C32,"") -> 0 | D33: =IFERROR(D31+D32,"") -> 0 | E33: =IFERROR(E31+E32,"") -> 0 | F33: =IFERROR(F31+F32,"") -> 0 | G33: =IFERROR(G31+G32,"") -> 0
A34: Profit before tax (PBT) | B34: ₹ L | C34: =IFERROR(SUM('Profitability (Monthly)'!C33:N33),"") -> 0 | D34: =IFERROR(SUM('Profitability (Monthly)'!O33:Z33),"") -> 0 | E34: =IFERROR(SUM('Profitability (Monthly)'!AA33:AL33),"") -> 0 | F34: =IFERROR(SUM('Profitability (Monthly)'!AM33:AX33),"") -> 0 | G34: =IFERROR(SUM('Profitability (Monthly)'!AY33:BJ33),"") -> 0
A35: Provision for tax | B35: ₹ L | C35: =IFERROR(SUM('Profitability (Monthly)'!C34:N34),"") -> 0 | D35: =IFERROR(SUM('Profitability (Monthly)'!O34:Z34),"") -> 0 | E35: =IFERROR(SUM('Profitability (Monthly)'!AA34:AL34),"") -> 0 | F35: =IFERROR(SUM('Profitability (Monthly)'!AM34:AX34),"") -> 0 | G35: =IFERROR(SUM('Profitability (Monthly)'!AY34:BJ34),"") -> 0
A36: PROFIT AFTER TAX (PAT) | B36: ₹ L | C36: =IFERROR(SUM('Profitability (Monthly)'!C35:N35),"") -> 0 | D36: =IFERROR(SUM('Profitability (Monthly)'!O35:Z35),"") -> 0 | E36: =IFERROR(SUM('Profitability (Monthly)'!AA35:AL35),"") -> 0 | F36: =IFERROR(SUM('Profitability (Monthly)'!AM35:AX35),"") -> 0 | G36: =IFERROR(SUM('Profitability (Monthly)'!AY35:BJ35),"") -> 0
A37: PAT margin | B37: % | C37: =IFERROR(IF(C9=0,0,C36/C9),"") -> 0 | D37: =IFERROR(IF(D9=0,0,D36/D9),"") -> 0 | E37: =IFERROR(IF(E9=0,0,E36/E9),"") -> 0 | F37: =IFERROR(IF(F9=0,0,F36/F9),"") -> 0 | G37: =IFERROR(IF(G9=0,0,G36/G9),"") -> 0
A38: Cash accruals (PAT + Depreciation) | B38: ₹ L | C38: =IFERROR(C36+C29,"") -> 0 | D38: =IFERROR(D36+D29,"") -> 0 | E38: =IFERROR(E36+E29,"") -> 0 | F38: =IFERROR(F36+F29,"") -> 0 | G38: =IFERROR(G36+G29,"") -> 0

Sheet Working Capital
A1: WORKING CAPITAL ASSESSMENT & MPBF (Tandon 2nd method) — ₹ Lakh
A2: Holding norms & margins from 'Assumptions'. Assessed bank finance (cash credit) drives WC interest in the P&L.
A4: Particulars | B4: Norm | C4: ="Yr1 FY"&RIGHT((IF(ISNUMBER(Assumptions!$B$6),Assumptions!$B$6,2026)+0+1),2) -> Yr1 FY27 | D4: ="Yr2 FY"&RIGHT((IF(ISNUMBER(Assumptions!$B$6),Assumptions!$B$6,2026)+1+1),2) -> Yr2 FY28 | E4: ="Yr3 FY"&RIGHT((IF(ISNUMBER(Assumptions!$B$6),Assumptions!$B$6,2026)+2+1),2) -> Yr3 FY29 | F4: ="Yr4 FY"&RIGHT((IF(ISNUMBER(Assumptions!$B$6),Assumptions!$B$6,2026)+3+1),2) -> Yr4 FY30 | G4: ="Yr5 FY"&RIGHT((IF(ISNUMBER(Assumptions!$B$6),Assumptions!$B$6,2026)+4+1),2) -> Yr5 FY31
A5: A. OPERATING BASE
A6: Net sales | B6: ₹ L | C6: =IFERROR(SUM('Production & Sales'!C12:N12),"") -> 0 | D6: =IFERROR(SUM('Production & Sales'!O12:Z12),"") -> 0 | E6: =IFERROR(SUM('Production & Sales'!AA12:AL12),"") -> 0 | F6: =IFERROR(SUM('Production & Sales'!AM12:AX12),"") -> 0 | G6: =IFERROR(SUM('Production & Sales'!AY12:BJ12),"") -> 0
A7: Output / sales volume | B7: =IFERROR(INDEX('Industry Labels'!$C$7:$Z$7,MATCH(Assumptions!$B$3,'Industry Labels'!$C$4:$Z$4,0)),"units") -> units | C7: =IFERROR(SUM('Production & Sales'!C9:N9),"") -> 0 | D7: =IFERROR(SUM('Production & Sales'!O9:Z9),"") -> 0 | E7: =IFERROR(SUM('Production & Sales'!AA9:AL9),"") -> 0 | F7: =IFERROR(SUM('Production & Sales'!AM9:AX9),"") -> 0 | G7: =IFERROR(SUM('Production & Sales'!AY9:BJ9),"") -> 0
A8: =IFERROR(INDEX('Industry Labels'!$C$21:$Z$21,MATCH(Assumptions!$B$3,'Industry Labels'!$C$4:$Z$4,0)),"Direct cost consumed") -> Direct cost consumed | B8: ₹ L | C8: =IFERROR(C7*Assumptions!$B$11*(1+Assumptions!$B$34)^(1-1)/100000,"") -> 0 | D8: =IFERROR(D7*Assumptions!$B$11*(1+Assumptions!$B$34)^(2-1)/100000,"") -> 0 | E8: =IFERROR(E7*Assumptions!$B$11*(1+Assumptions!$B$34)^(3-1)/100000,"") -> 0 | F8: =IFERROR(F7*Assumptions!$B$11*(1+Assumptions!$B$34)^(4-1)/100000,"") -> 0 | G8: =IFERROR(G7*Assumptions!$B$11*(1+Assumptions!$B$34)^(5-1)/100000,"") -> 0
A9: =IFERROR(INDEX('Industry Labels'!$C$22:$Z$22,MATCH(Assumptions!$B$3,'Industry Labels'!$C$4:$Z$4,0)),"Utilities & energy")&" (variable)" -> Utilities & energy (variable) | B9: ₹ L | C9: =IFERROR(C7*Assumptions!$B$39*(1+Assumptions!$B$35)^(1-1)/100000,"") -> 0 | D9: =IFERROR(D7*Assumptions!$B$39*(1+Assumptions!$B$35)^(2-1)/100000,"") -> 0 | E9: =IFERROR(E7*Assumptions!$B$39*(1+Assumptions!$B$35)^(3-1)/100000,"") -> 0 | F9: =IFERROR(F7*Assumptions!$B$39*(1+Assumptions!$B$35)^(4-1)/100000,"") -> 0 | G9: =IFERROR(G7*Assumptions!$B$39*(1+Assumptions!$B$35)^(5-1)/100000,"") -> 0
A10: =IFERROR(INDEX('Industry Labels'!$C$23:$Z$23,MATCH(Assumptions!$B$3,'Industry Labels'!$C$4:$Z$4,0)),"Consumables, supplies & packing") -> Consumables, supplies & packing | B10: ₹ L | C10: =IFERROR(C7*(Assumptions!$B$40+Assumptions!$B$41)*(1+Assumptions!$B$37)^(1-1)/100000,"") -> 0 | D10: =IFERROR(D7*(Assumptions!$B$40+Assumptions!$B$41)*(1+Assumptions!$B$37)^(2-1)/100000,"") -> 0 | E10: =IFERROR(E7*(Assumptions!$B$40+Assumptions!$B$41)*(1+Assumptions!$B$37)^(3-1)/100000,"") -> 0 | F10: =IFERROR(F7*(Assumptions!$B$40+Assumptions!$B$41)*(1+Assumptions!$B$37)^(4-1)/100000,"") -> 0 | G10: =IFERROR(G7*(Assumptions!$B$40+Assumptions!$B$41)*(1+Assumptions!$B$37)^(5-1)/100000,"") -> 0
A11: Direct labour | B11: ₹ L | C11: =IFERROR(Assumptions!$B$42*12*(1+Assumptions!$B$36)^(1-1),"") -> 0 | D11: =IFERROR(Assumptions!$B$42*12*(1+Assumptions!$B$36)^(2-1),"") -> 0 | E11: =IFERROR(Assumptions!$B$42*12*(1+Assumptions!$B$36)^(3-1),"") -> 0 | F11: =IFERROR(Assumptions!$B$42*12*(1+Assumptions!$B$36)^(4-1),"") -> 0 | G11: =IFERROR(Assumptions!$B$42*12*(1+Assumptions!$B$36)^(5-1),"") -> 0
A12: Facility fixed (R&M + fixed utilities + insurance) | B12: ₹ L | C12: =IFERROR((('Project Cost'!$C$7+'Project Cost'!$C$11)*Assumptions!$B$46+Assumptions!$B$45*12+('Project Cost'!$C$14-'Project Cost'!$C$5-'Project Cost'!$C$13)*Assumptions!$B$47)*(1+Assumptions!$B$37)^(1-1),"") -> 0 | D12: =IFERROR((('Project Cost'!$C$7+'Project Cost'!$C$11)*Assumptions!$B$46+Assumptions!$B$45*12+('Project Cost'!$C$14-'Project Cost'!$C$5-'Project Cost'!$C$13)*Assumptions!$B$47)*(1+Assumptions!$B$37)^(2-1),"") -> 0 | E12: =IFERROR((('Project Cost'!$C$7+'Project Cost'!$C$11)*Assumptions!$B$46+Assumptions!$B$45*12+('Project Cost'!$C$14-'Project Cost'!$C$5-'Project Cost'!$C$13)*Assumptions!$B$47)*(1+Assumptions!$B$37)^(3-1),"") -> 0 | F12: =IFERROR((('Project Cost'!$C$7+'Project Cost'!$C$11)*Assumptions!$B$46+Assumptions!$B$45*12+('Project Cost'!$C$14-'Project Cost'!$C$5-'Project Cost'!$C$13)*Assumptions!$B$47)*(1+Assumptions!$B$37)^(4-1),"") -> 0 | G12: =IFERROR((('Project Cost'!$C$7+'Project Cost'!$C$11)*Assumptions!$B$46+Assumptions!$B$45*12+('Project Cost'!$C$14-'Project Cost'!$C$5-'Project Cost'!$C$13)*Assumptions!$B$47)*(1+Assumptions!$B$37)^(5-1),"") -> 0
A13: =IFERROR(INDEX('Industry Labels'!$C$25:$Z$25,MATCH(Assumptions!$B$3,'Industry Labels'!$C$4:$Z$4,0)),"COST OF OPERATIONS") -> COST OF OPERATIONS | B13: ₹ L | C13: =IFERROR(SUM(C8:C12),"") -> 0 | D13: =IFERROR(SUM(D8:D12),"") -> 0 | E13: =IFERROR(SUM(E8:E12),"") -> 0 | F13: =IFERROR(SUM(F8:F12),"") -> 0 | G13: =IFERROR(SUM(G8:G12),"") -> 0
A14: B. CURRENT ASSETS
A15: =IFERROR(INDEX('Industry Labels'!$C$17:$Z$17,MATCH(Assumptions!$B$3,'Industry Labels'!$C$4:$Z$4,0)),"Raw-material / stock inventory") -> Raw-material / stock inventory | B15: ₹ L | C15: =IFERROR(C8*Assumptions!$B$58/360,"") -> 0 | D15: =IFERROR(D8*Assumptions!$B$58/360,"") -> 0 | E15: =IFERROR(E8*Assumptions!$B$58/360,"") -> 0 | F15: =IFERROR(F8*Assumptions!$B$58/360,"") -> 0 | G15: =IFERROR(G8*Assumptions!$B$58/360,"") -> 0
A16: =IFERROR(INDEX('Industry Labels'!$C$18:$Z$18,MATCH(Assumptions!$B$3,'Industry Labels'!$C$4:$Z$4,0)),"Finished goods / stock-in-trade") -> Finished goods / stock-in-trade | B16: ₹ L | C16: =IFERROR(C13*Assumptions!$B$59/360,"") -> 0 | D16: =IFERROR(D13*Assumptions!$B$59/360,"") -> 0 | E16: =IFERROR(E13*Assumptions!$B$59/360,"") -> 0 | F16: =IFERROR(F13*Assumptions!$B$59/360,"") -> 0 | G16: =IFERROR(G13*Assumptions!$B$59/360,"") -> 0
A17: Receivables (debtors) | B17: ₹ L | C17: =IFERROR(C6*Assumptions!$B$60/360,"") -> 0 | D17: =IFERROR(D6*Assumptions!$B$60/360,"") -> 0 | E17: =IFERROR(E6*Assumptions!$B$60/360,"") -> 0 | F17: =IFERROR(F6*Assumptions!$B$60/360,"") -> 0 | G17: =IFERROR(G6*Assumptions!$B$60/360,"") -> 0
A18: TOTAL CURRENT ASSETS | B18: ₹ L | C18: =IFERROR(C15+C16+C17,"") -> 0 | D18: =IFERROR(D15+D16+D17,"") -> 0 | E18: =IFERROR(E15+E16+E17,"") -> 0 | F18: =IFERROR(F15+F16+F17,"") -> 0 | G18: =IFERROR(G15+G16+G17,"") -> 0
A19: C. CURRENT LIABILITIES (other than bank)
A20: =IFERROR(INDEX('Industry Labels'!$C$19:$Z$19,MATCH(Assumptions!$B$3,'Industry Labels'!$C$4:$Z$4,0)),"Sundry creditors (suppliers)") -> Sundry creditors (suppliers) | B20: ₹ L | C20: =IFERROR(C8*Assumptions!$B$61/360,"") -> 0 | D20: =IFERROR(D8*Assumptions!$B$61/360,"") -> 0 | E20: =IFERROR(E8*Assumptions!$B$61/360,"") -> 0 | F20: =IFERROR(F8*Assumptions!$B$61/360,"") -> 0 | G20: =IFERROR(G8*Assumptions!$B$61/360,"") -> 0
A21: D. MPBF COMPUTATION (Tandon II)
A22: Working-capital gap (TCA − creditors) | B22: ₹ L | C22: =IFERROR(C18-C20,"") -> 0 | D22: =IFERROR(D18-D20,"") -> 0 | E22: =IFERROR(E18-E20,"") -> 0 | F22: =IFERROR(F18-F20,"") -> 0 | G22: =IFERROR(G18-G20,"") -> 0
A23: Less: min. margin (25% of TCA) | B23: ₹ L | C23: =IFERROR(C18*Assumptions!$B$62,"") -> 0 | D23: =IFERROR(D18*Assumptions!$B$62,"") -> 0 | E23: =IFERROR(E18*Assumptions!$B$62,"") -> 0 | F23: =IFERROR(F18*Assumptions!$B$62,"") -> 0 | G23: =IFERROR(G18*Assumptions!$B$62,"") -> 0
A24: MPBF / Assessed bank finance (CC limit) | B24: ₹ L | C24: =IFERROR(C22-C23,"") -> 0 | D24: =IFERROR(D22-D23,"") -> 0 | E24: =IFERROR(E22-E23,"") -> 0 | F24: =IFERROR(F22-F23,"") -> 0 | G24: =IFERROR(G22-G23,"") -> 0
A25: Net working capital (promoter funded) | B25: ₹ L | C25: =IFERROR(C18-C20-C24,"") -> 0 | D25: =IFERROR(D18-D20-D24,"") -> 0 | E25: =IFERROR(E18-E20-E24,"") -> 0 | F25: =IFERROR(F18-F20-F24,"") -> 0 | G25: =IFERROR(G18-G20-G24,"") -> 0
A26: E. WORKING-CAPITAL FINANCE COST
A27: Interest on cash credit (@ CC rate) | B27: ₹ L | C27: =IFERROR(C24*Assumptions!$B$56,"") -> 0 | D27: =IFERROR(D24*Assumptions!$B$56,"") -> 0 | E27: =IFERROR(E24*Assumptions!$B$56,"") -> 0 | F27: =IFERROR(F24*Assumptions!$B$56,"") -> 0 | G27: =IFERROR(G24*Assumptions!$B$56,"") -> 0
A28: (assumes limit fully drawn on average)

Sheet Balance Sheet
A1: PROJECTED BALANCE SHEET (5 YEARS) — ₹ Lakh [CMA Form III]
A2: 'At start' = position on commissioning. Cash & bank is the balancing figure; reconciled against the Cash-Flow statement.
A4: Particulars | C4: At start | D4: Year 1 | E4: Year 2 | F4: Year 3 | G4: Year 4 | H4: Year 5
A5: I. LIABILITIES / SOURCES OF FUNDS
A6: Promoter's capital / equity | C6: =IFERROR(Assumptions!$B$52,"") -> 0 | D6: =IFERROR(Assumptions!$B$52,"") -> 0 | E6: =IFERROR(Assumptions!$B$52,"") -> 0 | F6: =IFERROR(Assumptions!$B$52,"") -> 0 | G6: =IFERROR(Assumptions!$B$52,"") -> 0 | H6: =IFERROR(Assumptions!$B$52,"") -> 0
A7: Reserves & surplus (accumulated PAT) | C7: =IFERROR(0,"") -> 0 | D7: =IFERROR(C7+'Profitability (Annual)'!$C$36,"") -> 0 | E7: =IFERROR(D7+'Profitability (Annual)'!$D$36,"") -> 0 | F7: =IFERROR(E7+'Profitability (Annual)'!$E$36,"") -> 0 | G7: =IFERROR(F7+'Profitability (Annual)'!$F$36,"") -> 0 | H7: =IFERROR(G7+'Profitability (Annual)'!$G$36,"") -> 0
A8: Net worth | C8: =IFERROR(C6+C7,"") -> 0 | D8: =IFERROR(D6+D7,"") -> 0 | E8: =IFERROR(E6+E7,"") -> 0 | F8: =IFERROR(F6+F7,"") -> 0 | G8: =IFERROR(G6+G7,"") -> 0 | H8: =IFERROR(H6+H7,"") -> 0
A9: Term loan (closing) | C9: =IFERROR(Assumptions!$B$51,"") -> 0 | D9: =IFERROR('Term Loan'!N11,"") -> 0 | E9: =IFERROR('Term Loan'!Z11,"") -> 0 | F9: =IFERROR('Term Loan'!AL11,"") -> 0 | G9: =IFERROR('Term Loan'!AX11,"") -> 0 | H9: =IFERROR('Term Loan'!BJ11,"") -> 0
A10: Working-capital borrowing (cash credit) | C10: =IFERROR(0,"") -> 0 | D10: =IFERROR('Working Capital'!$C$24,"") -> 0 | E10: =IFERROR('Working Capital'!$D$24,"") -> 0 | F10: =IFERROR('Working Capital'!$E$24,"") -> 0 | G10: =IFERROR('Working Capital'!$F$24,"") -> 0 | H10: =IFERROR('Working Capital'!$G$24,"") -> 0
A11: Sundry creditors | C11: =IFERROR(0,"") -> 0 | D11: =IFERROR('Working Capital'!$C$20,"") -> 0 | E11: =IFERROR('Working Capital'!$D$20,"") -> 0 | F11: =IFERROR('Working Capital'!$E$20,"") -> 0 | G11: =IFERROR('Working Capital'!$F$20,"") -> 0 | H11: =IFERROR('Working Capital'!$G$20,"") -> 0
A12: TOTAL LIABILITIES | C12: =IFERROR(C8+C9+C10+C11,"") -> 0 | D12: =IFERROR(D8+D9+D10+D11,"") -> 0 | E12: =IFERROR(E8+E9+E10+E11,"") -> 0 | F12: =IFERROR(F8+F9+F10+F11,"") -> 0 | G12: =IFERROR(G8+G9+G10+G11,"") -> 0 | H12: =IFERROR(H8+H9+H10+H11,"") -> 0
A13: II. ASSETS / APPLICATION OF FUNDS
A14: Net fixed assets (incl. land) | C14: =IFERROR(('Project Cost'!$C$6+'Project Cost'!$C$7+'Project Cost'!$C$11+'Project Cost'!$C$8+'Project Cost'!$C$9+'Project Cost'!$C$10+'Project Cost'!$C$5),"") -> 0 | D14: =IFERROR(Depreciation!$F$13,"") -> 0 | E14: =IFERROR(Depreciation!$I$13,"") -> 0 | F14: =IFERROR(Depreciation!$L$13,"") -> 0 | G14: =IFERROR(Depreciation!$O$13,"") -> 0 | H14: =IFERROR(Depreciation!$R$13,"") -> 0
A15: Pre-operative expenses (unamortised) | C15: =IFERROR('Project Cost'!$C$12,"") -> 0 | D15: =IFERROR(Depreciation!$F$14,"") -> 0 | E15: =IFERROR(Depreciation!$I$14,"") -> 0 | F15: =IFERROR(Depreciation!$L$14,"") -> 0 | G15: =IFERROR(Depreciation!$O$14,"") -> 0 | H15: =IFERROR(Depreciation!$R$14,"") -> 0
A16: =IFERROR(INDEX('Industry Labels'!$C$17:$Z$17,MATCH(Assumptions!$B$3,'Industry Labels'!$C$4:$Z$4,0)),"Raw-material / stock inventory") -> Raw-material / stock inventory | C16: =IFERROR(0,"") -> 0 | D16: =IFERROR('Working Capital'!$C$15,"") -> 0 | E16: =IFERROR('Working Capital'!$D$15,"") -> 0 | F16: =IFERROR('Working Capital'!$E$15,"") -> 0 | G16: =IFERROR('Working Capital'!$F$15,"") -> 0 | H16: =IFERROR('Working Capital'!$G$15,"") -> 0
A17: =IFERROR(INDEX('Industry Labels'!$C$18:$Z$18,MATCH(Assumptions!$B$3,'Industry Labels'!$C$4:$Z$4,0)),"Finished goods / stock-in-trade") -> Finished goods / stock-in-trade | C17: =IFERROR(0,"") -> 0 | D17: =IFERROR('Working Capital'!$C$16,"") -> 0 | E17: =IFERROR('Working Capital'!$D$16,"") -> 0 | F17: =IFERROR('Working Capital'!$E$16,"") -> 0 | G17: =IFERROR('Working Capital'!$F$16,"") -> 0 | H17: =IFERROR('Working Capital'!$G$16,"") -> 0
A18: Receivables (debtors) | C18: =IFERROR(0,"") -> 0 | D18: =IFERROR('Working Capital'!$C$17,"") -> 0 | E18: =IFERROR('Working Capital'!$D$17,"") -> 0 | F18: =IFERROR('Working Capital'!$E$17,"") -> 0 | G18: =IFERROR('Working Capital'!$F$17,"") -> 0 | H18: =IFERROR('Working Capital'!$G$17,"") -> 0
A19: Cash & bank balance (balancing) | C19: =IFERROR(C12-(C14+C15+C16+C17+C18),"") -> 0 | D19: =IFERROR(D12-(D14+D15+D16+D17+D18),"") -> 0 | E19: =IFERROR(E12-(E14+E15+E16+E17+E18),"") -> 0 | F19: =IFERROR(F12-(F14+F15+F16+F17+F18),"") -> 0 | G19: =IFERROR(G12-(G14+G15+G16+G17+G18),"") -> 0 | H19: =IFERROR(H12-(H14+H15+H16+H17+H18),"") -> 0
A20: TOTAL ASSETS | C20: =IFERROR(C14+C15+C16+C17+C18+C19,"") -> 0 | D20: =IFERROR(D14+D15+D16+D17+D18+D19,"") -> 0 | E20: =IFERROR(E14+E15+E16+E17+E18+E19,"") -> 0 | F20: =IFERROR(F14+F15+F16+F17+F18+F19,"") -> 0 | G20: =IFERROR(G14+G15+G16+G17+G18+G19,"") -> 0 | H20: =IFERROR(H14+H15+H16+H17+H18+H19,"") -> 0
A21: Check (Assets − Liabilities) | C21: =IFERROR(C20-C12,"") -> 0 | D21: =IFERROR(D20-D12,"") -> 0 | E21: =IFERROR(E20-E12,"") -> 0 | F21: =IFERROR(F20-F12,"") -> 0 | G21: =IFERROR(G20-G12,"") -> 0 | H21: =IFERROR(H20-H12,"") -> 0

Sheet Cash Flow
A1: PROJECTED CASH-FLOW STATEMENT (5 YEARS) — ₹ Lakh [CMA Form VI]
A2: Closing cash reconciles to the Balance-Sheet cash line.
A4: Particulars | C4: At start | D4: Year 1 | E4: Year 2 | F4: Year 3 | G4: Year 4 | H4: Year 5
A5: SOURCES OF FUNDS
A6: Cash accruals (PAT + Depreciation) | C6: =IFERROR(0,"") -> 0 | D6: =IFERROR('Profitability (Annual)'!$C$38,"") -> 0 | E6: =IFERROR('Profitability (Annual)'!$D$38,"") -> 0 | F6: =IFERROR('Profitability (Annual)'!$E$38,"") -> 0 | G6: =IFERROR('Profitability (Annual)'!$F$38,"") -> 0 | H6: =IFERROR('Profitability (Annual)'!$G$38,"") -> 0
A7: Equity introduced | C7: =IFERROR(Assumptions!$B$52,"") -> 0 | D7: =IFERROR(0,"") -> 0 | E7: =IFERROR(0,"") -> 0 | F7: =IFERROR(0,"") -> 0 | G7: =IFERROR(0,"") -> 0 | H7: =IFERROR(0,"") -> 0
A8: Term loan drawn | C8: =IFERROR(Assumptions!$B$51,"") -> 0 | D8: =IFERROR(0,"") -> 0 | E8: =IFERROR(0,"") -> 0 | F8: =IFERROR(0,"") -> 0 | G8: =IFERROR(0,"") -> 0 | H8: =IFERROR(0,"") -> 0
A9: Increase in cash-credit borrowing | C9: =IFERROR(0,"") -> 0 | D9: =IFERROR('Working Capital'!$C$24,"") -> 0 | E9: =IFERROR('Working Capital'!$D$24-'Working Capital'!$C$24,"") -> 0 | F9: =IFERROR('Working Capital'!$E$24-'Working Capital'!$D$24,"") -> 0 | G9: =IFERROR('Working Capital'!$F$24-'Working Capital'!$E$24,"") -> 0 | H9: =IFERROR('Working Capital'!$G$24-'Working Capital'!$F$24,"") -> 0
A10: Increase in creditors | C10: =IFERROR(0,"") -> 0 | D10: =IFERROR('Working Capital'!$C$20,"") -> 0 | E10: =IFERROR('Working Capital'!$D$20-'Working Capital'!$C$20,"") -> 0 | F10: =IFERROR('Working Capital'!$E$20-'Working Capital'!$D$20,"") -> 0 | G10: =IFERROR('Working Capital'!$F$20-'Working Capital'!$E$20,"") -> 0 | H10: =IFERROR('Working Capital'!$G$20-'Working Capital'!$F$20,"") -> 0
A11: Total sources | C11: =IFERROR(SUM(C6:C10),"") -> 0 | D11: =IFERROR(SUM(D6:D10),"") -> 0 | E11: =IFERROR(SUM(E6:E10),"") -> 0 | F11: =IFERROR(SUM(F6:F10),"") -> 0 | G11: =IFERROR(SUM(G6:G10),"") -> 0 | H11: =IFERROR(SUM(H6:H10),"") -> 0
A12: USES OF FUNDS
A13: Capital expenditure (fixed assets + pre-op) | C13: =IFERROR(('Project Cost'!$C$6+'Project Cost'!$C$7+'Project Cost'!$C$11+'Project Cost'!$C$8+'Project Cost'!$C$9+'Project Cost'!$C$10+'Project Cost'!$C$5+'Project Cost'!$C$12),"") -> 0 | D13: =IFERROR(0,"") -> 0 | E13: =IFERROR(0,"") -> 0 | F13: =IFERROR(0,"") -> 0 | G13: =IFERROR(0,"") -> 0 | H13: =IFERROR(0,"") -> 0
A14: Increase in current assets (inventory + debtors) | C14: =IFERROR(0,"") -> 0 | D14: =IFERROR(('Working Capital'!$C$15+'Working Capital'!$C$16+'Working Capital'!$C$17),"") -> 0 | E14: =IFERROR(('Working Capital'!$D$15+'Working Capital'!$D$16+'Working Capital'!$D$17)-('Working Capital'!$C$15+'Working Capital'!$C$16+'Working Capital'!$C$17),"") -> 0 | F14: =IFERROR(('Working Capital'!$E$15+'Working Capital'!$E$16+'Working Capital'!$E$17)-('Working Capital'!$D$15+'Working Capital'!$D$16+'Working Capital'!$D$17),"") -> 0 | G14: =IFERROR(('Working Capital'!$F$15+'Working Capital'!$F$16+'Working Capital'!$F$17)-('Working Capital'!$E$15+'Working Capital'!$E$16+'Working Capital'!$E$17),"") -> 0 | H14: =IFERROR(('Working Capital'!$G$15+'Working Capital'!$G$16+'Working Capital'!$G$17)-('Working Capital'!$F$15+'Working Capital'!$F$16+'Working Capital'!$F$17),"") -> 0
A15: Term-loan principal repayment | C15: =IFERROR(0,"") -> 0 | D15: =IFERROR(SUM('Term Loan'!C9:N9),"") -> 0 | E15: =IFERROR(SUM('Term Loan'!O9:Z9),"") -> 0 | F15: =IFERROR(SUM('Term Loan'!AA9:AL9),"") -> 0 | G15: =IFERROR(SUM('Term Loan'!AM9:AX9),"") -> 0 | H15: =IFERROR(SUM('Term Loan'!AY9:BJ9),"") -> 0
A16: Total uses | C16: =IFERROR(C13+C14+C15,"") -> 0 | D16: =IFERROR(D13+D14+D15,"") -> 0 | E16: =IFERROR(E13+E14+E15,"") -> 0 | F16: =IFERROR(F13+F14+F15,"") -> 0 | G16: =IFERROR(G13+G14+G15,"") -> 0 | H16: =IFERROR(H13+H14+H15,"") -> 0
A17: NET CASH-FLOW & BALANCE
A18: Net surplus / (deficit) for the year | C18: =IFERROR(C11-C16,"") -> 0 | D18: =IFERROR(D11-D16,"") -> 0 | E18: =IFERROR(E11-E16,"") -> 0 | F18: =IFERROR(F11-F16,"") -> 0 | G18: =IFERROR(G11-G16,"") -> 0 | H18: =IFERROR(H11-H16,"") -> 0
A19: Opening cash balance | C19: =IFERROR(0,"") -> 0 | D19: =IFERROR(C20,"") -> 0 | E19: =IFERROR(D20,"") -> 0 | F19: =IFERROR(E20,"") -> 0 | G19: =IFERROR(F20,"") -> 0 | H19: =IFERROR(G20,"") -> 0
A20: Closing cash balance | C20: =IFERROR(C19+C18,"") -> 0 | D20: =IFERROR(D19+D18,"") -> 0 | E20: =IFERROR(E19+E18,"") -> 0 | F20: =IFERROR(F19+F18,"") -> 0 | G20: =IFERROR(G19+G18,"") -> 0 | H20: =IFERROR(H19+H18,"") -> 0
A21: Reconciliation: BS cash − CF closing | C21: =IFERROR('Balance Sheet'!$C$19-C20,"") -> 0 | D21: =IFERROR('Balance Sheet'!$D$19-D20,"") -> 0 | E21: =IFERROR('Balance Sheet'!$E$19-E20,"") -> 0 | F21: =IFERROR('Balance Sheet'!$F$19-F20,"") -> 0 | G21: =IFERROR('Balance Sheet'!$G$19-G20,"") -> 0 | H21: =IFERROR('Balance Sheet'!$H$19-H20,"") -> 0

Sheet Ratios & DSCR
A1: RATIO ANALYSIS & DEBT-SERVICE COVERAGE (DSCR)
A2: Key bankability ratios derived from the projected financials. Benchmarks shown for guidance only.
A4: Ratio | B4: Benchmark | C4: Yr1 | D4: Yr2 | E4: Yr3 | F4: Yr4 | G4: Yr5
A5: A. PROFITABILITY
A6: EBITDA margin | B6: ≥ 12% | C6: =IFERROR('Profitability (Annual)'!$C$27/'Profitability (Annual)'!$C$9,"") | D6: =IFERROR('Profitability (Annual)'!$D$27/'Profitability (Annual)'!$D$9,"") | E6: =IFERROR('Profitability (Annual)'!$E$27/'Profitability (Annual)'!$E$9,"") | F6: =IFERROR('Profitability (Annual)'!$F$27/'Profitability (Annual)'!$F$9,"") | G6: =IFERROR('Profitability (Annual)'!$G$27/'Profitability (Annual)'!$G$9,"")
A7: PBT margin | C7: =IFERROR('Profitability (Annual)'!$C$34/'Profitability (Annual)'!$C$9,"") | D7: =IFERROR('Profitability (Annual)'!$D$34/'Profitability (Annual)'!$D$9,"") | E7: =IFERROR('Profitability (Annual)'!$E$34/'Profitability (Annual)'!$E$9,"") | F7: =IFERROR('Profitability (Annual)'!$F$34/'Profitability (Annual)'!$F$9,"") | G7: =IFERROR('Profitability (Annual)'!$G$34/'Profitability (Annual)'!$G$9,"")
A8: PAT margin | C8: =IFERROR('Profitability (Annual)'!$C$36/'Profitability (Annual)'!$C$9,"") | D8: =IFERROR('Profitability (Annual)'!$D$36/'Profitability (Annual)'!$D$9,"") | E8: =IFERROR('Profitability (Annual)'!$E$36/'Profitability (Annual)'!$E$9,"") | F8: =IFERROR('Profitability (Annual)'!$F$36/'Profitability (Annual)'!$F$9,"") | G8: =IFERROR('Profitability (Annual)'!$G$36/'Profitability (Annual)'!$G$9,"")
A9: Return on capital employed (EBIT/CE) | B9: ≥ 12% | C9: =IFERROR('Profitability (Annual)'!$C$30/('Balance Sheet'!$D$8+('Term Loan'!N11+'Working Capital'!$C$24)),"") | D9: =IFERROR('Profitability (Annual)'!$D$30/('Balance Sheet'!$E$8+('Term Loan'!Z11+'Working Capital'!$D$24)),"") | E9: =IFERROR('Profitability (Annual)'!$E$30/('Balance Sheet'!$F$8+('Term Loan'!AL11+'Working Capital'!$E$24)),"") | F9: =IFERROR('Profitability (Annual)'!$F$30/('Balance Sheet'!$G$8+('Term Loan'!AX11+'Working Capital'!$F$24)),"") | G9: =IFERROR('Profitability (Annual)'!$G$30/('Balance Sheet'!$H$8+('Term Loan'!BJ11+'Working Capital'!$G$24)),"")
A10: Return on net worth (PAT/NW) | C10: =IFERROR('Profitability (Annual)'!$C$36/'Balance Sheet'!$D$8,"") | D10: =IFERROR('Profitability (Annual)'!$D$36/'Balance Sheet'!$E$8,"") | E10: =IFERROR('Profitability (Annual)'!$E$36/'Balance Sheet'!$F$8,"") | F10: =IFERROR('Profitability (Annual)'!$F$36/'Balance Sheet'!$G$8,"") | G10: =IFERROR('Profitability (Annual)'!$G$36/'Balance Sheet'!$H$8,"")
A11: B. LEVERAGE & COVERAGE
A12: Debt : Equity (total debt / NW) | B12: ≤ 3.0x | C12: =IFERROR(('Term Loan'!N11+'Working Capital'!$C$24)/'Balance Sheet'!$D$8,"") | D12: =IFERROR(('Term Loan'!Z11+'Working Capital'!$D$24)/'Balance Sheet'!$E$8,"") | E12: =IFERROR(('Term Loan'!AL11+'Working Capital'!$E$24)/'Balance Sheet'!$F$8,"") | F12: =IFERROR(('Term Loan'!AX11+'Working Capital'!$F$24)/'Balance Sheet'!$G$8,"") | G12: =IFERROR(('Term Loan'!BJ11+'Working Capital'!$G$24)/'Balance Sheet'!$H$8,"")
A13: TOL / TNW | B13: ≤ 4.0x | C13: =IFERROR((('Term Loan'!N11+'Working Capital'!$C$24)+'Working Capital'!$C$20)/'Balance Sheet'!$D$8,"") | D13: =IFERROR((('Term Loan'!Z11+'Working Capital'!$D$24)+'Working Capital'!$D$20)/'Balance Sheet'!$E$8,"") | E13: =IFERROR((('Term Loan'!AL11+'Working Capital'!$E$24)+'Working Capital'!$E$20)/'Balance Sheet'!$F$8,"") | F13: =IFERROR((('Term Loan'!AX11+'Working Capital'!$F$24)+'Working Capital'!$F$20)/'Balance Sheet'!$G$8,"") | G13: =IFERROR((('Term Loan'!BJ11+'Working Capital'!$G$24)+'Working Capital'!$G$20)/'Balance Sheet'!$H$8,"")
A14: Interest coverage (EBIT/Interest) | B14: ≥ 2.0x | C14: =IFERROR('Profitability (Annual)'!$C$30/'Profitability (Annual)'!$C$33,"") | D14: =IFERROR('Profitability (Annual)'!$D$30/'Profitability (Annual)'!$D$33,"") | E14: =IFERROR('Profitability (Annual)'!$E$30/'Profitability (Annual)'!$E$33,"") | F14: =IFERROR('Profitability (Annual)'!$F$30/'Profitability (Annual)'!$F$33,"") | G14: =IFERROR('Profitability (Annual)'!$G$30/'Profitability (Annual)'!$G$33,"")
A15: C. LIQUIDITY
A16: Current ratio (CA/CL) | B16: ≥ 1.33x | C16: =IFERROR(('Working Capital'!$C$18+'Balance Sheet'!$D$19)/('Working Capital'!$C$24+'Working Capital'!$C$20),"") | D16: =IFERROR(('Working Capital'!$D$18+'Balance Sheet'!$E$19)/('Working Capital'!$D$24+'Working Capital'!$D$20),"") | E16: =IFERROR(('Working Capital'!$E$18+'Balance Sheet'!$F$19)/('Working Capital'!$E$24+'Working Capital'!$E$20),"") | F16: =IFERROR(('Working Capital'!$F$18+'Balance Sheet'!$G$19)/('Working Capital'!$F$24+'Working Capital'!$F$20),"") | G16: =IFERROR(('Working Capital'!$G$18+'Balance Sheet'!$H$19)/('Working Capital'!$G$24+'Working Capital'!$G$20),"")
A17: Quick ratio | C17: =IFERROR((('Working Capital'!$C$18+'Balance Sheet'!$D$19)-'Working Capital'!$C$15-'Working Capital'!$C$16)/('Working Capital'!$C$24+'Working Capital'!$C$20),"") | D17: =IFERROR((('Working Capital'!$D$18+'Balance Sheet'!$E$19)-'Working Capital'!$D$15-'Working Capital'!$D$16)/('Working Capital'!$D$24+'Working Capital'!$D$20),"") | E17: =IFERROR((('Working Capital'!$E$18+'Balance Sheet'!$F$19)-'Working Capital'!$E$15-'Working Capital'!$E$16)/('Working Capital'!$E$24+'Working Capital'!$E$20),"") | F17: =IFERROR((('Working Capital'!$F$18+'Balance Sheet'!$G$19)-'Working Capital'!$F$15-'Working Capital'!$F$16)/('Working Capital'!$F$24+'Working Capital'!$F$20),"") | G17: =IFERROR((('Working Capital'!$G$18+'Balance Sheet'!$H$19)-'Working Capital'!$G$15-'Working Capital'!$G$16)/('Working Capital'!$G$24+'Working Capital'!$G$20),"")
A18: D. TURNOVER / EFFICIENCY
A19: Net asset turnover (Sales/TA) | C19: =IFERROR('Profitability (Annual)'!$C$9/('Balance Sheet'!$D$8+('Term Loan'!N11+'Working Capital'!$C$24)+'Working Capital'!$C$20),"") | D19: =IFERROR('Profitability (Annual)'!$D$9/('Balance Sheet'!$E$8+('Term Loan'!Z11+'Working Capital'!$D$24)+'Working Capital'!$D$20),"") | E19: =IFERROR('Profitability (Annual)'!$E$9/('Balance Sheet'!$F$8+('Term Loan'!AL11+'Working Capital'!$E$24)+'Working Capital'!$E$20),"") | F19: =IFERROR('Profitability (Annual)'!$F$9/('Balance Sheet'!$G$8+('Term Loan'!AX11+'Working Capital'!$F$24)+'Working Capital'!$F$20),"") | G19: =IFERROR('Profitability (Annual)'!$G$9/('Balance Sheet'!$H$8+('Term Loan'!BJ11+'Working Capital'!$G$24)+'Working Capital'!$G$20),"")
A20: Debtors | B20: days | C20: =IFERROR('Working Capital'!$C$17/'Profitability (Annual)'!$C$9*360,"") | D20: =IFERROR('Working Capital'!$D$17/'Profitability (Annual)'!$D$9*360,"") | E20: =IFERROR('Working Capital'!$E$17/'Profitability (Annual)'!$E$9*360,"") | F20: =IFERROR('Working Capital'!$F$17/'Profitability (Annual)'!$F$9*360,"") | G20: =IFERROR('Working Capital'!$G$17/'Profitability (Annual)'!$G$9*360,"")
A21: Inventory (stock) | B21: days | C21: =IFERROR(('Working Capital'!$C$15+'Working Capital'!$C$16)/'Profitability (Annual)'!$C$9*360,"") | D21: =IFERROR(('Working Capital'!$D$15+'Working Capital'!$D$16)/'Profitability (Annual)'!$D$9*360,"") | E21: =IFERROR(('Working Capital'!$E$15+'Working Capital'!$E$16)/'Profitability (Annual)'!$E$9*360,"") | F21: =IFERROR(('Working Capital'!$F$15+'Working Capital'!$F$16)/'Profitability (Annual)'!$F$9*360,"") | G21: =IFERROR(('Working Capital'!$G$15+'Working Capital'!$G$16)/'Profitability (Annual)'!$G$9*360,"")
A22: E. DEBT-SERVICE COVERAGE
A23: Cash available for debt service | C23: =IFERROR('Profitability (Annual)'!$C$36+'Profitability (Annual)'!$C$29+'Profitability (Annual)'!$C$31,"") -> 0 | D23: =IFERROR('Profitability (Annual)'!$D$36+'Profitability (Annual)'!$D$29+'Profitability (Annual)'!$D$31,"") -> 0 | E23: =IFERROR('Profitability (Annual)'!$E$36+'Profitability (Annual)'!$E$29+'Profitability (Annual)'!$E$31,"") -> 0 | F23: =IFERROR('Profitability (Annual)'!$F$36+'Profitability (Annual)'!$F$29+'Profitability (Annual)'!$F$31,"") -> 0 | G23: =IFERROR('Profitability (Annual)'!$G$36+'Profitability (Annual)'!$G$29+'Profitability (Annual)'!$G$31,"") -> 0
A24: Debt obligation (TL principal + interest) | C24: =IFERROR(SUM('Term Loan'!C9:N9)+'Profitability (Annual)'!$C$31,"") -> 0 | D24: =IFERROR(SUM('Term Loan'!O9:Z9)+'Profitability (Annual)'!$D$31,"") -> 0 | E24: =IFERROR(SUM('Term Loan'!AA9:AL9)+'Profitability (Annual)'!$E$31,"") -> 0 | F24: =IFERROR(SUM('Term Loan'!AM9:AX9)+'Profitability (Annual)'!$F$31,"") -> 0 | G24: =IFERROR(SUM('Term Loan'!AY9:BJ9)+'Profitability (Annual)'!$G$31,"") -> 0
A25: DSCR | B25: ≥ 1.50x | C25: =IFERROR(IF(C24=0,0,C23/C24),"") -> 0 | D25: =IFERROR(IF(D24=0,0,D23/D24),"") -> 0 | E25: =IFERROR(IF(E24=0,0,E23/E24),"") -> 0 | F25: =IFERROR(IF(F24=0,0,F23/F24),"") -> 0 | G25: =IFERROR(IF(G24=0,0,G23/G24),"") -> 0
A26: Average DSCR (Years 1-5) | C26: =IFERROR(AVERAGE(C25:G25),"") -> 0

Sheet Break-even & Sensitivity
A1: BREAK-EVEN & SENSITIVITY ANALYSIS — ₹ Lakh
A3: Break-even is computed on annual aggregates (fixed cost includes depreciation & interest).
A4: Particulars | B4: Unit | C4: Yr1 | D4: Yr2 | E4: Yr3 | F4: Yr4 | G4: Yr5
A5: BREAK-EVEN
A6: Net sales | B6: ₹ L | C6: =IFERROR('Profitability (Annual)'!$C$9,"") -> 0 | D6: =IFERROR('Profitability (Annual)'!$D$9,"") -> 0 | E6: =IFERROR('Profitability (Annual)'!$E$9,"") -> 0 | F6: =IFERROR('Profitability (Annual)'!$F$9,"") -> 0 | G6: =IFERROR('Profitability (Annual)'!$G$9,"") -> 0
A7: Contribution | B7: ₹ L | C7: =IFERROR('Profitability (Annual)'!$C$16,"") -> 0 | D7: =IFERROR('Profitability (Annual)'!$D$16,"") -> 0 | E7: =IFERROR('Profitability (Annual)'!$E$16,"") -> 0 | F7: =IFERROR('Profitability (Annual)'!$F$16,"") -> 0 | G7: =IFERROR('Profitability (Annual)'!$G$16,"") -> 0
A8: Contribution margin | B8: % | C8: =IFERROR(C7/C6,"") | D8: =IFERROR(D7/D6,"") | E8: =IFERROR(E7/E6,"") | F8: =IFERROR(F7/F6,"") | G8: =IFERROR(G7/G6,"")
A9: Fixed cost (overheads + dep + interest) | B9: ₹ L | C9: =IFERROR('Profitability (Annual)'!$C$25+'Profitability (Annual)'!$C$29+'Profitability (Annual)'!$C$33,"") -> 0 | D9: =IFERROR('Profitability (Annual)'!$D$25+'Profitability (Annual)'!$D$29+'Profitability (Annual)'!$D$33,"") -> 0 | E9: =IFERROR('Profitability (Annual)'!$E$25+'Profitability (Annual)'!$E$29+'Profitability (Annual)'!$E$33,"") -> 0 | F9: =IFERROR('Profitability (Annual)'!$F$25+'Profitability (Annual)'!$F$29+'Profitability (Annual)'!$F$33,"") -> 0 | G9: =IFERROR('Profitability (Annual)'!$G$25+'Profitability (Annual)'!$G$29+'Profitability (Annual)'!$G$33,"") -> 0
A10: Break-even sales | B10: ₹ L | C10: =IFERROR(C9/C8,"") | D10: =IFERROR(D9/D8,"") | E10: =IFERROR(E9/E8,"") | F10: =IFERROR(F9/F8,"") | G10: =IFERROR(G9/G8,"")
A11: Break-even (% of that year's sales) | B11: % | C11: =IFERROR(C10/C6,"") | D11: =IFERROR(D10/D6,"") | E11: =IFERROR(E10/E6,"") | F11: =IFERROR(F10/F6,"") | G11: =IFERROR(G10/G6,"")
A12: Margin of safety | B12: % | C12: =IFERROR(1-C11,"") | D12: =IFERROR(1-D11,"") | E12: =IFERROR(1-E11,"") | F12: =IFERROR(1-F11,"") | G12: =IFERROR(1-G11,"")
A13: Cash break-even sales (excl. depreciation) | B13: ₹ L | C13: =IFERROR(('Profitability (Annual)'!$C$25+'Profitability (Annual)'!$C$33)/C8,"") | D13: =IFERROR(('Profitability (Annual)'!$D$25+'Profitability (Annual)'!$D$33)/D8,"") | E13: =IFERROR(('Profitability (Annual)'!$E$25+'Profitability (Annual)'!$E$33)/E8,"") | F13: =IFERROR(('Profitability (Annual)'!$F$25+'Profitability (Annual)'!$F$33)/F8,"") | G13: =IFERROR(('Profitability (Annual)'!$G$25+'Profitability (Annual)'!$G$33)/G8,"")
A15: SENSITIVITY — impact on Year-3 PBT (₹ Lakh)
A16: Scenario | C16: -10% | D16: -5% | E16: Base | F16: +5% | G16: +10%
A17: Selling price change → PBT | B17: ₹ L | C17: =IFERROR('Profitability (Annual)'!$E$9*(1+-0.1)-'Profitability (Annual)'!$E$15-('Profitability (Annual)'!$E$25+'Profitability (Annual)'!$E$29+'Profitability (Annual)'!$E$33),"") -> 0 | D17: =IFERROR('Profitability (Annual)'!$E$9*(1+-0.05)-'Profitability (Annual)'!$E$15-('Profitability (Annual)'!$E$25+'Profitability (Annual)'!$E$29+'Profitability (Annual)'!$E$33),"") -> 0 | E17: =IFERROR('Profitability (Annual)'!$E$9*(1+0)-'Profitability (Annual)'!$E$15-('Profitability (Annual)'!$E$25+'Profitability (Annual)'!$E$29+'Profitability (Annual)'!$E$33),"") -> 0 | F17: =IFERROR('Profitability (Annual)'!$E$9*(1+0.05)-'Profitability (Annual)'!$E$15-('Profitability (Annual)'!$E$25+'Profitability (Annual)'!$E$29+'Profitability (Annual)'!$E$33),"") -> 0 | G17: =IFERROR('Profitability (Annual)'!$E$9*(1+0.1)-'Profitability (Annual)'!$E$15-('Profitability (Annual)'!$E$25+'Profitability (Annual)'!$E$29+'Profitability (Annual)'!$E$33),"") -> 0
A18: =IFERROR(INDEX('Industry Labels'!$C$26:$Z$26,MATCH(Assumptions!$B$3,'Industry Labels'!$C$4:$Z$4,0)),"Direct cost")&" change → PBT" -> Direct cost change → PBT | B18: ₹ L | C18: =IFERROR('Profitability (Annual)'!$E$9-('Profitability (Annual)'!$E$15+SUM('Profitability (Monthly)'!AA10:AL10)*-0.1)-('Profitability (Annual)'!$E$25+'Profitability (Annual)'!$E$29+'Profitability (Annual)'!$E$33),"") -> 0 | D18: =IFERROR('Profitability (Annual)'!$E$9-('Profitability (Annual)'!$E$15+SUM('Profitability (Monthly)'!AA10:AL10)*-0.05)-('Profitability (Annual)'!$E$25+'Profitability (Annual)'!$E$29+'Profitability (Annual)'!$E$33),"") -> 0 | E18: =IFERROR('Profitability (Annual)'!$E$9-('Profitability (Annual)'!$E$15+SUM('Profitability (Monthly)'!AA10:AL10)*0)-('Profitability (Annual)'!$E$25+'Profitability (Annual)'!$E$29+'Profitability (Annual)'!$E$33),"") -> 0 | F18: =IFERROR('Profitability (Annual)'!$E$9-('Profitability (Annual)'!$E$15+SUM('Profitability (Monthly)'!AA10:AL10)*0.05)-('Profitability (Annual)'!$E$25+'Profitability (Annual)'!$E$29+'Profitability (Annual)'!$E$33),"") -> 0 | G18: =IFERROR('Profitability (Annual)'!$E$9-('Profitability (Annual)'!$E$15+SUM('Profitability (Monthly)'!AA10:AL10)*0.1)-('Profitability (Annual)'!$E$25+'Profitability (Annual)'!$E$29+'Profitability (Annual)'!$E$33),"") -> 0
A19: Volume change → PBT | B19: ₹ L | C19: =IFERROR('Profitability (Annual)'!$E$9*(1+-0.1)-'Profitability (Annual)'!$E$15*(1+-0.1)-('Profitability (Annual)'!$E$25+'Profitability (Annual)'!$E$29+'Profitability (Annual)'!$E$33),"") -> 0 | D19: =IFERROR('Profitability (Annual)'!$E$9*(1+-0.05)-'Profitability (Annual)'!$E$15*(1+-0.05)-('Profitability (Annual)'!$E$25+'Profitability (Annual)'!$E$29+'Profitability (Annual)'!$E$33),"") -> 0 | E19: =IFERROR('Profitability (Annual)'!$E$9*(1+0)-'Profitability (Annual)'!$E$15*(1+0)-('Profitability (Annual)'!$E$25+'Profitability (Annual)'!$E$29+'Profitability (Annual)'!$E$33),"") -> 0 | F19: =IFERROR('Profitability (Annual)'!$E$9*(1+0.05)-'Profitability (Annual)'!$E$15*(1+0.05)-('Profitability (Annual)'!$E$25+'Profitability (Annual)'!$E$29+'Profitability (Annual)'!$E$33),"") -> 0 | G19: =IFERROR('Profitability (Annual)'!$E$9*(1+0.1)-'Profitability (Annual)'!$E$15*(1+0.1)-('Profitability (Annual)'!$E$25+'Profitability (Annual)'!$E$29+'Profitability (Annual)'!$E$33),"") -> 0
A21: Note: one-way sensitivity on Year-3 base; volume case scales sales & variable cost together (fixed cost constant).

Sheet Industry Labels
A1: INDUSTRY LABEL TABLE — drives every industry-specific label in the workbook
A2: Pick the industry on Assumptions!B3. Labels throughout the model change; no calculation changes. To add an industry: type its name in the next empty header cell of row 4 and fill that column's wording. It appears in the Assumptions!B3 dropdown automatically — no formula needs changing. 'Custom Industry' is a ready-made column to rename and edit.
A4: Label key | B4: Used for | C4: General Business | D4: Manufacturing | E4: Retail & E-Commerce | F4: Food & Restaurant | G4: Tourism & Hospitality | H4: Technology & Software | I4: Healthcare & Pharma | J4: Education & Training | K4: Import-Export Trading | L4: Transport & Logistics | M4: Media & Entertainment | N4: Agriculture & Farming | O4: Renewable Energy | P4: Custom Industry
A5: cap_name | B5: Assumptions A5, Production & Sales | C5: Installed / service capacity | D5: Installed / nameplate capacity | E5: Transaction capacity (store / platform) | F5: Seating capacity (covers) | G5: Room inventory (room-nights available) | H5: Subscriber / seat capacity | I5: Patient capacity (beds / OPD slots) | J5: Student capacity (seats) | K5: Trading capacity (units handled) | L5: Fleet capacity (trips / consignments) | M5: Content / subscriber capacity | N5: Production capacity (output units) | O5: Installed generation capacity (energy output) | P5: Installed / service capacity
A6: cap_unit | B6: Capacity unit per month | C6: units/month | D6: units/month | E6: transactions/month | F6: covers/month | G6: room-nights/month | H6: billed users/month | I6: patients/month | J6: students/month | K6: units/month | L6: trips/month | M6: units/month | N6: output units/month | O6: MWh/month | P6: units/month
A7: u_pl | B7: Unit names (plural) | C7: units | D7: units | E7: transactions | F7: covers | G7: room-nights | H7: billed users | I7: patients | J7: students | K7: units traded | L7: trips | M7: units / subscribers | N7: output units | O7: MWh | P7: units
A8: u_sg | B8: ₹ / unit labels | C8: unit | D8: unit | E8: transaction | F8: cover | G8: room-night | H8: user | I8: patient | J8: student | K8: unit | L8: trip | M8: unit | N8: unit | O8: MWh | P8: unit
A9: price | B9: Assumptions A10 | C9: Average selling price / unit (Yr1) | D9: Ex-factory selling price / unit (Yr1) | E9: Average bill value / transaction (Yr1) | F9: Average order value / cover (Yr1) | G9: Average room tariff (ARR) / room-night (Yr1) | H9: ARPU / billed user per month (Yr1) | I9: Average revenue / patient (Yr1) | J9: Fee / student per month (Yr1) | K9: Realisation / unit traded (Yr1) | L9: Revenue / trip (Yr1) | M9: Average revenue / unit or subscriber (Yr1) | N9: Average realisation / unit sold (Yr1) | O9: Tariff realisation / MWh (Yr1) | P9: Average selling price / unit (Yr1)
A10: dm | B10: Assumptions A11 | C10: Direct cost of goods / services per unit (Yr1) | D10: Direct material cost / unit (Yr1) | E10: Cost of goods sold / transaction (Yr1) | F10: Food & beverage cost / cover (Yr1) | G10: Room consumables & F&B cost / room-night | H10: Hosting & third-party cost / user (Yr1) | I10: Medicines & consumables cost / patient (Yr1) | J10: Course material & delivery cost / student (Yr1) | K10: Purchase cost / unit (Yr1) | L10: Fuel cost / trip (Yr1) | M10: Content & licensing cost / unit (Yr1) | N10: Seed, feed & input cost / unit (Yr1) | O10: Fuel / feedstock cost / MWh (Yr1) | P10: Direct cost of goods / services per unit (Yr1)
A11: v2 | B11: Assumptions A39 | C11: Utilities & energy / unit | D11: Power & fuel / unit | E11: Store utilities / transaction | F11: Gas, power & water / cover | G11: Power, water & linen / room-night | H11: Cloud & infrastructure / user | I11: Power, water & medical gases / patient | J11: Power & facilities / student | K11: Warehouse power & handling / unit | L11: Tolls & permits / trip | M11: Studio / delivery power / unit | N11: Irrigation, power & fuel / unit | O11: Grid & evacuation charges / MWh | P11: Utilities & energy / unit
A12: v3 | B12: Assumptions A40 | C12: Consumables & supplies / unit | D12: Consumables & stores / unit | E12: Payment gateway & consumables / transaction | F12: Consumables & disposables / cover | G12: Housekeeping supplies / room-night | H12: Support & tooling / user | I12: Disposables & lab reagents / patient | J12: Learning consumables / student | K12: Freight inward & duties / unit | L12: Tyres, lubricants & consumables / trip | M12: Production consumables / unit | N12: Fertiliser, medicines & consumables / unit | O12: O&M consumables / MWh | P12: Consumables & supplies / unit
A13: v4 | B13: Assumptions A41 | C13: Packing & delivery / unit | D13: Packing / unit | E13: Packaging & delivery / transaction | F13: Packaging & aggregator commission / cover | G13: OTA / distribution cost / room-night | H13: Payment gateway fees / user | I13: Sterilisation & waste handling / patient | J13: Admissions & marketing cost / student | K13: Packing & documentation / unit | L13: Loading / handling / trip | M13: Distribution & platform fees / unit | N13: Packing, grading & transport / unit | O13: Wheeling & scheduling charges / MWh | P13: Packing & delivery / unit
A14: labour | B14: Assumptions A42 | C14: Direct labour (Year-1) | D14: Direct labour (Year-1) | E14: Store & fulfilment staff (Year-1) | F14: Kitchen & service staff (Year-1) | G14: Front office, housekeeping & F&B staff (Year-1) | H14: Engineering & support staff (Year-1) | I14: Clinical & nursing staff (Year-1) | J14: Faculty & instructors (Year-1) | K14: Warehouse & logistics staff (Year-1) | L14: Drivers & operations staff (Year-1) | M14: Production & editorial staff (Year-1) | N14: Farm labour (Year-1) | O14: Plant O&M staff (Year-1) | P14: Direct labour (Year-1)
A15: bldg | B15: Project Cost, Depreciation | C15: Premises, building & civil / fit-out | D15: Factory building & civil works | E15: Store / warehouse build-out & civil | F15: Premises fit-out & civil works | G15: Hotel building & civil / interiors | H15: Office fit-out & civil | I15: Hospital / clinic building & civil | J15: Campus / centre building & fit-out | K15: Warehouse / office building & civil | L15: Depot / yard & civil works | M15: Studio / office build-out & civil | N15: Sheds, storage & farm civil works | O15: Site civil, foundations & control room | P15: Premises, building & civil / fit-out
... A30: dep_equip | B30: Assumptions label | C30: Equipment, machinery & systems depreciation (SLM) | D30: Plant & machinery – main line & ancillaries depreciation (SLM) | E30: Fixtures, POS, racking & IT systems depreciation (SLM) | F30: Kitchen equipment, furniture & POS depreciation (SLM) | G30: Furniture, HVAC, kitchen & FF&E depreciation (SLM) | H30: Servers, hardware & IT infrastructure depreciation (SLM) | I30: Medical equipment & systems depreciation (SLM) | J30: Labs, classroom equipment & IT depreciation (SLM) | K30: Handling equipment, racking & IT depreciation (SLM) | L30: Vehicles, fleet & tracking systems depreciation (SLM) | M30: Production & broadcast equipment depreciation (SLM) | N30: Farm machinery, irrigation & equipment depreciation (SLM) | O30: Solar modules / turbines / generation equipment depreciation (SLM) | P30: Equipment, machinery & systems depreciation (SLM)
